Workbook
Name Dash_FundingBasis: '12) Budget Line Mapping'!$M$2:$M$4
Name Dash_PeriodView: '12) Budget Line Mapping'!$L$2:$L$4
Name Dash_ReportCutOff: '1) Budget-Actuals Dashboard'!$C$4
Name WorkPackages: '12) Budget Line Mapping'!$N$2:$N$6

Sheet 0) ReadMe and Contents
A1: SHOC 2.0 (UNOFFICIAL)| UKRI Budget vs Actuals Project Dashboard
A2: Illustrative UKRI/ESRC fEC project tracker | Created by Alexander Pymm as a Proof of Concept for the RUSI OCP Project Officer Role
A4: Workbook purpose and Readme
A5: Project | B5: Strategic Hub for Organised Crime Research 2.0 (SHOC 2.0) | C5: WHAT IS THIS TOOL? In short, this workbook allows for real-time tracking of project costs against funder budgets, breaking down spend by category and forecasting areas of over and underspend (Variance Analysis). It also has capabilities to automate the import of new monthly transaction data from the accompanying .csv template, if enabled (see Tab 4).
A6: Lead Institution | B6: Royal United Services Institute (RUSI) - Organised Crime and Policing
A7: Funder | B7: Illustrative UKRI/ESRC award | C7: WHERE IS THIS DATA FROM? The Budget is a purely hypothetical example based around a typical full Economic Costing (fEC) model, alongside an 80% fEC UKRI contribution rate. The Budget is comprised of 3 Work Packages, each centered around a regional hub relevant to the OCP's recent engagement work: London (UK/Europe); Nairobi (/East Africa); and Bogota (Colombia/Latin America). Like the original SHOC project, promised outputs relate chiefly to engagement activities, such as workshops, conferences and panels, alongside broader collaborative opportunities.
A8: Project start | B8: 46113
A9: Project end | B9: 47208 | C9: IMPORTED TRANSACTIONS ARE ONLY ADDED TO THE LEDGER ONCE VERIFIED AGAINST CORRESPONDING BUDGET ITEMS A new batch remains excluded until its Refresh Log status is explicitly changed to 'APPROVED.'
A10: Reporting currency | B10: GBP
A12: Contents and Navigation
A13: Budget-vs-Actuals Dashboard | B13: Project overview: Budget, cost to date, variance, commitments and forecast, broken down by Work Package and cost category.
A14: Variance Detail | B14: Which Budget line is driving a variance, and by how much.
A15: Forecast Bridge | B15: The forecast for each budget line by Project Completion.
A16: Monthly Processes
A17: Monthly Update | B17: A step-by-step guide for updating the Dashboard with new monthly transactions.
A18: Refresh Log | B18: Provides a record of when new records have been added to the Dashboard, and which files/sources were used.
A19: Key Records
A20: Actuals Ledger | B20: Records all confirmed (personally verified) transactions contributing to the Directly Incurred costs on the project (e.g. Conference material, travel expenses and reimbursements etc.)
A21: Allocations | B21: Allocated Costs recorded against the project Budget. Includes allocated staff, estates and indirect costs (separate from directly incurred transaction/invoice costs).
A22: Commitments Forecast | B22: Open purchase orders and contracts (money committed but not yet spent)
A23: Back-end & Validation
A24: Budget Baseline | B24: The version of the Budget approved by the funder. The baseline reference against future project pending.
A25: Budget Changes | B25: Dated, approved changes to the original budget
A26: Model Checks | B26: A series of validity checks to check against common compliance issues or trechnical errors in the Excel file.
A27: Mappings
A29: Monthly Transaction Updates: Step-by-Step Process
A30: 1 | B30: Open and review the dashboard for currency | C30: After saving the Dashboard somewhere appropriate, it is recommended to check a few things to make sure you get the most out of the Dashboard: i) check the 'reporting cut-off' and 'last approved refresh' dates to make sure your data is up-to-date; and ii) check the model status indicator for existing errors.
A31: 2 | B31: Create a staged batch | C31: Add a 'STAGED' row on Refresh Log, alongside: i) a unique Batch ID; ii) an expected row count; and iii) a source control total.
A32: 3 | B32: Bring in transactions [manual/offline approach] | C32: Paste values into the blue input columns on the Actuals Ledger. Background route: follow the Monthly Update sheet to configure the optional Power Query staging import, then refresh it explicitly.
A33: 4 | B33: Validate | C33: Resolve every staging/ledger issue: schema, dates, amount, unique ID, mapping, evidence and reversal link. Reconcile rows and value to the source total.
A34: 5 | B34: Approve | C34: Only after review, change the batch status from STAGED to APPROVED. The dashboard will then include the batch.
A35: 6 | B35: Update exposure | C35: Update Allocations and Commitments separately. Review Forecast at Completion and the Checks sheet.
A36: 7 | B36: Close and save | C36: Set the Dashboard cut-off to the reviewed month-end, confirm PASS, record reviewer/source notes and save the monthly state.
A38: Dashboard Terms
A39: Term | B39: Definition | C39: Included in realised/recognised cost? | D39: Control treatment
A40: Original Budget | B40: Frozen accepted Budget at 100% fEC, with UKRI and RUSI shares retained. | C40: No: comparator | D40: Never overwritten
A41: Approved Budget | B41: Original Budget plus any subsequent authorised changes. | C41: No: comparator | D41: Changes recorded separately
A42: Confirmed DI Costs | B42: Confirmed, auditable project-identifiable transaction at booked GBP value. | C42: Yes | D42: Evidence, dates, mapping and duplicate tests
A43: Confirmed DA Costs | B43: Recorded DA staff, estate or indirect management allocation. Often not charged against the project like DI costs (e.g by invoice or Tx) | C43: Yes, shown separately | D43: Allocation basis and source required
A44: Committed Costs | B44: Payments liable for payment but not yet realised. (e.g. open purchase orders, contracts or other future exposures) | C44: No | D44: Separate ledger. Status must be Open
A45: Phased Budget | B45: Approved Budget distributed using the Budget timing profile. | C45: No: comparator | D45: Reconciles to approved Budget
A46: Forecast at Completion | B46: Confirmed costs + open commitments + uncommitted ETC. | C46: Forecast only | D46: Bridges by Budget item
A48: NOTE: The 80/20 fEC funder contribution split and given estate/indirect proxy values are used here for the sake of simplicity. Budget items elligible for exceptions (funded at 100% fEC) and RUSI's specific IRO rate basis may both differ significantly from these assumptions.

Sheet 1) Budget-Actuals Dashboard
A1: SHOC 2.0 | Budget vs Actuals Dashboard
A2: Illustrative UKRI/ESRC fEC project
A3: ="Illustrative portfolio data | As of "&TEXT(C4,"dd mmm yyyy")&" | Last approved refresh "&TEXT('14) Model Calc'!B27,"dd mmm yyyy hh:mm")&" | Model status "&'11) Model Audit Checks'!B2 -> Illustrative portfolio data | As of 31 Aug 2026 | Last approved refresh 01 Sep 2026 09:00 | Model status PASS
A4: Reporting cut-off | C4: 46265 | E4: Period view | G4: Cumulative | I4: Funding basis | K4: 100% fEC | M4: ='11) Model Audit Checks'!$B$2 -> PASS
A5: Work Package | C5: All | E5: fEC Heading | G5: Directly Incurred | I5: fEC Subheading | K5: All
A7: Phased Budget | D7: Confirmed Cost | G7: Variance to phased | J7: Open Commitments | M7: Forecast at Completion
A8: ='14) Model Calc'!B12 -> 12805.558 | D8: ='14) Model Calc'!B13 -> 13751.2 | G8: ='14) Model Calc'!B14 -> -945.64167 | J8: ='14) Model Calc'!B19 -> 27200 | M8: ='14) Model Calc'!B20 -> 157100.02
A10: Selected-period approved Budget | D10: Realised and verified DI + DA costs | G10: Budget minus confirmed; timing is not automatically favourable | J10: Future comittments (excluded from actuals) | M10: =IF('14) Model Calc'!B21<0,"Forecast is "&TEXT(ABS('14) Model Calc'!B21),"£#,##0")&" above approved Budget","Forecast is within approved Budget") -> Forecast is £2,900 above approved Budget
A25: DI measure
A26: Confirmed DI Costs | D26: ='14) Model Calc'!B22 -> 13751.2
A27: Remaining DI Budget | D27: ='14) Model Calc'!B24 -> 140448.82
A28: Budget consumed | D28: ='14) Model Calc'!B25 -> 0.08917768
A30: Selected-period position by Work Package | I30: Selected-period position by fEC Heading
A31: ='14) Model Calc'!A76 -> Work Package | B31: ='14) Model Calc'!B76 -> Selected-period Budget | C31: ='14) Model Calc'!C76 -> Recognised cost | D31: ='14) Model Calc'!D76 -> Variance | E31: ='14) Model Calc'!E76 -> Open commitments | F31: ='14) Model Calc'!F76 -> Forecast at Completion | G31: ='14) Model Calc'!G76 -> Full approved Budget | I31: ='14) Model Calc'!I76 -> fEC Heading | J31: ='14) Model Calc'!J76 -> Selected-period Budget | K31: ='14) Model Calc'!K76 -> Recognised cost | L31: ='14) Model Calc'!L76 -> Variance | M31: ='14) Model Calc'!M76 -> Open commitments | N31: ='14) Model Calc'!N76 -> Forecast at Completion | O31: ='14) Model Calc'!O76 -> Full approved Budget
A32: ='14) Model Calc'!A77 -> WP1 | B32: ='14) Model Calc'!B77 -> 15804.271 | C32: ='14) Model Calc'!C77 -> 16853.15 | D32: ='14) Model Calc'!D77 -> -1048.8792 | E32: ='14) Model Calc'!E77 -> 16350 | F32: ='14) Model Calc'!F77 -> 153817.23 | G32: ='14) Model Calc'!G77 -> 152117.23 | I32: ='14) Model Calc'!I77 -> Directly Allocated | J32: ='14) Model Calc'!J77 -> 10948.283 | K32: ='14) Model Calc'!K77 -> 10882.64 | L32: ='14) Model Calc'!L77 -> 65.643333 | M32: ='14) Model Calc'!M77 -> 0 | N32: ='14) Model Calc'!N77 -> 82553.88 | O32: ='14) Model Calc'!O77 -> 82553.88
A33: ='14) Model Calc'!A78 -> WP2 | B33: ='14) Model Calc'!B78 -> 8401.3125 | C33: ='14) Model Calc'!C78 -> 8380.3 | D33: ='14) Model Calc'!D78 -> 21.0125 | E33: ='14) Model Calc'!E78 -> 5300 | F33: ='14) Model Calc'!F78 -> 76939.45 | G33: ='14) Model Calc'!G78 -> 76489.45 | I33: ='14) Model Calc'!I78 -> Directly Incurred | J33: ='14) Model Calc'!J78 -> 12805.558 | K33: ='14) Model Calc'!K78 -> 13751.2 | L33: ='14) Model Calc'!L78 -> -945.64167 | M33: ='14) Model Calc'!M78 -> 27200 | N33: ='14) Model Calc'!N78 -> 157100.02 | O33: ='14) Model Calc'!O78 -> 154200.02
A34: ='14) Model Calc'!A79 -> WP3 | B34: ='14) Model Calc'!B79 -> 10569.667 | C34: ='14) Model Calc'!C79 -> 10355.67 | D34: ='14) Model Calc'!D79 -> 213.99667 | E34: ='14) Model Calc'!E79 -> 5550 | F34: ='14) Model Calc'!F79 -> 92851.6 | G34: ='14) Model Calc'!G79 -> 92101.6 | I34: ='14) Model Calc'!I79 -> Indirect | J34: ='14) Model Calc'!J79 -> 11021.408 | K34: ='14) Model Calc'!K79 -> 10955.28 | L34: ='14) Model Calc'!L79 -> 66.128333 | M34: ='14) Model Calc'!M79 -> 0 | N34: ='14) Model Calc'!N79 -> 83954.38 | O34: ='14) Model Calc'!O79 -> 83954.38
A35: ='14) Model Calc'!A80 -> Total | B35: ='14) Model Calc'!B80 -> 34775.25 | C35: ='14) Model Calc'!C80 -> 35589.12 | D35: ='14) Model Calc'!D80 -> -813.87 | E35: ='14) Model Calc'!E80 -> 27200 | F35: ='14) Model Calc'!F80 -> 323608.28 | G35: ='14) Model Calc'!G80 -> 320708.28 | I35: ='14) Model Calc'!I80 -> Total | J35: ='14) Model Calc'!J80 -> 34775.25 | K35: ='14) Model Calc'!K80 -> 35589.12 | L35: ='14) Model Calc'!L80 -> -813.87 | M35: ='14) Model Calc'!M80 -> 27200 | N35: ='14) Model Calc'!N80 -> 323608.28 | O35: ='14) Model Calc'!O80 -> 320708.28
A36: ="Management reading: recognised cost is "&TEXT('14) Model Calc'!B16,"£#,##0")&" against cumulative phased Budget of "&TEXT('14) Model Calc'!B15,"£#,##0")&" and simple pro-rata of "&TEXT('14) Model Calc'!B17,"£#,##0")&". Open commitments are shown separately." -> Management reading: recognised cost is £13,751 against cumulative phased Budget of £12,806 and simple pro-rata of £21,417. Open commitments are shown separately.

Sheet 2) Variance Detail
A1: Variance and exposure detail
A2: Budget-item drill-down using the Dashboard reporting cut-off, period view and funding basis
A4: ="Current view: "&'1) Budget-Actuals Dashboard'!$G$4&" | "&'1) Budget-Actuals Dashboard'!$K$4&" | cut-off "&TEXT('1) Budget-Actuals Dashboard'!$C$4,"dd mmm yyyy")&" | WP "&'1) Budget-Actuals Dashboard'!$C$5&" | heading "&'1) Budget-Actuals Dashboard'!$G$5&" | subheading "&'1) Budget-Actuals Dashboard'!$K$5 -> Current view: Cumulative | 100% fEC | cut-off 31 Aug 2026 | WP All | heading Directly Incurred | subheading All
A7: Budget Item ID | B7: Description | C7: Work Package | D7: fEC Heading | E7: fEC Subheading | F7: Reporting Category | G7: In Selected Scope? | H7: Period Budget | I7: Period Recognised | J7: Variance £ | K7: Variance % | L7: Open Commitments | M7: FAC Variance
A8: WP1_S01 | B8: RUSI - Project Officer (existing staff, DA) @GrB/4 | C8: WP1 | D8: Directly Allocated | E8: Staff | F8: Directly Allocated Staff | G8: =IF(AND(OR('1) Budget-Actuals Dashboard'!$C$5="All",C8='1) Budget-Actuals Dashboard'!$C$5),OR('1) Budget-Actuals Dashboard'!$G$5="All",D8='1) Budget-Actuals Dashboard'!$G$5),OR('1) Budget-Actuals Dashboard'!$K$5="All",E8='1) Budget-Actuals Dashboard'!$K$5)),"Yes","No") -> No | H8: =IF('1) Budget-Actuals Dashboard'!$K$4="100% fEC",SUMIFS('9) Budget Baseline'!$P$8:$P$1087,'9) Budget Baseline'!$B$8:$B$1087,A8,'9) Budget Baseline'!$H$8:$H$1087,">="&'14) Model Calc'!$B$9,'9) Budget Baseline'!$H$8:$H$1087,"<="&'14) Model Calc'!$B$10),IF('1) Budget-Actuals Dashboard'!$K$4="UKRI",SUMIFS('9) Budget Baseline'!$Q$8:$Q$1087,'9) Budget Baseline'!$B$8:$B$1087,A8,'9) Budget Baseline'!$H$8:$H$1087,">="&'14) Model Calc'!$B$9,'9) Budget Baseline'!$H$8:$H$1087,"<="&'14) Model Calc'!$B$10),SUMIFS('9) Budget Baseline'!$R$8:$R$1087,'9) Budget Baseline'!$B$8:$B$1087,A8,'9) Budget Baseline'!$H$8:$H$1087,">="&'14) Model Calc'!$B$9,'9) Budget Baseline'!$H$8:$H$1087,"<="&'14) Model Calc'!$B$10))) -> 1635.4167 | I8: =IF('1) Budget-Actuals Dashboard'!$K$4="100% fEC",SUMIFS('6) Actuals Ledger - DI Costs'!$R$8:$R$2007,'6) Actuals Ledger - DI Costs'!$G$8:$G$2007,A8,'6) Actuals Ledger - DI Costs'!$C$8:$C$2007,">="&'14) Model Calc'!$B$9,'6) Actuals Ledger - DI Costs'!$C$8:$C$2007,"<="&'14) Model Calc'!$B$10)+SUMIFS('7) Allocations - DA Costs'!$O$8:$O$2007,'7) Allocations - DA Costs'!$D$8:$D$2007,A8,'7) Allocations - DA Costs'!$C$8:$C$2007,">="&'14) Model Calc'!$B$9,'7) Allocations - DA Costs'!$C$8:$C$2007,"<="&'14) Model Calc'!$B$10),IF('1) Budget-Actuals Dashboard'!$K$4="UKRI",SUMIFS('6) Actuals Ledger - DI Costs'!$S$8:$S$2007,'6) Actuals Ledger - DI Costs'!$G$8:$G$2007,A8,'6) Actuals Ledger - DI Costs'!$C$8:$C$2007,">="&'14) Model Calc'!$B$9,'6) Actuals Ledger - DI Costs'!$C$8:$C$2007,"<="&'14) Model Calc'!$B$10)+SUMIFS('7) Allocations - DA Costs'!$P$8:$P$2007,'7) Allocations - DA Costs'!$D$8:$D$2007,A8,'7) Allocations - DA Costs'!$C$8:$C$2007,">="&'14) Model Calc'!$B$9,'7) Allocations - DA Costs'!$C$8:$C$2007,"<="&'14) Model Calc'!$B$10),SUMIFS('6) Actuals Ledger - DI Costs'!$T$8:$T$2007,'6) Actuals Ledger - DI Costs'!$G$8:$G$2007,A8,'6) Actuals Ledger - DI Costs'!$C$8:$C$2007,">="&'14) Model Calc'!$B$9,'6) Actuals Ledger - DI Costs'!$C$8:$C$2007,"<="&'14) Model Calc'!$B$10)+SUMIFS('7) Allocations - DA Costs'!$Q$8:$Q$2007,'7) Allocations - DA Costs'!$D$8:$D$2007,A8,'7) Allocations - DA Costs'!$C$8:$C$2007,">="&'14) Model Calc'!$B$9,'7) Allocations - DA Costs'!$C$8:$C$2007,"<="&'14) Model Calc'!$B$10))) -> 1625.59 | J8: =H8-I8 -> 9.8266667 | K8: =IF(H8=0,"",J8/H8) -> 0.0060086624 | L8: =IF('1) Budget-Actuals Dashboard'!$K$4="100% fEC",SUMIFS('8) Commitments Forecast'!$Q$8:$Q$507,'8) Commitments Forecast'!$H$8:$H$507,A8),IF('1) Budget-Actuals Dashboard'!$K$4="UKRI",SUMIFS('8) Commitments Forecast'!$R$8:$R$507,'8) Commitments Forecast'!$H$8:$H$507,A8),SUMIFS('8) Commitments Forecast'!$S$8:$S$507,'8) Commitments Forecast'!$H$8:$H$507,A8))) -> 0 | M8: =IFERROR(IF('1) Budget-Actuals Dashboard'!$K$4="100% fEC",INDEX('3) Forecast Bridge'!$L$8:$L$37,MATCH(A8,'3) Forecast Bridge'!$A$8:$A$37,0)),IF('1) Budget-Actuals Dashboard'!$K$4="UKRI",INDEX('3) Forecast Bridge'!$P$8:$P$37,MATCH(A8,'3) Forecast Bridge'!$A$8:$A$37,0)),INDEX('3) Forecast Bridge'!$Q$8:$Q$37,MATCH(A8,'3) Forecast Bridge'!$A$8:$A$37,0)))),0) -> 0
A9: WP1_S02 | B9: RUSI - Research Analyst (existing staff, DA) @GrC/8 | C9: WP1 | D9: Directly Allocated | E9: Staff | F9: Directly Allocated Staff | G9: =IF(AND(OR('1) Budget-Actuals Dashboard'!$C$5="All",C9='1) Budget-Actuals Dashboard'!$C$5),OR('1) Budget-Actuals Dashboard'!$G$5="All",D9='1) Budget-Actuals Dashboard'!$G$5),OR('1) Budget-Actuals Dashboard'!$K$5="All",E9='1) Budget-Actuals Dashboard'!$K$5)),"Yes","No") -> No | H9: =IF('1) Budget-Actuals Dashboard'!$K$4="100% fEC",SUMIFS('9) Budget Baseline'!$P$8:$P$1087,'9) Budget Baseline'!$B$8:$B$1087,A9,'9) Budget Baseline'!$H$8:$H$1087,">="&'14) Model Calc'!$B$9,'9) Budget Baseline'!$H$8:$H$1087,"<="&'14) Model Calc'!$B$10),IF('1) Budget-Actuals Dashboard'!$K$4="UKRI",SUMIFS('9) Budget Baseline'!$Q$8:$Q$1087,'9) Budget Baseline'!$B$8:$B$1087,A9,'9) Budget Baseline'!$H$8:$H$1087,">="&'14) Model Calc'!$B$9,'9) Budget Baseline'!$H$8:$H$1087,"<="&'14) Model Calc'!$B$10),SUMIFS('9) Budget Baseline'!$R$8:$R$1087,'9) Budget Baseline'!$B$8:$B$1087,A9,'9) Budget Baseline'!$H$8:$H$1087,">="&'14) Model Calc'!$B$9,'9) Budget Baseline'!$H$8:$H$1087,"<="&'14) Model Calc'!$B$10))) -> 1809.375 | I9: =IF('1) Budget-Actuals Dashboard'!$K$4="100% fEC",SUMIFS('6) Actuals Ledger - DI Costs'!$R$8:$R$2007,'6) Actuals Ledger - DI Costs'!$G$8:$G$2007,A9,'6) Actuals Ledger - DI Costs'!$C$8:$C$2007,">="&'14) Model Calc'!$B$9,'6) Actuals Ledger - DI Costs'!$C$8:$C$2007,"<="&'14) Model Calc'!$B$10)+SUMIFS('7) Allocations - DA Costs'!$O$8:$O$2007,'7) Allocations - DA Costs'!$D$8:$D$2007,A9,'7) Allocations - DA Costs'!$C$8:$C$2007,">="&'14) Model Calc'!$B$9,'7) Allocations - DA Costs'!$C$8:$C$2007,"<="&'14) Model Calc'!$B$10),IF('1) Budget-Actuals Dashboard'!$K$4="UKRI",SUMIFS('6) Actuals Ledger - DI Costs'!$S$8:$S$2007,'6) Actuals Ledger - DI Costs'!$G$8:$G$2007,A9,'6) Actuals Ledger - DI Costs'!$C$8:$C$2007,">="&'14) Model Calc'!$B$9,'6) Actuals Ledger - DI Costs'!$C$8:$C$2007,"<="&'14) Model Calc'!$B$10)+SUMIFS('7) Allocations - DA Costs'!$P$8:$P$2007,'7) Allocations - DA Costs'!$D$8:$D$2007,A9,'7) Allocations - DA Costs'!$C$8:$C$2007,">="&'14) Model Calc'!$B$9,'7) Allocations - DA Costs'!$C$8:$C$2007,"<="&'14) Model Calc'!$B$10),SUMIFS('6) Actuals Ledger - DI Costs'!$T$8:$T$2007,'6) Actuals Ledger - DI Costs'!$G$8:$G$2007,A9,'6) Actuals Ledger - DI Costs'!$C$8:$C$2007,">="&'14) Model Calc'!$B$9,'6) Actuals Ledger - DI Costs'!$C$8:$C$2007,"<="&'14) Model Calc'!$B$10)+SUMIFS('7) Allocations - DA Costs'!$Q$8:$Q$2007,'7) Allocations - DA Costs'!$D$8:$D$2007,A9,'7) Allocations - DA Costs'!$C$8:$C$2007,">="&'14) Model Calc'!$B$9,'7) Allocations - DA Costs'!$C$8:$C$2007,"<="&'14) Model Calc'!$B$10))) -> 1798.53 | J9: =H9-I9 -> 10.845 | K9: =IF(H9=0,"",J9/H9) -> 0.0059937824 | L9: =IF('1) Budget-Actuals Dashboard'!$K$4="100% fEC",SUMIFS('8) Commitments Forecast'!$Q$8:$Q$507,'8) Commitments Forecast'!$H$8:$H$507,A9),IF('1) Budget-Actuals Dashboard'!$K$4="UKRI",SUMIFS('8) Commitments Forecast'!$R$8:$R$507,'8) Commitments Forecast'!$H$8:$H$507,A9),SUMIFS('8) Commitments Forecast'!$S$8:$S$507,'8) Commitments Forecast'!$H$8:$H$507,A9))) -> 0 | M9: =IFERROR(IF('1) Budget-Actuals Dashboard'!$K$4="100% fEC",INDEX('3) Forecast Bridge'!$L$8:$L$37,MATCH(A9,'3) Forecast Bridge'!$A$8:$A$37,0)),IF('1) Budget-Actuals Dashboard'!$K$4="UKRI",INDEX('3) Forecast Bridge'!$P$8:$P$37,MATCH(A9,'3) Forecast Bridge'!$A$8:$A$37,0)),INDEX('3) Forecast Bridge'!$Q$8:$Q$37,MATCH(A9,'3) Forecast Bridge'!$A$8:$A$37,0)))),0) -> 0
A10: WP1_S03 | B10: RUSI - Programme/Project Lead (existing staff, DA) @GrE/14 | C10: WP1 | D10: Directly Allocated | E10: Staff | F10: Directly Allocated Staff | G10: =IF(AND(OR('1) Budget-Actuals Dashboard'!$C$5="All",C10='1) Budget-Actuals Dashboard'!$C$5),OR('1) Budget-Actuals Dashboard'!$G$5="All",D10='1) Budget-Actuals Dashboard'!$G$5),OR('1) Budget-Actuals Dashboard'!$K$5="All",E10='1) Budget-Actuals Dashboard'!$K$5)),"Yes","No") -> No | H10: =IF('1) Budget-Actuals Dashboard'!$K$4="100% fEC",SUMIFS('9) Budget Baseline'!$P$8:$P$1087,'9) Budget Baseline'!$B$8:$B$1087,A10,'9) Budget Baseline'!$H$8:$H$1087,">="&'14) Model Calc'!$B$9,'9) Budget Baseline'!$H$8:$H$1087,"<="&'14) Model Calc'!$B$10),IF('1) Budget-Actuals Dashboard'!$K$4="UKRI",SUMIFS('9) Budget Baseline'!$Q$8:$Q$1087,'9) Budget Baseline'!$B$8:$B$1087,A10,'9) Budget Baseline'!$H$8:$H$1087,">="&'14) Model Calc'!$B$9,'9) Budget Baseline'!$H$8:$H$1087,"<="&'14) Model Calc'!$B$10),SUMIFS('9) Budget Baseline'!$R$8:$R$1087,'9) Budget Baseline'!$B$8:$B$1087,A10,'9) Budget Baseline'!$H$8:$H$1087,">="&'14) Model Calc'!$B$9,'9) Budget Baseline'!$H$8:$H$1087,"<="&'14) Model Calc'!$B$10))) -> 1856.25 | I10: =IF('1) Budget-Actuals Dashboard'!$K$4="100% fEC",SUMIFS('6) Actuals Ledger - DI Costs'!$R$8:$R$2007,'6) Actuals Ledger - DI Costs'!$G$8:$G$2007,A10,'6) Actuals Ledger - DI Costs'!$C$8:$C$2007,">="&'14) Model Calc'!$B$9,'6) Actuals Ledger - DI Costs'!$C$8:$C$2007,"<="&'14) Model Calc'!$B$10)+SUMIFS('7) Allocations - DA Costs'!$O$8:$O$2007,'7) Allocations - DA Costs'!$D$8:$D$2007,A10,'7) Allocations - DA Costs'!$C$8:$C$2007,">="&'14) Model Calc'!$B$9,'7) Allocations - DA Costs'!$C$8:$C$2007,"<="&'14) Model Calc'!$B$10),IF('1) Budget-Actuals Dashboard'!$K$4="UKRI",SUMIFS('6) Actuals Ledger - DI Costs'!$S$8:$S$2007,'6) Actuals Ledger - DI Costs'!$G$8:$G$2007,A10,'6) Actuals Ledger - DI Costs'!$C$8:$C$2007,">="&'14) Model Calc'!$B$9,'6) Actuals Ledger - DI Costs'!$C$8:$C$2007,"<="&'14) Model Calc'!$B$10)+SUMIFS('7) Allocations - DA Costs'!$P$8:$P$2007,'7) Allocations - DA Costs'!$D$8:$D$2007,A10,'7) Allocations - DA Costs'!$C$8:$C$2007,">="&'14) Model Calc'!$B$9,'7) Allocations - DA Costs'!$C$8:$C$2007,"<="&'14) Model Calc'!$B$10),SUMIFS('6) Actuals Ledger - DI Costs'!$T$8:$T$2007,'6) Actuals Ledger - DI Costs'!$G$8:$G$2007,A10,'6) Actuals Ledger - DI Costs'!$C$8:$C$2007,">="&'14) Model Calc'!$B$9,'6) Actuals Ledger - DI Costs'!$C$8:$C$2007,"<="&'14) Model Calc'!$B$10)+SUMIFS('7) Allocations - DA Costs'!$Q$8:$Q$2007,'7) Allocations - DA Costs'!$D$8:$D$2007,A10,'7) Allocations - DA Costs'!$C$8:$C$2007,">="&'14) Model Calc'!$B$9,'7) Allocations - DA Costs'!$C$8:$C$2007,"<="&'14) Model Calc'!$B$10))) -> 1845.11 | J10: =H10-I10 -> 11.14 | K10: =IF(H10=0,"",J10/H10) -> 0.0060013468 | L10: =IF('1) Budget-Actuals Dashboard'!$K$4="100% fEC",SUMIFS('8) Commitments Forecast'!$Q$8:$Q$507,'8) Commitments Forecast'!$H$8:$H$507,A10),IF('1) Budget-Actuals Dashboard'!$K$4="UKRI",SUMIFS('8) Commitments Forecast'!$R$8:$R$507,'8) Commitments Forecast'!$H$8:$H$507,A10),SUMIFS('8) Commitments Forecast'!$S$8:$S$507,'8) Commitments Forecast'!$H$8:$H$507,A10))) -> 0 | M10: =IFERROR(IF('1) Budget-Actuals Dashboard'!$K$4="100% fEC",INDEX('3) Forecast Bridge'!$L$8:$L$37,MATCH(A10,'3) Forecast Bridge'!$A$8:$A$37,0)),IF('1) Budget-Actuals Dashboard'!$K$4="UKRI",INDEX('3) Forecast Bridge'!$P$8:$P$37,MATCH(A10,'3) Forecast Bridge'!$A$8:$A$37,0)),INDEX('3) Forecast Bridge'!$Q$8:$Q$37,MATCH(A10,'3) Forecast Bridge'!$A$8:$A$37,0)))),0) -> 0
A11: WP1_TRAVEL | B11: RUSI - UK rail, local travel and subsistence Budget | C11: WP1 | D11: Directly Incurred | E11: Travel & Subsistence | F11: Travel & Subsistence | G11: =IF(AND(OR('1) Budget-Actuals Dashboard'!$C$5="All",C11='1) Budget-Actuals Dashboard'!$C$5),OR('1) Budget-Actuals Dashboard'!$G$5="All",D11='1) Budget-Actuals Dashboard'!$G$5),OR('1) Budget-Actuals Dashboard'!$K$5="All",E11='1) Budget-Actuals Dashboard'!$K$5)),"Yes","No") -> Yes | H11: =IF('1) Budget-Actuals Dashboard'!$K$4="100% fEC",SUMIFS('9) Budget Baseline'!$P$8:$P$1087,'9) Budget Baseline'!$B$8:$B$1087,A11,'9) Budget Baseline'!$H$8:$H$1087,">="&'14) Model Calc'!$B$9,'9) Budget Baseline'!$H$8:$H$1087,"<="&'14) Model Calc'!$B$10),IF('1) Budget-Actuals Dashboard'!$K$4="UKRI",SUMIFS('9) Budget Baseline'!$Q$8:$Q$1087,'9) Budget Baseline'!$B$8:$B$1087,A11,'9) Budget Baseline'!$H$8:$H$1087,">="&'14) Model Calc'!$B$9,'9) Budget Baseline'!$H$8:$H$1087,"<="&'14) Model Calc'!$B$10),SUMIFS('9) Budget Baseline'!$R$8:$R$1087,'9) Budget Baseline'!$B$8:$B$1087,A11,'9) Budget Baseline'!$H$8:$H$1087,">="&'14) Model Calc'!$B$9,'9) Budget Baseline'!$H$8:$H$1087,"<="&'14) Model Calc'!$B$10))) -> 1041.6667 | I11: =IF('1) Budget-Actuals Dashboard'!$K$4="100% fEC",SUMIFS('6) Actuals Ledger - DI Costs'!$R$8:$R$2007,'6) Actuals Ledger - DI Costs'!$G$8:$G$2007,A11,'6) Actuals Ledger - DI Costs'!$C$8:$C$2007,">="&'14) Model Calc'!$B$9,'6) Actuals Ledger - DI Costs'!$C$8:$C$2007,"<="&'14) Model Calc'!$B$10)+SUMIFS('7) Allocations - DA Costs'!$O$8:$O$2007,'7) Allocations - DA Costs'!$D$8:$D$2007,A11,'7) Allocations - DA Costs'!$C$8:$C$2007,">="&'14) Model Calc'!$B$9,'7) Allocations - DA Costs'!$C$8:$C$2007,"<="&'14) Model Calc'!$B$10),IF('1) Budget-Actuals Dashboard'!$K$4="UKRI",SUMIFS('6) Actuals Ledger - DI Costs'!$S$8:$S$2007,'6) Actuals Ledger - DI Costs'!$G$8:$G$2007,A11,'6) Actuals Ledger - DI Costs'!$C$8:$C$2007,">="&'14) Model Calc'!$B$9,'6) Actuals Ledger - DI Costs'!$C$8:$C$2007,"<="&'14) Model Calc'!$B$10)+SUMIFS('7) Allocations - DA Costs'!$P$8:$P$2007,'7) Allocations - DA Costs'!$D$8:$D$2007,A11,'7) Allocations - DA Costs'!$C$8:$C$2007,">="&'14) Model Calc'!$B$9,'7) Allocations - DA Costs'!$C$8:$C$2007,"<="&'14) Model Calc'!$B$10),SUMIFS('6) Actuals Ledger - DI Costs'!$T$8:$T$2007,'6) Actuals Ledger - DI Costs'!$G$8:$G$2007,A11,'6) Actuals Ledger - DI Costs'!$C$8:$C$2007,">="&'14) Model Calc'!$B$9,'6) Actuals Ledger - DI Costs'!$C$8:$C$2007,"<="&'14) Model Calc'!$B$10)+SUMIFS('7) Allocations - DA Costs'!$Q$8:$Q$2007,'7) Allocations - DA Costs'!$D$8:$D$2007,A11,'7) Allocations - DA Costs'!$C$8:$C$2007,">="&'14) Model Calc'!$B$9,'7) Allocations - DA Costs'!$C$8:$C$2007,"<="&'14) Model Calc'!$B$10))) -> 1356.2 | J11: =H11-I11 -> -314.53333 | K11: =IF(H11=0,"",J11/H11) -> -0.301952 | L11: =IF('1) Budget-Actuals Dashboard'!$K$4="100% fEC",SUMIFS('8) Commitments Forecast'!$Q$8:$Q$507,'8) Commitments Forecast'!$H$8:$H$507,A11),IF('1) Budget-Actuals Dashboard'!$K$4="UKRI",SUMIFS('8) Commitments Forecast'!$R$8:$R$507,'8) Commitments Forecast'!$H$8:$H$507,A11),SUMIFS('8) Commitments Forecast'!$S$8:$S$507,'8) Commitments Forecast'!$H$8:$H$507,A11))) -> 0 | M11: =IFERROR(IF('1) Budget-Actuals Dashboard'!$K$4="100% fEC",INDEX('3) Forecast Bridge'!$L$8:$L$37,MATCH(A11,'3) Forecast Bridge'!$A$8:$A$37,0)),IF('1) Budget-Actuals Dashboard'!$K$4="UKRI",INDEX('3) Forecast Bridge'!$P$8:$P$37,MATCH(A11,'3) Forecast Bridge'!$A$8:$A$37,0)),INDEX('3) Forecast Bridge'!$Q$8:$Q$37,MATCH(A11,'3) Forecast Bridge'!$A$8:$A$37,0)))),0) -> 0
A12: WP1_CONF | B12: RUSI - five-day flagship London conferences (launch and close) | C12: WP1 | D12: Directly Incurred | E12: Other Directly Incurred | F12: Conferences | G12: =IF(AND(OR('1) Budget-Actuals Dashboard'!$C$5="All",C12='1) Budget-Actuals Dashboard'!$C$5),OR('1) Budget-Actuals Dashboard'!$G$5="All",D12='1) Budget-Actuals Dashboard'!$G$5),OR('1) Budget-Actuals Dashboard'!$K$5="All",E12='1) Budget-Actuals Dashboard'!$K$5)),"Yes","No") -> Yes | H12: =IF('1) Budget-Actuals Dashboard'!$K$4="100% fEC",SUMIFS('9) Budget Baseline'!$P$8:$P$1087,'9) Budget Baseline'!$B$8:$B$1087,A12,'9) Budget Baseline'!$H$8:$H$1087,">="&'14) Model Calc'!$B$9,'9) Budget Baseline'!$H$8:$H$1087,"<="&'14) Model Calc'!$B$10),IF('1) Budget-Actuals Dashboard'!$K$4="UKRI",SUMIFS('9) Budget Baseline'!$Q$8:$Q$1087,'9) Budget Baseline'!$B$8:$B$1087,A12,'9) Budget Baseline'!$H$8:$H$1087,">="&'14) Model Calc'!$B$9,'9) Budget Baseline'!$H$8:$H$1087,"<="&'14) Model Calc'!$B$10),SUMIFS('9) Budget Baseline'!$R$8:$R$1087,'9) Budget Baseline'!$B$8:$B$1087,A12,'9) Budget Baseline'!$H$8:$H$1087,">="&'14) Model Calc'!$B$9,'9) Budget Baseline'!$H$8:$H$1087,"<="&'14) Model Calc'!$B$10))) -> 0 | I12: =IF('1) Budget-Actuals Dashboard'!$K$4="100% fEC",SUMIFS('6) Actuals Ledger - DI Costs'!$R$8:$R$2007,'6) Actuals Ledger - DI Costs'!$G$8:$G$2007,A12,'6) Actuals Ledger - DI Costs'!$C$8:$C$2007,">="&'14) Model Calc'!$B$9,'6) Actuals Ledger - DI Costs'!$C$8:$C$2007,"<="&'14) Model Calc'!$B$10)+SUMIFS('7) Allocations - DA Costs'!$O$8:$O$2007,'7) Allocations - DA Costs'!$D$8:$D$2007,A12,'7) Allocations - DA Costs'!$C$8:$C$2007,">="&'14) Model Calc'!$B$9,'7) Allocations - DA Costs'!$C$8:$C$2007,"<="&'14) Model Calc'!$B$10),IF('1) Budget-Actuals Dashboard'!$K$4="UKRI",SUMIFS('6) Actuals Ledger - DI Costs'!$S$8:$S$2007,'6) Actuals Ledger - DI Costs'!$G$8:$G$2007,A12,'6) Actuals Ledger - DI Costs'!$C$8:$C$2007,">="&'14) Model Calc'!$B$9,'6) Actuals Ledger - DI Costs'!$C$8:$C$2007,"<="&'14) Model Calc'!$B$10)+SUMIFS('7) Allocations - DA Costs'!$P$8:$P$2007,'7) Allocations - DA Costs'!$D$8:$D$2007,A12,'7) Allocations - DA Costs'!$C$8:$C$2007,">="&'14) Model Calc'!$B$9,'7) Allocations - DA Costs'!$C$8:$C$2007,"<="&'14) Model Calc'!$B$10),SUMIFS('6) Actuals Ledger - DI Costs'!$T$8:$T$2007,'6) Actuals Ledger - DI Costs'!$G$8:$G$2007,A12,'6) Actuals Ledger - DI Costs'!$C$8:$C$2007,">="&'14) Model Calc'!$B$9,'6) Actuals Ledger - DI Costs'!$C$8:$C$2007,"<="&'14) Model Calc'!$B$10)+SUMIFS('7) Allocations - DA Costs'!$Q$8:$Q$2007,'7) Allocations - DA Costs'!$D$8:$D$2007,A12,'7) Allocations - DA Costs'!$C$8:$C$2007,">="&'14) Model Calc'!$B$9,'7) Allocations - DA Costs'!$C$8:$C$2007,"<="&'14) Model Calc'!$B$10))) -> 0 | J12: =H12-I12 -> 0 | K12: =IF(H12=0,"",J12/H12) | L12: =IF('1) Budget-Actuals Dashboard'!$K$4="100% fEC",SUMIFS('8) Commitments Forecast'!$Q$8:$Q$507,'8) Commitments Forecast'!$H$8:$H$507,A12),IF('1) Budget-Actuals Dashboard'!$K$4="UKRI",SUMIFS('8) Commitments Forecast'!$R$8:$R$507,'8) Commitments Forecast'!$H$8:$H$507,A12),SUMIFS('8) Commitments Forecast'!$S$8:$S$507,'8) Commitments Forecast'!$H$8:$H$507,A12))) -> 14700 | M12: =IFERROR(IF('1) Budget-Actuals Dashboard'!$K$4="100% fEC",INDEX('3) Forecast Bridge'!$L$8:$L$37,MATCH(A12,'3) Forecast Bridge'!$A$8:$A$37,0)),IF('1) Budget-Actuals Dashboard'!$K$4="UKRI",INDEX('3) Forecast Bridge'!$P$8:$P$37,MATCH(A12,'3) Forecast Bridge'!$A$8:$A$37,0)),INDEX('3) Forecast Bridge'!$Q$8:$Q$37,MATCH(A12,'3) Forecast Bridge'!$A$8:$A$37,0)))),0) -> -1800
A13: WP1_WORKSHOP | B13: RUSI - UK national and regional workshops | C13: WP1 | D13: Directly Incurred | E13: Other Directly Incurred | F13: Workshops | G13: =IF(AND(OR('1) Budget-Actuals Dashboard'!$C$5="All",C13='1) Budget-Actuals Dashboard'!$C$5),OR('1) Budget-Actuals Dashboard'!$G$5="All",D13='1) Budget-Actuals Dashboard'!$G$5),OR('1) Budget-Actuals Dashboard'!$K$5="All",E13='1) Budget-Actuals Dashboard'!$K$5)),"Yes","No") -> Yes | H13: =IF('1) Budget-Actuals Dashboard'!$K$4="100% fEC",SUMIFS('9) Budget Baseline'!$P$8:$P$1087,'9) Budget Baseline'!$B$8:$B$1087,A13,'9) Budget Baseline'!$H$8:$H$1087,">="&'14) Model Calc'!$B$9,'9) Budget Baseline'!$H$8:$H$1087,"<="&'14) Model Calc'!$B$10),IF('1) Budget-Actuals Dashboard'!$K$4="UKRI",SUMIFS('9) Budget Baseline'!$Q$8:$Q$1087,'9) Budget Baseline'!$B$8:$B$1087,A13,'9) Budget Baseline'!$H$8:$H$1087,">="&'14) Model Calc'!$B$9,'9) Budget Baseline'!$H$8:$H$1087,"<="&'14) Model Calc'!$B$10),SUMIFS('9) Budget Baseline'!$R$8:$R$1087,'9) Budget Baseline'!$B$8:$B$1087,A13,'9) Budget Baseline'!$H$8:$H$1087,">="&'14) Model Calc'!$B$9,'9) Budget Baseline'!$H$8:$H$1087,"<="&'14) Model Calc'!$B$10))) -> 1666.6667 | I13: =IF('1) Budget-Actuals Dashboard'!$K$4="100% fEC",SUMIFS('6) Actuals Ledger - DI Costs'!$R$8:$R$2007,'6) Actuals Ledger - DI Costs'!$G$8:$G$2007,A13,'6) Actuals Ledger - DI Costs'!$C$8:$C$2007,">="&'14) Model Calc'!$B$9,'6) Actuals Ledger - DI Costs'!$C$8:$C$2007,"<="&'14) Model Calc'!$B$10)+SUMIFS('7) Allocations - DA Costs'!$O$8:$O$2007,'7) Allocations - DA Costs'!$D$8:$D$2007,A13,'7) Allocations - DA Costs'!$C$8:$C$2007,">="&'14) Model Calc'!$B$9,'7) Allocations - DA Costs'!$C$8:$C$2007,"<="&'14) Model Calc'!$B$10),IF('1) Budget-Actuals Dashboard'!$K$4="UKRI",SUMIFS('6) Actuals Ledger - DI Costs'!$S$8:$S$2007,'6) Actuals Ledger - DI Costs'!$G$8:$G$2007,A13,'6) Actuals Ledger - DI Costs'!$C$8:$C$2007,">="&'14) Model Calc'!$B$9,'6) Actuals Ledger - DI Costs'!$C$8:$C$2007,"<="&'14) Model Calc'!$B$10)+SUMIFS('7) Allocations - DA Costs'!$P$8:$P$2007,'7) Allocations - DA Costs'!$D$8:$D$2007,A13,'7) Allocations - DA Costs'!$C$8:$C$2007,">="&'14) Model Calc'!$B$9,'7) Allocations - DA Costs'!$C$8:$C$2007,"<="&'14) Model Calc'!$B$10),SUMIFS('6) Actuals Ledger - DI Costs'!$T$8:$T$2007,'6) Actuals Ledger - DI Costs'!$G$8:$G$2007,A13,'6) Actuals Ledger - DI Costs'!$C$8:$C$2007,">="&'14) Model Calc'!$B$9,'6) Actuals Ledger - DI Costs'!$C$8:$C$2007,"<="&'14) Model Calc'!$B$10)+SUMIFS('7) Allocations - DA Costs'!$Q$8:$Q$2007,'7) Allocations - DA Costs'!$D$8:$D$2007,A13,'7) Allocations - DA Costs'!$C$8:$C$2007,">="&'14) Model Calc'!$B$9,'7) Allocations - DA Costs'!$C$8:$C$2007,"<="&'14) Model Calc'!$B$10))) -> 2150 | J13: =H13-I13 -> -483.33333 | K13: =IF(H13=0,"",J13/H13) -> -0.29 | L13: =IF('1) Budget-Actuals Dashboard'!$K$4="100% fEC",SUMIFS('8) Commitments Forecast'!$Q$8:$Q$507,'8) Commitments Forecast'!$H$8:$H$507,A13),IF('1) Budget-Actuals Dashboard'!$K$4="UKRI",SUMIFS('8) Commitments Forecast'!$R$8:$R$507,'8) Commitments Forecast'!$H$8:$H$507,A13),SUMIFS('8) Commitments Forecast'!$S$8:$S$507,'8) Commitments Forecast'!$H$8:$H$507,A13))) -> 1200 | M13: =IFERROR(IF('1) Budget-Actuals Dashboard'!$K$4="100% fEC",INDEX('3) Forecast Bridge'!$L$8:$L$37,MATCH(A13,'3) Forecast Bridge'!$A$8:$A$37,0)),IF('1) Budget-Actuals Dashboard'!$K$4="UKRI",INDEX('3) Forecast Bridge'!$P$8:$P$37,MATCH(A13,'3) Forecast Bridge'!$A$8:$A$37,0)),INDEX('3) Forecast Bridge'!$Q$8:$Q$37,MATCH(A13,'3) Forecast Bridge'!$A$8:$A$37,0)))),0) -> 0
A14: WP1_PANEL | B14: RUSI - hybrid panels and practitioner roundtables | C14: WP1 | D14: Directly Incurred | E14: Other Directly Incurred | F14: Panels & Roundtables | G14: =IF(AND(OR('1) Budget-Actuals Dashboard'!$C$5="All",C14='1) Budget-Actuals Dashboard'!$C$5),OR('1) Budget-Actuals Dashboard'!$G$5="All",D14='1) Budget-Actuals Dashboard'!$G$5),OR('1) Budget-Actuals Dashboard'!$K$5="All",E14='1) Budget-Actuals Dashboard'!$K$5)),"Yes","No") -> Yes | H14: =IF('1) Budget-Actuals Dashboard'!$K$4="100% fEC",SUMIFS('9) Budget Baseline'!$P$8:$P$1087,'9) Budget Baseline'!$B$8:$B$1087,A14,'9) Budget Baseline'!$H$8:$H$1087,">="&'14) Model Calc'!$B$9,'9) Budget Baseline'!$H$8:$H$1087,"<="&'14) Model Calc'!$B$10),IF('1) Budget-Actuals Dashboard'!$K$4="UKRI",SUMIFS('9) Budget Baseline'!$Q$8:$Q$1087,'9) Budget Baseline'!$B$8:$B$1087,A14,'9) Budget Baseline'!$H$8:$H$1087,">="&'14) Model Calc'!$B$9,'9) Budget Baseline'!$H$8:$H$1087,"<="&'14) Model Calc'!$B$10),SUMIFS('9) Budget Baseline'!$R$8:$R$1087,'9) Budget Baseline'!$B$8:$B$1087,A14,'9) Budget Baseline'!$H$8:$H$1087,">="&'14) Model Calc'!$B$9,'9) Budget Baseline'!$H$8:$H$1087,"<="&'14) Model Calc'!$B$10))) -> 625 | I14: =IF('1) Budget-Actuals Dashboard'!$K$4="100% fEC",SUMIFS('6) Actuals Ledger - DI Costs'!$R$8:$R$2007,'6) Actuals Ledger - DI Costs'!$G$8:$G$2007,A14,'6) Actuals Ledger - DI Costs'!$C$8:$C$2007,">="&'14) Model Calc'!$B$9,'6) Actuals Ledger - DI Costs'!$C$8:$C$2007,"<="&'14) Model Calc'!$B$10)+SUMIFS('7) Allocations - DA Costs'!$O$8:$O$2007,'7) Allocations - DA Costs'!$D$8:$D$2007,A14,'7) Allocations - DA Costs'!$C$8:$C$2007,">="&'14) Model Calc'!$B$9,'7) Allocations - DA Costs'!$C$8:$C$2007,"<="&'14) Model Calc'!$B$10),IF('1) Budget-Actuals Dashboard'!$K$4="UKRI",SUMIFS('6) Actuals Ledger - DI Costs'!$S$8:$S$2007,'6) Actuals Ledger - DI Costs'!$G$8:$G$2007,A14,'6) Actuals Ledger - DI Costs'!$C$8:$C$2007,">="&'14) Model Calc'!$B$9,'6) Actuals Ledger - DI Costs'!$C$8:$C$2007,"<="&'14) Model Calc'!$B$10)+SUMIFS('7) Allocations - DA Costs'!$P$8:$P$2007,'7) Allocations - DA Costs'!$D$8:$D$2007,A14,'7) Allocations - DA Costs'!$C$8:$C$2007,">="&'14) Model Calc'!$B$9,'7) Allocations - DA Costs'!$C$8:$C$2007,"<="&'14) Model Calc'!$B$10),SUMIFS('6) Actuals Ledger - DI Costs'!$T$8:$T$2007,'6) Actuals Ledger - DI Costs'!$G$8:$G$2007,A14,'6) Actuals Ledger - DI Costs'!$C$8:$C$2007,">="&'14) Model Calc'!$B$9,'6) Actuals Ledger - DI Costs'!$C$8:$C$2007,"<="&'14) Model Calc'!$B$10)+SUMIFS('7) Allocations - DA Costs'!$Q$8:$Q$2007,'7) Allocations - DA Costs'!$D$8:$D$2007,A14,'7) Allocations - DA Costs'!$C$8:$C$2007,">="&'14) Model Calc'!$B$9,'7) Allocations - DA Costs'!$C$8:$C$2007,"<="&'14) Model Calc'!$B$10))) -> 790 | J14: =H14-I14 -> -165 | K14: =IF(H14=0,"",J14/H14) -> -0.264 | L14: =IF('1) Budget-Actuals Dashboard'!$K$4="100% fEC",SUMIFS('8) Commitments Forecast'!$Q$8:$Q$507,'8) Commitments Forecast'!$H$8:$H$507,A14),IF('1) Budget-Actuals Dashboard'!$K$4="UKRI",SUMIFS('8) Commitments Forecast'!$R$8:$R$507,'8) Commitments Forecast'!$H$8:$H$507,A14),SUMIFS('8) Commitments Forecast'!$S$8:$S$507,'8) Commitments Forecast'!$H$8:$H$507,A14))) -> 0 | M14: =IFERROR(IF('1) Budget-Actuals Dashboard'!$K$4="100% fEC",INDEX('3) Forecast Bridge'!$L$8:$L$37,MATCH(A14,'3) Forecast Bridge'!$A$8:$A$37,0)),IF('1) Budget-Actuals Dashboard'!$K$4="UKRI",INDEX('3) Forecast Bridge'!$P$8:$P$37,MATCH(A14,'3) Forecast Bridge'!$A$8:$A$37,0)),INDEX('3) Forecast Bridge'!$Q$8:$Q$37,MATCH(A14,'3) Forecast Bridge'!$A$8:$A$37,0)))),0) -> 0
A15: WP1_COMMS | B15: RUSI - knowledge products and digital communications | C15: WP1 | D15: Directly Incurred | E15: Other Directly Incurred | F15: Communications & Knowledge Products | G15: =IF(AND(OR('1) Budget-Actuals Dashboard'!$C$5="All",C15='1) Budget-Actuals Dashboard'!$C$5),OR('1) Budget-Actuals Dashboard'!$G$5="All",D15='1) Budget-Actuals Dashboard'!$G$5),OR('1) Budget-Actuals Dashboard'!$K$5="All",E15='1) Budget-Actuals Dashboard'!$K$5)),"Yes","No") -> Yes | H15: =IF('1) Budget-Actuals Dashboard'!$K$4="100% fEC",SUMIFS('9) Budget Baseline'!$P$8:$P$1087,'9) Budget Baseline'!$B$8:$B$1087,A15,'9) Budget Baseline'!$H$8:$H$1087,">="&'14) Model Calc'!$B$9,'9) Budget Baseline'!$H$8:$H$1087,"<="&'14) Model Calc'!$B$10),IF('1) Budget-Actuals Dashboard'!$K$4="UKRI",SUMIFS('9) Budget Baseline'!$Q$8:$Q$1087,'9) Budget Baseline'!$B$8:$B$1087,A15,'9) Budget Baseline'!$H$8:$H$1087,">="&'14) Model Calc'!$B$9,'9) Budget Baseline'!$H$8:$H$1087,"<="&'14) Model Calc'!$B$10),SUMIFS('9) Budget Baseline'!$R$8:$R$1087,'9) Budget Baseline'!$B$8:$B$1087,A15,'9) Budget Baseline'!$H$8:$H$1087,">="&'14) Model Calc'!$B$9,'9) Budget Baseline'!$H$8:$H$1087,"<="&'14) Model Calc'!$B$10))) -> 416.66667 | I15: =IF('1) Budget-Actuals Dashboard'!$K$4="100% fEC",SUMIFS('6) Actuals Ledger - DI Costs'!$R$8:$R$2007,'6) Actuals Ledger - DI Costs'!$G$8:$G$2007,A15,'6) Actuals Ledger - DI Costs'!$C$8:$C$2007,">="&'14) Model Calc'!$B$9,'6) Actuals Ledger - DI Costs'!$C$8:$C$2007,"<="&'14) Model Calc'!$B$10)+SUMIFS('7) Allocations - DA Costs'!$O$8:$O$2007,'7) Allocations - DA Costs'!$D$8:$D$2007,A15,'7) Allocations - DA Costs'!$C$8:$C$2007,">="&'14) Model Calc'!$B$9,'7) Allocations - DA Costs'!$C$8:$C$2007,"<="&'14) Model Calc'!$B$10),IF('1) Budget-Actuals Dashboard'!$K$4="UKRI",SUMIFS('6) Actuals Ledger - DI Costs'!$S$8:$S$2007,'6) Actuals Ledger - DI Costs'!$G$8:$G$2007,A15,'6) Actuals Ledger - DI Costs'!$C$8:$C$2007,">="&'14) Model Calc'!$B$9,'6) Actuals Ledger - DI Costs'!$C$8:$C$2007,"<="&'14) Model Calc'!$B$10)+SUMIFS('7) Allocations - DA Costs'!$P$8:$P$2007,'7) Allocations - DA Costs'!$D$8:$D$2007,A15,'7) Allocations - DA Costs'!$C$8:$C$2007,">="&'14) Model Calc'!$B$9,'7) Allocations - DA Costs'!$C$8:$C$2007,"<="&'14) Model Calc'!$B$10),SUMIFS('6) Actuals Ledger - DI Costs'!$T$8:$T$2007,'6) Actuals Ledger - DI Costs'!$G$8:$G$2007,A15,'6) Actuals Ledger - DI Costs'!$C$8:$C$2007,">="&'14) Model Calc'!$B$9,'6) Actuals Ledger - DI Costs'!$C$8:$C$2007,"<="&'14) Model Calc'!$B$10)+SUMIFS('7) Allocations - DA Costs'!$Q$8:$Q$2007,'7) Allocations - DA Costs'!$D$8:$D$2007,A15,'7) Allocations - DA Costs'!$C$8:$C$2007,">="&'14) Model Calc'!$B$9,'7) Allocations - DA Costs'!$C$8:$C$2007,"<="&'14) Model Calc'!$B$10))) -> 575 | J15: =H15-I15 -> -158.33333 | K15: =IF(H15=0,"",J15/H15) -> -0.38 | L15: =IF('1) Budget-Actuals Dashboard'!$K$4="100% fEC",SUMIFS('8) Commitments Forecast'!$Q$8:$Q$507,'8) Commitments Forecast'!$H$8:$H$507,A15),IF('1) Budget-Actuals Dashboard'!$K$4="UKRI",SUMIFS('8) Commitments Forecast'!$R$8:$R$507,'8) Commitments Forecast'!$H$8:$H$507,A15),SUMIFS('8) Commitments Forecast'!$S$8:$S$507,'8) Commitments Forecast'!$H$8:$H$507,A15))) -> 450 | M15: =IFERROR(IF('1) Budget-Actuals Dashboard'!$K$4="100% fEC",INDEX('3) Forecast Bridge'!$L$8:$L$37,MATCH(A15,'3) Forecast Bridge'!$A$8:$A$37,0)),IF('1) Budget-Actuals Dashboard'!$K$4="UKRI",INDEX('3) Forecast Bridge'!$P$8:$P$37,MATCH(A15,'3) Forecast Bridge'!$A$8:$A$37,0)),INDEX('3) Forecast Bridge'!$Q$8:$Q$37,MATCH(A15,'3) Forecast Bridge'!$A$8:$A$37,0)))),0) -> 100
A16: WP1_IND | B16: RUSI - indirect allocation (dispensation proxy × eligible staff FTE) | C16: WP1 | D16: Indirect | E16: Indirect | F16: Indirect Costs | G16: =IF(AND(OR('1) Budget-Actuals Dashboard'!$C$5="All",C16='1) Budget-Actuals Dashboard'!$C$5),OR('1) Budget-Actuals Dashboard'!$G$5="All",D16='1) Budget-Actuals Dashboard'!$G$5),OR('1) Budget-Actuals Dashboard'!$K$5="All",E16='1) Budget-Actuals Dashboard'!$K$5)),"Yes","No") -> No | H16: =IF('1) Budget-Actuals Dashboard'!$K$4="100% fEC",SUMIFS('9) Budget Baseline'!$P$8:$P$1087,'9) Budget Baseline'!$B$8:$B$1087,A16,'9) Budget Baseline'!$H$8:$H$1087,">="&'14) Model Calc'!$B$9,'9) Budget Baseline'!$H$8:$H$1087,"<="&'14) Model Calc'!$B$10),IF('1) Budget-Actuals Dashboard'!$K$4="UKRI",SUMIFS('9) Budget Baseline'!$Q$8:$Q$1087,'9) Budget Baseline'!$B$8:$B$1087,A16,'9) Budget Baseline'!$H$8:$H$1087,">="&'14) Model Calc'!$B$9,'9) Budget Baseline'!$H$8:$H$1087,"<="&'14) Model Calc'!$B$10),SUMIFS('9) Budget Baseline'!$R$8:$R$1087,'9) Budget Baseline'!$B$8:$B$1087,A16,'9) Budget Baseline'!$H$8:$H$1087,">="&'14) Model Calc'!$B$9,'9) Budget Baseline'!$H$8:$H$1087,"<="&'14) Model Calc'!$B$10))) -> 5989.8958 | I16: =IF('1) Budget-Actuals Dashboard'!$K$4="100% fEC",SUMIFS('6) Actuals Ledger - DI Costs'!$R$8:$R$2007,'6) Actuals Ledger - DI Costs'!$G$8:$G$2007,A16,'6) Actuals Ledger - DI Costs'!$C$8:$C$2007,">="&'14) Model Calc'!$B$9,'6) Actuals Ledger - DI Costs'!$C$8:$C$2007,"<="&'14) Model Calc'!$B$10)+SUMIFS('7) Allocations - DA Costs'!$O$8:$O$2007,'7) Allocations - DA Costs'!$D$8:$D$2007,A16,'7) Allocations - DA Costs'!$C$8:$C$2007,">="&'14) Model Calc'!$B$9,'7) Allocations - DA Costs'!$C$8:$C$2007,"<="&'14) Model Calc'!$B$10),IF('1) Budget-Actuals Dashboard'!$K$4="UKRI",SUMIFS('6) Actuals Ledger - DI Costs'!$S$8:$S$2007,'6) Actuals Ledger - DI Costs'!$G$8:$G$2007,A16,'6) Actuals Ledger - DI Costs'!$C$8:$C$2007,">="&'14) Model Calc'!$B$9,'6) Actuals Ledger - DI Costs'!$C$8:$C$2007,"<="&'14) Model Calc'!$B$10)+SUMIFS('7) Allocations - DA Costs'!$P$8:$P$2007,'7) Allocations - DA Costs'!$D$8:$D$2007,A16,'7) Allocations - DA Costs'!$C$8:$C$2007,">="&'14) Model Calc'!$B$9,'7) Allocations - DA Costs'!$C$8:$C$2007,"<="&'14) Model Calc'!$B$10),SUMIFS('6) Actuals Ledger - DI Costs'!$T$8:$T$2007,'6) Actuals Ledger - DI Costs'!$G$8:$G$2007,A16,'6) Actuals Ledger - DI Costs'!$C$8:$C$2007,">="&'14) Model Calc'!$B$9,'6) Actuals Ledger - DI Costs'!$C$8:$C$2007,"<="&'14) Model Calc'!$B$10)+SUMIFS('7) Allocations - DA Costs'!$Q$8:$Q$2007,'7) Allocations - DA Costs'!$D$8:$D$2007,A16,'7) Allocations - DA Costs'!$C$8:$C$2007,">="&'14) Model Calc'!$B$9,'7) Allocations - DA Costs'!$C$8:$C$2007,"<="&'14) Model Calc'!$B$10))) -> 5953.96 | J16: =H16-I16 -> 35.935833 | K16: =IF(H16=0,"",J16/H16) -> 0.0059994087 | L16: =IF('1) Budget-Actuals Dashboard'!$K$4="100% fEC",SUMIFS('8) Commitments Forecast'!$Q$8:$Q$507,'8) Commitments Forecast'!$H$8:$H$507,A16),IF('1) Budget-Actuals Dashboard'!$K$4="UKRI",SUMIFS('8) Commitments Forecast'!$R$8:$R$507,'8) Commitments Forecast'!$H$8:$H$507,A16),SUMIFS('8) Commitments Forecast'!$S$8:$S$507,'8) Commitments Forecast'!$H$8:$H$507,A16))) -> 0 | M16: =IFERROR(IF('1) Budget-Actuals Dashboard'!$K$4="100% fEC",INDEX('3) Forecast Bridge'!$L$8:$L$37,MATCH(A16,'3) Forecast Bridge'!$A$8:$A$37,0)),IF('1) Budget-Actuals Dashboard'!$K$4="UKRI",INDEX('3) Forecast Bridge'!$P$8:$P$37,MATCH(A16,'3) Forecast Bridge'!$A$8:$A$37,0)),INDEX('3) Forecast Bridge'!$Q$8:$Q$37,MATCH(A16,'3) Forecast Bridge'!$A$8:$A$37,0)))),0) -> 0
A17: WP1_EST | B17: RUSI - non-laboratory estate allocation (dispensation proxy × eligible staff FTE) | C17: WP1 | D17: Directly Allocated | E17: Estates | F17: Estate Costs | G17: =IF(AND(OR('1) Budget-Actuals Dashboard'!$C$5="All",C17='1) Budget-Actuals Dashboard'!$C$5),OR('1) Budget-Actuals Dashboard'!$G$5="All",D17='1) Budget-Actuals Dashboard'!$G$5),OR('1) Budget-Actuals Dashboard'!$K$5="All",E17='1) Budget-Actuals Dashboard'!$K$5)),"Yes","No") -> No | H17: =IF('1) Budget-Actuals Dashboard'!$K$4="100% fEC",SUMIFS('9) Budget Baseline'!$P$8:$P$1087,'9) Budget Baseline'!$B$8:$B$1087,A17,'9) Budget Baseline'!$H$8:$H$1087,">="&'14) Model Calc'!$B$9,'9) Budget Baseline'!$H$8:$H$1087,"<="&'14) Model Calc'!$B$10),IF('1) Budget-Actuals Dashboard'!$K$4="UKRI",SUMIFS('9) Budget Baseline'!$Q$8:$Q$1087,'9) Budget Baseline'!$B$8:$B$1087,A17,'9) Budget Baseline'!$H$8:$H$1087,">="&'14) Model Calc'!$B$9,'9) Budget Baseline'!$H$8:$H$1087,"<="&'14) Model Calc'!$B$10),SUMIFS('9) Budget Baseline'!$R$8:$R$1087,'9) Budget Baseline'!$B$8:$B$1087,A17,'9) Budget Baseline'!$H$8:$H$1087,">="&'14) Model Calc'!$B$9,'9) Budget Baseline'!$H$8:$H$1087,"<="&'14) Model Calc'!$B$10))) -> 763.33333 | I17: =IF('1) Budget-Actuals Dashboard'!$K$4="100% fEC",SUMIFS('6) Actuals Ledger - DI Costs'!$R$8:$R$2007,'6) Actuals Ledger - DI Costs'!$G$8:$G$2007,A17,'6) Actuals Ledger - DI Costs'!$C$8:$C$2007,">="&'14) Model Calc'!$B$9,'6) Actuals Ledger - DI Costs'!$C$8:$C$2007,"<="&'14) Model Calc'!$B$10)+SUMIFS('7) Allocations - DA Costs'!$O$8:$O$2007,'7) Allocations - DA Costs'!$D$8:$D$2007,A17,'7) Allocations - DA Costs'!$C$8:$C$2007,">="&'14) Model Calc'!$B$9,'7) Allocations - DA Costs'!$C$8:$C$2007,"<="&'14) Model Calc'!$B$10),IF('1) Budget-Actuals Dashboard'!$K$4="UKRI",SUMIFS('6) Actuals Ledger - DI Costs'!$S$8:$S$2007,'6) Actuals Ledger - DI Costs'!$G$8:$G$2007,A17,'6) Actuals Ledger - DI Costs'!$C$8:$C$2007,">="&'14) Model Calc'!$B$9,'6) Actuals Ledger - DI Costs'!$C$8:$C$2007,"<="&'14) Model Calc'!$B$10)+SUMIFS('7) Allocations - DA Costs'!$P$8:$P$2007,'7) Allocations - DA Costs'!$D$8:$D$2007,A17,'7) Allocations - DA Costs'!$C$8:$C$2007,">="&'14) Model Calc'!$B$9,'7) Allocations - DA Costs'!$C$8:$C$2007,"<="&'14) Model Calc'!$B$10),SUMIFS('6) Actuals Ledger - DI Costs'!$T$8:$T$2007,'6) Actuals Ledger - DI Costs'!$G$8:$G$2007,A17,'6) Actuals Ledger - DI Costs'!$C$8:$C$2007,">="&'14) Model Calc'!$B$9,'6) Actuals Ledger - DI Costs'!$C$8:$C$2007,"<="&'14) Model Calc'!$B$10)+SUMIFS('7) Allocations - DA Costs'!$Q$8:$Q$2007,'7) Allocations - DA Costs'!$D$8:$D$2007,A17,'7) Allocations - DA Costs'!$C$8:$C$2007,">="&'14) Model Calc'!$B$9,'7) Allocations - DA Costs'!$C$8:$C$2007,"<="&'14) Model Calc'!$B$10))) -> 758.76 | J17: =H17-I17 -> 4.5733333 | K17: =IF(H17=0,"",J17/H17) -> 0.0059912664 | L17: =IF('1) Budget-Actuals Dashboard'!$K$4="100% fEC",SUMIFS('8) Commitments Forecast'!$Q$8:$Q$507,'8) Commitments Forecast'!$H$8:$H$507,A17),IF('1) Budget-Actuals Dashboard'!$K$4="UKRI",SUMIFS('8) Commitments Forecast'!$R$8:$R$507,'8) Commitments Forecast'!$H$8:$H$507,A17),SUMIFS('8) Commitments Forecast'!$S$8:$S$507,'8) Commitments Forecast'!$H$8:$H$507,A17))) -> 0 | M17: =IFERROR(IF('1) Budget-Actuals Dashboard'!$K$4="100% fEC",INDEX('3) Forecast Bridge'!$L$8:$L$37,MATCH(A17,'3) Forecast Bridge'!$A$8:$A$37,0)),IF('1) Budget-Actuals Dashboard'!$K$4="UKRI",INDEX('3) Forecast Bridge'!$P$8:$P$37,MATCH(A17,'3) Forecast Bridge'!$A$8:$A$37,0)),INDEX('3) Forecast Bridge'!$Q$8:$Q$37,MATCH(A17,'3) Forecast Bridge'!$A$8:$A$37,0)))),0) -> 0
A18: WP2_S01 | B18: RUSI - Project Officer (existing staff, DA) @GrB/4 | C18: WP2 | D18: Directly Allocated | E18: Staff | F18: Directly Allocated Staff | G18: =IF(AND(OR('1) Budget-Actuals Dashboard'!$C$5="All",C18='1) Budget-Actuals Dashboard'!$C$5),OR('1) Budget-Actuals Dashboard'!$G$5="All",D18='1) Budget-Actuals Dashboard'!$G$5),OR('1) Budget-Actuals Dashboard'!$K$5="All",E18='1) Budget-Actuals Dashboard'!$K$5)),"Yes","No") -> No | H18: =IF('1) Budget-Actuals Dashboard'!$K$4="100% fEC",SUMIFS('9) Budget Baseline'!$P$8:$P$1087,'9) Budget Baseline'!$B$8:$B$1087,A18,'9) Budget Baseline'!$H$8:$H$1087,">="&'14) Model Calc'!$B$9,'9) Budget Baseline'!$H$8:$H$1087,"<="&'14) Model Calc'!$B$10),IF('1) Budget-Actuals Dashboard'!$K$4="UKRI",SUMIFS('9) Budget Baseline'!$Q$8:$Q$1087,'9) Budget Baseline'!$B$8:$B$1087,A18,'9) Budget Baseline'!$H$8:$H$1087,">="&'14) Model Calc'!$B$9,'9) Budget Baseline'!$H$8:$H$1087,"<="&'14) Model Calc'!$B$10),SUMIFS('9) Budget Baseline'!$R$8:$R$1087,'9) Budget Baseline'!$B$8:$B$1087,A18,'9) Budget Baseline'!$H$8:$H$1087,">="&'14) Model Calc'!$B$9,'9) Budget Baseline'!$H$8:$H$1087,"<="&'14) Model Calc'!$B$10))) -> 490.625 | I18: =IF('1) Budget-Actuals Dashboard'!$K$4="100% fEC",SUMIFS('6) Actuals Ledger - DI Costs'!$R$8:$R$2007,'6) Actuals Ledger - DI Costs'!$G$8:$G$2007,A18,'6) Actuals Ledger - DI Costs'!$C$8:$C$2007,">="&'14) Model Calc'!$B$9,'6) Actuals Ledger - DI Costs'!$C$8:$C$2007,"<="&'14) Model Calc'!$B$10)+SUMIFS('7) Allocations - DA Costs'!$O$8:$O$2007,'7) Allocations - DA Costs'!$D$8:$D$2007,A18,'7) Allocations - DA Costs'!$C$8:$C$2007,">="&'14) Model Calc'!$B$9,'7) Allocations - DA Costs'!$C$8:$C$2007,"<="&'14) Model Calc'!$B$10),IF('1) Budget-Actuals Dashboard'!$K$4="UKRI",SUMIFS('6) Actuals Ledger - DI Costs'!$S$8:$S$2007,'6) Actuals Ledger - DI Costs'!$G$8:$G$2007,A18,'6) Actuals Ledger - DI Costs'!$C$8:$C$2007,">="&'14) Model Calc'!$B$9,'6) Actuals Ledger - DI Costs'!$C$8:$C$2007,"<="&'14) Model Calc'!$B$10)+SUMIFS('7) Allocations - DA Costs'!$P$8:$P$2007,'7) Allocations - DA Costs'!$D$8:$D$2007,A18,'7) Allocations - DA Costs'!$C$8:$C$2007,">="&'14) Model Calc'!$B$9,'7) Allocations - DA Costs'!$C$8:$C$2007,"<="&'14) Model Calc'!$B$10),SUMIFS('6) Actuals Ledger - DI Costs'!$T$8:$T$2007,'6) Actuals Ledger - DI Costs'!$G$8:$G$2007,A18,'6) Actuals Ledger - DI Costs'!$C$8:$C$2007,">="&'14) Model Calc'!$B$9,'6) Actuals Ledger - DI Costs'!$C$8:$C$2007,"<="&'14) Model Calc'!$B$10)+SUMIFS('7) Allocations - DA Costs'!$Q$8:$Q$2007,'7) Allocations - DA Costs'!$D$8:$D$2007,A18,'7) Allocations - DA Costs'!$C$8:$C$2007,">="&'14) Model Calc'!$B$9,'7) Allocations - DA Costs'!$C$8:$C$2007,"<="&'14) Model Calc'!$B$10))) -> 487.69 | J18: =H18-I18 -> 2.935 | K18: =IF(H18=0,"",J18/H18) -> 0.0059821656 | L18: =IF('1) Budget-Actuals Dashboard'!$K$4="100% fEC",SUMIFS('8) Commitments Forecast'!$Q$8:$Q$507,'8) Commitments Forecast'!$H$8:$H$507,A18),IF('1) Budget-Actuals Dashboard'!$K$4="UKRI",SUMIFS('8) Commitments Forecast'!$R$8:$R$507,'8) Commitments Forecast'!$H$8:$H$507,A18),SUMIFS('8) Commitments Forecast'!$S$8:$S$507,'8) Commitments Forecast'!$H$8:$H$507,A18))) -> 0 | M18: =IFERROR(IF('1) Budget-Actuals Dashboard'!$K$4="100% fEC",INDEX('3) Forecast Bridge'!$L$8:$L$37,MATCH(A18,'3) Forecast Bridge'!$A$8:$A$37,0)),IF('1) Budget-Actuals Dashboard'!$K$4="UKRI",INDEX('3) Forecast Bridge'!$P$8:$P$37,MATCH(A18,'3) Forecast Bridge'!$A$8:$A$37,0)),INDEX('3) Forecast Bridge'!$Q$8:$Q$37,MATCH(A18,'3) Forecast Bridge'!$A$8:$A$37,0)))),0) -> 0
A19: WP2_S02 | B19: RUSI - Research Analyst (existing staff, DA) @GrC/8 | C19: WP2 | D19: Directly Allocated | E19: Staff | F19: Directly Allocated Staff | G19: =IF(AND(OR('1) Budget-Actuals Dashboard'!$C$5="All",C19='1) Budget-Actuals Dashboard'!$C$5),OR('1) Budget-Actuals Dashboard'!$G$5="All",D19='1) Budget-Actuals Dashboard'!$G$5),OR('1) Budget-Actuals Dashboard'!$K$5="All",E19='1) Budget-Actuals Dashboard'!$K$5)),"Yes","No") -> No | H19: =IF('1) Budget-Actuals Dashboard'!$K$4="100% fEC",SUMIFS('9) Budget Baseline'!$P$8:$P$1087,'9) Budget Baseline'!$B$8:$B$1087,A19,'9) Budget Baseline'!$H$8:$H$1087,">="&'14) Model Calc'!$B$9,'9) Budget Baseline'!$H$8:$H$1087,"<="&'14) Model Calc'!$B$10),IF('1) Budget-Actuals Dashboard'!$K$4="UKRI",SUMIFS('9) Budget Baseline'!$Q$8:$Q$1087,'9) Budget Baseline'!$B$8:$B$1087,A19,'9) Budget Baseline'!$H$8:$H$1087,">="&'14) Model Calc'!$B$9,'9) Budget Baseline'!$H$8:$H$1087,"<="&'14) Model Calc'!$B$10),SUMIFS('9) Budget Baseline'!$R$8:$R$1087,'9) Budget Baseline'!$B$8:$B$1087,A19,'9) Budget Baseline'!$H$8:$H$1087,">="&'14) Model Calc'!$B$9,'9) Budget Baseline'!$H$8:$H$1087,"<="&'14) Model Calc'!$B$10))) -> 603.125 | I19: =IF('1) Budget-Actuals Dashboard'!$K$4="100% fEC",SUMIFS('6) Actuals Ledger - DI Costs'!$R$8:$R$2007,'6) Actuals Ledger - DI Costs'!$G$8:$G$2007,A19,'6) Actuals Ledger - DI Costs'!$C$8:$C$2007,">="&'14) Model Calc'!$B$9,'6) Actuals Ledger - DI Costs'!$C$8:$C$2007,"<="&'14) Model Calc'!$B$10)+SUMIFS('7) Allocations - DA Costs'!$O$8:$O$2007,'7) Allocations - DA Costs'!$D$8:$D$2007,A19,'7) Allocations - DA Costs'!$C$8:$C$2007,">="&'14) Model Calc'!$B$9,'7) Allocations - DA Costs'!$C$8:$C$2007,"<="&'14) Model Calc'!$B$10),IF('1) Budget-Actuals Dashboard'!$K$4="UKRI",SUMIFS('6) Actuals Ledger - DI Costs'!$S$8:$S$2007,'6) Actuals Ledger - DI Costs'!$G$8:$G$2007,A19,'6) Actuals Ledger - DI Costs'!$C$8:$C$2007,">="&'14) Model Calc'!$B$9,'6) Actuals Ledger - DI Costs'!$C$8:$C$2007,"<="&'14) Model Calc'!$B$10)+SUMIFS('7) Allocations - DA Costs'!$P$8:$P$2007,'7) Allocations - DA Costs'!$D$8:$D$2007,A19,'7) Allocations - DA Costs'!$C$8:$C$2007,">="&'14) Model Calc'!$B$9,'7) Allocations - DA Costs'!$C$8:$C$2007,"<="&'14) Model Calc'!$B$10),SUMIFS('6) Actuals Ledger - DI Costs'!$T$8:$T$2007,'6) Actuals Ledger - DI Costs'!$G$8:$G$2007,A19,'6) Actuals Ledger - DI Costs'!$C$8:$C$2007,">="&'14) Model Calc'!$B$9,'6) Actuals Ledger - DI Costs'!$C$8:$C$2007,"<="&'14) Model Calc'!$B$10)+SUMIFS('7) Allocations - DA Costs'!$Q$8:$Q$2007,'7) Allocations - DA Costs'!$D$8:$D$2007,A19,'7) Allocations - DA Costs'!$C$8:$C$2007,">="&'14) Model Calc'!$B$9,'7) Allocations - DA Costs'!$C$8:$C$2007,"<="&'14) Model Calc'!$B$10))) -> 599.52 | J19: =H19-I19 -> 3.605 | K19: =IF(H19=0,"",J19/H19) -> 0.0059772021 | L19: =IF('1) Budget-Actuals Dashboard'!$K$4="100% fEC",SUMIFS('8) Commitments Forecast'!$Q$8:$Q$507,'8) Commitments Forecast'!$H$8:$H$507,A19),IF('1) Budget-Actuals Dashboard'!$K$4="UKRI",SUMIFS('8) Commitments Forecast'!$R$8:$R$507,'8) Commitments Forecast'!$H$8:$H$507,A19),SUMIFS('8) Commitments Forecast'!$S$8:$S$507,'8) Commitments Forecast'!$H$8:$H$507,A19))) -> 0 | M19: =IFERROR(IF('1) Budget-Actuals Dashboard'!$K$4="100% fEC",INDEX('3) Forecast Bridge'!$L$8:$L$37,MATCH(A19,'3) Forecast Bridge'!$A$8:$A$37,0)),IF('1) Budget-Actuals Dashboard'!$K$4="UKRI",INDEX('3) Forecast Bridge'!$P$8:$P$37,MATCH(A19,'3) Forecast Bridge'!$A$8:$A$37,0)),INDEX('3) Forecast Bridge'!$Q$8:$Q$37,MATCH(A19,'3) Forecast Bridge'!$A$8:$A$37,0)))),0) -> 0
... A37: WP3_EST | B37: RUSI - non-laboratory estate allocation (dispensation proxy × eligible staff FTE) | C37: WP3 | D37: Directly Allocated | E37: Estates | F37: Estate Costs | G37: =IF(AND(OR('1) Budget-Actuals Dashboard'!$C$5="All",C37='1) Budget-Actuals Dashboard'!$C$5),OR('1) Budget-Actuals Dashboard'!$G$5="All",D37='1) Budget-Actuals Dashboard'!$G$5),OR('1) Budget-Actuals Dashboard'!$K$5="All",E37='1) Budget-Actuals Dashboard'!$K$5)),"Yes","No") -> No | H37: =IF('1) Budget-Actuals Dashboard'!$K$4="100% fEC",SUMIFS('9) Budget Baseline'!$P$8:$P$1087,'9) Budget Baseline'!$B$8:$B$1087,A37,'9) Budget Baseline'!$H$8:$H$1087,">="&'14) Model Calc'!$B$9,'9) Budget Baseline'!$H$8:$H$1087,"<="&'14) Model Calc'!$B$10),IF('1) Budget-Actuals Dashboard'!$K$4="UKRI",SUMIFS('9) Budget Baseline'!$Q$8:$Q$1087,'9) Budget Baseline'!$B$8:$B$1087,A37,'9) Budget Baseline'!$H$8:$H$1087,">="&'14) Model Calc'!$B$9,'9) Budget Baseline'!$H$8:$H$1087,"<="&'14) Model Calc'!$B$10),SUMIFS('9) Budget Baseline'!$R$8:$R$1087,'9) Budget Baseline'!$B$8:$B$1087,A37,'9) Budget Baseline'!$H$8:$H$1087,">="&'14) Model Calc'!$B$9,'9) Budget Baseline'!$H$8:$H$1087,"<="&'14) Model Calc'!$B$10))) -> 396.93333 | I37: =IF('1) Budget-Actuals Dashboard'!$K$4="100% fEC",SUMIFS('6) Actuals Ledger - DI Costs'!$R$8:$R$2007,'6) Actuals Ledger - DI Costs'!$G$8:$G$2007,A37,'6) Actuals Ledger - DI Costs'!$C$8:$C$2007,">="&'14) Model Calc'!$B$9,'6) Actuals Ledger - DI Costs'!$C$8:$C$2007,"<="&'14) Model Calc'!$B$10)+SUMIFS('7) Allocations - DA Costs'!$O$8:$O$2007,'7) Allocations - DA Costs'!$D$8:$D$2007,A37,'7) Allocations - DA Costs'!$C$8:$C$2007,">="&'14) Model Calc'!$B$9,'7) Allocations - DA Costs'!$C$8:$C$2007,"<="&'14) Model Calc'!$B$10),IF('1) Budget-Actuals Dashboard'!$K$4="UKRI",SUMIFS('6) Actuals Ledger - DI Costs'!$S$8:$S$2007,'6) Actuals Ledger - DI Costs'!$G$8:$G$2007,A37,'6) Actuals Ledger - DI Costs'!$C$8:$C$2007,">="&'14) Model Calc'!$B$9,'6) Actuals Ledger - DI Costs'!$C$8:$C$2007,"<="&'14) Model Calc'!$B$10)+SUMIFS('7) Allocations - DA Costs'!$P$8:$P$2007,'7) Allocations - DA Costs'!$D$8:$D$2007,A37,'7) Allocations - DA Costs'!$C$8:$C$2007,">="&'14) Model Calc'!$B$9,'7) Allocations - DA Costs'!$C$8:$C$2007,"<="&'14) Model Calc'!$B$10),SUMIFS('6) Actuals Ledger - DI Costs'!$T$8:$T$2007,'6) Actuals Ledger - DI Costs'!$G$8:$G$2007,A37,'6) Actuals Ledger - DI Costs'!$C$8:$C$2007,">="&'14) Model Calc'!$B$9,'6) Actuals Ledger - DI Costs'!$C$8:$C$2007,"<="&'14) Model Calc'!$B$10)+SUMIFS('7) Allocations - DA Costs'!$Q$8:$Q$2007,'7) Allocations - DA Costs'!$D$8:$D$2007,A37,'7) Allocations - DA Costs'!$C$8:$C$2007,">="&'14) Model Calc'!$B$9,'7) Allocations - DA Costs'!$C$8:$C$2007,"<="&'14) Model Calc'!$B$10))) -> 394.56 | J37: =H37-I37 -> 2.3733333 | K37: =IF(H37=0,"",J37/H37) -> 0.0059791737 | L37: =IF('1) Budget-Actuals Dashboard'!$K$4="100% fEC",SUMIFS('8) Commitments Forecast'!$Q$8:$Q$507,'8) Commitments Forecast'!$H$8:$H$507,A37),IF('1) Budget-Actuals Dashboard'!$K$4="UKRI",SUMIFS('8) Commitments Forecast'!$R$8:$R$507,'8) Commitments Forecast'!$H$8:$H$507,A37),SUMIFS('8) Commitments Forecast'!$S$8:$S$507,'8) Commitments Forecast'!$H$8:$H$507,A37))) -> 0 | M37: =IFERROR(IF('1) Budget-Actuals Dashboard'!$K$4="100% fEC",INDEX('3) Forecast Bridge'!$L$8:$L$37,MATCH(A37,'3) Forecast Bridge'!$A$8:$A$37,0)),IF('1) Budget-Actuals Dashboard'!$K$4="UKRI",INDEX('3) Forecast Bridge'!$P$8:$P$37,MATCH(A37,'3) Forecast Bridge'!$A$8:$A$37,0)),INDEX('3) Forecast Bridge'!$Q$8:$Q$37,MATCH(A37,'3) Forecast Bridge'!$A$8:$A$37,0)))),0) -> 0
A40: Interpretation: positive variance is remaining headroom and negative variance is overspend/exposure. Neither is automatically favourable or unfavourable: timing, delivery progress, eligibility and evidence must be reviewed together.

Sheet 3) Forecast Bridge
A1: Item-level Forecast at Completion bridge
A2: Budget breakdown by each line item and current spend against. Confirmed (Realised costs) + Committed (costs liable to pay but unrealised) + Unspent (unrealised costs) = 100% fCE* *At the time of the Dashboard cut-off and based on costs being verified against the project
A4: Forecast at Completion should never overwrites the approved Budget. Only us the blue Forecast Adjustment column as an input (use it to record an expected committment, anticipated risk or saving etc.) and review monthly. Everything else is forecasted from the baseline budget, confirmedf cost ledgers and the commitment register.
A7: Budget Item ID | B7: Description | C7: Work Package | D7: fEC Heading | E7: fEC Subheading | F7: Approved Budget | G7: Spend to Date | H7: Open Commitments | I7: Forecast Adjustment | J7: Uncommitted ETC | K7: Forecast at Completion | L7: Variance to Budget | M7: Funding Rate | N7: FAC UKRI | O7: FAC RUSI | P7: Variance UKRI | Q7: Variance RUSI | R7: Notes
A8: WP1_S01 | B8: RUSI - Project Officer (existing staff, DA) @GrB/4 | C8: WP1 | D8: Directly Allocated | E8: Staff | F8: =SUMIFS('9) Budget Baseline'!$P$8:$P$1087,'9) Budget Baseline'!$B$8:$B$1087,A8) -> 14915 | G8: =SUMIFS('6) Actuals Ledger - DI Costs'!$R$8:$R$2007,'6) Actuals Ledger - DI Costs'!$G$8:$G$2007,A8,'6) Actuals Ledger - DI Costs'!$C$8:$C$2007,"<="&'1) Budget-Actuals Dashboard'!$C$4)+SUMIFS('7) Allocations - DA Costs'!$O$8:$O$2007,'7) Allocations - DA Costs'!$D$8:$D$2007,A8,'7) Allocations - DA Costs'!$C$8:$C$2007,"<="&'1) Budget-Actuals Dashboard'!$C$4) -> 1625.59 | H8: =SUMIFS('8) Commitments Forecast'!$Q$8:$Q$507,'8) Commitments Forecast'!$H$8:$H$507,A8) -> 0 | I8: 0 | J8: =MAX(0,F8+I8-G8-H8) -> 13289.41 | K8: =G8+H8+J8 -> 14915 | L8: =F8-K8 -> 0 | M8: =IFERROR(INDEX('12) Budget Line Mapping'!$G$8:$G$37,MATCH(A8,'12) Budget Line Mapping'!$A$8:$A$37,0)),0) -> 0.8 | N8: =K8*M8 -> 11932 | O8: =K8-N8 -> 2983 | P8: =L8*M8 -> 0 | Q8: =L8-P8 -> 0 | R8: Base ETC follows remaining approved Budget.
A9: WP1_S02 | B9: RUSI - Research Analyst (existing staff, DA) @GrC/8 | C9: WP1 | D9: Directly Allocated | E9: Staff | F9: =SUMIFS('9) Budget Baseline'!$P$8:$P$1087,'9) Budget Baseline'!$B$8:$B$1087,A9) -> 13027.5 | G9: =SUMIFS('6) Actuals Ledger - DI Costs'!$R$8:$R$2007,'6) Actuals Ledger - DI Costs'!$G$8:$G$2007,A9,'6) Actuals Ledger - DI Costs'!$C$8:$C$2007,"<="&'1) Budget-Actuals Dashboard'!$C$4)+SUMIFS('7) Allocations - DA Costs'!$O$8:$O$2007,'7) Allocations - DA Costs'!$D$8:$D$2007,A9,'7) Allocations - DA Costs'!$C$8:$C$2007,"<="&'1) Budget-Actuals Dashboard'!$C$4) -> 1798.53 | H9: =SUMIFS('8) Commitments Forecast'!$Q$8:$Q$507,'8) Commitments Forecast'!$H$8:$H$507,A9) -> 0 | I9: 0 | J9: =MAX(0,F9+I9-G9-H9) -> 11228.97 | K9: =G9+H9+J9 -> 13027.5 | L9: =F9-K9 -> 0 | M9: =IFERROR(INDEX('12) Budget Line Mapping'!$G$8:$G$37,MATCH(A9,'12) Budget Line Mapping'!$A$8:$A$37,0)),0) -> 0.8 | N9: =K9*M9 -> 10422 | O9: =K9-N9 -> 2605.5 | P9: =L9*M9 -> 0 | Q9: =L9-P9 -> 0 | R9: Base ETC follows remaining approved Budget.
A10: WP1_S03 | B10: RUSI - Programme/Project Lead (existing staff, DA) @GrE/14 | C10: WP1 | D10: Directly Allocated | E10: Staff | F10: =SUMIFS('9) Budget Baseline'!$P$8:$P$1087,'9) Budget Baseline'!$B$8:$B$1087,A10) -> 13365 | G10: =SUMIFS('6) Actuals Ledger - DI Costs'!$R$8:$R$2007,'6) Actuals Ledger - DI Costs'!$G$8:$G$2007,A10,'6) Actuals Ledger - DI Costs'!$C$8:$C$2007,"<="&'1) Budget-Actuals Dashboard'!$C$4)+SUMIFS('7) Allocations - DA Costs'!$O$8:$O$2007,'7) Allocations - DA Costs'!$D$8:$D$2007,A10,'7) Allocations - DA Costs'!$C$8:$C$2007,"<="&'1) Budget-Actuals Dashboard'!$C$4) -> 1845.11 | H10: =SUMIFS('8) Commitments Forecast'!$Q$8:$Q$507,'8) Commitments Forecast'!$H$8:$H$507,A10) -> 0 | I10: 0 | J10: =MAX(0,F10+I10-G10-H10) -> 11519.89 | K10: =G10+H10+J10 -> 13365 | L10: =F10-K10 -> 0 | M10: =IFERROR(INDEX('12) Budget Line Mapping'!$G$8:$G$37,MATCH(A10,'12) Budget Line Mapping'!$A$8:$A$37,0)),0) -> 0.8 | N10: =K10*M10 -> 10692 | O10: =K10-N10 -> 2673 | P10: =L10*M10 -> 0 | Q10: =L10-P10 -> 0 | R10: Base ETC follows remaining approved Budget.
A11: WP1_TRAVEL | B11: RUSI - UK rail, local travel and subsistence Budget | C11: WP1 | D11: Directly Incurred | E11: Travel & Subsistence | F11: =SUMIFS('9) Budget Baseline'!$P$8:$P$1087,'9) Budget Baseline'!$B$8:$B$1087,A11) -> 7500 | G11: =SUMIFS('6) Actuals Ledger - DI Costs'!$R$8:$R$2007,'6) Actuals Ledger - DI Costs'!$G$8:$G$2007,A11,'6) Actuals Ledger - DI Costs'!$C$8:$C$2007,"<="&'1) Budget-Actuals Dashboard'!$C$4)+SUMIFS('7) Allocations - DA Costs'!$O$8:$O$2007,'7) Allocations - DA Costs'!$D$8:$D$2007,A11,'7) Allocations - DA Costs'!$C$8:$C$2007,"<="&'1) Budget-Actuals Dashboard'!$C$4) -> 1356.2 | H11: =SUMIFS('8) Commitments Forecast'!$Q$8:$Q$507,'8) Commitments Forecast'!$H$8:$H$507,A11) -> 0 | I11: 0 | J11: =MAX(0,F11+I11-G11-H11) -> 6143.8 | K11: =G11+H11+J11 -> 7500 | L11: =F11-K11 -> 0 | M11: =IFERROR(INDEX('12) Budget Line Mapping'!$G$8:$G$37,MATCH(A11,'12) Budget Line Mapping'!$A$8:$A$37,0)),0) -> 0.8 | N11: =K11*M11 -> 6000 | O11: =K11-N11 -> 1500 | P11: =L11*M11 -> 0 | Q11: =L11-P11 -> 0 | R11: Base ETC follows remaining approved Budget.
A12: WP1_CONF | B12: RUSI - five-day flagship London conferences (launch and close) | C12: WP1 | D12: Directly Incurred | E12: Other Directly Incurred | F12: =SUMIFS('9) Budget Baseline'!$P$8:$P$1087,'9) Budget Baseline'!$B$8:$B$1087,A12) -> 30000 | G12: =SUMIFS('6) Actuals Ledger - DI Costs'!$R$8:$R$2007,'6) Actuals Ledger - DI Costs'!$G$8:$G$2007,A12,'6) Actuals Ledger - DI Costs'!$C$8:$C$2007,"<="&'1) Budget-Actuals Dashboard'!$C$4)+SUMIFS('7) Allocations - DA Costs'!$O$8:$O$2007,'7) Allocations - DA Costs'!$D$8:$D$2007,A12,'7) Allocations - DA Costs'!$C$8:$C$2007,"<="&'1) Budget-Actuals Dashboard'!$C$4) -> 0 | H12: =SUMIFS('8) Commitments Forecast'!$Q$8:$Q$507,'8) Commitments Forecast'!$H$8:$H$507,A12) -> 14700 | I12: 1800 | J12: =MAX(0,F12+I12-G12-H12) -> 17100 | K12: =G12+H12+J12 -> 31800 | L12: =F12-K12 -> -1800 | M12: =IFERROR(INDEX('12) Budget Line Mapping'!$G$8:$G$37,MATCH(A12,'12) Budget Line Mapping'!$A$8:$A$37,0)),0) -> 0.8 | N12: =K12*M12 -> 25440 | O12: =K12-N12 -> 6360 | P12: =L12*M12 -> -1440 | Q12: =L12-P12 -> -360 | R12: Illustrative risk/saving adjustment; review monthly.
A13: WP1_WORKSHOP | B13: RUSI - UK national and regional workshops | C13: WP1 | D13: Directly Incurred | E13: Other Directly Incurred | F13: =SUMIFS('9) Budget Baseline'!$P$8:$P$1087,'9) Budget Baseline'!$B$8:$B$1087,A13) -> 12000 | G13: =SUMIFS('6) Actuals Ledger - DI Costs'!$R$8:$R$2007,'6) Actuals Ledger - DI Costs'!$G$8:$G$2007,A13,'6) Actuals Ledger - DI Costs'!$C$8:$C$2007,"<="&'1) Budget-Actuals Dashboard'!$C$4)+SUMIFS('7) Allocations - DA Costs'!$O$8:$O$2007,'7) Allocations - DA Costs'!$D$8:$D$2007,A13,'7) Allocations - DA Costs'!$C$8:$C$2007,"<="&'1) Budget-Actuals Dashboard'!$C$4) -> 2150 | H13: =SUMIFS('8) Commitments Forecast'!$Q$8:$Q$507,'8) Commitments Forecast'!$H$8:$H$507,A13) -> 1200 | I13: 0 | J13: =MAX(0,F13+I13-G13-H13) -> 8650 | K13: =G13+H13+J13 -> 12000 | L13: =F13-K13 -> 0 | M13: =IFERROR(INDEX('12) Budget Line Mapping'!$G$8:$G$37,MATCH(A13,'12) Budget Line Mapping'!$A$8:$A$37,0)),0) -> 0.8 | N13: =K13*M13 -> 9600 | O13: =K13-N13 -> 2400 | P13: =L13*M13 -> 0 | Q13: =L13-P13 -> 0 | R13: Base ETC follows remaining approved Budget.
A14: WP1_PANEL | B14: RUSI - hybrid panels and practitioner roundtables | C14: WP1 | D14: Directly Incurred | E14: Other Directly Incurred | F14: =SUMIFS('9) Budget Baseline'!$P$8:$P$1087,'9) Budget Baseline'!$B$8:$B$1087,A14) -> 4500 | G14: =SUMIFS('6) Actuals Ledger - DI Costs'!$R$8:$R$2007,'6) Actuals Ledger - DI Costs'!$G$8:$G$2007,A14,'6) Actuals Ledger - DI Costs'!$C$8:$C$2007,"<="&'1) Budget-Actuals Dashboard'!$C$4)+SUMIFS('7) Allocations - DA Costs'!$O$8:$O$2007,'7) Allocations - DA Costs'!$D$8:$D$2007,A14,'7) Allocations - DA Costs'!$C$8:$C$2007,"<="&'1) Budget-Actuals Dashboard'!$C$4) -> 790 | H14: =SUMIFS('8) Commitments Forecast'!$Q$8:$Q$507,'8) Commitments Forecast'!$H$8:$H$507,A14) -> 0 | I14: 0 | J14: =MAX(0,F14+I14-G14-H14) -> 3710 | K14: =G14+H14+J14 -> 4500 | L14: =F14-K14 -> 0 | M14: =IFERROR(INDEX('12) Budget Line Mapping'!$G$8:$G$37,MATCH(A14,'12) Budget Line Mapping'!$A$8:$A$37,0)),0) -> 0.8 | N14: =K14*M14 -> 3600 | O14: =K14-N14 -> 900 | P14: =L14*M14 -> 0 | Q14: =L14-P14 -> 0 | R14: Base ETC follows remaining approved Budget.
A15: WP1_COMMS | B15: RUSI - knowledge products and digital communications | C15: WP1 | D15: Directly Incurred | E15: Other Directly Incurred | F15: =SUMIFS('9) Budget Baseline'!$P$8:$P$1087,'9) Budget Baseline'!$B$8:$B$1087,A15) -> 3000 | G15: =SUMIFS('6) Actuals Ledger - DI Costs'!$R$8:$R$2007,'6) Actuals Ledger - DI Costs'!$G$8:$G$2007,A15,'6) Actuals Ledger - DI Costs'!$C$8:$C$2007,"<="&'1) Budget-Actuals Dashboard'!$C$4)+SUMIFS('7) Allocations - DA Costs'!$O$8:$O$2007,'7) Allocations - DA Costs'!$D$8:$D$2007,A15,'7) Allocations - DA Costs'!$C$8:$C$2007,"<="&'1) Budget-Actuals Dashboard'!$C$4) -> 575 | H15: =SUMIFS('8) Commitments Forecast'!$Q$8:$Q$507,'8) Commitments Forecast'!$H$8:$H$507,A15) -> 450 | I15: -100 | J15: =MAX(0,F15+I15-G15-H15) -> 1875 | K15: =G15+H15+J15 -> 2900 | L15: =F15-K15 -> 100 | M15: =IFERROR(INDEX('12) Budget Line Mapping'!$G$8:$G$37,MATCH(A15,'12) Budget Line Mapping'!$A$8:$A$37,0)),0) -> 0.8 | N15: =K15*M15 -> 2320 | O15: =K15-N15 -> 580 | P15: =L15*M15 -> 80 | Q15: =L15-P15 -> 20 | R15: Illustrative risk/saving adjustment; review monthly.
A16: WP1_IND | B16: RUSI - indirect allocation (dispensation proxy × eligible staff FTE) | C16: WP1 | D16: Indirect | E16: Indirect | F16: =SUMIFS('9) Budget Baseline'!$P$8:$P$1087,'9) Budget Baseline'!$B$8:$B$1087,A16) -> 47727.49 | G16: =SUMIFS('6) Actuals Ledger - DI Costs'!$R$8:$R$2007,'6) Actuals Ledger - DI Costs'!$G$8:$G$2007,A16,'6) Actuals Ledger - DI Costs'!$C$8:$C$2007,"<="&'1) Budget-Actuals Dashboard'!$C$4)+SUMIFS('7) Allocations - DA Costs'!$O$8:$O$2007,'7) Allocations - DA Costs'!$D$8:$D$2007,A16,'7) Allocations - DA Costs'!$C$8:$C$2007,"<="&'1) Budget-Actuals Dashboard'!$C$4) -> 5953.96 | H16: =SUMIFS('8) Commitments Forecast'!$Q$8:$Q$507,'8) Commitments Forecast'!$H$8:$H$507,A16) -> 0 | I16: 0 | J16: =MAX(0,F16+I16-G16-H16) -> 41773.53 | K16: =G16+H16+J16 -> 47727.49 | L16: =F16-K16 -> 0 | M16: =IFERROR(INDEX('12) Budget Line Mapping'!$G$8:$G$37,MATCH(A16,'12) Budget Line Mapping'!$A$8:$A$37,0)),0) -> 0.8 | N16: =K16*M16 -> 38181.992 | O16: =K16-N16 -> 9545.498 | P16: =L16*M16 -> 0 | Q16: =L16-P16 -> 0 | R16: Base ETC follows remaining approved Budget.
A17: WP1_EST | B17: RUSI - non-laboratory estate allocation (dispensation proxy × eligible staff FTE) | C17: WP1 | D17: Directly Allocated | E17: Estates | F17: =SUMIFS('9) Budget Baseline'!$P$8:$P$1087,'9) Budget Baseline'!$B$8:$B$1087,A17) -> 6082.24 | G17: =SUMIFS('6) Actuals Ledger - DI Costs'!$R$8:$R$2007,'6) Actuals Ledger - DI Costs'!$G$8:$G$2007,A17,'6) Actuals Ledger - DI Costs'!$C$8:$C$2007,"<="&'1) Budget-Actuals Dashboard'!$C$4)+SUMIFS('7) Allocations - DA Costs'!$O$8:$O$2007,'7) Allocations - DA Costs'!$D$8:$D$2007,A17,'7) Allocations - DA Costs'!$C$8:$C$2007,"<="&'1) Budget-Actuals Dashboard'!$C$4) -> 758.76 | H17: =SUMIFS('8) Commitments Forecast'!$Q$8:$Q$507,'8) Commitments Forecast'!$H$8:$H$507,A17) -> 0 | I17: 0 | J17: =MAX(0,F17+I17-G17-H17) -> 5323.48 | K17: =G17+H17+J17 -> 6082.24 | L17: =F17-K17 -> 0 | M17: =IFERROR(INDEX('12) Budget Line Mapping'!$G$8:$G$37,MATCH(A17,'12) Budget Line Mapping'!$A$8:$A$37,0)),0) -> 0.8 | N17: =K17*M17 -> 4865.792 | O17: =K17-N17 -> 1216.448 | P17: =L17*M17 -> 0 | Q17: =L17-P17 -> 0 | R17: Base ETC follows remaining approved Budget.
A18: WP2_S01 | B18: RUSI - Project Officer (existing staff, DA) @GrB/4 | C18: WP2 | D18: Directly Allocated | E18: Staff | F18: =SUMIFS('9) Budget Baseline'!$P$8:$P$1087,'9) Budget Baseline'!$B$8:$B$1087,A18) -> 3532.5 | G18: =SUMIFS('6) Actuals Ledger - DI Costs'!$R$8:$R$2007,'6) Actuals Ledger - DI Costs'!$G$8:$G$2007,A18,'6) Actuals Ledger - DI Costs'!$C$8:$C$2007,"<="&'1) Budget-Actuals Dashboard'!$C$4)+SUMIFS('7) Allocations - DA Costs'!$O$8:$O$2007,'7) Allocations - DA Costs'!$D$8:$D$2007,A18,'7) Allocations - DA Costs'!$C$8:$C$2007,"<="&'1) Budget-Actuals Dashboard'!$C$4) -> 487.69 | H18: =SUMIFS('8) Commitments Forecast'!$Q$8:$Q$507,'8) Commitments Forecast'!$H$8:$H$507,A18) -> 0 | I18: 0 | J18: =MAX(0,F18+I18-G18-H18) -> 3044.81 | K18: =G18+H18+J18 -> 3532.5 | L18: =F18-K18 -> 0 | M18: =IFERROR(INDEX('12) Budget Line Mapping'!$G$8:$G$37,MATCH(A18,'12) Budget Line Mapping'!$A$8:$A$37,0)),0) -> 0.8 | N18: =K18*M18 -> 2826 | O18: =K18-N18 -> 706.5 | P18: =L18*M18 -> 0 | Q18: =L18-P18 -> 0 | R18: Base ETC follows remaining approved Budget.
A19: WP2_S02 | B19: RUSI - Research Analyst (existing staff, DA) @GrC/8 | C19: WP2 | D19: Directly Allocated | E19: Staff | F19: =SUMIFS('9) Budget Baseline'!$P$8:$P$1087,'9) Budget Baseline'!$B$8:$B$1087,A19) -> 4342.5 | G19: =SUMIFS('6) Actuals Ledger - DI Costs'!$R$8:$R$2007,'6) Actuals Ledger - DI Costs'!$G$8:$G$2007,A19,'6) Actuals Ledger - DI Costs'!$C$8:$C$2007,"<="&'1) Budget-Actuals Dashboard'!$C$4)+SUMIFS('7) Allocations - DA Costs'!$O$8:$O$2007,'7) Allocations - DA Costs'!$D$8:$D$2007,A19,'7) Allocations - DA Costs'!$C$8:$C$2007,"<="&'1) Budget-Actuals Dashboard'!$C$4) -> 599.52 | H19: =SUMIFS('8) Commitments Forecast'!$Q$8:$Q$507,'8) Commitments Forecast'!$H$8:$H$507,A19) -> 0 | I19: 0 | J19: =MAX(0,F19+I19-G19-H19) -> 3742.98 | K19: =G19+H19+J19 -> 4342.5 | L19: =F19-K19 -> 0 | M19: =IFERROR(INDEX('12) Budget Line Mapping'!$G$8:$G$37,MATCH(A19,'12) Budget Line Mapping'!$A$8:$A$37,0)),0) -> 0.8 | N19: =K19*M19 -> 3474 | O19: =K19-N19 -> 868.5 | P19: =L19*M19 -> 0 | Q19: =L19-P19 -> 0 | R19: Base ETC follows remaining approved Budget.
... A37: WP3_EST | B37: RUSI - non-laboratory estate allocation (dispensation proxy × eligible staff FTE) | C37: WP3 | D37: Directly Allocated | E37: Estates | F37: =SUMIFS('9) Budget Baseline'!$P$8:$P$1087,'9) Budget Baseline'!$B$8:$B$1087,A37) -> 2857.92 | G37: =SUMIFS('6) Actuals Ledger - DI Costs'!$R$8:$R$2007,'6) Actuals Ledger - DI Costs'!$G$8:$G$2007,A37,'6) Actuals Ledger - DI Costs'!$C$8:$C$2007,"<="&'1) Budget-Actuals Dashboard'!$C$4)+SUMIFS('7) Allocations - DA Costs'!$O$8:$O$2007,'7) Allocations - DA Costs'!$D$8:$D$2007,A37,'7) Allocations - DA Costs'!$C$8:$C$2007,"<="&'1) Budget-Actuals Dashboard'!$C$4) -> 394.56 | H37: =SUMIFS('8) Commitments Forecast'!$Q$8:$Q$507,'8) Commitments Forecast'!$H$8:$H$507,A37) -> 0 | I37: 0 | J37: =MAX(0,F37+I37-G37-H37) -> 2463.36 | K37: =G37+H37+J37 -> 2857.92 | L37: =F37-K37 -> 0 | M37: =IFERROR(INDEX('12) Budget Line Mapping'!$G$8:$G$37,MATCH(A37,'12) Budget Line Mapping'!$A$8:$A$37,0)),0) -> 0.8 | N37: =K37*M37 -> 2286.336 | O37: =K37-N37 -> 571.584 | P37: =L37*M37 -> 0 | Q37: =L37-P37 -> 0 | R37: Base ETC follows remaining approved Budget.

Sheet 4) Monthly Update
A1: Monthly update centre
A2: [Optional] Instructions for automated transaction import process (in Power Query)
A4: 1. Configure a staged import (blue cells)
A6: Parameter | B6: Value | D6: Staging control | E6: Value
A7: Source CSV path | B7: SHOC2_transaction_import_template.csv | D7: Loaded rows | E7: =COUNTA($A$49:$A$548) -> 0
A8: Staged Batch ID | B8: STAGED-2026-09 | D8: Loaded amount | E8: =SUM($F$49:$F$548) -> 0
A9: Source control total | D9: Control difference | E9: =IF($B$9="","",E8-$B$9)
A10: Staged reporting cut-off | B10: 46265 | D10: Rows READY | E10: =COUNTIF($L$49:$L$548,"READY") -> 0
A11: Query behaviour | B11: Manual refresh only; never refresh on open | D11: Rows with issues | E11: =MAX(0,E7-E10) -> 0
D12: Promotion | E12: Manual after review
A14: 2. Explicit refresh, review and promotion
A15: Step | B15: Action | D15: What success looks like
A16: 1 | B16: Export a cumulative or monthly-delta CSV using the schema shown below. | D16: Dates and Amount GBP are true values; every transaction has a stable ID.
A17: 2 | B17: Enter the full CSV path, unique Batch ID, source control total and cut-off above. | D17: The inputs remain visible and auditable.
A18: 3 | B18: In Excel: Data → Refresh All, or refresh only SHOC2_Transaction_Import. | D18: The staging table is populated; the saved dashboard does not change.
A19: 4 | B19: Filter Import Status and fix all non-READY rows at source or through an authorised mapping. | D19: READY rows equal the source row count and the amount reconciles to the control total.
A20: 5 | B20: Copy staging columns A:K and paste values into the blue A:K columns of Actuals Ledger. | D20: Ledger Row Status is OK for every pasted record.
A21: 6 | B21: Add/check the matching Refresh Log row as STAGED; compare rows and amount; document reviewer and notes. | D21: Difference is zero and no ledger exception remains.
A22: 7 | B22: Change Refresh Log Status to APPROVED, update Dashboard cut-off, verify Checks PASS, and save. | D22: The new batch appears across dashboard, detail and controls.
A24: Expected CSV headers: Transaction ID | Accounting Date | Incurred Date | Description | Amount GBP | Budget Item ID | Evidence Ref | Source Ref | Reversal Of | Notes. The query adds the staged Batch ID and Import Status.
A28: 3. One-time setup: create the optional Power Query staging import
A29: For ease of use immediately from the download link on my website, the workbook doesn't contain any queries pre-stored, so as to minimise the scope for potential compatibility issues associated with external connections, organisational privacy permissions, or similar. The manual route (set out above) achieves the same result without this functionality, and is broadly recommended for demo purposes. To enable automated transaction imports, follow the below steps and Save the file.
A32: Step | B32: Follow these steps in Excel
A33: PQ1 | B33: Save the accompanying template .CSV (that shipped alongside this workbook somewhere stable, then put its full path in cell B7 above.
A34: PQ2 | B34: Data → Get Data → From File → From Text/CSV. Select that CSV. Click Transform Data (not Load).
A35: PQ3 | B35: In the editor, rename the query to SHOC2_Transaction_Import.
A36: PQ4 | B36: Set column types: Transaction ID, Description, Budget Item ID, Evidence Ref, Source Ref, Reversal Of and Notes to Text; Accounting Date and Incurred Date to Date; Amount GBP to Decimal Number.
A37: PQ5 | B37: Add Column → Custom Column, name it Batch ID, formula: = Excel.CurrentWorkbook(){[Name="StagedBatchID"]}[Content]{0}[Column1]
A38: PQ6 | B38: Add Column → Custom Column, name it Import Status, formula: = if [Transaction ID] = null then "MISSING ID" else if [Amount GBP] = null then "MISSING AMOUNT" else if [Incurred Date] = null then "MISSING DATE" else if [Budget Item ID] = null then "UNMAPPED" else "READY"
A39: PQ7 | B39: Before closing: select cell B8, and in the Name Box (left of the formula bar) type StagedBatchID and press Enter.
A40: PQ8 | B40: Home → Close & Load To… → Table → Existing worksheet → =$A$48 on this sheet. Click OK.
A41: PQ9 | B41: Right-click the query in Queries & Connections → Properties. UNTICK "Refresh data when opening the file" and UNTICK "Enable background refresh". Tick "Refresh this connection on Refresh All". OK.
A42: PQ10 | B42: Save the workbook. Test it: close, reopen with connections disabled, and confirm the Dashboard is unchanged and still reads PASS.
A45: 4. Staging output area - review only; do not type into a refresh output
A46: Load the query to cell A48 of this sheet (step PQ8). Until then this area is intentionally empty and the workbook is complete without it. The staging controls above read rows 49-548.
A48: Transaction ID | B48: Batch ID | C48: Accounting Date | D48: Incurred Date | E48: Description | F48: Amount GBP | G48: Budget Item ID | H48: Evidence Ref | I48: Source Ref | J48: Reversal Of | K48: Notes | L48: Import Status

Sheet 5) Refresh Log
A1: Refresh and approval log
A2: Audit gate for actuals, allocations and commitments; only APPROVED batches feed reporting
A4: Status value determines whether a newly imported transaction (batch) is added to ledger of actual costs. Enter 'STAGED' while still reviewing. Resolve ledger exceptions, record reviewer/notes, then change to APPROVED.
A7: Batch ID | B7: Data Type | C7: Source File/System | D7: Cut-off | E7: Refresh Timestamp | F7: Status | G7: Expected Rows | H7: Loaded Rows | I7: Source Control £ | J7: Loaded Amount £ | K7: Difference £ | L7: Reviewer | M7: Notes
A8: DEMO-2026-08 | B8: Actuals | C8: ILLUSTRATIVE_GL_2026-08.csv | D8: 46265 | E8: 46266.375 | F8: APPROVED | G8: 56 | H8: =IF(B8="Actuals",COUNTIF('6) Actuals Ledger - DI Costs'!$B$8:$B$2007,A8),IF(B8="Allocations",COUNTIF('7) Allocations - DA Costs'!$B$8:$B$2007,A8),IF(B8="Commitments",COUNTIF('8) Commitments Forecast'!$B$8:$B$507,A8),0))) -> 56 | I8: 13751.2 | J8: =IF(B8="Actuals",SUMIF('6) Actuals Ledger - DI Costs'!$B$8:$B$2007,A8,'6) Actuals Ledger - DI Costs'!$F$8:$F$2007),IF(B8="Allocations",SUMIF('7) Allocations - DA Costs'!$B$8:$B$2007,A8,'7) Allocations - DA Costs'!$E$8:$E$2007),IF(B8="Commitments",SUMIF('8) Commitments Forecast'!$B$8:$B$507,A8,'8) Commitments Forecast'!$G$8:$G$507),0))) -> 13751.2 | K8: =J8-I8 -> 0 | L8: Portfolio reviewer | M8: Hypothetical cumulative transaction extract through 31 August 2026.
A9: ALLOC-2026-08 | B9: Allocations | C9: ILLUSTRATIVE_ALLOC_SCHEDULE_2026-08 | D9: 46265 | E9: 46266.375 | F9: APPROVED | G9: 75 | H9: =IF(B9="Actuals",COUNTIF('6) Actuals Ledger - DI Costs'!$B$8:$B$2007,A9),IF(B9="Allocations",COUNTIF('7) Allocations - DA Costs'!$B$8:$B$2007,A9),IF(B9="Commitments",COUNTIF('8) Commitments Forecast'!$B$8:$B$507,A9),0))) -> 75 | I9: 21837.92 | J9: =IF(B9="Actuals",SUMIF('6) Actuals Ledger - DI Costs'!$B$8:$B$2007,A9,'6) Actuals Ledger - DI Costs'!$F$8:$F$2007),IF(B9="Allocations",SUMIF('7) Allocations - DA Costs'!$B$8:$B$2007,A9,'7) Allocations - DA Costs'!$E$8:$E$2007),IF(B9="Commitments",SUMIF('8) Commitments Forecast'!$B$8:$B$507,A9,'8) Commitments Forecast'!$G$8:$G$507),0))) -> 21837.92 | K9: =J9-I9 -> 0 | L9: Portfolio reviewer | M9: Illustrative allocation postings; not DI evidence.
A10: COMMIT-2026-08 | B10: Commitments | C10: ILLUSTRATIVE_COMMITMENT_REGISTER_2026-08 | D10: 46265 | E10: 46266.375 | F10: APPROVED | G10: 10 | H10: =IF(B10="Actuals",COUNTIF('6) Actuals Ledger - DI Costs'!$B$8:$B$2007,A10),IF(B10="Allocations",COUNTIF('7) Allocations - DA Costs'!$B$8:$B$2007,A10),IF(B10="Commitments",COUNTIF('8) Commitments Forecast'!$B$8:$B$507,A10),0))) -> 10 | I10: 27200 | J10: =IF(B10="Actuals",SUMIF('6) Actuals Ledger - DI Costs'!$B$8:$B$2007,A10,'6) Actuals Ledger - DI Costs'!$F$8:$F$2007),IF(B10="Allocations",SUMIF('7) Allocations - DA Costs'!$B$8:$B$2007,A10,'7) Allocations - DA Costs'!$E$8:$E$2007),IF(B10="Commitments",SUMIF('8) Commitments Forecast'!$B$8:$B$507,A10,'8) Commitments Forecast'!$G$8:$G$507),0))) -> 27200 | K10: =J10-I10 -> 0 | L10: Portfolio reviewer | M10: Hypothetical open commitments as at 31 August 2026.

Sheet 6) Actuals Ledger - DI Costs
A1: Accepted DI transaction ledger
A2: One transaction/source per row. Blue columns are pasted/imported values from previous batches. Adjacent formulas map and validate against standardised fCE headings
A4: Only accepted Directly Incurred transactions belong here. DA staff, estates and indirect charges are held on the separate Allocations sheet. Negative values require a valid Reversal Of transaction ID.
A7: Transaction ID | B7: Batch ID | C7: Accounting Date | D7: Incurred Date | E7: Description | F7: Amount GBP | G7: Budget Item ID | H7: Evidence Ref | I7: Source Ref | J7: Reversal Of | K7: Notes | L7: Batch Approved | M7: Work Package | N7: fEC Heading | O7: fEC Subheading | P7: Funding Rate | Q7: Row Status | R7: Included GBP | S7: Included UKRI | T7: Included RUSI
A8: DEMO-2026-04-001 | B8: DEMO-2026-08 | C8: 46142 | D8: 46124 | E8: UK rail and local travel for network scoping | F8: 212.4 | G8: WP1_TRAVEL | H8: EVID-202604-001 | I8: ILLUSTRATIVE_GL_2026-08.csv | K8: Hypothetical portfolio transaction; not RUSI accounting data. | L8: =IF(A8="","",IF(COUNTIFS('5) Refresh Log'!$A$8:$A$107,B8,'5) Refresh Log'!$F$8:$F$107,"APPROVED")>0,"YES","NO")) -> YES | M8: =IFERROR(INDEX('12) Budget Line Mapping'!$C$8:$C$37,MATCH(G8,'12) Budget Line Mapping'!$A$8:$A$37,0)),"") -> WP1 | N8: =IFERROR(INDEX('12) Budget Line Mapping'!$D$8:$D$37,MATCH(G8,'12) Budget Line Mapping'!$A$8:$A$37,0)),"") -> Directly Incurred | O8: =IFERROR(INDEX('12) Budget Line Mapping'!$E$8:$E$37,MATCH(G8,'12) Budget Line Mapping'!$A$8:$A$37,0)),"") -> Travel & Subsistence | P8: =IFERROR(INDEX('12) Budget Line Mapping'!$G$8:$G$37,MATCH(G8,'12) Budget Line Mapping'!$A$8:$A$37,0)),0) -> 0.8 | Q8: =IF(A8="","",IF(COUNTIF($A$8:$A$2007,A8)>1,"DUPLICATE",IF(L8<>"YES","NOT APPROVED",IF(OR(C8="",D8="",F8="",G8=""),"MISSING REQUIRED",IF(OR(D8<'0) ReadMe and Contents'!$B$8,D8>'0) ReadMe and Contents'!$B$9),"OUT OF PERIOD",IF(M8="","UNMAPPED",IF(N8<>"Directly Incurred","WRONG LEDGER",IF(H8="","MISSING EVIDENCE",IF(AND(F8<0,OR(J8="",COUNTIF($A$8:$A$2007,J8)=0)),"REVERSAL LINK INVALID","OK"))))))))) -> OK | R8: =IF(Q8="OK",F8,0) -> 212.4 | S8: =R8*P8 -> 169.92 | T8: =R8-S8 -> 42.48
A9: DEMO-2026-04-002 | B9: DEMO-2026-08 | C9: 46142 | D9: 46130 | E9: Digital briefing template and launch communications | F9: 185 | G9: WP1_COMMS | H9: EVID-202604-002 | I9: ILLUSTRATIVE_GL_2026-08.csv | K9: Hypothetical portfolio transaction; not RUSI accounting data. | L9: =IF(A9="","",IF(COUNTIFS('5) Refresh Log'!$A$8:$A$107,B9,'5) Refresh Log'!$F$8:$F$107,"APPROVED")>0,"YES","NO")) -> YES | M9: =IFERROR(INDEX('12) Budget Line Mapping'!$C$8:$C$37,MATCH(G9,'12) Budget Line Mapping'!$A$8:$A$37,0)),"") -> WP1 | N9: =IFERROR(INDEX('12) Budget Line Mapping'!$D$8:$D$37,MATCH(G9,'12) Budget Line Mapping'!$A$8:$A$37,0)),"") -> Directly Incurred | O9: =IFERROR(INDEX('12) Budget Line Mapping'!$E$8:$E$37,MATCH(G9,'12) Budget Line Mapping'!$A$8:$A$37,0)),"") -> Other Directly Incurred | P9: =IFERROR(INDEX('12) Budget Line Mapping'!$G$8:$G$37,MATCH(G9,'12) Budget Line Mapping'!$A$8:$A$37,0)),0) -> 0.8 | Q9: =IF(A9="","",IF(COUNTIF($A$8:$A$2007,A9)>1,"DUPLICATE",IF(L9<>"YES","NOT APPROVED",IF(OR(C9="",D9="",F9="",G9=""),"MISSING REQUIRED",IF(OR(D9<'0) ReadMe and Contents'!$B$8,D9>'0) ReadMe and Contents'!$B$9),"OUT OF PERIOD",IF(M9="","UNMAPPED",IF(N9<>"Directly Incurred","WRONG LEDGER",IF(H9="","MISSING EVIDENCE",IF(AND(F9<0,OR(J9="",COUNTIF($A$8:$A$2007,J9)=0)),"REVERSAL LINK INVALID","OK"))))))))) -> OK | R9: =IF(Q9="OK",F9,0) -> 185 | S9: =R9*P9 -> 148 | T9: =R9-S9 -> 37
A10: DEMO-2026-04-003 | B10: DEMO-2026-08 | C10: 46142 | D10: 46134 | E10: Nairobi network broker - one consultant day | F10: 350 | G10: WP2_CONSULT | H10: EVID-202604-003 | I10: ILLUSTRATIVE_GL_2026-08.csv | K10: Hypothetical portfolio transaction; not RUSI accounting data. | L10: =IF(A10="","",IF(COUNTIFS('5) Refresh Log'!$A$8:$A$107,B10,'5) Refresh Log'!$F$8:$F$107,"APPROVED")>0,"YES","NO")) -> YES | M10: =IFERROR(INDEX('12) Budget Line Mapping'!$C$8:$C$37,MATCH(G10,'12) Budget Line Mapping'!$A$8:$A$37,0)),"") -> WP2 | N10: =IFERROR(INDEX('12) Budget Line Mapping'!$D$8:$D$37,MATCH(G10,'12) Budget Line Mapping'!$A$8:$A$37,0)),"") -> Directly Incurred | O10: =IFERROR(INDEX('12) Budget Line Mapping'!$E$8:$E$37,MATCH(G10,'12) Budget Line Mapping'!$A$8:$A$37,0)),"") -> Other Directly Incurred | P10: =IFERROR(INDEX('12) Budget Line Mapping'!$G$8:$G$37,MATCH(G10,'12) Budget Line Mapping'!$A$8:$A$37,0)),0) -> 0.8 | Q10: =IF(A10="","",IF(COUNTIF($A$8:$A$2007,A10)>1,"DUPLICATE",IF(L10<>"YES","NOT APPROVED",IF(OR(C10="",D10="",F10="",G10=""),"MISSING REQUIRED",IF(OR(D10<'0) ReadMe and Contents'!$B$8,D10>'0) ReadMe and Contents'!$B$9),"OUT OF PERIOD",IF(M10="","UNMAPPED",IF(N10<>"Directly Incurred","WRONG LEDGER",IF(H10="","MISSING EVIDENCE",IF(AND(F10<0,OR(J10="",COUNTIF($A$8:$A$2007,J10)=0)),"REVERSAL LINK INVALID","OK"))))))))) -> OK | R10: =IF(Q10="OK",F10,0) -> 350 | S10: =R10*P10 -> 280 | T10: =R10-S10 -> 70
A11: DEMO-2026-04-004 | B11: DEMO-2026-08 | C11: 46142 | D11: 46136 | E11: Regional stakeholder local travel | F11: 145 | G11: WP2_TRAVEL | H11: EVID-202604-004 | I11: ILLUSTRATIVE_GL_2026-08.csv | K11: Hypothetical portfolio transaction; not RUSI accounting data. | L11: =IF(A11="","",IF(COUNTIFS('5) Refresh Log'!$A$8:$A$107,B11,'5) Refresh Log'!$F$8:$F$107,"APPROVED")>0,"YES","NO")) -> YES | M11: =IFERROR(INDEX('12) Budget Line Mapping'!$C$8:$C$37,MATCH(G11,'12) Budget Line Mapping'!$A$8:$A$37,0)),"") -> WP2 | N11: =IFERROR(INDEX('12) Budget Line Mapping'!$D$8:$D$37,MATCH(G11,'12) Budget Line Mapping'!$A$8:$A$37,0)),"") -> Directly Incurred | O11: =IFERROR(INDEX('12) Budget Line Mapping'!$E$8:$E$37,MATCH(G11,'12) Budget Line Mapping'!$A$8:$A$37,0)),"") -> Travel & Subsistence | P11: =IFERROR(INDEX('12) Budget Line Mapping'!$G$8:$G$37,MATCH(G11,'12) Budget Line Mapping'!$A$8:$A$37,0)),0) -> 0.8 | Q11: =IF(A11="","",IF(COUNTIF($A$8:$A$2007,A11)>1,"DUPLICATE",IF(L11<>"YES","NOT APPROVED",IF(OR(C11="",D11="",F11="",G11=""),"MISSING REQUIRED",IF(OR(D11<'0) ReadMe and Contents'!$B$8,D11>'0) ReadMe and Contents'!$B$9),"OUT OF PERIOD",IF(M11="","UNMAPPED",IF(N11<>"Directly Incurred","WRONG LEDGER",IF(H11="","MISSING EVIDENCE",IF(AND(F11<0,OR(J11="",COUNTIF($A$8:$A$2007,J11)=0)),"REVERSAL LINK INVALID","OK"))))))))) -> OK | R11: =IF(Q11="OK",F11,0) -> 145 | S11: =R11*P11 -> 116 | T11: =R11-S11 -> 29
A12: DEMO-2026-04-005 | B12: DEMO-2026-08 | C12: 46142 | D12: 46138 | E12: Participant briefing materials | F12: 75 | G12: WP2_COMMS | H12: EVID-202604-005 | I12: ILLUSTRATIVE_GL_2026-08.csv | K12: Hypothetical portfolio transaction; not RUSI accounting data. | L12: =IF(A12="","",IF(COUNTIFS('5) Refresh Log'!$A$8:$A$107,B12,'5) Refresh Log'!$F$8:$F$107,"APPROVED")>0,"YES","NO")) -> YES | M12: =IFERROR(INDEX('12) Budget Line Mapping'!$C$8:$C$37,MATCH(G12,'12) Budget Line Mapping'!$A$8:$A$37,0)),"") -> WP2 | N12: =IFERROR(INDEX('12) Budget Line Mapping'!$D$8:$D$37,MATCH(G12,'12) Budget Line Mapping'!$A$8:$A$37,0)),"") -> Directly Incurred | O12: =IFERROR(INDEX('12) Budget Line Mapping'!$E$8:$E$37,MATCH(G12,'12) Budget Line Mapping'!$A$8:$A$37,0)),"") -> Other Directly Incurred | P12: =IFERROR(INDEX('12) Budget Line Mapping'!$G$8:$G$37,MATCH(G12,'12) Budget Line Mapping'!$A$8:$A$37,0)),0) -> 0.8 | Q12: =IF(A12="","",IF(COUNTIF($A$8:$A$2007,A12)>1,"DUPLICATE",IF(L12<>"YES","NOT APPROVED",IF(OR(C12="",D12="",F12="",G12=""),"MISSING REQUIRED",IF(OR(D12<'0) ReadMe and Contents'!$B$8,D12>'0) ReadMe and Contents'!$B$9),"OUT OF PERIOD",IF(M12="","UNMAPPED",IF(N12<>"Directly Incurred","WRONG LEDGER",IF(H12="","MISSING EVIDENCE",IF(AND(F12<0,OR(J12="",COUNTIF($A$8:$A$2007,J12)=0)),"REVERSAL LINK INVALID","OK"))))))))) -> OK | R12: =IF(Q12="OK",F12,0) -> 75 | S12: =R12*P12 -> 60 | T12: =R12-S12 -> 15
A13: DEMO-2026-04-006 | B13: DEMO-2026-08 | C13: 46142 | D13: 46133 | E13: Latin America network broker - one consultant day | F13: 350 | G13: WP3_CONSULT | H13: EVID-202604-006 | I13: ILLUSTRATIVE_GL_2026-08.csv | K13: Hypothetical portfolio transaction; not RUSI accounting data. | L13: =IF(A13="","",IF(COUNTIFS('5) Refresh Log'!$A$8:$A$107,B13,'5) Refresh Log'!$F$8:$F$107,"APPROVED")>0,"YES","NO")) -> YES | M13: =IFERROR(INDEX('12) Budget Line Mapping'!$C$8:$C$37,MATCH(G13,'12) Budget Line Mapping'!$A$8:$A$37,0)),"") -> WP3 | N13: =IFERROR(INDEX('12) Budget Line Mapping'!$D$8:$D$37,MATCH(G13,'12) Budget Line Mapping'!$A$8:$A$37,0)),"") -> Directly Incurred | O13: =IFERROR(INDEX('12) Budget Line Mapping'!$E$8:$E$37,MATCH(G13,'12) Budget Line Mapping'!$A$8:$A$37,0)),"") -> Other Directly Incurred | P13: =IFERROR(INDEX('12) Budget Line Mapping'!$G$8:$G$37,MATCH(G13,'12) Budget Line Mapping'!$A$8:$A$37,0)),0) -> 0.8 | Q13: =IF(A13="","",IF(COUNTIF($A$8:$A$2007,A13)>1,"DUPLICATE",IF(L13<>"YES","NOT APPROVED",IF(OR(C13="",D13="",F13="",G13=""),"MISSING REQUIRED",IF(OR(D13<'0) ReadMe and Contents'!$B$8,D13>'0) ReadMe and Contents'!$B$9),"OUT OF PERIOD",IF(M13="","UNMAPPED",IF(N13<>"Directly Incurred","WRONG LEDGER",IF(H13="","MISSING EVIDENCE",IF(AND(F13<0,OR(J13="",COUNTIF($A$8:$A$2007,J13)=0)),"REVERSAL LINK INVALID","OK"))))))))) -> OK | R13: =IF(Q13="OK",F13,0) -> 350 | S13: =R13*P13 -> 280 | T13: =R13-S13 -> 70
A14: DEMO-2026-04-007 | B14: DEMO-2026-08 | C14: 46142 | D14: 46139 | E14: Spanish-language stakeholder materials | F14: 95 | G14: WP3_COMMS | H14: EVID-202604-007 | I14: ILLUSTRATIVE_GL_2026-08.csv | K14: Hypothetical portfolio transaction; not RUSI accounting data. | L14: =IF(A14="","",IF(COUNTIFS('5) Refresh Log'!$A$8:$A$107,B14,'5) Refresh Log'!$F$8:$F$107,"APPROVED")>0,"YES","NO")) -> YES | M14: =IFERROR(INDEX('12) Budget Line Mapping'!$C$8:$C$37,MATCH(G14,'12) Budget Line Mapping'!$A$8:$A$37,0)),"") -> WP3 | N14: =IFERROR(INDEX('12) Budget Line Mapping'!$D$8:$D$37,MATCH(G14,'12) Budget Line Mapping'!$A$8:$A$37,0)),"") -> Directly Incurred | O14: =IFERROR(INDEX('12) Budget Line Mapping'!$E$8:$E$37,MATCH(G14,'12) Budget Line Mapping'!$A$8:$A$37,0)),"") -> Other Directly Incurred | P14: =IFERROR(INDEX('12) Budget Line Mapping'!$G$8:$G$37,MATCH(G14,'12) Budget Line Mapping'!$A$8:$A$37,0)),0) -> 0.8 | Q14: =IF(A14="","",IF(COUNTIF($A$8:$A$2007,A14)>1,"DUPLICATE",IF(L14<>"YES","NOT APPROVED",IF(OR(C14="",D14="",F14="",G14=""),"MISSING REQUIRED",IF(OR(D14<'0) ReadMe and Contents'!$B$8,D14>'0) ReadMe and Contents'!$B$9),"OUT OF PERIOD",IF(M14="","UNMAPPED",IF(N14<>"Directly Incurred","WRONG LEDGER",IF(H14="","MISSING EVIDENCE",IF(AND(F14<0,OR(J14="",COUNTIF($A$8:$A$2007,J14)=0)),"REVERSAL LINK INVALID","OK"))))))))) -> OK | R14: =IF(Q14="OK",F14,0) -> 95 | S14: =R14*P14 -> 76 | T14: =R14-S14 -> 19
A15: DEMO-2026-05-008 | B15: DEMO-2026-08 | C15: 46173 | D15: 46148 | E15: UK stakeholder rail travel and subsistence | F15: 318.2 | G15: WP1_TRAVEL | H15: EVID-202605-008 | I15: ILLUSTRATIVE_GL_2026-08.csv | K15: Hypothetical portfolio transaction; not RUSI accounting data. | L15: =IF(A15="","",IF(COUNTIFS('5) Refresh Log'!$A$8:$A$107,B15,'5) Refresh Log'!$F$8:$F$107,"APPROVED")>0,"YES","NO")) -> YES | M15: =IFERROR(INDEX('12) Budget Line Mapping'!$C$8:$C$37,MATCH(G15,'12) Budget Line Mapping'!$A$8:$A$37,0)),"") -> WP1 | N15: =IFERROR(INDEX('12) Budget Line Mapping'!$D$8:$D$37,MATCH(G15,'12) Budget Line Mapping'!$A$8:$A$37,0)),"") -> Directly Incurred | O15: =IFERROR(INDEX('12) Budget Line Mapping'!$E$8:$E$37,MATCH(G15,'12) Budget Line Mapping'!$A$8:$A$37,0)),"") -> Travel & Subsistence | P15: =IFERROR(INDEX('12) Budget Line Mapping'!$G$8:$G$37,MATCH(G15,'12) Budget Line Mapping'!$A$8:$A$37,0)),0) -> 0.8 | Q15: =IF(A15="","",IF(COUNTIF($A$8:$A$2007,A15)>1,"DUPLICATE",IF(L15<>"YES","NOT APPROVED",IF(OR(C15="",D15="",F15="",G15=""),"MISSING REQUIRED",IF(OR(D15<'0) ReadMe and Contents'!$B$8,D15>'0) ReadMe and Contents'!$B$9),"OUT OF PERIOD",IF(M15="","UNMAPPED",IF(N15<>"Directly Incurred","WRONG LEDGER",IF(H15="","MISSING EVIDENCE",IF(AND(F15<0,OR(J15="",COUNTIF($A$8:$A$2007,J15)=0)),"REVERSAL LINK INVALID","OK"))))))))) -> OK | R15: =IF(Q15="OK",F15,0) -> 318.2 | S15: =R15*P15 -> 254.56 | T15: =R15-S15 -> 63.64
A16: DEMO-2026-05-009 | B16: DEMO-2026-08 | C16: 46173 | D16: 46153 | E16: UK workshop room hire and catering | F16: 620 | G16: WP1_WORKSHOP | H16: EVID-202605-009 | I16: ILLUSTRATIVE_GL_2026-08.csv | K16: Hypothetical portfolio transaction; not RUSI accounting data. | L16: =IF(A16="","",IF(COUNTIFS('5) Refresh Log'!$A$8:$A$107,B16,'5) Refresh Log'!$F$8:$F$107,"APPROVED")>0,"YES","NO")) -> YES | M16: =IFERROR(INDEX('12) Budget Line Mapping'!$C$8:$C$37,MATCH(G16,'12) Budget Line Mapping'!$A$8:$A$37,0)),"") -> WP1 | N16: =IFERROR(INDEX('12) Budget Line Mapping'!$D$8:$D$37,MATCH(G16,'12) Budget Line Mapping'!$A$8:$A$37,0)),"") -> Directly Incurred | O16: =IFERROR(INDEX('12) Budget Line Mapping'!$E$8:$E$37,MATCH(G16,'12) Budget Line Mapping'!$A$8:$A$37,0)),"") -> Other Directly Incurred | P16: =IFERROR(INDEX('12) Budget Line Mapping'!$G$8:$G$37,MATCH(G16,'12) Budget Line Mapping'!$A$8:$A$37,0)),0) -> 0.8 | Q16: =IF(A16="","",IF(COUNTIF($A$8:$A$2007,A16)>1,"DUPLICATE",IF(L16<>"YES","NOT APPROVED",IF(OR(C16="",D16="",F16="",G16=""),"MISSING REQUIRED",IF(OR(D16<'0) ReadMe and Contents'!$B$8,D16>'0) ReadMe and Contents'!$B$9),"OUT OF PERIOD",IF(M16="","UNMAPPED",IF(N16<>"Directly Incurred","WRONG LEDGER",IF(H16="","MISSING EVIDENCE",IF(AND(F16<0,OR(J16="",COUNTIF($A$8:$A$2007,J16)=0)),"REVERSAL LINK INVALID","OK"))))))))) -> OK | R16: =IF(Q16="OK",F16,0) -> 620 | S16: =R16*P16 -> 496 | T16: =R16-S16 -> 124
A17: DEMO-2026-05-010 | B17: DEMO-2026-08 | C17: 46173 | D17: 46156 | E17: Hybrid panel technical support | F17: 240 | G17: WP1_PANEL | H17: EVID-202605-010 | I17: ILLUSTRATIVE_GL_2026-08.csv | K17: Hypothetical portfolio transaction; not RUSI accounting data. | L17: =IF(A17="","",IF(COUNTIFS('5) Refresh Log'!$A$8:$A$107,B17,'5) Refresh Log'!$F$8:$F$107,"APPROVED")>0,"YES","NO")) -> YES | M17: =IFERROR(INDEX('12) Budget Line Mapping'!$C$8:$C$37,MATCH(G17,'12) Budget Line Mapping'!$A$8:$A$37,0)),"") -> WP1 | N17: =IFERROR(INDEX('12) Budget Line Mapping'!$D$8:$D$37,MATCH(G17,'12) Budget Line Mapping'!$A$8:$A$37,0)),"") -> Directly Incurred | O17: =IFERROR(INDEX('12) Budget Line Mapping'!$E$8:$E$37,MATCH(G17,'12) Budget Line Mapping'!$A$8:$A$37,0)),"") -> Other Directly Incurred | P17: =IFERROR(INDEX('12) Budget Line Mapping'!$G$8:$G$37,MATCH(G17,'12) Budget Line Mapping'!$A$8:$A$37,0)),0) -> 0.8 | Q17: =IF(A17="","",IF(COUNTIF($A$8:$A$2007,A17)>1,"DUPLICATE",IF(L17<>"YES","NOT APPROVED",IF(OR(C17="",D17="",F17="",G17=""),"MISSING REQUIRED",IF(OR(D17<'0) ReadMe and Contents'!$B$8,D17>'0) ReadMe and Contents'!$B$9),"OUT OF PERIOD",IF(M17="","UNMAPPED",IF(N17<>"Directly Incurred","WRONG LEDGER",IF(H17="","MISSING EVIDENCE",IF(AND(F17<0,OR(J17="",COUNTIF($A$8:$A$2007,J17)=0)),"REVERSAL LINK INVALID","OK"))))))))) -> OK | R17: =IF(Q17="OK",F17,0) -> 240 | S17: =R17*P17 -> 192 | T17: =R17-S17 -> 48
A18: DEMO-2026-05-011 | B18: DEMO-2026-08 | C18: 46173 | D18: 46160 | E18: Digital event materials | F18: 110 | G18: WP1_COMMS | H18: EVID-202605-011 | I18: ILLUSTRATIVE_GL_2026-08.csv | K18: Hypothetical portfolio transaction; not RUSI accounting data. | L18: =IF(A18="","",IF(COUNTIFS('5) Refresh Log'!$A$8:$A$107,B18,'5) Refresh Log'!$F$8:$F$107,"APPROVED")>0,"YES","NO")) -> YES | M18: =IFERROR(INDEX('12) Budget Line Mapping'!$C$8:$C$37,MATCH(G18,'12) Budget Line Mapping'!$A$8:$A$37,0)),"") -> WP1 | N18: =IFERROR(INDEX('12) Budget Line Mapping'!$D$8:$D$37,MATCH(G18,'12) Budget Line Mapping'!$A$8:$A$37,0)),"") -> Directly Incurred | O18: =IFERROR(INDEX('12) Budget Line Mapping'!$E$8:$E$37,MATCH(G18,'12) Budget Line Mapping'!$A$8:$A$37,0)),"") -> Other Directly Incurred | P18: =IFERROR(INDEX('12) Budget Line Mapping'!$G$8:$G$37,MATCH(G18,'12) Budget Line Mapping'!$A$8:$A$37,0)),0) -> 0.8 | Q18: =IF(A18="","",IF(COUNTIF($A$8:$A$2007,A18)>1,"DUPLICATE",IF(L18<>"YES","NOT APPROVED",IF(OR(C18="",D18="",F18="",G18=""),"MISSING REQUIRED",IF(OR(D18<'0) ReadMe and Contents'!$B$8,D18>'0) ReadMe and Contents'!$B$9),"OUT OF PERIOD",IF(M18="","UNMAPPED",IF(N18<>"Directly Incurred","WRONG LEDGER",IF(H18="","MISSING EVIDENCE",IF(AND(F18<0,OR(J18="",COUNTIF($A$8:$A$2007,J18)=0)),"REVERSAL LINK INVALID","OK"))))))))) -> OK | R18: =IF(Q18="OK",F18,0) -> 110 | S18: =R18*P18 -> 88 | T18: =R18-S18 -> 22
A19: DEMO-2026-05-012 | B19: DEMO-2026-08 | C19: 46173 | D19: 46162 | E19: Nairobi network broker - one consultant day | F19: 350 | G19: WP2_CONSULT | H19: EVID-202605-012 | I19: ILLUSTRATIVE_GL_2026-08.csv | K19: Hypothetical portfolio transaction; not RUSI accounting data. | L19: =IF(A19="","",IF(COUNTIFS('5) Refresh Log'!$A$8:$A$107,B19,'5) Refresh Log'!$F$8:$F$107,"APPROVED")>0,"YES","NO")) -> YES | M19: =IFERROR(INDEX('12) Budget Line Mapping'!$C$8:$C$37,MATCH(G19,'12) Budget Line Mapping'!$A$8:$A$37,0)),"") -> WP2 | N19: =IFERROR(INDEX('12) Budget Line Mapping'!$D$8:$D$37,MATCH(G19,'12) Budget Line Mapping'!$A$8:$A$37,0)),"") -> Directly Incurred | O19: =IFERROR(INDEX('12) Budget Line Mapping'!$E$8:$E$37,MATCH(G19,'12) Budget Line Mapping'!$A$8:$A$37,0)),"") -> Other Directly Incurred | P19: =IFERROR(INDEX('12) Budget Line Mapping'!$G$8:$G$37,MATCH(G19,'12) Budget Line Mapping'!$A$8:$A$37,0)),0) -> 0.8 | Q19: =IF(A19="","",IF(COUNTIF($A$8:$A$2007,A19)>1,"DUPLICATE",IF(L19<>"YES","NOT APPROVED",IF(OR(C19="",D19="",F19="",G19=""),"MISSING REQUIRED",IF(OR(D19<'0) ReadMe and Contents'!$B$8,D19>'0) ReadMe and Contents'!$B$9),"OUT OF PERIOD",IF(M19="","UNMAPPED",IF(N19<>"Directly Incurred","WRONG LEDGER",IF(H19="","MISSING EVIDENCE",IF(AND(F19<0,OR(J19="",COUNTIF($A$8:$A$2007,J19)=0)),"REVERSAL LINK INVALID","OK"))))))))) -> OK | R19: =IF(Q19="OK",F19,0) -> 350 | S19: =R19*P19 -> 280 | T19: =R19-S19 -> 70
... A62: DEMO-2026-08-055 | B62: DEMO-2026-08 | C62: 46265 | D62: 46261 | E62: Translation and digital materials | F62: 65 | G62: WP3_COMMS | H62: EVID-202608-055 | I62: ILLUSTRATIVE_GL_2026-08.csv | K62: Hypothetical portfolio transaction; not RUSI accounting data. | L62: =IF(A62="","",IF(COUNTIFS('5) Refresh Log'!$A$8:$A$107,B62,'5) Refresh Log'!$F$8:$F$107,"APPROVED")>0,"YES","NO")) -> YES | M62: =IFERROR(INDEX('12) Budget Line Mapping'!$C$8:$C$37,MATCH(G62,'12) Budget Line Mapping'!$A$8:$A$37,0)),"") -> WP3 | N62: =IFERROR(INDEX('12) Budget Line Mapping'!$D$8:$D$37,MATCH(G62,'12) Budget Line Mapping'!$A$8:$A$37,0)),"") -> Directly Incurred | O62: =IFERROR(INDEX('12) Budget Line Mapping'!$E$8:$E$37,MATCH(G62,'12) Budget Line Mapping'!$A$8:$A$37,0)),"") -> Other Directly Incurred | P62: =IFERROR(INDEX('12) Budget Line Mapping'!$G$8:$G$37,MATCH(G62,'12) Budget Line Mapping'!$A$8:$A$37,0)),0) -> 0.8 | Q62: =IF(A62="","",IF(COUNTIF($A$8:$A$2007,A62)>1,"DUPLICATE",IF(L62<>"YES","NOT APPROVED",IF(OR(C62="",D62="",F62="",G62=""),"MISSING REQUIRED",IF(OR(D62<'0) ReadMe and Contents'!$B$8,D62>'0) ReadMe and Contents'!$B$9),"OUT OF PERIOD",IF(M62="","UNMAPPED",IF(N62<>"Directly Incurred","WRONG LEDGER",IF(H62="","MISSING EVIDENCE",IF(AND(F62<0,OR(J62="",COUNTIF($A$8:$A$2007,J62)=0)),"REVERSAL LINK INVALID","OK"))))))))) -> OK | R62: =IF(Q62="OK",F62,0) -> 65 | S62: =R62*P62 -> 52 | T62: =R62-S62 -> 13
A63: DEMO-2026-08-056 | B63: DEMO-2026-08 | C63: 46265 | D63: 46263 | E63: Rail ticket refund/credit note | F63: -85 | G63: WP1_TRAVEL | H63: CRN-202608-056 | I63: ILLUSTRATIVE_GL_2026-08.csv | J63: DEMO-2026-05-008 | K63: Hypothetical portfolio transaction; not RUSI accounting data. | L63: =IF(A63="","",IF(COUNTIFS('5) Refresh Log'!$A$8:$A$107,B63,'5) Refresh Log'!$F$8:$F$107,"APPROVED")>0,"YES","NO")) -> YES | M63: =IFERROR(INDEX('12) Budget Line Mapping'!$C$8:$C$37,MATCH(G63,'12) Budget Line Mapping'!$A$8:$A$37,0)),"") -> WP1 | N63: =IFERROR(INDEX('12) Budget Line Mapping'!$D$8:$D$37,MATCH(G63,'12) Budget Line Mapping'!$A$8:$A$37,0)),"") -> Directly Incurred | O63: =IFERROR(INDEX('12) Budget Line Mapping'!$E$8:$E$37,MATCH(G63,'12) Budget Line Mapping'!$A$8:$A$37,0)),"") -> Travel & Subsistence | P63: =IFERROR(INDEX('12) Budget Line Mapping'!$G$8:$G$37,MATCH(G63,'12) Budget Line Mapping'!$A$8:$A$37,0)),0) -> 0.8 | Q63: =IF(A63="","",IF(COUNTIF($A$8:$A$2007,A63)>1,"DUPLICATE",IF(L63<>"YES","NOT APPROVED",IF(OR(C63="",D63="",F63="",G63=""),"MISSING REQUIRED",IF(OR(D63<'0) ReadMe and Contents'!$B$8,D63>'0) ReadMe and Contents'!$B$9),"OUT OF PERIOD",IF(M63="","UNMAPPED",IF(N63<>"Directly Incurred","WRONG LEDGER",IF(H63="","MISSING EVIDENCE",IF(AND(F63<0,OR(J63="",COUNTIF($A$8:$A$2007,J63)=0)),"REVERSAL LINK INVALID","OK"))))))))) -> OK | R63: =IF(Q63="OK",F63,0) -> -85 | S63: =R63*P63 -> -68 | T63: =R63-S63 -> -17

Sheet 7) Allocations - DA Costs
A1: Recognised allocation ledger
A2: Directly Allocated (DA) staff, estates and indirect management costs.
A4: The below are arbitrary transaction records produced for the purposes of this model demonstration.
A7: Allocation ID | B7: Batch ID | C7: Period End | D7: Budget Item ID | E7: Amount GBP | F7: Allocation Basis | G7: Source Ref | H7: Notes | I7: Batch Approved | J7: Work Package | K7: fEC Heading | L7: fEC Subheading | M7: Funding Rate | N7: Row Status | O7: Included GBP | P7: Included UKRI | Q7: Included RUSI
A8: ALLOC-202604-WP1_S01 | B8: ALLOC-2026-08 | C8: 46142 | D8: WP1_S01 | E8: 317.27 | F8: Illustrative monthly management allocation; not DI transaction evidence | G8: ILLUSTRATIVE_ALLOC_SCHEDULE_2026-08 | H8: Applied at 97% of the phased monthly amount for demonstration. | I8: =IF(A8="","",IF(COUNTIFS('5) Refresh Log'!$A$8:$A$107,B8,'5) Refresh Log'!$F$8:$F$107,"APPROVED")>0,"YES","NO")) -> YES | J8: =IFERROR(INDEX('12) Budget Line Mapping'!$C$8:$C$37,MATCH(D8,'12) Budget Line Mapping'!$A$8:$A$37,0)),"") -> WP1 | K8: =IFERROR(INDEX('12) Budget Line Mapping'!$D$8:$D$37,MATCH(D8,'12) Budget Line Mapping'!$A$8:$A$37,0)),"") -> Directly Allocated | L8: =IFERROR(INDEX('12) Budget Line Mapping'!$E$8:$E$37,MATCH(D8,'12) Budget Line Mapping'!$A$8:$A$37,0)),"") -> Staff | M8: =IFERROR(INDEX('12) Budget Line Mapping'!$G$8:$G$37,MATCH(D8,'12) Budget Line Mapping'!$A$8:$A$37,0)),0) -> 0.8 | N8: =IF(A8="","",IF(COUNTIF($A$8:$A$2007,A8)>1,"DUPLICATE",IF(I8<>"YES","NOT APPROVED",IF(OR(C8="",D8="",E8="",F8="",G8=""),"MISSING REQUIRED",IF(OR(C8<'0) ReadMe and Contents'!$B$8,C8>'0) ReadMe and Contents'!$B$9),"OUT OF PERIOD",IF(J8="","UNMAPPED",IF(K8="Directly Incurred","WRONG LEDGER","OK"))))))) -> OK | O8: =IF(N8="OK",E8,0) -> 317.27 | P8: =O8*M8 -> 253.816 | Q8: =O8-P8 -> 63.454
A9: ALLOC-202605-WP1_S01 | B9: ALLOC-2026-08 | C9: 46173 | D9: WP1_S01 | E9: 327.08 | F9: Illustrative monthly management allocation; not DI transaction evidence | G9: ILLUSTRATIVE_ALLOC_SCHEDULE_2026-08 | H9: Applied at 100% of the phased monthly amount for demonstration. | I9: =IF(A9="","",IF(COUNTIFS('5) Refresh Log'!$A$8:$A$107,B9,'5) Refresh Log'!$F$8:$F$107,"APPROVED")>0,"YES","NO")) -> YES | J9: =IFERROR(INDEX('12) Budget Line Mapping'!$C$8:$C$37,MATCH(D9,'12) Budget Line Mapping'!$A$8:$A$37,0)),"") -> WP1 | K9: =IFERROR(INDEX('12) Budget Line Mapping'!$D$8:$D$37,MATCH(D9,'12) Budget Line Mapping'!$A$8:$A$37,0)),"") -> Directly Allocated | L9: =IFERROR(INDEX('12) Budget Line Mapping'!$E$8:$E$37,MATCH(D9,'12) Budget Line Mapping'!$A$8:$A$37,0)),"") -> Staff | M9: =IFERROR(INDEX('12) Budget Line Mapping'!$G$8:$G$37,MATCH(D9,'12) Budget Line Mapping'!$A$8:$A$37,0)),0) -> 0.8 | N9: =IF(A9="","",IF(COUNTIF($A$8:$A$2007,A9)>1,"DUPLICATE",IF(I9<>"YES","NOT APPROVED",IF(OR(C9="",D9="",E9="",F9="",G9=""),"MISSING REQUIRED",IF(OR(C9<'0) ReadMe and Contents'!$B$8,C9>'0) ReadMe and Contents'!$B$9),"OUT OF PERIOD",IF(J9="","UNMAPPED",IF(K9="Directly Incurred","WRONG LEDGER","OK"))))))) -> OK | O9: =IF(N9="OK",E9,0) -> 327.08 | P9: =O9*M9 -> 261.664 | Q9: =O9-P9 -> 65.416
A10: ALLOC-202606-WP1_S01 | B10: ALLOC-2026-08 | C10: 46203 | D10: WP1_S01 | E10: 323.81 | F10: Illustrative monthly management allocation; not DI transaction evidence | G10: ILLUSTRATIVE_ALLOC_SCHEDULE_2026-08 | H10: Applied at 99% of the phased monthly amount for demonstration. | I10: =IF(A10="","",IF(COUNTIFS('5) Refresh Log'!$A$8:$A$107,B10,'5) Refresh Log'!$F$8:$F$107,"APPROVED")>0,"YES","NO")) -> YES | J10: =IFERROR(INDEX('12) Budget Line Mapping'!$C$8:$C$37,MATCH(D10,'12) Budget Line Mapping'!$A$8:$A$37,0)),"") -> WP1 | K10: =IFERROR(INDEX('12) Budget Line Mapping'!$D$8:$D$37,MATCH(D10,'12) Budget Line Mapping'!$A$8:$A$37,0)),"") -> Directly Allocated | L10: =IFERROR(INDEX('12) Budget Line Mapping'!$E$8:$E$37,MATCH(D10,'12) Budget Line Mapping'!$A$8:$A$37,0)),"") -> Staff | M10: =IFERROR(INDEX('12) Budget Line Mapping'!$G$8:$G$37,MATCH(D10,'12) Budget Line Mapping'!$A$8:$A$37,0)),0) -> 0.8 | N10: =IF(A10="","",IF(COUNTIF($A$8:$A$2007,A10)>1,"DUPLICATE",IF(I10<>"YES","NOT APPROVED",IF(OR(C10="",D10="",E10="",F10="",G10=""),"MISSING REQUIRED",IF(OR(C10<'0) ReadMe and Contents'!$B$8,C10>'0) ReadMe and Contents'!$B$9),"OUT OF PERIOD",IF(J10="","UNMAPPED",IF(K10="Directly Incurred","WRONG LEDGER","OK"))))))) -> OK | O10: =IF(N10="OK",E10,0) -> 323.81 | P10: =O10*M10 -> 259.048 | Q10: =O10-P10 -> 64.762
A11: ALLOC-202607-WP1_S01 | B11: ALLOC-2026-08 | C11: 46234 | D11: WP1_S01 | E11: 330.35 | F11: Illustrative monthly management allocation; not DI transaction evidence | G11: ILLUSTRATIVE_ALLOC_SCHEDULE_2026-08 | H11: Applied at 101% of the phased monthly amount for demonstration. | I11: =IF(A11="","",IF(COUNTIFS('5) Refresh Log'!$A$8:$A$107,B11,'5) Refresh Log'!$F$8:$F$107,"APPROVED")>0,"YES","NO")) -> YES | J11: =IFERROR(INDEX('12) Budget Line Mapping'!$C$8:$C$37,MATCH(D11,'12) Budget Line Mapping'!$A$8:$A$37,0)),"") -> WP1 | K11: =IFERROR(INDEX('12) Budget Line Mapping'!$D$8:$D$37,MATCH(D11,'12) Budget Line Mapping'!$A$8:$A$37,0)),"") -> Directly Allocated | L11: =IFERROR(INDEX('12) Budget Line Mapping'!$E$8:$E$37,MATCH(D11,'12) Budget Line Mapping'!$A$8:$A$37,0)),"") -> Staff | M11: =IFERROR(INDEX('12) Budget Line Mapping'!$G$8:$G$37,MATCH(D11,'12) Budget Line Mapping'!$A$8:$A$37,0)),0) -> 0.8 | N11: =IF(A11="","",IF(COUNTIF($A$8:$A$2007,A11)>1,"DUPLICATE",IF(I11<>"YES","NOT APPROVED",IF(OR(C11="",D11="",E11="",F11="",G11=""),"MISSING REQUIRED",IF(OR(C11<'0) ReadMe and Contents'!$B$8,C11>'0) ReadMe and Contents'!$B$9),"OUT OF PERIOD",IF(J11="","UNMAPPED",IF(K11="Directly Incurred","WRONG LEDGER","OK"))))))) -> OK | O11: =IF(N11="OK",E11,0) -> 330.35 | P11: =O11*M11 -> 264.28 | Q11: =O11-P11 -> 66.07
A12: ALLOC-202608-WP1_S01 | B12: ALLOC-2026-08 | C12: 46265 | D12: WP1_S01 | E12: 327.08 | F12: Illustrative monthly management allocation; not DI transaction evidence | G12: ILLUSTRATIVE_ALLOC_SCHEDULE_2026-08 | H12: Applied at 100% of the phased monthly amount for demonstration. | I12: =IF(A12="","",IF(COUNTIFS('5) Refresh Log'!$A$8:$A$107,B12,'5) Refresh Log'!$F$8:$F$107,"APPROVED")>0,"YES","NO")) -> YES | J12: =IFERROR(INDEX('12) Budget Line Mapping'!$C$8:$C$37,MATCH(D12,'12) Budget Line Mapping'!$A$8:$A$37,0)),"") -> WP1 | K12: =IFERROR(INDEX('12) Budget Line Mapping'!$D$8:$D$37,MATCH(D12,'12) Budget Line Mapping'!$A$8:$A$37,0)),"") -> Directly Allocated | L12: =IFERROR(INDEX('12) Budget Line Mapping'!$E$8:$E$37,MATCH(D12,'12) Budget Line Mapping'!$A$8:$A$37,0)),"") -> Staff | M12: =IFERROR(INDEX('12) Budget Line Mapping'!$G$8:$G$37,MATCH(D12,'12) Budget Line Mapping'!$A$8:$A$37,0)),0) -> 0.8 | N12: =IF(A12="","",IF(COUNTIF($A$8:$A$2007,A12)>1,"DUPLICATE",IF(I12<>"YES","NOT APPROVED",IF(OR(C12="",D12="",E12="",F12="",G12=""),"MISSING REQUIRED",IF(OR(C12<'0) ReadMe and Contents'!$B$8,C12>'0) ReadMe and Contents'!$B$9),"OUT OF PERIOD",IF(J12="","UNMAPPED",IF(K12="Directly Incurred","WRONG LEDGER","OK"))))))) -> OK | O12: =IF(N12="OK",E12,0) -> 327.08 | P12: =O12*M12 -> 261.664 | Q12: =O12-P12 -> 65.416
A13: ALLOC-202604-WP1_S02 | B13: ALLOC-2026-08 | C13: 46142 | D13: WP1_S02 | E13: 351.02 | F13: Illustrative monthly management allocation; not DI transaction evidence | G13: ILLUSTRATIVE_ALLOC_SCHEDULE_2026-08 | H13: Applied at 97% of the phased monthly amount for demonstration. | I13: =IF(A13="","",IF(COUNTIFS('5) Refresh Log'!$A$8:$A$107,B13,'5) Refresh Log'!$F$8:$F$107,"APPROVED")>0,"YES","NO")) -> YES | J13: =IFERROR(INDEX('12) Budget Line Mapping'!$C$8:$C$37,MATCH(D13,'12) Budget Line Mapping'!$A$8:$A$37,0)),"") -> WP1 | K13: =IFERROR(INDEX('12) Budget Line Mapping'!$D$8:$D$37,MATCH(D13,'12) Budget Line Mapping'!$A$8:$A$37,0)),"") -> Directly Allocated | L13: =IFERROR(INDEX('12) Budget Line Mapping'!$E$8:$E$37,MATCH(D13,'12) Budget Line Mapping'!$A$8:$A$37,0)),"") -> Staff | M13: =IFERROR(INDEX('12) Budget Line Mapping'!$G$8:$G$37,MATCH(D13,'12) Budget Line Mapping'!$A$8:$A$37,0)),0) -> 0.8 | N13: =IF(A13="","",IF(COUNTIF($A$8:$A$2007,A13)>1,"DUPLICATE",IF(I13<>"YES","NOT APPROVED",IF(OR(C13="",D13="",E13="",F13="",G13=""),"MISSING REQUIRED",IF(OR(C13<'0) ReadMe and Contents'!$B$8,C13>'0) ReadMe and Contents'!$B$9),"OUT OF PERIOD",IF(J13="","UNMAPPED",IF(K13="Directly Incurred","WRONG LEDGER","OK"))))))) -> OK | O13: =IF(N13="OK",E13,0) -> 351.02 | P13: =O13*M13 -> 280.816 | Q13: =O13-P13 -> 70.204
A14: ALLOC-202605-WP1_S02 | B14: ALLOC-2026-08 | C14: 46173 | D14: WP1_S02 | E14: 361.88 | F14: Illustrative monthly management allocation; not DI transaction evidence | G14: ILLUSTRATIVE_ALLOC_SCHEDULE_2026-08 | H14: Applied at 100% of the phased monthly amount for demonstration. | I14: =IF(A14="","",IF(COUNTIFS('5) Refresh Log'!$A$8:$A$107,B14,'5) Refresh Log'!$F$8:$F$107,"APPROVED")>0,"YES","NO")) -> YES | J14: =IFERROR(INDEX('12) Budget Line Mapping'!$C$8:$C$37,MATCH(D14,'12) Budget Line Mapping'!$A$8:$A$37,0)),"") -> WP1 | K14: =IFERROR(INDEX('12) Budget Line Mapping'!$D$8:$D$37,MATCH(D14,'12) Budget Line Mapping'!$A$8:$A$37,0)),"") -> Directly Allocated | L14: =IFERROR(INDEX('12) Budget Line Mapping'!$E$8:$E$37,MATCH(D14,'12) Budget Line Mapping'!$A$8:$A$37,0)),"") -> Staff | M14: =IFERROR(INDEX('12) Budget Line Mapping'!$G$8:$G$37,MATCH(D14,'12) Budget Line Mapping'!$A$8:$A$37,0)),0) -> 0.8 | N14: =IF(A14="","",IF(COUNTIF($A$8:$A$2007,A14)>1,"DUPLICATE",IF(I14<>"YES","NOT APPROVED",IF(OR(C14="",D14="",E14="",F14="",G14=""),"MISSING REQUIRED",IF(OR(C14<'0) ReadMe and Contents'!$B$8,C14>'0) ReadMe and Contents'!$B$9),"OUT OF PERIOD",IF(J14="","UNMAPPED",IF(K14="Directly Incurred","WRONG LEDGER","OK"))))))) -> OK | O14: =IF(N14="OK",E14,0) -> 361.88 | P14: =O14*M14 -> 289.504 | Q14: =O14-P14 -> 72.376
A15: ALLOC-202606-WP1_S02 | B15: ALLOC-2026-08 | C15: 46203 | D15: WP1_S02 | E15: 358.26 | F15: Illustrative monthly management allocation; not DI transaction evidence | G15: ILLUSTRATIVE_ALLOC_SCHEDULE_2026-08 | H15: Applied at 99% of the phased monthly amount for demonstration. | I15: =IF(A15="","",IF(COUNTIFS('5) Refresh Log'!$A$8:$A$107,B15,'5) Refresh Log'!$F$8:$F$107,"APPROVED")>0,"YES","NO")) -> YES | J15: =IFERROR(INDEX('12) Budget Line Mapping'!$C$8:$C$37,MATCH(D15,'12) Budget Line Mapping'!$A$8:$A$37,0)),"") -> WP1 | K15: =IFERROR(INDEX('12) Budget Line Mapping'!$D$8:$D$37,MATCH(D15,'12) Budget Line Mapping'!$A$8:$A$37,0)),"") -> Directly Allocated | L15: =IFERROR(INDEX('12) Budget Line Mapping'!$E$8:$E$37,MATCH(D15,'12) Budget Line Mapping'!$A$8:$A$37,0)),"") -> Staff | M15: =IFERROR(INDEX('12) Budget Line Mapping'!$G$8:$G$37,MATCH(D15,'12) Budget Line Mapping'!$A$8:$A$37,0)),0) -> 0.8 | N15: =IF(A15="","",IF(COUNTIF($A$8:$A$2007,A15)>1,"DUPLICATE",IF(I15<>"YES","NOT APPROVED",IF(OR(C15="",D15="",E15="",F15="",G15=""),"MISSING REQUIRED",IF(OR(C15<'0) ReadMe and Contents'!$B$8,C15>'0) ReadMe and Contents'!$B$9),"OUT OF PERIOD",IF(J15="","UNMAPPED",IF(K15="Directly Incurred","WRONG LEDGER","OK"))))))) -> OK | O15: =IF(N15="OK",E15,0) -> 358.26 | P15: =O15*M15 -> 286.608 | Q15: =O15-P15 -> 71.652
A16: ALLOC-202607-WP1_S02 | B16: ALLOC-2026-08 | C16: 46234 | D16: WP1_S02 | E16: 365.49 | F16: Illustrative monthly management allocation; not DI transaction evidence | G16: ILLUSTRATIVE_ALLOC_SCHEDULE_2026-08 | H16: Applied at 101% of the phased monthly amount for demonstration. | I16: =IF(A16="","",IF(COUNTIFS('5) Refresh Log'!$A$8:$A$107,B16,'5) Refresh Log'!$F$8:$F$107,"APPROVED")>0,"YES","NO")) -> YES | J16: =IFERROR(INDEX('12) Budget Line Mapping'!$C$8:$C$37,MATCH(D16,'12) Budget Line Mapping'!$A$8:$A$37,0)),"") -> WP1 | K16: =IFERROR(INDEX('12) Budget Line Mapping'!$D$8:$D$37,MATCH(D16,'12) Budget Line Mapping'!$A$8:$A$37,0)),"") -> Directly Allocated | L16: =IFERROR(INDEX('12) Budget Line Mapping'!$E$8:$E$37,MATCH(D16,'12) Budget Line Mapping'!$A$8:$A$37,0)),"") -> Staff | M16: =IFERROR(INDEX('12) Budget Line Mapping'!$G$8:$G$37,MATCH(D16,'12) Budget Line Mapping'!$A$8:$A$37,0)),0) -> 0.8 | N16: =IF(A16="","",IF(COUNTIF($A$8:$A$2007,A16)>1,"DUPLICATE",IF(I16<>"YES","NOT APPROVED",IF(OR(C16="",D16="",E16="",F16="",G16=""),"MISSING REQUIRED",IF(OR(C16<'0) ReadMe and Contents'!$B$8,C16>'0) ReadMe and Contents'!$B$9),"OUT OF PERIOD",IF(J16="","UNMAPPED",IF(K16="Directly Incurred","WRONG LEDGER","OK"))))))) -> OK | O16: =IF(N16="OK",E16,0) -> 365.49 | P16: =O16*M16 -> 292.392 | Q16: =O16-P16 -> 73.098
A17: ALLOC-202608-WP1_S02 | B17: ALLOC-2026-08 | C17: 46265 | D17: WP1_S02 | E17: 361.88 | F17: Illustrative monthly management allocation; not DI transaction evidence | G17: ILLUSTRATIVE_ALLOC_SCHEDULE_2026-08 | H17: Applied at 100% of the phased monthly amount for demonstration. | I17: =IF(A17="","",IF(COUNTIFS('5) Refresh Log'!$A$8:$A$107,B17,'5) Refresh Log'!$F$8:$F$107,"APPROVED")>0,"YES","NO")) -> YES | J17: =IFERROR(INDEX('12) Budget Line Mapping'!$C$8:$C$37,MATCH(D17,'12) Budget Line Mapping'!$A$8:$A$37,0)),"") -> WP1 | K17: =IFERROR(INDEX('12) Budget Line Mapping'!$D$8:$D$37,MATCH(D17,'12) Budget Line Mapping'!$A$8:$A$37,0)),"") -> Directly Allocated | L17: =IFERROR(INDEX('12) Budget Line Mapping'!$E$8:$E$37,MATCH(D17,'12) Budget Line Mapping'!$A$8:$A$37,0)),"") -> Staff | M17: =IFERROR(INDEX('12) Budget Line Mapping'!$G$8:$G$37,MATCH(D17,'12) Budget Line Mapping'!$A$8:$A$37,0)),0) -> 0.8 | N17: =IF(A17="","",IF(COUNTIF($A$8:$A$2007,A17)>1,"DUPLICATE",IF(I17<>"YES","NOT APPROVED",IF(OR(C17="",D17="",E17="",F17="",G17=""),"MISSING REQUIRED",IF(OR(C17<'0) ReadMe and Contents'!$B$8,C17>'0) ReadMe and Contents'!$B$9),"OUT OF PERIOD",IF(J17="","UNMAPPED",IF(K17="Directly Incurred","WRONG LEDGER","OK"))))))) -> OK | O17: =IF(N17="OK",E17,0) -> 361.88 | P17: =O17*M17 -> 289.504 | Q17: =O17-P17 -> 72.376
A18: ALLOC-202604-WP1_S03 | B18: ALLOC-2026-08 | C18: 46142 | D18: WP1_S03 | E18: 360.11 | F18: Illustrative monthly management allocation; not DI transaction evidence | G18: ILLUSTRATIVE_ALLOC_SCHEDULE_2026-08 | H18: Applied at 97% of the phased monthly amount for demonstration. | I18: =IF(A18="","",IF(COUNTIFS('5) Refresh Log'!$A$8:$A$107,B18,'5) Refresh Log'!$F$8:$F$107,"APPROVED")>0,"YES","NO")) -> YES | J18: =IFERROR(INDEX('12) Budget Line Mapping'!$C$8:$C$37,MATCH(D18,'12) Budget Line Mapping'!$A$8:$A$37,0)),"") -> WP1 | K18: =IFERROR(INDEX('12) Budget Line Mapping'!$D$8:$D$37,MATCH(D18,'12) Budget Line Mapping'!$A$8:$A$37,0)),"") -> Directly Allocated | L18: =IFERROR(INDEX('12) Budget Line Mapping'!$E$8:$E$37,MATCH(D18,'12) Budget Line Mapping'!$A$8:$A$37,0)),"") -> Staff | M18: =IFERROR(INDEX('12) Budget Line Mapping'!$G$8:$G$37,MATCH(D18,'12) Budget Line Mapping'!$A$8:$A$37,0)),0) -> 0.8 | N18: =IF(A18="","",IF(COUNTIF($A$8:$A$2007,A18)>1,"DUPLICATE",IF(I18<>"YES","NOT APPROVED",IF(OR(C18="",D18="",E18="",F18="",G18=""),"MISSING REQUIRED",IF(OR(C18<'0) ReadMe and Contents'!$B$8,C18>'0) ReadMe and Contents'!$B$9),"OUT OF PERIOD",IF(J18="","UNMAPPED",IF(K18="Directly Incurred","WRONG LEDGER","OK"))))))) -> OK | O18: =IF(N18="OK",E18,0) -> 360.11 | P18: =O18*M18 -> 288.088 | Q18: =O18-P18 -> 72.022
A19: ALLOC-202605-WP1_S03 | B19: ALLOC-2026-08 | C19: 46173 | D19: WP1_S03 | E19: 371.25 | F19: Illustrative monthly management allocation; not DI transaction evidence | G19: ILLUSTRATIVE_ALLOC_SCHEDULE_2026-08 | H19: Applied at 100% of the phased monthly amount for demonstration. | I19: =IF(A19="","",IF(COUNTIFS('5) Refresh Log'!$A$8:$A$107,B19,'5) Refresh Log'!$F$8:$F$107,"APPROVED")>0,"YES","NO")) -> YES | J19: =IFERROR(INDEX('12) Budget Line Mapping'!$C$8:$C$37,MATCH(D19,'12) Budget Line Mapping'!$A$8:$A$37,0)),"") -> WP1 | K19: =IFERROR(INDEX('12) Budget Line Mapping'!$D$8:$D$37,MATCH(D19,'12) Budget Line Mapping'!$A$8:$A$37,0)),"") -> Directly Allocated | L19: =IFERROR(INDEX('12) Budget Line Mapping'!$E$8:$E$37,MATCH(D19,'12) Budget Line Mapping'!$A$8:$A$37,0)),"") -> Staff | M19: =IFERROR(INDEX('12) Budget Line Mapping'!$G$8:$G$37,MATCH(D19,'12) Budget Line Mapping'!$A$8:$A$37,0)),0) -> 0.8 | N19: =IF(A19="","",IF(COUNTIF($A$8:$A$2007,A19)>1,"DUPLICATE",IF(I19<>"YES","NOT APPROVED",IF(OR(C19="",D19="",E19="",F19="",G19=""),"MISSING REQUIRED",IF(OR(C19<'0) ReadMe and Contents'!$B$8,C19>'0) ReadMe and Contents'!$B$9),"OUT OF PERIOD",IF(J19="","UNMAPPED",IF(K19="Directly Incurred","WRONG LEDGER","OK"))))))) -> OK | O19: =IF(N19="OK",E19,0) -> 371.25 | P19: =O19*M19 -> 297 | Q19: =O19-P19 -> 74.25
... A82: ALLOC-202608-WP3_EST | B82: ALLOC-2026-08 | C82: 46265 | D82: WP3_EST | E82: 79.39 | F82: Illustrative monthly management allocation; not DI transaction evidence | G82: ILLUSTRATIVE_ALLOC_SCHEDULE_2026-08 | H82: Applied at 100% of the phased monthly amount for demonstration. | I82: =IF(A82="","",IF(COUNTIFS('5) Refresh Log'!$A$8:$A$107,B82,'5) Refresh Log'!$F$8:$F$107,"APPROVED")>0,"YES","NO")) -> YES | J82: =IFERROR(INDEX('12) Budget Line Mapping'!$C$8:$C$37,MATCH(D82,'12) Budget Line Mapping'!$A$8:$A$37,0)),"") -> WP3 | K82: =IFERROR(INDEX('12) Budget Line Mapping'!$D$8:$D$37,MATCH(D82,'12) Budget Line Mapping'!$A$8:$A$37,0)),"") -> Directly Allocated | L82: =IFERROR(INDEX('12) Budget Line Mapping'!$E$8:$E$37,MATCH(D82,'12) Budget Line Mapping'!$A$8:$A$37,0)),"") -> Estates | M82: =IFERROR(INDEX('12) Budget Line Mapping'!$G$8:$G$37,MATCH(D82,'12) Budget Line Mapping'!$A$8:$A$37,0)),0) -> 0.8 | N82: =IF(A82="","",IF(COUNTIF($A$8:$A$2007,A82)>1,"DUPLICATE",IF(I82<>"YES","NOT APPROVED",IF(OR(C82="",D82="",E82="",F82="",G82=""),"MISSING REQUIRED",IF(OR(C82<'0) ReadMe and Contents'!$B$8,C82>'0) ReadMe and Contents'!$B$9),"OUT OF PERIOD",IF(J82="","UNMAPPED",IF(K82="Directly Incurred","WRONG LEDGER","OK"))))))) -> OK | O82: =IF(N82="OK",E82,0) -> 79.39 | P82: =O82*M82 -> 63.512 | Q82: =O82-P82 -> 15.878

Sheet 8) Commitments Forecast
A1: Commitments and forecast exposure
A2: Open commitments = Costs liable for but not yet unrealised. Forecast at Completion bridges recognised cost, commitments and ETC
A4: The seeded commitments are hypothetical. Included GBP is limited to valid, approved OPEN commitments. Closed or cancelled records remain visible but contribute zero.
A7: Commitment ID | B7: Batch ID | C7: Status | D7: Commitment Date | E7: Expected Incurred Date | F7: Description | G7: Amount GBP | H7: Budget Item ID | I7: PO/Contract Ref | J7: Notes | K7: Batch Approved | L7: Work Package | M7: fEC Heading | N7: fEC Subheading | O7: Funding Rate | P7: Row Status | Q7: Included GBP | R7: Included UKRI | S7: Included RUSI
A8: CMT-001 | B8: COMMIT-2026-08 | C8: Open | D8: 46244 | E8: 46295 | F8: London launch conference venue, catering and production | G8: 13800 | H8: WP1_CONF | I8: PO-DEMO-1001 | J8: Hypothetical open exposure; not realised expenditure. | K8: =IF(A8="","",IF(COUNTIFS('5) Refresh Log'!$A$8:$A$107,B8,'5) Refresh Log'!$F$8:$F$107,"APPROVED")>0,"YES","NO")) -> YES | L8: =IFERROR(INDEX('12) Budget Line Mapping'!$C$8:$C$37,MATCH(H8,'12) Budget Line Mapping'!$A$8:$A$37,0)),"") -> WP1 | M8: =IFERROR(INDEX('12) Budget Line Mapping'!$D$8:$D$37,MATCH(H8,'12) Budget Line Mapping'!$A$8:$A$37,0)),"") -> Directly Incurred | N8: =IFERROR(INDEX('12) Budget Line Mapping'!$E$8:$E$37,MATCH(H8,'12) Budget Line Mapping'!$A$8:$A$37,0)),"") -> Other Directly Incurred | O8: =IFERROR(INDEX('12) Budget Line Mapping'!$G$8:$G$37,MATCH(H8,'12) Budget Line Mapping'!$A$8:$A$37,0)),0) -> 0.8 | P8: =IF(A8="","",IF(COUNTIF($A$8:$A$507,A8)>1,"DUPLICATE",IF(K8<>"YES","NOT APPROVED",IF(C8="Closed","CLOSED",IF(C8="Cancelled","CANCELLED",IF(C8<>"Open","INVALID STATUS",IF(OR(D8="",E8="",G8="",H8="",I8=""),"MISSING REQUIRED",IF(OR(E8<'0) ReadMe and Contents'!$B$8,E8>'0) ReadMe and Contents'!$B$9),"OUT OF PERIOD",IF(L8="","UNMAPPED",IF(G8<=0,"INVALID AMOUNT","OK")))))))))) -> OK | Q8: =IF(P8="OK",G8,0) -> 13800 | R8: =Q8*O8 -> 11040 | S8: =Q8-R8 -> 2760
A9: CMT-002 | B9: COMMIT-2026-08 | C9: Open | D9: 46246 | E9: 46295 | F9: Launch conference speaker travel and accommodation | G9: 900 | H9: WP1_CONF | I9: PO-DEMO-1002 | J9: Hypothetical open exposure; not realised expenditure. | K9: =IF(A9="","",IF(COUNTIFS('5) Refresh Log'!$A$8:$A$107,B9,'5) Refresh Log'!$F$8:$F$107,"APPROVED")>0,"YES","NO")) -> YES | L9: =IFERROR(INDEX('12) Budget Line Mapping'!$C$8:$C$37,MATCH(H9,'12) Budget Line Mapping'!$A$8:$A$37,0)),"") -> WP1 | M9: =IFERROR(INDEX('12) Budget Line Mapping'!$D$8:$D$37,MATCH(H9,'12) Budget Line Mapping'!$A$8:$A$37,0)),"") -> Directly Incurred | N9: =IFERROR(INDEX('12) Budget Line Mapping'!$E$8:$E$37,MATCH(H9,'12) Budget Line Mapping'!$A$8:$A$37,0)),"") -> Other Directly Incurred | O9: =IFERROR(INDEX('12) Budget Line Mapping'!$G$8:$G$37,MATCH(H9,'12) Budget Line Mapping'!$A$8:$A$37,0)),0) -> 0.8 | P9: =IF(A9="","",IF(COUNTIF($A$8:$A$507,A9)>1,"DUPLICATE",IF(K9<>"YES","NOT APPROVED",IF(C9="Closed","CLOSED",IF(C9="Cancelled","CANCELLED",IF(C9<>"Open","INVALID STATUS",IF(OR(D9="",E9="",G9="",H9="",I9=""),"MISSING REQUIRED",IF(OR(E9<'0) ReadMe and Contents'!$B$8,E9>'0) ReadMe and Contents'!$B$9),"OUT OF PERIOD",IF(L9="","UNMAPPED",IF(G9<=0,"INVALID AMOUNT","OK")))))))))) -> OK | Q9: =IF(P9="OK",G9,0) -> 900 | R9: =Q9*O9 -> 720 | S9: =Q9-R9 -> 180
A10: CMT-003 | B10: COMMIT-2026-08 | C10: Open | D10: 46249 | E10: 46341 | F10: UK regional workshop series | G10: 1200 | H10: WP1_WORKSHOP | I10: PO-DEMO-1003 | J10: Hypothetical open exposure; not realised expenditure. | K10: =IF(A10="","",IF(COUNTIFS('5) Refresh Log'!$A$8:$A$107,B10,'5) Refresh Log'!$F$8:$F$107,"APPROVED")>0,"YES","NO")) -> YES | L10: =IFERROR(INDEX('12) Budget Line Mapping'!$C$8:$C$37,MATCH(H10,'12) Budget Line Mapping'!$A$8:$A$37,0)),"") -> WP1 | M10: =IFERROR(INDEX('12) Budget Line Mapping'!$D$8:$D$37,MATCH(H10,'12) Budget Line Mapping'!$A$8:$A$37,0)),"") -> Directly Incurred | N10: =IFERROR(INDEX('12) Budget Line Mapping'!$E$8:$E$37,MATCH(H10,'12) Budget Line Mapping'!$A$8:$A$37,0)),"") -> Other Directly Incurred | O10: =IFERROR(INDEX('12) Budget Line Mapping'!$G$8:$G$37,MATCH(H10,'12) Budget Line Mapping'!$A$8:$A$37,0)),0) -> 0.8 | P10: =IF(A10="","",IF(COUNTIF($A$8:$A$507,A10)>1,"DUPLICATE",IF(K10<>"YES","NOT APPROVED",IF(C10="Closed","CLOSED",IF(C10="Cancelled","CANCELLED",IF(C10<>"Open","INVALID STATUS",IF(OR(D10="",E10="",G10="",H10="",I10=""),"MISSING REQUIRED",IF(OR(E10<'0) ReadMe and Contents'!$B$8,E10>'0) ReadMe and Contents'!$B$9),"OUT OF PERIOD",IF(L10="","UNMAPPED",IF(G10<=0,"INVALID AMOUNT","OK")))))))))) -> OK | Q10: =IF(P10="OK",G10,0) -> 1200 | R10: =Q10*O10 -> 960 | S10: =Q10-R10 -> 240
A11: CMT-004 | B11: COMMIT-2026-08 | C11: Open | D11: 46252 | E11: 46477 | F11: Nairobi network broker remaining FY contract | G11: 2450 | H11: WP2_CONSULT | I11: CON-DEMO-2001 | J11: Hypothetical open exposure; not realised expenditure. | K11: =IF(A11="","",IF(COUNTIFS('5) Refresh Log'!$A$8:$A$107,B11,'5) Refresh Log'!$F$8:$F$107,"APPROVED")>0,"YES","NO")) -> YES | L11: =IFERROR(INDEX('12) Budget Line Mapping'!$C$8:$C$37,MATCH(H11,'12) Budget Line Mapping'!$A$8:$A$37,0)),"") -> WP2 | M11: =IFERROR(INDEX('12) Budget Line Mapping'!$D$8:$D$37,MATCH(H11,'12) Budget Line Mapping'!$A$8:$A$37,0)),"") -> Directly Incurred | N11: =IFERROR(INDEX('12) Budget Line Mapping'!$E$8:$E$37,MATCH(H11,'12) Budget Line Mapping'!$A$8:$A$37,0)),"") -> Other Directly Incurred | O11: =IFERROR(INDEX('12) Budget Line Mapping'!$G$8:$G$37,MATCH(H11,'12) Budget Line Mapping'!$A$8:$A$37,0)),0) -> 0.8 | P11: =IF(A11="","",IF(COUNTIF($A$8:$A$507,A11)>1,"DUPLICATE",IF(K11<>"YES","NOT APPROVED",IF(C11="Closed","CLOSED",IF(C11="Cancelled","CANCELLED",IF(C11<>"Open","INVALID STATUS",IF(OR(D11="",E11="",G11="",H11="",I11=""),"MISSING REQUIRED",IF(OR(E11<'0) ReadMe and Contents'!$B$8,E11>'0) ReadMe and Contents'!$B$9),"OUT OF PERIOD",IF(L11="","UNMAPPED",IF(G11<=0,"INVALID AMOUNT","OK")))))))))) -> OK | Q11: =IF(P11="OK",G11,0) -> 2450 | R11: =Q11*O11 -> 1960 | S11: =Q11-R11 -> 490
A12: CMT-005 | B12: COMMIT-2026-08 | C12: Open | D12: 46252 | E12: 46477 | F12: Latin America network broker remaining FY contract | G12: 2450 | H12: WP3_CONSULT | I12: CON-DEMO-3001 | J12: Hypothetical open exposure; not realised expenditure. | K12: =IF(A12="","",IF(COUNTIFS('5) Refresh Log'!$A$8:$A$107,B12,'5) Refresh Log'!$F$8:$F$107,"APPROVED")>0,"YES","NO")) -> YES | L12: =IFERROR(INDEX('12) Budget Line Mapping'!$C$8:$C$37,MATCH(H12,'12) Budget Line Mapping'!$A$8:$A$37,0)),"") -> WP3 | M12: =IFERROR(INDEX('12) Budget Line Mapping'!$D$8:$D$37,MATCH(H12,'12) Budget Line Mapping'!$A$8:$A$37,0)),"") -> Directly Incurred | N12: =IFERROR(INDEX('12) Budget Line Mapping'!$E$8:$E$37,MATCH(H12,'12) Budget Line Mapping'!$A$8:$A$37,0)),"") -> Other Directly Incurred | O12: =IFERROR(INDEX('12) Budget Line Mapping'!$G$8:$G$37,MATCH(H12,'12) Budget Line Mapping'!$A$8:$A$37,0)),0) -> 0.8 | P12: =IF(A12="","",IF(COUNTIF($A$8:$A$507,A12)>1,"DUPLICATE",IF(K12<>"YES","NOT APPROVED",IF(C12="Closed","CLOSED",IF(C12="Cancelled","CANCELLED",IF(C12<>"Open","INVALID STATUS",IF(OR(D12="",E12="",G12="",H12="",I12=""),"MISSING REQUIRED",IF(OR(E12<'0) ReadMe and Contents'!$B$8,E12>'0) ReadMe and Contents'!$B$9),"OUT OF PERIOD",IF(L12="","UNMAPPED",IF(G12<=0,"INVALID AMOUNT","OK")))))))))) -> OK | Q12: =IF(P12="OK",G12,0) -> 2450 | R12: =Q12*O12 -> 1960 | S12: =Q12-R12 -> 490
A13: CMT-006 | B13: COMMIT-2026-08 | C13: Open | D13: 46254 | E13: 46326 | F13: East Africa scoping visit | G13: 1850 | H13: WP2_TRAVEL | I13: PO-DEMO-2002 | J13: Hypothetical open exposure; not realised expenditure. | K13: =IF(A13="","",IF(COUNTIFS('5) Refresh Log'!$A$8:$A$107,B13,'5) Refresh Log'!$F$8:$F$107,"APPROVED")>0,"YES","NO")) -> YES | L13: =IFERROR(INDEX('12) Budget Line Mapping'!$C$8:$C$37,MATCH(H13,'12) Budget Line Mapping'!$A$8:$A$37,0)),"") -> WP2 | M13: =IFERROR(INDEX('12) Budget Line Mapping'!$D$8:$D$37,MATCH(H13,'12) Budget Line Mapping'!$A$8:$A$37,0)),"") -> Directly Incurred | N13: =IFERROR(INDEX('12) Budget Line Mapping'!$E$8:$E$37,MATCH(H13,'12) Budget Line Mapping'!$A$8:$A$37,0)),"") -> Travel & Subsistence | O13: =IFERROR(INDEX('12) Budget Line Mapping'!$G$8:$G$37,MATCH(H13,'12) Budget Line Mapping'!$A$8:$A$37,0)),0) -> 0.8 | P13: =IF(A13="","",IF(COUNTIF($A$8:$A$507,A13)>1,"DUPLICATE",IF(K13<>"YES","NOT APPROVED",IF(C13="Closed","CLOSED",IF(C13="Cancelled","CANCELLED",IF(C13<>"Open","INVALID STATUS",IF(OR(D13="",E13="",G13="",H13="",I13=""),"MISSING REQUIRED",IF(OR(E13<'0) ReadMe and Contents'!$B$8,E13>'0) ReadMe and Contents'!$B$9),"OUT OF PERIOD",IF(L13="","UNMAPPED",IF(G13<=0,"INVALID AMOUNT","OK")))))))))) -> OK | Q13: =IF(P13="OK",G13,0) -> 1850 | R13: =Q13*O13 -> 1480 | S13: =Q13-R13 -> 370
A14: CMT-007 | B14: COMMIT-2026-08 | C14: Open | D14: 46254 | E14: 46356 | F14: Latin America partner meeting | G14: 2100 | H14: WP3_TRAVEL | I14: PO-DEMO-3002 | J14: Hypothetical open exposure; not realised expenditure. | K14: =IF(A14="","",IF(COUNTIFS('5) Refresh Log'!$A$8:$A$107,B14,'5) Refresh Log'!$F$8:$F$107,"APPROVED")>0,"YES","NO")) -> YES | L14: =IFERROR(INDEX('12) Budget Line Mapping'!$C$8:$C$37,MATCH(H14,'12) Budget Line Mapping'!$A$8:$A$37,0)),"") -> WP3 | M14: =IFERROR(INDEX('12) Budget Line Mapping'!$D$8:$D$37,MATCH(H14,'12) Budget Line Mapping'!$A$8:$A$37,0)),"") -> Directly Incurred | N14: =IFERROR(INDEX('12) Budget Line Mapping'!$E$8:$E$37,MATCH(H14,'12) Budget Line Mapping'!$A$8:$A$37,0)),"") -> Travel & Subsistence | O14: =IFERROR(INDEX('12) Budget Line Mapping'!$G$8:$G$37,MATCH(H14,'12) Budget Line Mapping'!$A$8:$A$37,0)),0) -> 0.8 | P14: =IF(A14="","",IF(COUNTIF($A$8:$A$507,A14)>1,"DUPLICATE",IF(K14<>"YES","NOT APPROVED",IF(C14="Closed","CLOSED",IF(C14="Cancelled","CANCELLED",IF(C14<>"Open","INVALID STATUS",IF(OR(D14="",E14="",G14="",H14="",I14=""),"MISSING REQUIRED",IF(OR(E14<'0) ReadMe and Contents'!$B$8,E14>'0) ReadMe and Contents'!$B$9),"OUT OF PERIOD",IF(L14="","UNMAPPED",IF(G14<=0,"INVALID AMOUNT","OK")))))))))) -> OK | Q14: =IF(P14="OK",G14,0) -> 2100 | R14: =Q14*O14 -> 1680 | S14: =Q14-R14 -> 420
A15: CMT-008 | B15: COMMIT-2026-08 | C15: Open | D15: 46256 | E15: 46371 | F15: East Africa practitioner workshop | G15: 1000 | H15: WP2_WORKSHOP | I15: PO-DEMO-2003 | J15: Hypothetical open exposure; not realised expenditure. | K15: =IF(A15="","",IF(COUNTIFS('5) Refresh Log'!$A$8:$A$107,B15,'5) Refresh Log'!$F$8:$F$107,"APPROVED")>0,"YES","NO")) -> YES | L15: =IFERROR(INDEX('12) Budget Line Mapping'!$C$8:$C$37,MATCH(H15,'12) Budget Line Mapping'!$A$8:$A$37,0)),"") -> WP2 | M15: =IFERROR(INDEX('12) Budget Line Mapping'!$D$8:$D$37,MATCH(H15,'12) Budget Line Mapping'!$A$8:$A$37,0)),"") -> Directly Incurred | N15: =IFERROR(INDEX('12) Budget Line Mapping'!$E$8:$E$37,MATCH(H15,'12) Budget Line Mapping'!$A$8:$A$37,0)),"") -> Other Directly Incurred | O15: =IFERROR(INDEX('12) Budget Line Mapping'!$G$8:$G$37,MATCH(H15,'12) Budget Line Mapping'!$A$8:$A$37,0)),0) -> 0.8 | P15: =IF(A15="","",IF(COUNTIF($A$8:$A$507,A15)>1,"DUPLICATE",IF(K15<>"YES","NOT APPROVED",IF(C15="Closed","CLOSED",IF(C15="Cancelled","CANCELLED",IF(C15<>"Open","INVALID STATUS",IF(OR(D15="",E15="",G15="",H15="",I15=""),"MISSING REQUIRED",IF(OR(E15<'0) ReadMe and Contents'!$B$8,E15>'0) ReadMe and Contents'!$B$9),"OUT OF PERIOD",IF(L15="","UNMAPPED",IF(G15<=0,"INVALID AMOUNT","OK")))))))))) -> OK | Q15: =IF(P15="OK",G15,0) -> 1000 | R15: =Q15*O15 -> 800 | S15: =Q15-R15 -> 200
A16: CMT-009 | B16: COMMIT-2026-08 | C16: Open | D16: 46256 | E16: 46433 | F16: Latin America practitioner workshop | G16: 1000 | H16: WP3_WORKSHOP | I16: PO-DEMO-3003 | J16: Hypothetical open exposure; not realised expenditure. | K16: =IF(A16="","",IF(COUNTIFS('5) Refresh Log'!$A$8:$A$107,B16,'5) Refresh Log'!$F$8:$F$107,"APPROVED")>0,"YES","NO")) -> YES | L16: =IFERROR(INDEX('12) Budget Line Mapping'!$C$8:$C$37,MATCH(H16,'12) Budget Line Mapping'!$A$8:$A$37,0)),"") -> WP3 | M16: =IFERROR(INDEX('12) Budget Line Mapping'!$D$8:$D$37,MATCH(H16,'12) Budget Line Mapping'!$A$8:$A$37,0)),"") -> Directly Incurred | N16: =IFERROR(INDEX('12) Budget Line Mapping'!$E$8:$E$37,MATCH(H16,'12) Budget Line Mapping'!$A$8:$A$37,0)),"") -> Other Directly Incurred | O16: =IFERROR(INDEX('12) Budget Line Mapping'!$G$8:$G$37,MATCH(H16,'12) Budget Line Mapping'!$A$8:$A$37,0)),0) -> 0.8 | P16: =IF(A16="","",IF(COUNTIF($A$8:$A$507,A16)>1,"DUPLICATE",IF(K16<>"YES","NOT APPROVED",IF(C16="Closed","CLOSED",IF(C16="Cancelled","CANCELLED",IF(C16<>"Open","INVALID STATUS",IF(OR(D16="",E16="",G16="",H16="",I16=""),"MISSING REQUIRED",IF(OR(E16<'0) ReadMe and Contents'!$B$8,E16>'0) ReadMe and Contents'!$B$9),"OUT OF PERIOD",IF(L16="","UNMAPPED",IF(G16<=0,"INVALID AMOUNT","OK")))))))))) -> OK | Q16: =IF(P16="OK",G16,0) -> 1000 | R16: =Q16*O16 -> 800 | S16: =Q16-R16 -> 200
A17: CMT-010 | B17: COMMIT-2026-08 | C17: Open | D17: 46259 | E17: 46310 | F17: Launch communications production | G17: 450 | H17: WP1_COMMS | I17: PO-DEMO-1004 | J17: Hypothetical open exposure; not realised expenditure. | K17: =IF(A17="","",IF(COUNTIFS('5) Refresh Log'!$A$8:$A$107,B17,'5) Refresh Log'!$F$8:$F$107,"APPROVED")>0,"YES","NO")) -> YES | L17: =IFERROR(INDEX('12) Budget Line Mapping'!$C$8:$C$37,MATCH(H17,'12) Budget Line Mapping'!$A$8:$A$37,0)),"") -> WP1 | M17: =IFERROR(INDEX('12) Budget Line Mapping'!$D$8:$D$37,MATCH(H17,'12) Budget Line Mapping'!$A$8:$A$37,0)),"") -> Directly Incurred | N17: =IFERROR(INDEX('12) Budget Line Mapping'!$E$8:$E$37,MATCH(H17,'12) Budget Line Mapping'!$A$8:$A$37,0)),"") -> Other Directly Incurred | O17: =IFERROR(INDEX('12) Budget Line Mapping'!$G$8:$G$37,MATCH(H17,'12) Budget Line Mapping'!$A$8:$A$37,0)),0) -> 0.8 | P17: =IF(A17="","",IF(COUNTIF($A$8:$A$507,A17)>1,"DUPLICATE",IF(K17<>"YES","NOT APPROVED",IF(C17="Closed","CLOSED",IF(C17="Cancelled","CANCELLED",IF(C17<>"Open","INVALID STATUS",IF(OR(D17="",E17="",G17="",H17="",I17=""),"MISSING REQUIRED",IF(OR(E17<'0) ReadMe and Contents'!$B$8,E17>'0) ReadMe and Contents'!$B$9),"OUT OF PERIOD",IF(L17="","UNMAPPED",IF(G17<=0,"INVALID AMOUNT","OK")))))))))) -> OK | Q17: =IF(P17="OK",G17,0) -> 450 | R17: =Q17*O17 -> 360 | S17: =Q17-R17 -> 90

Sheet 9) Budget Baseline
A1: Frozen Budget baseline and approved profile
A2: One Budget Item × month record; original fEC, UKRI and RUSI bases are preserved
A4: Approved Budget = (Original Budget) + (Approved amendments). This example contains no such amendments
A7: Budget Record ID | B7: Budget Item ID | C7: Description | D7: Work Package | E7: fEC Heading | F7: fEC Subheading | G7: Reporting Category | H7: Period End | I7: Financial Year | J7: Phasing Method | K7: Funding Rate | L7: Original Budget 100% fEC | M7: Original UKRI | N7: Original RUSI | O7: Approved Change 100% | P7: Approved Budget 100% | Q7: Approved UKRI | R7: Approved RUSI
A8: WP1_S01-202604 | B8: WP1_S01 | C8: RUSI - Project Officer (existing staff, DA) @GrB/4 | D8: WP1 | E8: Directly Allocated | F8: Staff | G8: Directly Allocated Staff | H8: 46142 | I8: 2026/27 | J8: Straight-line | K8: 0.8 | L8: 327.08333 | M8: 261.66667 | N8: 65.416667 | O8: =SUMIFS('10) Budget Changes'!$E$8:$E$107,'10) Budget Changes'!$D$8:$D$107,B8,'10) Budget Changes'!$C$8:$C$107,H8,'10) Budget Changes'!$I$8:$I$107,"APPROVED") -> 0 | P8: =L8+O8 -> 327.08333 | Q8: =P8*K8 -> 261.66667 | R8: =P8-Q8 -> 65.416667
A9: WP1_S01-202605 | B9: WP1_S01 | C9: RUSI - Project Officer (existing staff, DA) @GrB/4 | D9: WP1 | E9: Directly Allocated | F9: Staff | G9: Directly Allocated Staff | H9: 46173 | I9: 2026/27 | J9: Straight-line | K9: 0.8 | L9: 327.08333 | M9: 261.66667 | N9: 65.416667 | O9: =SUMIFS('10) Budget Changes'!$E$8:$E$107,'10) Budget Changes'!$D$8:$D$107,B9,'10) Budget Changes'!$C$8:$C$107,H9,'10) Budget Changes'!$I$8:$I$107,"APPROVED") -> 0 | P9: =L9+O9 -> 327.08333 | Q9: =P9*K9 -> 261.66667 | R9: =P9-Q9 -> 65.416667
A10: WP1_S01-202606 | B10: WP1_S01 | C10: RUSI - Project Officer (existing staff, DA) @GrB/4 | D10: WP1 | E10: Directly Allocated | F10: Staff | G10: Directly Allocated Staff | H10: 46203 | I10: 2026/27 | J10: Straight-line | K10: 0.8 | L10: 327.08333 | M10: 261.66667 | N10: 65.416667 | O10: =SUMIFS('10) Budget Changes'!$E$8:$E$107,'10) Budget Changes'!$D$8:$D$107,B10,'10) Budget Changes'!$C$8:$C$107,H10,'10) Budget Changes'!$I$8:$I$107,"APPROVED") -> 0 | P10: =L10+O10 -> 327.08333 | Q10: =P10*K10 -> 261.66667 | R10: =P10-Q10 -> 65.416667
A11: WP1_S01-202607 | B11: WP1_S01 | C11: RUSI - Project Officer (existing staff, DA) @GrB/4 | D11: WP1 | E11: Directly Allocated | F11: Staff | G11: Directly Allocated Staff | H11: 46234 | I11: 2026/27 | J11: Straight-line | K11: 0.8 | L11: 327.08333 | M11: 261.66667 | N11: 65.416667 | O11: =SUMIFS('10) Budget Changes'!$E$8:$E$107,'10) Budget Changes'!$D$8:$D$107,B11,'10) Budget Changes'!$C$8:$C$107,H11,'10) Budget Changes'!$I$8:$I$107,"APPROVED") -> 0 | P11: =L11+O11 -> 327.08333 | Q11: =P11*K11 -> 261.66667 | R11: =P11-Q11 -> 65.416667
A12: WP1_S01-202608 | B12: WP1_S01 | C12: RUSI - Project Officer (existing staff, DA) @GrB/4 | D12: WP1 | E12: Directly Allocated | F12: Staff | G12: Directly Allocated Staff | H12: 46265 | I12: 2026/27 | J12: Straight-line | K12: 0.8 | L12: 327.08333 | M12: 261.66667 | N12: 65.416667 | O12: =SUMIFS('10) Budget Changes'!$E$8:$E$107,'10) Budget Changes'!$D$8:$D$107,B12,'10) Budget Changes'!$C$8:$C$107,H12,'10) Budget Changes'!$I$8:$I$107,"APPROVED") -> 0 | P12: =L12+O12 -> 327.08333 | Q12: =P12*K12 -> 261.66667 | R12: =P12-Q12 -> 65.416667
A13: WP1_S01-202609 | B13: WP1_S01 | C13: RUSI - Project Officer (existing staff, DA) @GrB/4 | D13: WP1 | E13: Directly Allocated | F13: Staff | G13: Directly Allocated Staff | H13: 46295 | I13: 2026/27 | J13: Straight-line | K13: 0.8 | L13: 327.08333 | M13: 261.66667 | N13: 65.416667 | O13: =SUMIFS('10) Budget Changes'!$E$8:$E$107,'10) Budget Changes'!$D$8:$D$107,B13,'10) Budget Changes'!$C$8:$C$107,H13,'10) Budget Changes'!$I$8:$I$107,"APPROVED") -> 0 | P13: =L13+O13 -> 327.08333 | Q13: =P13*K13 -> 261.66667 | R13: =P13-Q13 -> 65.416667
A14: WP1_S01-202610 | B14: WP1_S01 | C14: RUSI - Project Officer (existing staff, DA) @GrB/4 | D14: WP1 | E14: Directly Allocated | F14: Staff | G14: Directly Allocated Staff | H14: 46326 | I14: 2026/27 | J14: Straight-line | K14: 0.8 | L14: 327.08333 | M14: 261.66667 | N14: 65.416667 | O14: =SUMIFS('10) Budget Changes'!$E$8:$E$107,'10) Budget Changes'!$D$8:$D$107,B14,'10) Budget Changes'!$C$8:$C$107,H14,'10) Budget Changes'!$I$8:$I$107,"APPROVED") -> 0 | P14: =L14+O14 -> 327.08333 | Q14: =P14*K14 -> 261.66667 | R14: =P14-Q14 -> 65.416667
A15: WP1_S01-202611 | B15: WP1_S01 | C15: RUSI - Project Officer (existing staff, DA) @GrB/4 | D15: WP1 | E15: Directly Allocated | F15: Staff | G15: Directly Allocated Staff | H15: 46356 | I15: 2026/27 | J15: Straight-line | K15: 0.8 | L15: 327.08333 | M15: 261.66667 | N15: 65.416667 | O15: =SUMIFS('10) Budget Changes'!$E$8:$E$107,'10) Budget Changes'!$D$8:$D$107,B15,'10) Budget Changes'!$C$8:$C$107,H15,'10) Budget Changes'!$I$8:$I$107,"APPROVED") -> 0 | P15: =L15+O15 -> 327.08333 | Q15: =P15*K15 -> 261.66667 | R15: =P15-Q15 -> 65.416667
A16: WP1_S01-202612 | B16: WP1_S01 | C16: RUSI - Project Officer (existing staff, DA) @GrB/4 | D16: WP1 | E16: Directly Allocated | F16: Staff | G16: Directly Allocated Staff | H16: 46387 | I16: 2026/27 | J16: Straight-line | K16: 0.8 | L16: 327.08333 | M16: 261.66667 | N16: 65.416667 | O16: =SUMIFS('10) Budget Changes'!$E$8:$E$107,'10) Budget Changes'!$D$8:$D$107,B16,'10) Budget Changes'!$C$8:$C$107,H16,'10) Budget Changes'!$I$8:$I$107,"APPROVED") -> 0 | P16: =L16+O16 -> 327.08333 | Q16: =P16*K16 -> 261.66667 | R16: =P16-Q16 -> 65.416667
A17: WP1_S01-202701 | B17: WP1_S01 | C17: RUSI - Project Officer (existing staff, DA) @GrB/4 | D17: WP1 | E17: Directly Allocated | F17: Staff | G17: Directly Allocated Staff | H17: 46418 | I17: 2026/27 | J17: Straight-line | K17: 0.8 | L17: 327.08333 | M17: 261.66667 | N17: 65.416667 | O17: =SUMIFS('10) Budget Changes'!$E$8:$E$107,'10) Budget Changes'!$D$8:$D$107,B17,'10) Budget Changes'!$C$8:$C$107,H17,'10) Budget Changes'!$I$8:$I$107,"APPROVED") -> 0 | P17: =L17+O17 -> 327.08333 | Q17: =P17*K17 -> 261.66667 | R17: =P17-Q17 -> 65.416667
A18: WP1_S01-202702 | B18: WP1_S01 | C18: RUSI - Project Officer (existing staff, DA) @GrB/4 | D18: WP1 | E18: Directly Allocated | F18: Staff | G18: Directly Allocated Staff | H18: 46446 | I18: 2026/27 | J18: Straight-line | K18: 0.8 | L18: 327.08333 | M18: 261.66667 | N18: 65.416667 | O18: =SUMIFS('10) Budget Changes'!$E$8:$E$107,'10) Budget Changes'!$D$8:$D$107,B18,'10) Budget Changes'!$C$8:$C$107,H18,'10) Budget Changes'!$I$8:$I$107,"APPROVED") -> 0 | P18: =L18+O18 -> 327.08333 | Q18: =P18*K18 -> 261.66667 | R18: =P18-Q18 -> 65.416667
A19: WP1_S01-202703 | B19: WP1_S01 | C19: RUSI - Project Officer (existing staff, DA) @GrB/4 | D19: WP1 | E19: Directly Allocated | F19: Staff | G19: Directly Allocated Staff | H19: 46477 | I19: 2026/27 | J19: Straight-line | K19: 0.8 | L19: 327.08333 | M19: 261.66667 | N19: 65.416667 | O19: =SUMIFS('10) Budget Changes'!$E$8:$E$107,'10) Budget Changes'!$D$8:$D$107,B19,'10) Budget Changes'!$C$8:$C$107,H19,'10) Budget Changes'!$I$8:$I$107,"APPROVED") -> 0 | P19: =L19+O19 -> 327.08333 | Q19: =P19*K19 -> 261.66667 | R19: =P19-Q19 -> 65.416667
... A1087: WP3_EST-202903 | B1087: WP3_EST | C1087: RUSI - non-laboratory estate allocation (dispensation proxy × eligible staff FTE) | D1087: WP3 | E1087: Directly Allocated | F1087: Estates | G1087: Estate Costs | H1087: 47208 | I1087: 2028/29 | J1087: Straight-line | K1087: 0.8 | L1087: 79.386667 | M1087: 63.509333 | N1087: 15.877333 | O1087: =SUMIFS('10) Budget Changes'!$E$8:$E$107,'10) Budget Changes'!$D$8:$D$107,B1087,'10) Budget Changes'!$C$8:$C$107,H1087,'10) Budget Changes'!$I$8:$I$107,"APPROVED") -> 0 | P1087: =L1087+O1087 -> 79.386667 | Q1087: =P1087*K1087 -> 63.509333 | R1087: =P1087-Q1087 -> 15.877333

Sheet 10) Budget Changes
A1: Approved Budget changes
A2: Log any changes made to the originally proposed project Budget here (adjustments, virements etc.) Note: The original Budget is never overwritten
A4: No changes are approved in this example. Add one row per item and effective month when adding changes. For virements, record the transfer-out and transfer-in lines.
A7: Change ID | B7: Approved Date | C7: Effective Period | D7: Budget Item ID | E7: Amount 100% fEC | F7: Authority | G7: Rationale | H7: Notes | I7: Status

Sheet 11) Model Audit Checks
A1: Workbook controls and reconciliations
A2: MODEL STATUS | B2: =IF(COUNTIF(F7:F35,"FAIL")=0,"PASS","FAIL") -> PASS
A4: Controls use the frozen source Budget, approved-batch totals and item-level forecast bridge. Power Query configuration is deliberately not a PASS condition because the workbook must remain complete offline.
A6: Check | B6: Actual | C6: Expected | D6: Difference | E6: Tolerance | F6: Status | G6: Where to fix | H6: Notes
A7: Original 100% fEC equals frozen source total | B7: =SUM('9) Budget Baseline'!$L$8:$L$1087) -> 320708.28 | C7: 320708.28 | D7: =B7-C7 -> 0 | E7: 0.01 | F7: =IF(ABS(D7)<=E7,"PASS","FAIL") -> PASS | G7: Budget Baseline | H7: Source workbook total
A8: Original UKRI plus RUSI equals full fEC | B8: =SUM('9) Budget Baseline'!$M$8:$M$1087)+SUM('9) Budget Baseline'!$N$8:$N$1087) -> 320708.28 | C8: =SUM('9) Budget Baseline'!$L$8:$L$1087) -> 320708.28 | D8: =B8-C8 -> 0 | E8: 0.01 | F8: =IF(ABS(D8)<=E8,"PASS","FAIL") -> PASS | G8: Budget Baseline | H8: Funding-basis reconciliation
A9: Budget baseline contains 1,080 records | B9: =COUNTA('9) Budget Baseline'!$A$8:$A$1087) -> 1080 | C9: 1080 | D9: =B9-C9 -> 0 | E9: 0 | F9: =IF(ABS(D9)<=E9,"PASS","FAIL") -> PASS | G9: Budget Baseline | H9: 30 items × 36 months
A10: Every mapped Budget item has 36 monthly records | B10: {=SUMPRODUCT(--(COUNTIF('9) Budget Baseline'!$B$8:$B$1087,'12) Budget Line Mapping'!$A$8:$A$37)<>36))} -> 0 | C10: 0 | D10: =B10-C10 -> 0 | E10: 0 | F10: =IF(ABS(D10)<=E10,"PASS","FAIL") -> PASS | G10: Budget Baseline/Mappings | H10: Count of items failing the 36-month test
A11: Project monthly span is 36 months | B11: =(YEAR(MAX('9) Budget Baseline'!$H$8:$H$1087))-YEAR(MIN('9) Budget Baseline'!$H$8:$H$1087)))*12+MONTH(MAX('9) Budget Baseline'!$H$8:$H$1087))-MONTH(MIN('9) Budget Baseline'!$H$8:$H$1087))+1 -> 36 | C11: 36 | D11: =B11-C11 -> 0 | E11: 0 | F11: =IF(ABS(D11)<=E11,"PASS","FAIL") -> PASS | G11: Budget Baseline | H11: April 2026 to March 2029
A12: Approved Budget equals original plus approved changes | B12: =SUM('9) Budget Baseline'!$P$8:$P$1087) -> 320708.28 | C12: =SUM('9) Budget Baseline'!$L$8:$L$1087)+SUMIFS('10) Budget Changes'!$E$8:$E$107,'10) Budget Changes'!$I$8:$I$107,"APPROVED") -> 320708.28 | D12: =B12-C12 -> 0 | E12: 0.01 | F12: =IF(ABS(D12)<=E12,"PASS","FAIL") -> PASS | G12: Budget Changes | H12: Original baseline is not overwritten
A13: Approved UKRI plus RUSI equals approved full cost | B13: =SUM('9) Budget Baseline'!$Q$8:$Q$1087)+SUM('9) Budget Baseline'!$R$8:$R$1087) -> 320708.28 | C13: =SUM('9) Budget Baseline'!$P$8:$P$1087) -> 320708.28 | D13: =B13-C13 -> 0 | E13: 0.01 | F13: =IF(ABS(D13)<=E13,"PASS","FAIL") -> PASS | G13: Mappings/Budget Baseline | H13: Supports future 100% exceptions
A14: Actuals source row count reconciles | B14: ='5) Refresh Log'!$H$8 -> 56 | C14: ='5) Refresh Log'!$G$8 -> 56 | D14: =B14-C14 -> 0 | E14: 0 | F14: =IF(ABS(D14)<=E14,"PASS","FAIL") -> PASS | G14: Refresh Log/Actuals Ledger | H14: Approved demo batch
A15: Actuals source amount reconciles | B15: ='5) Refresh Log'!$J$8 -> 13751.2 | C15: ='5) Refresh Log'!$I$8 -> 13751.2 | D15: =B15-C15 -> 0 | E15: 0.01 | F15: =IF(ABS(D15)<=E15,"PASS","FAIL") -> PASS | G15: Refresh Log/Actuals Ledger | H15: Approved demo batch
A16: Allocation source row count reconciles | B16: ='5) Refresh Log'!$H$9 -> 75 | C16: ='5) Refresh Log'!$G$9 -> 75 | D16: =B16-C16 -> 0 | E16: 0 | F16: =IF(ABS(D16)<=E16,"PASS","FAIL") -> PASS | G16: Refresh Log/Allocations | H16: Approved demo batch
A17: Allocation source amount reconciles | B17: ='5) Refresh Log'!$J$9 -> 21837.92 | C17: ='5) Refresh Log'!$I$9 -> 21837.92 | D17: =B17-C17 -> 0 | E17: 0.01 | F17: =IF(ABS(D17)<=E17,"PASS","FAIL") -> PASS | G17: Refresh Log/Allocations | H17: Approved demo batch
A18: Commitment source row count reconciles | B18: ='5) Refresh Log'!$H$10 -> 10 | C18: ='5) Refresh Log'!$G$10 -> 10 | D18: =B18-C18 -> 0 | E18: 0 | F18: =IF(ABS(D18)<=E18,"PASS","FAIL") -> PASS | G18: Refresh Log/Commitments Forecast | H18: Approved demo batch
A19: Commitment source amount reconciles | B19: ='5) Refresh Log'!$J$10 -> 27200 | C19: ='5) Refresh Log'!$I$10 -> 27200 | D19: =B19-C19 -> 0 | E19: 0.01 | F19: =IF(ABS(D19)<=E19,"PASS","FAIL") -> PASS | G19: Refresh Log/Commitments Forecast | H19: Approved demo batch
A20: No invalid actual transaction rows | B20: =COUNTIFS('6) Actuals Ledger - DI Costs'!$A$8:$A$2007,"<>",'6) Actuals Ledger - DI Costs'!$Q$8:$Q$2007,"<>OK") -> 0 | C20: 0 | D20: =B20-C20 -> 0 | E20: 0 | F20: =IF(ABS(D20)<=E20,"PASS","FAIL") -> PASS | G20: Actuals Ledger | H20: Resolve every non-OK populated row
A21: No invalid allocation rows | B21: =COUNTIFS('7) Allocations - DA Costs'!$A$8:$A$2007,"<>",'7) Allocations - DA Costs'!$N$8:$N$2007,"<>OK") -> 0 | C21: 0 | D21: =B21-C21 -> 0 | E21: 0 | F21: =IF(ABS(D21)<=E21,"PASS","FAIL") -> PASS | G21: Allocations | H21: Resolve every non-OK populated row
A22: No invalid open commitment rows | B22: =COUNTIFS('8) Commitments Forecast'!$A$8:$A$507,"<>",'8) Commitments Forecast'!$P$8:$P$507,"<>OK",'8) Commitments Forecast'!$P$8:$P$507,"<>CLOSED",'8) Commitments Forecast'!$P$8:$P$507,"<>CANCELLED") -> 0 | C22: 0 | D22: =B22-C22 -> 0 | E22: 0 | F22: =IF(ABS(D22)<=E22,"PASS","FAIL") -> PASS | G22: Commitments Forecast | H22: Closed/cancelled records are permitted
A23: Recognised total agrees to item forecast bridge | B23: =SUMIFS('6) Actuals Ledger - DI Costs'!$R$8:$R$2007,'6) Actuals Ledger - DI Costs'!$C$8:$C$2007,"<="&'1) Budget-Actuals Dashboard'!$C$4)+SUMIFS('7) Allocations - DA Costs'!$O$8:$O$2007,'7) Allocations - DA Costs'!$C$8:$C$2007,"<="&'1) Budget-Actuals Dashboard'!$C$4) -> 35589.12 | C23: =SUM('3) Forecast Bridge'!$G$8:$G$37) -> 35589.12 | D23: =B23-C23 -> 0 | E23: 0.01 | F23: =IF(ABS(D23)<=E23,"PASS","FAIL") -> PASS | G23: Forecast Bridge | H23: Full-cost recognised total at cut-off
A24: Forecast bridge adds recognised, commitments and ETC | B24: =SUM('3) Forecast Bridge'!$K$8:$K$37) -> 323608.28 | C24: =SUM('3) Forecast Bridge'!$G$8:$G$37)+SUM('3) Forecast Bridge'!$H$8:$H$37)+SUM('3) Forecast Bridge'!$J$8:$J$37) -> 323608.28 | D24: =B24-C24 -> 0 | E24: 0.01 | F24: =IF(ABS(D24)<=E24,"PASS","FAIL") -> PASS | G24: Forecast Bridge | H24: No double counting
A25: Forecast item Budgets agree to approved Budget | B25: =SUM('3) Forecast Bridge'!$F$8:$F$37) -> 320708.28 | C25: =SUM('9) Budget Baseline'!$P$8:$P$1087) -> 320708.28 | D25: =B25-C25 -> 0 | E25: 0.01 | F25: =IF(ABS(D25)<=E25,"PASS","FAIL") -> PASS | G25: Forecast Bridge/Budget Baseline | H25: 30 item bridge
A26: Actuals funding shares reconcile to full value | B26: =SUM('6) Actuals Ledger - DI Costs'!$S$8:$S$2007)+SUM('6) Actuals Ledger - DI Costs'!$T$8:$T$2007) -> 13751.2 | C26: =SUM('6) Actuals Ledger - DI Costs'!$R$8:$R$2007) -> 13751.2 | D26: =B26-C26 -> 0 | E26: 0.01 | F26: =IF(ABS(D26)<=E26,"PASS","FAIL") -> PASS | G26: Actuals Ledger | H26: Current rows use mapped funding rates
A27: Allocation funding shares reconcile to full value | B27: =SUM('7) Allocations - DA Costs'!$P$8:$P$2007)+SUM('7) Allocations - DA Costs'!$Q$8:$Q$2007) -> 21837.92 | C27: =SUM('7) Allocations - DA Costs'!$O$8:$O$2007) -> 21837.92 | D27: =B27-C27 -> 0 | E27: 0.01 | F27: =IF(ABS(D27)<=E27,"PASS","FAIL") -> PASS | G27: Allocations | H27: Current rows use mapped funding rates
A28: Commitment funding shares reconcile to full value | B28: =SUM('8) Commitments Forecast'!$R$8:$R$507)+SUM('8) Commitments Forecast'!$S$8:$S$507) -> 27200 | C28: =SUM('8) Commitments Forecast'!$Q$8:$Q$507) -> 27200 | D28: =B28-C28 -> 0 | E28: 0.01 | F28: =IF(ABS(D28)<=E28,"PASS","FAIL") -> PASS | G28: Commitments Forecast | H28: Current rows use mapped funding rates
A29: Allocation ledger contains no DI rows | B29: =COUNTIF('7) Allocations - DA Costs'!$K$8:$K$2007,"Directly Incurred") -> 0 | C29: 0 | D29: =B29-C29 -> 0 | E29: 0 | F29: =IF(ABS(D29)<=E29,"PASS","FAIL") -> PASS | G29: Allocations/Mappings | H29: DI belongs in Actuals Ledger
A30: Funding rates are between 0% and 100% | B30: =COUNTIFS('12) Budget Line Mapping'!$G$8:$G$37,"<0")+COUNTIFS('12) Budget Line Mapping'!$G$8:$G$37,">1") -> 0 | C30: 0 | D30: =B30-C30 -> 0 | E30: 0 | F30: =IF(ABS(D30)<=E30,"PASS","FAIL") -> PASS | G30: Mappings | H30: Allows 80% and authorised 100% lines
A31: Reporting cut-off is within the project | B31: =--AND('1) Budget-Actuals Dashboard'!$C$4>='0) ReadMe and Contents'!$B$8,'1) Budget-Actuals Dashboard'!$C$4<='0) ReadMe and Contents'!$B$9) -> 1 | C31: 1 | D31: =B31-C31 -> 0 | E31: 0 | F31: =IF(ABS(D31)<=E31,"PASS","FAIL") -> PASS | G31: Dashboard | H31: Use a valid reporting cut-off
A32: Period-view selector is valid | B32: =COUNTIF('12) Budget Line Mapping'!$L$2:$L$4,'1) Budget-Actuals Dashboard'!$G$4) -> 1 | C32: 1 | D32: =B32-C32 -> 0 | E32: 0 | F32: =IF(ABS(D32)<=E32,"PASS","FAIL") -> PASS | G32: Dashboard | H32: Cumulative, Monthly or Quarterly
A33: Funding-basis selector is valid | B33: =COUNTIF('12) Budget Line Mapping'!$M$2:$M$4,'1) Budget-Actuals Dashboard'!$K$4) -> 1 | C33: 1 | D33: =B33-C33 -> 0 | E33: 0 | F33: =IF(ABS(D33)<=E33,"PASS","FAIL") -> PASS | G33: Dashboard | H33: 100% fEC, UKRI or RUSI
A34: UKRI and RUSI source control totals match the frozen award | B34: =ROUND(SUM('9) Budget Baseline'!$M$8:$M$1087),2)+ROUND(SUM('9) Budget Baseline'!$N$8:$N$1087),2) -> 320708.28 | C34: 320708.28 | D34: =B34-C34 -> 0 | E34: 0.01 | F34: =IF(ABS(D34)<=E34,"PASS","FAIL") -> PASS | G34: Budget Baseline | H34: Two-decimal presentation basis
A35: No approved Budget changes are assumed in the demo | B35: =COUNTIFS('10) Budget Changes'!$I$8:$I$107,"APPROVED") -> 0 | C35: 0 | D35: =B35-C35 -> 0 | E35: 0 | F35: =IF(ABS(D35)<=E35,"PASS","FAIL") -> PASS | G35: Budget Changes | H35: Update only with documented authority

Sheet 12) Budget Line Mapping
A1: Budget-item mappings | L1: Period View | M1: Funding Basis | N1: Work Package | O1: fEC Heading | P1: fEC Subheading | Q1: Statuses
A2: Validation table mapping various Budget headings and funding rates across different Budget levels, from specifdic Work Package lines to top-level fEC cost headings (e.g. 'Directly Incurred' or 'Indirects'). | L2: Cumulative | M2: 100% fEC | N2: All | O2: All | P2: All | Q2: APPROVED
L3: Monthly | M3: Price to Funder (UKRI) | N3: WP1 | O3: Directly Allocated | P3: Staff | Q3: STAGED
A4: This hypothetical Budget assumes there are no Exceptional costs (fEC 100%). 80% UKRI is assumed for all lines. If an Exception is introduced, update the mapped funding rate and keep the original award baseline for reference. | L4: Quarterly | M4: RUSI | N4: WP2 | O4: Directly Incurred | P4: Estates | Q4: REJECTED
N5: WP3 | O5: Indirect | P5: Travel & Subsistence | Q5: Open
P6: Other Directly Incurred | Q6: Closed
A7: Budget Item ID | B7: Description | C7: Work Package | D7: fEC Heading | E7: fEC Subheading | F7: Reporting Category | G7: Funding Rate | H7: DI Eligible? | I7: Evidence Expectation | J7: Notes | P7: Indirect | Q7: Cancelled
A8: WP1_S01 | B8: RUSI - Project Officer (existing staff, DA) @GrB/4 | C8: WP1 | D8: Directly Allocated | E8: Staff | F8: Directly Allocated Staff | G8: 0.8 | H8: No | I8: Approved staff-time/allocation basis | J8: Illustrative mapping from source Budget
A9: WP1_S02 | B9: RUSI - Research Analyst (existing staff, DA) @GrC/8 | C9: WP1 | D9: Directly Allocated | E9: Staff | F9: Directly Allocated Staff | G9: 0.8 | H9: No | I9: Approved staff-time/allocation basis | J9: Illustrative mapping from source Budget
A10: WP1_S03 | B10: RUSI - Programme/Project Lead (existing staff, DA) @GrE/14 | C10: WP1 | D10: Directly Allocated | E10: Staff | F10: Directly Allocated Staff | G10: 0.8 | H10: No | I10: Approved staff-time/allocation basis | J10: Illustrative mapping from source Budget
A11: WP1_TRAVEL | B11: RUSI - UK rail, local travel and subsistence Budget | C11: WP1 | D11: Directly Incurred | E11: Travel & Subsistence | F11: Travel & Subsistence | G11: 0.8 | H11: Yes | I11: Invoice, expense or contract evidence | J11: Illustrative mapping from source Budget
A12: WP1_CONF | B12: RUSI - five-day flagship London conferences (launch and close) | C12: WP1 | D12: Directly Incurred | E12: Other Directly Incurred | F12: Conferences | G12: 0.8 | H12: Yes | I12: Invoice, expense or contract evidence | J12: Illustrative mapping from source Budget
A13: WP1_WORKSHOP | B13: RUSI - UK national and regional workshops | C13: WP1 | D13: Directly Incurred | E13: Other Directly Incurred | F13: Workshops | G13: 0.8 | H13: Yes | I13: Invoice, expense or contract evidence | J13: Illustrative mapping from source Budget
A14: WP1_PANEL | B14: RUSI - hybrid panels and practitioner roundtables | C14: WP1 | D14: Directly Incurred | E14: Other Directly Incurred | F14: Panels & Roundtables | G14: 0.8 | H14: Yes | I14: Invoice, expense or contract evidence | J14: Illustrative mapping from source Budget
A15: WP1_COMMS | B15: RUSI - knowledge products and digital communications | C15: WP1 | D15: Directly Incurred | E15: Other Directly Incurred | F15: Communications & Knowledge Products | G15: 0.8 | H15: Yes | I15: Invoice, expense or contract evidence | J15: Illustrative mapping from source Budget
A16: WP1_IND | B16: RUSI - indirect allocation (dispensation proxy × eligible staff FTE) | C16: WP1 | D16: Indirect | E16: Indirect | F16: Indirect Costs | G16: 0.8 | H16: No | I16: Approved indirect allocation basis | J16: Illustrative mapping from source Budget
A17: WP1_EST | B17: RUSI - non-laboratory estate allocation (dispensation proxy × eligible staff FTE) | C17: WP1 | D17: Directly Allocated | E17: Estates | F17: Estate Costs | G17: 0.8 | H17: No | I17: Approved estate allocation basis | J17: Illustrative mapping from source Budget
A18: WP2_S01 | B18: RUSI - Project Officer (existing staff, DA) @GrB/4 | C18: WP2 | D18: Directly Allocated | E18: Staff | F18: Directly Allocated Staff | G18: 0.8 | H18: No | I18: Approved staff-time/allocation basis | J18: Illustrative mapping from source Budget
A19: WP2_S02 | B19: RUSI - Research Analyst (existing staff, DA) @GrC/8 | C19: WP2 | D19: Directly Allocated | E19: Staff | F19: Directly Allocated Staff | G19: 0.8 | H19: No | I19: Approved staff-time/allocation basis | J19: Illustrative mapping from source Budget
... A37: WP3_EST | B37: RUSI - non-laboratory estate allocation (dispensation proxy × eligible staff FTE) | C37: WP3 | D37: Directly Allocated | E37: Estates | F37: Estate Costs | G37: 0.8 | H37: No | I37: Approved estate allocation basis | J37: Illustrative mapping from source Budget

Sheet 14) Model Calc
A1: Model calculations
A2: Control | B2: Value | D2: Helper columns for storing various slicer values, KPIs, charts and reconciliations
A3: Reporting cut-off | B3: =Dash_ReportCutOff -> 46265
A4: Period view | B4: ='1) Budget-Actuals Dashboard'!$G$4 -> Cumulative
A5: Funding basis | B5: ='1) Budget-Actuals Dashboard'!$K$4 -> 100% fEC
A6: Work Package | B6: ='1) Budget-Actuals Dashboard'!$C$5 -> All
A7: fEC Heading | B7: ='1) Budget-Actuals Dashboard'!$G$5 -> Directly Incurred
A8: fEC Subheading | B8: ='1) Budget-Actuals Dashboard'!$K$5 -> All
A9: Selected period start | B9: =IF(B4="Monthly",EOMONTH(B3,-1)+1,IF(B4="Quarterly",EDATE(DATE(YEAR(B3)-(MONTH(B3)<4),4,1),3*INT(MOD(MONTH(B3)-4,12)/3)),'0) ReadMe and Contents'!$B$8)) -> 46113
A10: Selected period end | B10: =B3 -> 46265
A12: Selected-period phased Budget | B12: =IF($B$5="100% fEC",SUMIFS('9) Budget Baseline'!$P$8:$P$1087,'9) Budget Baseline'!$H$8:$H$1087,">="&$B$9,'9) Budget Baseline'!$H$8:$H$1087,"<="&$B$10,'9) Budget Baseline'!$D$8:$D$1087,IF($B$6="All","*",$B$6),'9) Budget Baseline'!$E$8:$E$1087,IF($B$7="All","*",$B$7),'9) Budget Baseline'!$F$8:$F$1087,IF($B$8="All","*",$B$8)),IF($B$5="UKRI",SUMIFS('9) Budget Baseline'!$Q$8:$Q$1087,'9) Budget Baseline'!$H$8:$H$1087,">="&$B$9,'9) Budget Baseline'!$H$8:$H$1087,"<="&$B$10,'9) Budget Baseline'!$D$8:$D$1087,IF($B$6="All","*",$B$6),'9) Budget Baseline'!$E$8:$E$1087,IF($B$7="All","*",$B$7),'9) Budget Baseline'!$F$8:$F$1087,IF($B$8="All","*",$B$8)),SUMIFS('9) Budget Baseline'!$R$8:$R$1087,'9) Budget Baseline'!$H$8:$H$1087,">="&$B$9,'9) Budget Baseline'!$H$8:$H$1087,"<="&$B$10,'9) Budget Baseline'!$D$8:$D$1087,IF($B$6="All","*",$B$6),'9) Budget Baseline'!$E$8:$E$1087,IF($B$7="All","*",$B$7),'9) Budget Baseline'!$F$8:$F$1087,IF($B$8="All","*",$B$8)))) -> 12805.558
A13: Selected-period recognised cost | B13: =IF($B$5="100% fEC",SUMIFS('6) Actuals Ledger - DI Costs'!$R$8:$R$2007,'6) Actuals Ledger - DI Costs'!$C$8:$C$2007,">="&$B$9,'6) Actuals Ledger - DI Costs'!$C$8:$C$2007,"<="&$B$10,'6) Actuals Ledger - DI Costs'!$M$8:$M$2007,IF($B$6="All","*",$B$6),'6) Actuals Ledger - DI Costs'!$N$8:$N$2007,IF($B$7="All","*",$B$7),'6) Actuals Ledger - DI Costs'!$O$8:$O$2007,IF($B$8="All","*",$B$8))+SUMIFS('7) Allocations - DA Costs'!$O$8:$O$2007,'7) Allocations - DA Costs'!$C$8:$C$2007,">="&$B$9,'7) Allocations - DA Costs'!$C$8:$C$2007,"<="&$B$10,'7) Allocations - DA Costs'!$J$8:$J$2007,IF($B$6="All","*",$B$6),'7) Allocations - DA Costs'!$K$8:$K$2007,IF($B$7="All","*",$B$7),'7) Allocations - DA Costs'!$L$8:$L$2007,IF($B$8="All","*",$B$8)),IF($B$5="UKRI",SUMIFS('6) Actuals Ledger - DI Costs'!$S$8:$S$2007,'6) Actuals Ledger - DI Costs'!$C$8:$C$2007,">="&$B$9,'6) Actuals Ledger - DI Costs'!$C$8:$C$2007,"<="&$B$10,'6) Actuals Ledger - DI Costs'!$M$8:$M$2007,IF($B$6="All","*",$B$6),'6) Actuals Ledger - DI Costs'!$N$8:$N$2007,IF($B$7="All","*",$B$7),'6) Actuals Ledger - DI Costs'!$O$8:$O$2007,IF($B$8="All","*",$B$8))+SUMIFS('7) Allocations - DA Costs'!$P$8:$P$2007,'7) Allocations - DA Costs'!$C$8:$C$2007,">="&$B$9,'7) Allocations - DA Costs'!$C$8:$C$2007,"<="&$B$10,'7) Allocations - DA Costs'!$J$8:$J$2007,IF($B$6="All","*",$B$6),'7) Allocations - DA Costs'!$K$8:$K$2007,IF($B$7="All","*",$B$7),'7) Allocations - DA Costs'!$L$8:$L$2007,IF($B$8="All","*",$B$8)),SUMIFS('6) Actuals Ledger - DI Costs'!$T$8:$T$2007,'6) Actuals Ledger - DI Costs'!$C$8:$C$2007,">="&$B$9,'6) Actuals Ledger - DI Costs'!$C$8:$C$2007,"<="&$B$10,'6) Actuals Ledger - DI Costs'!$M$8:$M$2007,IF($B$6="All","*",$B$6),'6) Actuals Ledger - DI Costs'!$N$8:$N$2007,IF($B$7="All","*",$B$7),'6) Actuals Ledger - DI Costs'!$O$8:$O$2007,IF($B$8="All","*",$B$8))+SUMIFS('7) Allocations - DA Costs'!$Q$8:$Q$2007,'7) Allocations - DA Costs'!$C$8:$C$2007,">="&$B$9,'7) Allocations - DA Costs'!$C$8:$C$2007,"<="&$B$10,'7) Allocations - DA Costs'!$J$8:$J$2007,IF($B$6="All","*",$B$6),'7) Allocations - DA Costs'!$K$8:$K$2007,IF($B$7="All","*",$B$7),'7) Allocations - DA Costs'!$L$8:$L$2007,IF($B$8="All","*",$B$8)))) -> 13751.2
A14: Variance to phased | B14: =B12-B13 -> -945.64167
A15: Cumulative phased Budget | B15: =IF($B$5="100% fEC",SUMIFS('9) Budget Baseline'!$P$8:$P$1087,'9) Budget Baseline'!$H$8:$H$1087,">="&'0) ReadMe and Contents'!$B$8,'9) Budget Baseline'!$H$8:$H$1087,"<="&$B$3,'9) Budget Baseline'!$D$8:$D$1087,IF($B$6="All","*",$B$6),'9) Budget Baseline'!$E$8:$E$1087,IF($B$7="All","*",$B$7),'9) Budget Baseline'!$F$8:$F$1087,IF($B$8="All","*",$B$8)),IF($B$5="UKRI",SUMIFS('9) Budget Baseline'!$Q$8:$Q$1087,'9) Budget Baseline'!$H$8:$H$1087,">="&'0) ReadMe and Contents'!$B$8,'9) Budget Baseline'!$H$8:$H$1087,"<="&$B$3,'9) Budget Baseline'!$D$8:$D$1087,IF($B$6="All","*",$B$6),'9) Budget Baseline'!$E$8:$E$1087,IF($B$7="All","*",$B$7),'9) Budget Baseline'!$F$8:$F$1087,IF($B$8="All","*",$B$8)),SUMIFS('9) Budget Baseline'!$R$8:$R$1087,'9) Budget Baseline'!$H$8:$H$1087,">="&'0) ReadMe and Contents'!$B$8,'9) Budget Baseline'!$H$8:$H$1087,"<="&$B$3,'9) Budget Baseline'!$D$8:$D$1087,IF($B$6="All","*",$B$6),'9) Budget Baseline'!$E$8:$E$1087,IF($B$7="All","*",$B$7),'9) Budget Baseline'!$F$8:$F$1087,IF($B$8="All","*",$B$8)))) -> 12805.558
A16: Cumulative recognised cost | B16: =IF($B$5="100% fEC",SUMIFS('6) Actuals Ledger - DI Costs'!$R$8:$R$2007,'6) Actuals Ledger - DI Costs'!$C$8:$C$2007,">="&'0) ReadMe and Contents'!$B$8,'6) Actuals Ledger - DI Costs'!$C$8:$C$2007,"<="&$B$3,'6) Actuals Ledger - DI Costs'!$M$8:$M$2007,IF($B$6="All","*",$B$6),'6) Actuals Ledger - DI Costs'!$N$8:$N$2007,IF($B$7="All","*",$B$7),'6) Actuals Ledger - DI Costs'!$O$8:$O$2007,IF($B$8="All","*",$B$8))+SUMIFS('7) Allocations - DA Costs'!$O$8:$O$2007,'7) Allocations - DA Costs'!$C$8:$C$2007,">="&'0) ReadMe and Contents'!$B$8,'7) Allocations - DA Costs'!$C$8:$C$2007,"<="&$B$3,'7) Allocations - DA Costs'!$J$8:$J$2007,IF($B$6="All","*",$B$6),'7) Allocations - DA Costs'!$K$8:$K$2007,IF($B$7="All","*",$B$7),'7) Allocations - DA Costs'!$L$8:$L$2007,IF($B$8="All","*",$B$8)),IF($B$5="UKRI",SUMIFS('6) Actuals Ledger - DI Costs'!$S$8:$S$2007,'6) Actuals Ledger - DI Costs'!$C$8:$C$2007,">="&'0) ReadMe and Contents'!$B$8,'6) Actuals Ledger - DI Costs'!$C$8:$C$2007,"<="&$B$3,'6) Actuals Ledger - DI Costs'!$M$8:$M$2007,IF($B$6="All","*",$B$6),'6) Actuals Ledger - DI Costs'!$N$8:$N$2007,IF($B$7="All","*",$B$7),'6) Actuals Ledger - DI Costs'!$O$8:$O$2007,IF($B$8="All","*",$B$8))+SUMIFS('7) Allocations - DA Costs'!$P$8:$P$2007,'7) Allocations - DA Costs'!$C$8:$C$2007,">="&'0) ReadMe and Contents'!$B$8,'7) Allocations - DA Costs'!$C$8:$C$2007,"<="&$B$3,'7) Allocations - DA Costs'!$J$8:$J$2007,IF($B$6="All","*",$B$6),'7) Allocations - DA Costs'!$K$8:$K$2007,IF($B$7="All","*",$B$7),'7) Allocations - DA Costs'!$L$8:$L$2007,IF($B$8="All","*",$B$8)),SUMIFS('6) Actuals Ledger - DI Costs'!$T$8:$T$2007,'6) Actuals Ledger - DI Costs'!$C$8:$C$2007,">="&'0) ReadMe and Contents'!$B$8,'6) Actuals Ledger - DI Costs'!$C$8:$C$2007,"<="&$B$3,'6) Actuals Ledger - DI Costs'!$M$8:$M$2007,IF($B$6="All","*",$B$6),'6) Actuals Ledger - DI Costs'!$N$8:$N$2007,IF($B$7="All","*",$B$7),'6) Actuals Ledger - DI Costs'!$O$8:$O$2007,IF($B$8="All","*",$B$8))+SUMIFS('7) Allocations - DA Costs'!$Q$8:$Q$2007,'7) Allocations - DA Costs'!$C$8:$C$2007,">="&'0) ReadMe and Contents'!$B$8,'7) Allocations - DA Costs'!$C$8:$C$2007,"<="&$B$3,'7) Allocations - DA Costs'!$J$8:$J$2007,IF($B$6="All","*",$B$6),'7) Allocations - DA Costs'!$K$8:$K$2007,IF($B$7="All","*",$B$7),'7) Allocations - DA Costs'!$L$8:$L$2007,IF($B$8="All","*",$B$8)))) -> 13751.2
A17: Cumulative simple pro-rata | B17: =B18*MIN(36,MAX(0,(YEAR(B3)-YEAR('0) ReadMe and Contents'!$B$8))*12+MONTH(B3)-MONTH('0) ReadMe and Contents'!$B$8)+1))/36 -> 21416.669
A18: Full approved Budget | B18: =IF($B$5="100% fEC",SUMIFS('9) Budget Baseline'!$P$8:$P$1087,'9) Budget Baseline'!$H$8:$H$1087,">="&'0) ReadMe and Contents'!$B$8,'9) Budget Baseline'!$H$8:$H$1087,"<="&'0) ReadMe and Contents'!$B$9,'9) Budget Baseline'!$D$8:$D$1087,IF($B$6="All","*",$B$6),'9) Budget Baseline'!$E$8:$E$1087,IF($B$7="All","*",$B$7),'9) Budget Baseline'!$F$8:$F$1087,IF($B$8="All","*",$B$8)),IF($B$5="UKRI",SUMIFS('9) Budget Baseline'!$Q$8:$Q$1087,'9) Budget Baseline'!$H$8:$H$1087,">="&'0) ReadMe and Contents'!$B$8,'9) Budget Baseline'!$H$8:$H$1087,"<="&'0) ReadMe and Contents'!$B$9,'9) Budget Baseline'!$D$8:$D$1087,IF($B$6="All","*",$B$6),'9) Budget Baseline'!$E$8:$E$1087,IF($B$7="All","*",$B$7),'9) Budget Baseline'!$F$8:$F$1087,IF($B$8="All","*",$B$8)),SUMIFS('9) Budget Baseline'!$R$8:$R$1087,'9) Budget Baseline'!$H$8:$H$1087,">="&'0) ReadMe and Contents'!$B$8,'9) Budget Baseline'!$H$8:$H$1087,"<="&'0) ReadMe and Contents'!$B$9,'9) Budget Baseline'!$D$8:$D$1087,IF($B$6="All","*",$B$6),'9) Budget Baseline'!$E$8:$E$1087,IF($B$7="All","*",$B$7),'9) Budget Baseline'!$F$8:$F$1087,IF($B$8="All","*",$B$8)))) -> 154200.02
A19: Open commitments | B19: =IF($B$5="100% fEC",SUMIFS('8) Commitments Forecast'!$Q$8:$Q$507,'8) Commitments Forecast'!$L$8:$L$507,IF($B$6="All","*",$B$6),'8) Commitments Forecast'!$M$8:$M$507,IF($B$7="All","*",$B$7),'8) Commitments Forecast'!$N$8:$N$507,IF($B$8="All","*",$B$8)),IF($B$5="UKRI",SUMIFS('8) Commitments Forecast'!$R$8:$R$507,'8) Commitments Forecast'!$L$8:$L$507,IF($B$6="All","*",$B$6),'8) Commitments Forecast'!$M$8:$M$507,IF($B$7="All","*",$B$7),'8) Commitments Forecast'!$N$8:$N$507,IF($B$8="All","*",$B$8)),SUMIFS('8) Commitments Forecast'!$S$8:$S$507,'8) Commitments Forecast'!$L$8:$L$507,IF($B$6="All","*",$B$6),'8) Commitments Forecast'!$M$8:$M$507,IF($B$7="All","*",$B$7),'8) Commitments Forecast'!$N$8:$N$507,IF($B$8="All","*",$B$8)))) -> 27200
A20: Forecast at Completion | B20: =IF($B$5="100% fEC",SUMIFS('3) Forecast Bridge'!$K$8:$K$37,'3) Forecast Bridge'!$C$8:$C$37,IF($B$6="All","*",$B$6),'3) Forecast Bridge'!$D$8:$D$37,IF($B$7="All","*",$B$7),'3) Forecast Bridge'!$E$8:$E$37,IF($B$8="All","*",$B$8)),IF($B$5="UKRI",SUMIFS('3) Forecast Bridge'!$N$8:$N$37,'3) Forecast Bridge'!$C$8:$C$37,IF($B$6="All","*",$B$6),'3) Forecast Bridge'!$D$8:$D$37,IF($B$7="All","*",$B$7),'3) Forecast Bridge'!$E$8:$E$37,IF($B$8="All","*",$B$8)),SUMIFS('3) Forecast Bridge'!$O$8:$O$37,'3) Forecast Bridge'!$C$8:$C$37,IF($B$6="All","*",$B$6),'3) Forecast Bridge'!$D$8:$D$37,IF($B$7="All","*",$B$7),'3) Forecast Bridge'!$E$8:$E$37,IF($B$8="All","*",$B$8)))) -> 157100.02
A21: Forecast variance | B21: =B18-B20 -> -2900
A22: Confirmed DI Costs | B22: =SUMIFS('6) Actuals Ledger - DI Costs'!$R$8:$R$2007,'6) Actuals Ledger - DI Costs'!$C$8:$C$2007,"<="&$B$3) -> 13751.2
A23: Approved DI Budget | B23: =SUMIFS('9) Budget Baseline'!$P$8:$P$1087,'9) Budget Baseline'!$E$8:$E$1087,"Directly Incurred") -> 154200.02
A24: Remaining DI Budget | B24: =MAX(0,B23-B22) -> 140448.82
A25: DI Budget consumed | B25: =IF(B23=0,0,B22/B23) -> 0.08917768
A26: Model status | B26: ='11) Model Audit Checks'!$B$2 -> PASS
A27: Last refresh | B27: =MAX('5) Refresh Log'!$E$8:$E$107) -> 46266.375
A31: Month | B31: Cumulative phased Budget | C31: Cumulative recognised cost | D31: Simple pro-rata
A32: 46142 | B32: =IF($B$5="100% fEC",SUMIFS('9) Budget Baseline'!$P$8:$P$1087,'9) Budget Baseline'!$H$8:$H$1087,">="&'0) ReadMe and Contents'!$B$8,'9) Budget Baseline'!$H$8:$H$1087,"<="&A32,'9) Budget Baseline'!$D$8:$D$1087,IF($B$6="All","*",$B$6),'9) Budget Baseline'!$E$8:$E$1087,IF($B$7="All","*",$B$7),'9) Budget Baseline'!$F$8:$F$1087,IF($B$8="All","*",$B$8)),IF($B$5="UKRI",SUMIFS('9) Budget Baseline'!$Q$8:$Q$1087,'9) Budget Baseline'!$H$8:$H$1087,">="&'0) ReadMe and Contents'!$B$8,'9) Budget Baseline'!$H$8:$H$1087,"<="&A32,'9) Budget Baseline'!$D$8:$D$1087,IF($B$6="All","*",$B$6),'9) Budget Baseline'!$E$8:$E$1087,IF($B$7="All","*",$B$7),'9) Budget Baseline'!$F$8:$F$1087,IF($B$8="All","*",$B$8)),SUMIFS('9) Budget Baseline'!$R$8:$R$1087,'9) Budget Baseline'!$H$8:$H$1087,">="&'0) ReadMe and Contents'!$B$8,'9) Budget Baseline'!$H$8:$H$1087,"<="&A32,'9) Budget Baseline'!$D$8:$D$1087,IF($B$6="All","*",$B$6),'9) Budget Baseline'!$E$8:$E$1087,IF($B$7="All","*",$B$7),'9) Budget Baseline'!$F$8:$F$1087,IF($B$8="All","*",$B$8)))) -> 2561.1117 | C32: =IF(A32>$B$3,NA(),IF($B$5="100% fEC",SUMIFS('6) Actuals Ledger - DI Costs'!$R$8:$R$2007,'6) Actuals Ledger - DI Costs'!$C$8:$C$2007,">="&'0) ReadMe and Contents'!$B$8,'6) Actuals Ledger - DI Costs'!$C$8:$C$2007,"<="&A32,'6) Actuals Ledger - DI Costs'!$M$8:$M$2007,IF($B$6="All","*",$B$6),'6) Actuals Ledger - DI Costs'!$N$8:$N$2007,IF($B$7="All","*",$B$7),'6) Actuals Ledger - DI Costs'!$O$8:$O$2007,IF($B$8="All","*",$B$8))+SUMIFS('7) Allocations - DA Costs'!$O$8:$O$2007,'7) Allocations - DA Costs'!$C$8:$C$2007,">="&'0) ReadMe and Contents'!$B$8,'7) Allocations - DA Costs'!$C$8:$C$2007,"<="&A32,'7) Allocations - DA Costs'!$J$8:$J$2007,IF($B$6="All","*",$B$6),'7) Allocations - DA Costs'!$K$8:$K$2007,IF($B$7="All","*",$B$7),'7) Allocations - DA Costs'!$L$8:$L$2007,IF($B$8="All","*",$B$8)),IF($B$5="UKRI",SUMIFS('6) Actuals Ledger - DI Costs'!$S$8:$S$2007,'6) Actuals Ledger - DI Costs'!$C$8:$C$2007,">="&'0) ReadMe and Contents'!$B$8,'6) Actuals Ledger - DI Costs'!$C$8:$C$2007,"<="&A32,'6) Actuals Ledger - DI Costs'!$M$8:$M$2007,IF($B$6="All","*",$B$6),'6) Actuals Ledger - DI Costs'!$N$8:$N$2007,IF($B$7="All","*",$B$7),'6) Actuals Ledger - DI Costs'!$O$8:$O$2007,IF($B$8="All","*",$B$8))+SUMIFS('7) Allocations - DA Costs'!$P$8:$P$2007,'7) Allocations - DA Costs'!$C$8:$C$2007,">="&'0) ReadMe and Contents'!$B$8,'7) Allocations - DA Costs'!$C$8:$C$2007,"<="&A32,'7) Allocations - DA Costs'!$J$8:$J$2007,IF($B$6="All","*",$B$6),'7) Allocations - DA Costs'!$K$8:$K$2007,IF($B$7="All","*",$B$7),'7) Allocations - DA Costs'!$L$8:$L$2007,IF($B$8="All","*",$B$8)),SUMIFS('6) Actuals Ledger - DI Costs'!$T$8:$T$2007,'6) Actuals Ledger - DI Costs'!$C$8:$C$2007,">="&'0) ReadMe and Contents'!$B$8,'6) Actuals Ledger - DI Costs'!$C$8:$C$2007,"<="&A32,'6) Actuals Ledger - DI Costs'!$M$8:$M$2007,IF($B$6="All","*",$B$6),'6) Actuals Ledger - DI Costs'!$N$8:$N$2007,IF($B$7="All","*",$B$7),'6) Actuals Ledger - DI Costs'!$O$8:$O$2007,IF($B$8="All","*",$B$8))+SUMIFS('7) Allocations - DA Costs'!$Q$8:$Q$2007,'7) Allocations - DA Costs'!$C$8:$C$2007,">="&'0) ReadMe and Contents'!$B$8,'7) Allocations - DA Costs'!$C$8:$C$2007,"<="&A32,'7) Allocations - DA Costs'!$J$8:$J$2007,IF($B$6="All","*",$B$6),'7) Allocations - DA Costs'!$K$8:$K$2007,IF($B$7="All","*",$B$7),'7) Allocations - DA Costs'!$L$8:$L$2007,IF($B$8="All","*",$B$8))))) -> 1412.4 | D32: =$B$18*1/36 -> 4283.3339
A33: 46173 | B33: =IF($B$5="100% fEC",SUMIFS('9) Budget Baseline'!$P$8:$P$1087,'9) Budget Baseline'!$H$8:$H$1087,">="&'0) ReadMe and Contents'!$B$8,'9) Budget Baseline'!$H$8:$H$1087,"<="&A33,'9) Budget Baseline'!$D$8:$D$1087,IF($B$6="All","*",$B$6),'9) Budget Baseline'!$E$8:$E$1087,IF($B$7="All","*",$B$7),'9) Budget Baseline'!$F$8:$F$1087,IF($B$8="All","*",$B$8)),IF($B$5="UKRI",SUMIFS('9) Budget Baseline'!$Q$8:$Q$1087,'9) Budget Baseline'!$H$8:$H$1087,">="&'0) ReadMe and Contents'!$B$8,'9) Budget Baseline'!$H$8:$H$1087,"<="&A33,'9) Budget Baseline'!$D$8:$D$1087,IF($B$6="All","*",$B$6),'9) Budget Baseline'!$E$8:$E$1087,IF($B$7="All","*",$B$7),'9) Budget Baseline'!$F$8:$F$1087,IF($B$8="All","*",$B$8)),SUMIFS('9) Budget Baseline'!$R$8:$R$1087,'9) Budget Baseline'!$H$8:$H$1087,">="&'0) ReadMe and Contents'!$B$8,'9) Budget Baseline'!$H$8:$H$1087,"<="&A33,'9) Budget Baseline'!$D$8:$D$1087,IF($B$6="All","*",$B$6),'9) Budget Baseline'!$E$8:$E$1087,IF($B$7="All","*",$B$7),'9) Budget Baseline'!$F$8:$F$1087,IF($B$8="All","*",$B$8)))) -> 5122.2233 | C33: =IF(A33>$B$3,NA(),IF($B$5="100% fEC",SUMIFS('6) Actuals Ledger - DI Costs'!$R$8:$R$2007,'6) Actuals Ledger - DI Costs'!$C$8:$C$2007,">="&'0) ReadMe and Contents'!$B$8,'6) Actuals Ledger - DI Costs'!$C$8:$C$2007,"<="&A33,'6) Actuals Ledger - DI Costs'!$M$8:$M$2007,IF($B$6="All","*",$B$6),'6) Actuals Ledger - DI Costs'!$N$8:$N$2007,IF($B$7="All","*",$B$7),'6) Actuals Ledger - DI Costs'!$O$8:$O$2007,IF($B$8="All","*",$B$8))+SUMIFS('7) Allocations - DA Costs'!$O$8:$O$2007,'7) Allocations - DA Costs'!$C$8:$C$2007,">="&'0) ReadMe and Contents'!$B$8,'7) Allocations - DA Costs'!$C$8:$C$2007,"<="&A33,'7) Allocations - DA Costs'!$J$8:$J$2007,IF($B$6="All","*",$B$6),'7) Allocations - DA Costs'!$K$8:$K$2007,IF($B$7="All","*",$B$7),'7) Allocations - DA Costs'!$L$8:$L$2007,IF($B$8="All","*",$B$8)),IF($B$5="UKRI",SUMIFS('6) Actuals Ledger - DI Costs'!$S$8:$S$2007,'6) Actuals Ledger - DI Costs'!$C$8:$C$2007,">="&'0) ReadMe and Contents'!$B$8,'6) Actuals Ledger - DI Costs'!$C$8:$C$2007,"<="&A33,'6) Actuals Ledger - DI Costs'!$M$8:$M$2007,IF($B$6="All","*",$B$6),'6) Actuals Ledger - DI Costs'!$N$8:$N$2007,IF($B$7="All","*",$B$7),'6) Actuals Ledger - DI Costs'!$O$8:$O$2007,IF($B$8="All","*",$B$8))+SUMIFS('7) Allocations - DA Costs'!$P$8:$P$2007,'7) Allocations - DA Costs'!$C$8:$C$2007,">="&'0) ReadMe and Contents'!$B$8,'7) Allocations - DA Costs'!$C$8:$C$2007,"<="&A33,'7) Allocations - DA Costs'!$J$8:$J$2007,IF($B$6="All","*",$B$6),'7) Allocations - DA Costs'!$K$8:$K$2007,IF($B$7="All","*",$B$7),'7) Allocations - DA Costs'!$L$8:$L$2007,IF($B$8="All","*",$B$8)),SUMIFS('6) Actuals Ledger - DI Costs'!$T$8:$T$2007,'6) Actuals Ledger - DI Costs'!$C$8:$C$2007,">="&'0) ReadMe and Contents'!$B$8,'6) Actuals Ledger - DI Costs'!$C$8:$C$2007,"<="&A33,'6) Actuals Ledger - DI Costs'!$M$8:$M$2007,IF($B$6="All","*",$B$6),'6) Actuals Ledger - DI Costs'!$N$8:$N$2007,IF($B$7="All","*",$B$7),'6) Actuals Ledger - DI Costs'!$O$8:$O$2007,IF($B$8="All","*",$B$8))+SUMIFS('7) Allocations - DA Costs'!$Q$8:$Q$2007,'7) Allocations - DA Costs'!$C$8:$C$2007,">="&'0) ReadMe and Contents'!$B$8,'7) Allocations - DA Costs'!$C$8:$C$2007,"<="&A33,'7) Allocations - DA Costs'!$J$8:$J$2007,IF($B$6="All","*",$B$6),'7) Allocations - DA Costs'!$K$8:$K$2007,IF($B$7="All","*",$B$7),'7) Allocations - DA Costs'!$L$8:$L$2007,IF($B$8="All","*",$B$8))))) -> 4370.6 | D33: =$B$18*2/36 -> 8566.6678
A34: 46203 | B34: =IF($B$5="100% fEC",SUMIFS('9) Budget Baseline'!$P$8:$P$1087,'9) Budget Baseline'!$H$8:$H$1087,">="&'0) ReadMe and Contents'!$B$8,'9) Budget Baseline'!$H$8:$H$1087,"<="&A34,'9) Budget Baseline'!$D$8:$D$1087,IF($B$6="All","*",$B$6),'9) Budget Baseline'!$E$8:$E$1087,IF($B$7="All","*",$B$7),'9) Budget Baseline'!$F$8:$F$1087,IF($B$8="All","*",$B$8)),IF($B$5="UKRI",SUMIFS('9) Budget Baseline'!$Q$8:$Q$1087,'9) Budget Baseline'!$H$8:$H$1087,">="&'0) ReadMe and Contents'!$B$8,'9) Budget Baseline'!$H$8:$H$1087,"<="&A34,'9) Budget Baseline'!$D$8:$D$1087,IF($B$6="All","*",$B$6),'9) Budget Baseline'!$E$8:$E$1087,IF($B$7="All","*",$B$7),'9) Budget Baseline'!$F$8:$F$1087,IF($B$8="All","*",$B$8)),SUMIFS('9) Budget Baseline'!$R$8:$R$1087,'9) Budget Baseline'!$H$8:$H$1087,">="&'0) ReadMe and Contents'!$B$8,'9) Budget Baseline'!$H$8:$H$1087,"<="&A34,'9) Budget Baseline'!$D$8:$D$1087,IF($B$6="All","*",$B$6),'9) Budget Baseline'!$E$8:$E$1087,IF($B$7="All","*",$B$7),'9) Budget Baseline'!$F$8:$F$1087,IF($B$8="All","*",$B$8)))) -> 7683.335 | C34: =IF(A34>$B$3,NA(),IF($B$5="100% fEC",SUMIFS('6) Actuals Ledger - DI Costs'!$R$8:$R$2007,'6) Actuals Ledger - DI Costs'!$C$8:$C$2007,">="&'0) ReadMe and Contents'!$B$8,'6) Actuals Ledger - DI Costs'!$C$8:$C$2007,"<="&A34,'6) Actuals Ledger - DI Costs'!$M$8:$M$2007,IF($B$6="All","*",$B$6),'6) Actuals Ledger - DI Costs'!$N$8:$N$2007,IF($B$7="All","*",$B$7),'6) Actuals Ledger - DI Costs'!$O$8:$O$2007,IF($B$8="All","*",$B$8))+SUMIFS('7) Allocations - DA Costs'!$O$8:$O$2007,'7) Allocations - DA Costs'!$C$8:$C$2007,">="&'0) ReadMe and Contents'!$B$8,'7) Allocations - DA Costs'!$C$8:$C$2007,"<="&A34,'7) Allocations - DA Costs'!$J$8:$J$2007,IF($B$6="All","*",$B$6),'7) Allocations - DA Costs'!$K$8:$K$2007,IF($B$7="All","*",$B$7),'7) Allocations - DA Costs'!$L$8:$L$2007,IF($B$8="All","*",$B$8)),IF($B$5="UKRI",SUMIFS('6) Actuals Ledger - DI Costs'!$S$8:$S$2007,'6) Actuals Ledger - DI Costs'!$C$8:$C$2007,">="&'0) ReadMe and Contents'!$B$8,'6) Actuals Ledger - DI Costs'!$C$8:$C$2007,"<="&A34,'6) Actuals Ledger - DI Costs'!$M$8:$M$2007,IF($B$6="All","*",$B$6),'6) Actuals Ledger - DI Costs'!$N$8:$N$2007,IF($B$7="All","*",$B$7),'6) Actuals Ledger - DI Costs'!$O$8:$O$2007,IF($B$8="All","*",$B$8))+SUMIFS('7) Allocations - DA Costs'!$P$8:$P$2007,'7) Allocations - DA Costs'!$C$8:$C$2007,">="&'0) ReadMe and Contents'!$B$8,'7) Allocations - DA Costs'!$C$8:$C$2007,"<="&A34,'7) Allocations - DA Costs'!$J$8:$J$2007,IF($B$6="All","*",$B$6),'7) Allocations - DA Costs'!$K$8:$K$2007,IF($B$7="All","*",$B$7),'7) Allocations - DA Costs'!$L$8:$L$2007,IF($B$8="All","*",$B$8)),SUMIFS('6) Actuals Ledger - DI Costs'!$T$8:$T$2007,'6) Actuals Ledger - DI Costs'!$C$8:$C$2007,">="&'0) ReadMe and Contents'!$B$8,'6) Actuals Ledger - DI Costs'!$C$8:$C$2007,"<="&A34,'6) Actuals Ledger - DI Costs'!$M$8:$M$2007,IF($B$6="All","*",$B$6),'6) Actuals Ledger - DI Costs'!$N$8:$N$2007,IF($B$7="All","*",$B$7),'6) Actuals Ledger - DI Costs'!$O$8:$O$2007,IF($B$8="All","*",$B$8))+SUMIFS('7) Allocations - DA Costs'!$Q$8:$Q$2007,'7) Allocations - DA Costs'!$C$8:$C$2007,">="&'0) ReadMe and Contents'!$B$8,'7) Allocations - DA Costs'!$C$8:$C$2007,"<="&A34,'7) Allocations - DA Costs'!$J$8:$J$2007,IF($B$6="All","*",$B$6),'7) Allocations - DA Costs'!$K$8:$K$2007,IF($B$7="All","*",$B$7),'7) Allocations - DA Costs'!$L$8:$L$2007,IF($B$8="All","*",$B$8))))) -> 7459.2 | D34: =$B$18*3/36 -> 12850.002
A35: 46234 | B35: =IF($B$5="100% fEC",SUMIFS('9) Budget Baseline'!$P$8:$P$1087,'9) Budget Baseline'!$H$8:$H$1087,">="&'0) ReadMe and Contents'!$B$8,'9) Budget Baseline'!$H$8:$H$1087,"<="&A35,'9) Budget Baseline'!$D$8:$D$1087,IF($B$6="All","*",$B$6),'9) Budget Baseline'!$E$8:$E$1087,IF($B$7="All","*",$B$7),'9) Budget Baseline'!$F$8:$F$1087,IF($B$8="All","*",$B$8)),IF($B$5="UKRI",SUMIFS('9) Budget Baseline'!$Q$8:$Q$1087,'9) Budget Baseline'!$H$8:$H$1087,">="&'0) ReadMe and Contents'!$B$8,'9) Budget Baseline'!$H$8:$H$1087,"<="&A35,'9) Budget Baseline'!$D$8:$D$1087,IF($B$6="All","*",$B$6),'9) Budget Baseline'!$E$8:$E$1087,IF($B$7="All","*",$B$7),'9) Budget Baseline'!$F$8:$F$1087,IF($B$8="All","*",$B$8)),SUMIFS('9) Budget Baseline'!$R$8:$R$1087,'9) Budget Baseline'!$H$8:$H$1087,">="&'0) ReadMe and Contents'!$B$8,'9) Budget Baseline'!$H$8:$H$1087,"<="&A35,'9) Budget Baseline'!$D$8:$D$1087,IF($B$6="All","*",$B$6),'9) Budget Baseline'!$E$8:$E$1087,IF($B$7="All","*",$B$7),'9) Budget Baseline'!$F$8:$F$1087,IF($B$8="All","*",$B$8)))) -> 10244.447 | C35: =IF(A35>$B$3,NA(),IF($B$5="100% fEC",SUMIFS('6) Actuals Ledger - DI Costs'!$R$8:$R$2007,'6) Actuals Ledger - DI Costs'!$C$8:$C$2007,">="&'0) ReadMe and Contents'!$B$8,'6) Actuals Ledger - DI Costs'!$C$8:$C$2007,"<="&A35,'6) Actuals Ledger - DI Costs'!$M$8:$M$2007,IF($B$6="All","*",$B$6),'6) Actuals Ledger - DI Costs'!$N$8:$N$2007,IF($B$7="All","*",$B$7),'6) Actuals Ledger - DI Costs'!$O$8:$O$2007,IF($B$8="All","*",$B$8))+SUMIFS('7) Allocations - DA Costs'!$O$8:$O$2007,'7) Allocations - DA Costs'!$C$8:$C$2007,">="&'0) ReadMe and Contents'!$B$8,'7) Allocations - DA Costs'!$C$8:$C$2007,"<="&A35,'7) Allocations - DA Costs'!$J$8:$J$2007,IF($B$6="All","*",$B$6),'7) Allocations - DA Costs'!$K$8:$K$2007,IF($B$7="All","*",$B$7),'7) Allocations - DA Costs'!$L$8:$L$2007,IF($B$8="All","*",$B$8)),IF($B$5="UKRI",SUMIFS('6) Actuals Ledger - DI Costs'!$S$8:$S$2007,'6) Actuals Ledger - DI Costs'!$C$8:$C$2007,">="&'0) ReadMe and Contents'!$B$8,'6) Actuals Ledger - DI Costs'!$C$8:$C$2007,"<="&A35,'6) Actuals Ledger - DI Costs'!$M$8:$M$2007,IF($B$6="All","*",$B$6),'6) Actuals Ledger - DI Costs'!$N$8:$N$2007,IF($B$7="All","*",$B$7),'6) Actuals Ledger - DI Costs'!$O$8:$O$2007,IF($B$8="All","*",$B$8))+SUMIFS('7) Allocations - DA Costs'!$P$8:$P$2007,'7) Allocations - DA Costs'!$C$8:$C$2007,">="&'0) ReadMe and Contents'!$B$8,'7) Allocations - DA Costs'!$C$8:$C$2007,"<="&A35,'7) Allocations - DA Costs'!$J$8:$J$2007,IF($B$6="All","*",$B$6),'7) Allocations - DA Costs'!$K$8:$K$2007,IF($B$7="All","*",$B$7),'7) Allocations - DA Costs'!$L$8:$L$2007,IF($B$8="All","*",$B$8)),SUMIFS('6) Actuals Ledger - DI Costs'!$T$8:$T$2007,'6) Actuals Ledger - DI Costs'!$C$8:$C$2007,">="&'0) ReadMe and Contents'!$B$8,'6) Actuals Ledger - DI Costs'!$C$8:$C$2007,"<="&A35,'6) Actuals Ledger - DI Costs'!$M$8:$M$2007,IF($B$6="All","*",$B$6),'6) Actuals Ledger - DI Costs'!$N$8:$N$2007,IF($B$7="All","*",$B$7),'6) Actuals Ledger - DI Costs'!$O$8:$O$2007,IF($B$8="All","*",$B$8))+SUMIFS('7) Allocations - DA Costs'!$Q$8:$Q$2007,'7) Allocations - DA Costs'!$C$8:$C$2007,">="&'0) ReadMe and Contents'!$B$8,'7) Allocations - DA Costs'!$C$8:$C$2007,"<="&A35,'7) Allocations - DA Costs'!$J$8:$J$2007,IF($B$6="All","*",$B$6),'7) Allocations - DA Costs'!$K$8:$K$2007,IF($B$7="All","*",$B$7),'7) Allocations - DA Costs'!$L$8:$L$2007,IF($B$8="All","*",$B$8))))) -> 10426.2 | D35: =$B$18*4/36 -> 17133.336
A36: 46265 | B36: =IF($B$5="100% fEC",SUMIFS('9) Budget Baseline'!$P$8:$P$1087,'9) Budget Baseline'!$H$8:$H$1087,">="&'0) ReadMe and Contents'!$B$8,'9) Budget Baseline'!$H$8:$H$1087,"<="&A36,'9) Budget Baseline'!$D$8:$D$1087,IF($B$6="All","*",$B$6),'9) Budget Baseline'!$E$8:$E$1087,IF($B$7="All","*",$B$7),'9) Budget Baseline'!$F$8:$F$1087,IF($B$8="All","*",$B$8)),IF($B$5="UKRI",SUMIFS('9) Budget Baseline'!$Q$8:$Q$1087,'9) Budget Baseline'!$H$8:$H$1087,">="&'0) ReadMe and Contents'!$B$8,'9) Budget Baseline'!$H$8:$H$1087,"<="&A36,'9) Budget Baseline'!$D$8:$D$1087,IF($B$6="All","*",$B$6),'9) Budget Baseline'!$E$8:$E$1087,IF($B$7="All","*",$B$7),'9) Budget Baseline'!$F$8:$F$1087,IF($B$8="All","*",$B$8)),SUMIFS('9) Budget Baseline'!$R$8:$R$1087,'9) Budget Baseline'!$H$8:$H$1087,">="&'0) ReadMe and Contents'!$B$8,'9) Budget Baseline'!$H$8:$H$1087,"<="&A36,'9) Budget Baseline'!$D$8:$D$1087,IF($B$6="All","*",$B$6),'9) Budget Baseline'!$E$8:$E$1087,IF($B$7="All","*",$B$7),'9) Budget Baseline'!$F$8:$F$1087,IF($B$8="All","*",$B$8)))) -> 12805.558 | C36: =IF(A36>$B$3,NA(),IF($B$5="100% fEC",SUMIFS('6) Actuals Ledger - DI Costs'!$R$8:$R$2007,'6) Actuals Ledger - DI Costs'!$C$8:$C$2007,">="&'0) ReadMe and Contents'!$B$8,'6) Actuals Ledger - DI Costs'!$C$8:$C$2007,"<="&A36,'6) Actuals Ledger - DI Costs'!$M$8:$M$2007,IF($B$6="All","*",$B$6),'6) Actuals Ledger - DI Costs'!$N$8:$N$2007,IF($B$7="All","*",$B$7),'6) Actuals Ledger - DI Costs'!$O$8:$O$2007,IF($B$8="All","*",$B$8))+SUMIFS('7) Allocations - DA Costs'!$O$8:$O$2007,'7) Allocations - DA Costs'!$C$8:$C$2007,">="&'0) ReadMe and Contents'!$B$8,'7) Allocations - DA Costs'!$C$8:$C$2007,"<="&A36,'7) Allocations - DA Costs'!$J$8:$J$2007,IF($B$6="All","*",$B$6),'7) Allocations - DA Costs'!$K$8:$K$2007,IF($B$7="All","*",$B$7),'7) Allocations - DA Costs'!$L$8:$L$2007,IF($B$8="All","*",$B$8)),IF($B$5="UKRI",SUMIFS('6) Actuals Ledger - DI Costs'!$S$8:$S$2007,'6) Actuals Ledger - DI Costs'!$C$8:$C$2007,">="&'0) ReadMe and Contents'!$B$8,'6) Actuals Ledger - DI Costs'!$C$8:$C$2007,"<="&A36,'6) Actuals Ledger - DI Costs'!$M$8:$M$2007,IF($B$6="All","*",$B$6),'6) Actuals Ledger - DI Costs'!$N$8:$N$2007,IF($B$7="All","*",$B$7),'6) Actuals Ledger - DI Costs'!$O$8:$O$2007,IF($B$8="All","*",$B$8))+SUMIFS('7) Allocations - DA Costs'!$P$8:$P$2007,'7) Allocations - DA Costs'!$C$8:$C$2007,">="&'0) ReadMe and Contents'!$B$8,'7) Allocations - DA Costs'!$C$8:$C$2007,"<="&A36,'7) Allocations - DA Costs'!$J$8:$J$2007,IF($B$6="All","*",$B$6),'7) Allocations - DA Costs'!$K$8:$K$2007,IF($B$7="All","*",$B$7),'7) Allocations - DA Costs'!$L$8:$L$2007,IF($B$8="All","*",$B$8)),SUMIFS('6) Actuals Ledger - DI Costs'!$T$8:$T$2007,'6) Actuals Ledger - DI Costs'!$C$8:$C$2007,">="&'0) ReadMe and Contents'!$B$8,'6) Actuals Ledger - DI Costs'!$C$8:$C$2007,"<="&A36,'6) Actuals Ledger - DI Costs'!$M$8:$M$2007,IF($B$6="All","*",$B$6),'6) Actuals Ledger - DI Costs'!$N$8:$N$2007,IF($B$7="All","*",$B$7),'6) Actuals Ledger - DI Costs'!$O$8:$O$2007,IF($B$8="All","*",$B$8))+SUMIFS('7) Allocations - DA Costs'!$Q$8:$Q$2007,'7) Allocations - DA Costs'!$C$8:$C$2007,">="&'0) ReadMe and Contents'!$B$8,'7) Allocations - DA Costs'!$C$8:$C$2007,"<="&A36,'7) Allocations - DA Costs'!$J$8:$J$2007,IF($B$6="All","*",$B$6),'7) Allocations - DA Costs'!$K$8:$K$2007,IF($B$7="All","*",$B$7),'7) Allocations - DA Costs'!$L$8:$L$2007,IF($B$8="All","*",$B$8))))) -> 13751.2 | D36: =$B$18*5/36 -> 21416.669
A37: 46295 | B37: =IF($B$5="100% fEC",SUMIFS('9) Budget Baseline'!$P$8:$P$1087,'9) Budget Baseline'!$H$8:$H$1087,">="&'0) ReadMe and Contents'!$B$8,'9) Budget Baseline'!$H$8:$H$1087,"<="&A37,'9) Budget Baseline'!$D$8:$D$1087,IF($B$6="All","*",$B$6),'9) Budget Baseline'!$E$8:$E$1087,IF($B$7="All","*",$B$7),'9) Budget Baseline'!$F$8:$F$1087,IF($B$8="All","*",$B$8)),IF($B$5="UKRI",SUMIFS('9) Budget Baseline'!$Q$8:$Q$1087,'9) Budget Baseline'!$H$8:$H$1087,">="&'0) ReadMe and Contents'!$B$8,'9) Budget Baseline'!$H$8:$H$1087,"<="&A37,'9) Budget Baseline'!$D$8:$D$1087,IF($B$6="All","*",$B$6),'9) Budget Baseline'!$E$8:$E$1087,IF($B$7="All","*",$B$7),'9) Budget Baseline'!$F$8:$F$1087,IF($B$8="All","*",$B$8)),SUMIFS('9) Budget Baseline'!$R$8:$R$1087,'9) Budget Baseline'!$H$8:$H$1087,">="&'0) ReadMe and Contents'!$B$8,'9) Budget Baseline'!$H$8:$H$1087,"<="&A37,'9) Budget Baseline'!$D$8:$D$1087,IF($B$6="All","*",$B$6),'9) Budget Baseline'!$E$8:$E$1087,IF($B$7="All","*",$B$7),'9) Budget Baseline'!$F$8:$F$1087,IF($B$8="All","*",$B$8)))) -> 30366.67 | C37: =IF(A37>$B$3,NA(),IF($B$5="100% fEC",SUMIFS('6) Actuals Ledger - DI Costs'!$R$8:$R$2007,'6) Actuals Ledger - DI Costs'!$C$8:$C$2007,">="&'0) ReadMe and Contents'!$B$8,'6) Actuals Ledger - DI Costs'!$C$8:$C$2007,"<="&A37,'6) Actuals Ledger - DI Costs'!$M$8:$M$2007,IF($B$6="All","*",$B$6),'6) Actuals Ledger - DI Costs'!$N$8:$N$2007,IF($B$7="All","*",$B$7),'6) Actuals Ledger - DI Costs'!$O$8:$O$2007,IF($B$8="All","*",$B$8))+SUMIFS('7) Allocations - DA Costs'!$O$8:$O$2007,'7) Allocations - DA Costs'!$C$8:$C$2007,">="&'0) ReadMe and Contents'!$B$8,'7) Allocations - DA Costs'!$C$8:$C$2007,"<="&A37,'7) Allocations - DA Costs'!$J$8:$J$2007,IF($B$6="All","*",$B$6),'7) Allocations - DA Costs'!$K$8:$K$2007,IF($B$7="All","*",$B$7),'7) Allocations - DA Costs'!$L$8:$L$2007,IF($B$8="All","*",$B$8)),IF($B$5="UKRI",SUMIFS('6) Actuals Ledger - DI Costs'!$S$8:$S$2007,'6) Actuals Ledger - DI Costs'!$C$8:$C$2007,">="&'0) ReadMe and Contents'!$B$8,'6) Actuals Ledger - DI Costs'!$C$8:$C$2007,"<="&A37,'6) Actuals Ledger - DI Costs'!$M$8:$M$2007,IF($B$6="All","*",$B$6),'6) Actuals Ledger - DI Costs'!$N$8:$N$2007,IF($B$7="All","*",$B$7),'6) Actuals Ledger - DI Costs'!$O$8:$O$2007,IF($B$8="All","*",$B$8))+SUMIFS('7) Allocations - DA Costs'!$P$8:$P$2007,'7) Allocations - DA Costs'!$C$8:$C$2007,">="&'0) ReadMe and Contents'!$B$8,'7) Allocations - DA Costs'!$C$8:$C$2007,"<="&A37,'7) Allocations - DA Costs'!$J$8:$J$2007,IF($B$6="All","*",$B$6),'7) Allocations - DA Costs'!$K$8:$K$2007,IF($B$7="All","*",$B$7),'7) Allocations - DA Costs'!$L$8:$L$2007,IF($B$8="All","*",$B$8)),SUMIFS('6) Actuals Ledger - DI Costs'!$T$8:$T$2007,'6) Actuals Ledger - DI Costs'!$C$8:$C$2007,">="&'0) ReadMe and Contents'!$B$8,'6) Actuals Ledger - DI Costs'!$C$8:$C$2007,"<="&A37,'6) Actuals Ledger - DI Costs'!$M$8:$M$2007,IF($B$6="All","*",$B$6),'6) Actuals Ledger - DI Costs'!$N$8:$N$2007,IF($B$7="All","*",$B$7),'6) Actuals Ledger - DI Costs'!$O$8:$O$2007,IF($B$8="All","*",$B$8))+SUMIFS('7) Allocations - DA Costs'!$Q$8:$Q$2007,'7) Allocations - DA Costs'!$C$8:$C$2007,">="&'0) ReadMe and Contents'!$B$8,'7) Allocations - DA Costs'!$C$8:$C$2007,"<="&A37,'7) Allocations - DA Costs'!$J$8:$J$2007,IF($B$6="All","*",$B$6),'7) Allocations - DA Costs'!$K$8:$K$2007,IF($B$7="All","*",$B$7),'7) Allocations - DA Costs'!$L$8:$L$2007,IF($B$8="All","*",$B$8))))) -> #N/A | D37: =$B$18*6/36 -> 25700.003
A38: 46326 | B38: =IF($B$5="100% fEC",SUMIFS('9) Budget Baseline'!$P$8:$P$1087,'9) Budget Baseline'!$H$8:$H$1087,">="&'0) ReadMe and Contents'!$B$8,'9) Budget Baseline'!$H$8:$H$1087,"<="&A38,'9) Budget Baseline'!$D$8:$D$1087,IF($B$6="All","*",$B$6),'9) Budget Baseline'!$E$8:$E$1087,IF($B$7="All","*",$B$7),'9) Budget Baseline'!$F$8:$F$1087,IF($B$8="All","*",$B$8)),IF($B$5="UKRI",SUMIFS('9) Budget Baseline'!$Q$8:$Q$1087,'9) Budget Baseline'!$H$8:$H$1087,">="&'0) ReadMe and Contents'!$B$8,'9) Budget Baseline'!$H$8:$H$1087,"<="&A38,'9) Budget Baseline'!$D$8:$D$1087,IF($B$6="All","*",$B$6),'9) Budget Baseline'!$E$8:$E$1087,IF($B$7="All","*",$B$7),'9) Budget Baseline'!$F$8:$F$1087,IF($B$8="All","*",$B$8)),SUMIFS('9) Budget Baseline'!$R$8:$R$1087,'9) Budget Baseline'!$H$8:$H$1087,">="&'0) ReadMe and Contents'!$B$8,'9) Budget Baseline'!$H$8:$H$1087,"<="&A38,'9) Budget Baseline'!$D$8:$D$1087,IF($B$6="All","*",$B$6),'9) Budget Baseline'!$E$8:$E$1087,IF($B$7="All","*",$B$7),'9) Budget Baseline'!$F$8:$F$1087,IF($B$8="All","*",$B$8)))) -> 32927.782 | C38: =IF(A38>$B$3,NA(),IF($B$5="100% fEC",SUMIFS('6) Actuals Ledger - DI Costs'!$R$8:$R$2007,'6) Actuals Ledger - DI Costs'!$C$8:$C$2007,">="&'0) ReadMe and Contents'!$B$8,'6) Actuals Ledger - DI Costs'!$C$8:$C$2007,"<="&A38,'6) Actuals Ledger - DI Costs'!$M$8:$M$2007,IF($B$6="All","*",$B$6),'6) Actuals Ledger - DI Costs'!$N$8:$N$2007,IF($B$7="All","*",$B$7),'6) Actuals Ledger - DI Costs'!$O$8:$O$2007,IF($B$8="All","*",$B$8))+SUMIFS('7) Allocations - DA Costs'!$O$8:$O$2007,'7) Allocations - DA Costs'!$C$8:$C$2007,">="&'0) ReadMe and Contents'!$B$8,'7) Allocations - DA Costs'!$C$8:$C$2007,"<="&A38,'7) Allocations - DA Costs'!$J$8:$J$2007,IF($B$6="All","*",$B$6),'7) Allocations - DA Costs'!$K$8:$K$2007,IF($B$7="All","*",$B$7),'7) Allocations - DA Costs'!$L$8:$L$2007,IF($B$8="All","*",$B$8)),IF($B$5="UKRI",SUMIFS('6) Actuals Ledger - DI Costs'!$S$8:$S$2007,'6) Actuals Ledger - DI Costs'!$C$8:$C$2007,">="&'0) ReadMe and Contents'!$B$8,'6) Actuals Ledger - DI Costs'!$C$8:$C$2007,"<="&A38,'6) Actuals Ledger - DI Costs'!$M$8:$M$2007,IF($B$6="All","*",$B$6),'6) Actuals Ledger - DI Costs'!$N$8:$N$2007,IF($B$7="All","*",$B$7),'6) Actuals Ledger - DI Costs'!$O$8:$O$2007,IF($B$8="All","*",$B$8))+SUMIFS('7) Allocations - DA Costs'!$P$8:$P$2007,'7) Allocations - DA Costs'!$C$8:$C$2007,">="&'0) ReadMe and Contents'!$B$8,'7) Allocations - DA Costs'!$C$8:$C$2007,"<="&A38,'7) Allocations - DA Costs'!$J$8:$J$2007,IF($B$6="All","*",$B$6),'7) Allocations - DA Costs'!$K$8:$K$2007,IF($B$7="All","*",$B$7),'7) Allocations - DA Costs'!$L$8:$L$2007,IF($B$8="All","*",$B$8)),SUMIFS('6) Actuals Ledger - DI Costs'!$T$8:$T$2007,'6) Actuals Ledger - DI Costs'!$C$8:$C$2007,">="&'0) ReadMe and Contents'!$B$8,'6) Actuals Ledger - DI Costs'!$C$8:$C$2007,"<="&A38,'6) Actuals Ledger - DI Costs'!$M$8:$M$2007,IF($B$6="All","*",$B$6),'6) Actuals Ledger - DI Costs'!$N$8:$N$2007,IF($B$7="All","*",$B$7),'6) Actuals Ledger - DI Costs'!$O$8:$O$2007,IF($B$8="All","*",$B$8))+SUMIFS('7) Allocations - DA Costs'!$Q$8:$Q$2007,'7) Allocations - DA Costs'!$C$8:$C$2007,">="&'0) ReadMe and Contents'!$B$8,'7) Allocations - DA Costs'!$C$8:$C$2007,"<="&A38,'7) Allocations - DA Costs'!$J$8:$J$2007,IF($B$6="All","*",$B$6),'7) Allocations - DA Costs'!$K$8:$K$2007,IF($B$7="All","*",$B$7),'7) Allocations - DA Costs'!$L$8:$L$2007,IF($B$8="All","*",$B$8))))) -> #N/A | D38: =$B$18*7/36 -> 29983.337
A39: 46356 | B39: =IF($B$5="100% fEC",SUMIFS('9) Budget Baseline'!$P$8:$P$1087,'9) Budget Baseline'!$H$8:$H$1087,">="&'0) ReadMe and Contents'!$B$8,'9) Budget Baseline'!$H$8:$H$1087,"<="&A39,'9) Budget Baseline'!$D$8:$D$1087,IF($B$6="All","*",$B$6),'9) Budget Baseline'!$E$8:$E$1087,IF($B$7="All","*",$B$7),'9) Budget Baseline'!$F$8:$F$1087,IF($B$8="All","*",$B$8)),IF($B$5="UKRI",SUMIFS('9) Budget Baseline'!$Q$8:$Q$1087,'9) Budget Baseline'!$H$8:$H$1087,">="&'0) ReadMe and Contents'!$B$8,'9) Budget Baseline'!$H$8:$H$1087,"<="&A39,'9) Budget Baseline'!$D$8:$D$1087,IF($B$6="All","*",$B$6),'9) Budget Baseline'!$E$8:$E$1087,IF($B$7="All","*",$B$7),'9) Budget Baseline'!$F$8:$F$1087,IF($B$8="All","*",$B$8)),SUMIFS('9) Budget Baseline'!$R$8:$R$1087,'9) Budget Baseline'!$H$8:$H$1087,">="&'0) ReadMe and Contents'!$B$8,'9) Budget Baseline'!$H$8:$H$1087,"<="&A39,'9) Budget Baseline'!$D$8:$D$1087,IF($B$6="All","*",$B$6),'9) Budget Baseline'!$E$8:$E$1087,IF($B$7="All","*",$B$7),'9) Budget Baseline'!$F$8:$F$1087,IF($B$8="All","*",$B$8)))) -> 35488.893 | C39: =IF(A39>$B$3,NA(),IF($B$5="100% fEC",SUMIFS('6) Actuals Ledger - DI Costs'!$R$8:$R$2007,'6) Actuals Ledger - DI Costs'!$C$8:$C$2007,">="&'0) ReadMe and Contents'!$B$8,'6) Actuals Ledger - DI Costs'!$C$8:$C$2007,"<="&A39,'6) Actuals Ledger - DI Costs'!$M$8:$M$2007,IF($B$6="All","*",$B$6),'6) Actuals Ledger - DI Costs'!$N$8:$N$2007,IF($B$7="All","*",$B$7),'6) Actuals Ledger - DI Costs'!$O$8:$O$2007,IF($B$8="All","*",$B$8))+SUMIFS('7) Allocations - DA Costs'!$O$8:$O$2007,'7) Allocations - DA Costs'!$C$8:$C$2007,">="&'0) ReadMe and Contents'!$B$8,'7) Allocations - DA Costs'!$C$8:$C$2007,"<="&A39,'7) Allocations - DA Costs'!$J$8:$J$2007,IF($B$6="All","*",$B$6),'7) Allocations - DA Costs'!$K$8:$K$2007,IF($B$7="All","*",$B$7),'7) Allocations - DA Costs'!$L$8:$L$2007,IF($B$8="All","*",$B$8)),IF($B$5="UKRI",SUMIFS('6) Actuals Ledger - DI Costs'!$S$8:$S$2007,'6) Actuals Ledger - DI Costs'!$C$8:$C$2007,">="&'0) ReadMe and Contents'!$B$8,'6) Actuals Ledger - DI Costs'!$C$8:$C$2007,"<="&A39,'6) Actuals Ledger - DI Costs'!$M$8:$M$2007,IF($B$6="All","*",$B$6),'6) Actuals Ledger - DI Costs'!$N$8:$N$2007,IF($B$7="All","*",$B$7),'6) Actuals Ledger - DI Costs'!$O$8:$O$2007,IF($B$8="All","*",$B$8))+SUMIFS('7) Allocations - DA Costs'!$P$8:$P$2007,'7) Allocations - DA Costs'!$C$8:$C$2007,">="&'0) ReadMe and Contents'!$B$8,'7) Allocations - DA Costs'!$C$8:$C$2007,"<="&A39,'7) Allocations - DA Costs'!$J$8:$J$2007,IF($B$6="All","*",$B$6),'7) Allocations - DA Costs'!$K$8:$K$2007,IF($B$7="All","*",$B$7),'7) Allocations - DA Costs'!$L$8:$L$2007,IF($B$8="All","*",$B$8)),SUMIFS('6) Actuals Ledger - DI Costs'!$T$8:$T$2007,'6) Actuals Ledger - DI Costs'!$C$8:$C$2007,">="&'0) ReadMe and Contents'!$B$8,'6) Actuals Ledger - DI Costs'!$C$8:$C$2007,"<="&A39,'6) Actuals Ledger - DI Costs'!$M$8:$M$2007,IF($B$6="All","*",$B$6),'6) Actuals Ledger - DI Costs'!$N$8:$N$2007,IF($B$7="All","*",$B$7),'6) Actuals Ledger - DI Costs'!$O$8:$O$2007,IF($B$8="All","*",$B$8))+SUMIFS('7) Allocations - DA Costs'!$Q$8:$Q$2007,'7) Allocations - DA Costs'!$C$8:$C$2007,">="&'0) ReadMe and Contents'!$B$8,'7) Allocations - DA Costs'!$C$8:$C$2007,"<="&A39,'7) Allocations - DA Costs'!$J$8:$J$2007,IF($B$6="All","*",$B$6),'7) Allocations - DA Costs'!$K$8:$K$2007,IF($B$7="All","*",$B$7),'7) Allocations - DA Costs'!$L$8:$L$2007,IF($B$8="All","*",$B$8))))) -> #N/A | D39: =$B$18*8/36 -> 34266.671
A40: 46387 | B40: =IF($B$5="100% fEC",SUMIFS('9) Budget Baseline'!$P$8:$P$1087,'9) Budget Baseline'!$H$8:$H$1087,">="&'0) ReadMe and Contents'!$B$8,'9) Budget Baseline'!$H$8:$H$1087,"<="&A40,'9) Budget Baseline'!$D$8:$D$1087,IF($B$6="All","*",$B$6),'9) Budget Baseline'!$E$8:$E$1087,IF($B$7="All","*",$B$7),'9) Budget Baseline'!$F$8:$F$1087,IF($B$8="All","*",$B$8)),IF($B$5="UKRI",SUMIFS('9) Budget Baseline'!$Q$8:$Q$1087,'9) Budget Baseline'!$H$8:$H$1087,">="&'0) ReadMe and Contents'!$B$8,'9) Budget Baseline'!$H$8:$H$1087,"<="&A40,'9) Budget Baseline'!$D$8:$D$1087,IF($B$6="All","*",$B$6),'9) Budget Baseline'!$E$8:$E$1087,IF($B$7="All","*",$B$7),'9) Budget Baseline'!$F$8:$F$1087,IF($B$8="All","*",$B$8)),SUMIFS('9) Budget Baseline'!$R$8:$R$1087,'9) Budget Baseline'!$H$8:$H$1087,">="&'0) ReadMe and Contents'!$B$8,'9) Budget Baseline'!$H$8:$H$1087,"<="&A40,'9) Budget Baseline'!$D$8:$D$1087,IF($B$6="All","*",$B$6),'9) Budget Baseline'!$E$8:$E$1087,IF($B$7="All","*",$B$7),'9) Budget Baseline'!$F$8:$F$1087,IF($B$8="All","*",$B$8)))) -> 38050.005 | C40: =IF(A40>$B$3,NA(),IF($B$5="100% fEC",SUMIFS('6) Actuals Ledger - DI Costs'!$R$8:$R$2007,'6) Actuals Ledger - DI Costs'!$C$8:$C$2007,">="&'0) ReadMe and Contents'!$B$8,'6) Actuals Ledger - DI Costs'!$C$8:$C$2007,"<="&A40,'6) Actuals Ledger - DI Costs'!$M$8:$M$2007,IF($B$6="All","*",$B$6),'6) Actuals Ledger - DI Costs'!$N$8:$N$2007,IF($B$7="All","*",$B$7),'6) Actuals Ledger - DI Costs'!$O$8:$O$2007,IF($B$8="All","*",$B$8))+SUMIFS('7) Allocations - DA Costs'!$O$8:$O$2007,'7) Allocations - DA Costs'!$C$8:$C$2007,">="&'0) ReadMe and Contents'!$B$8,'7) Allocations - DA Costs'!$C$8:$C$2007,"<="&A40,'7) Allocations - DA Costs'!$J$8:$J$2007,IF($B$6="All","*",$B$6),'7) Allocations - DA Costs'!$K$8:$K$2007,IF($B$7="All","*",$B$7),'7) Allocations - DA Costs'!$L$8:$L$2007,IF($B$8="All","*",$B$8)),IF($B$5="UKRI",SUMIFS('6) Actuals Ledger - DI Costs'!$S$8:$S$2007,'6) Actuals Ledger - DI Costs'!$C$8:$C$2007,">="&'0) ReadMe and Contents'!$B$8,'6) Actuals Ledger - DI Costs'!$C$8:$C$2007,"<="&A40,'6) Actuals Ledger - DI Costs'!$M$8:$M$2007,IF($B$6="All","*",$B$6),'6) Actuals Ledger - DI Costs'!$N$8:$N$2007,IF($B$7="All","*",$B$7),'6) Actuals Ledger - DI Costs'!$O$8:$O$2007,IF($B$8="All","*",$B$8))+SUMIFS('7) Allocations - DA Costs'!$P$8:$P$2007,'7) Allocations - DA Costs'!$C$8:$C$2007,">="&'0) ReadMe and Contents'!$B$8,'7) Allocations - DA Costs'!$C$8:$C$2007,"<="&A40,'7) Allocations - DA Costs'!$J$8:$J$2007,IF($B$6="All","*",$B$6),'7) Allocations - DA Costs'!$K$8:$K$2007,IF($B$7="All","*",$B$7),'7) Allocations - DA Costs'!$L$8:$L$2007,IF($B$8="All","*",$B$8)),SUMIFS('6) Actuals Ledger - DI Costs'!$T$8:$T$2007,'6) Actuals Ledger - DI Costs'!$C$8:$C$2007,">="&'0) ReadMe and Contents'!$B$8,'6) Actuals Ledger - DI Costs'!$C$8:$C$2007,"<="&A40,'6) Actuals Ledger - DI Costs'!$M$8:$M$2007,IF($B$6="All","*",$B$6),'6) Actuals Ledger - DI Costs'!$N$8:$N$2007,IF($B$7="All","*",$B$7),'6) Actuals Ledger - DI Costs'!$O$8:$O$2007,IF($B$8="All","*",$B$8))+SUMIFS('7) Allocations - DA Costs'!$Q$8:$Q$2007,'7) Allocations - DA Costs'!$C$8:$C$2007,">="&'0) ReadMe and Contents'!$B$8,'7) Allocations - DA Costs'!$C$8:$C$2007,"<="&A40,'7) Allocations - DA Costs'!$J$8:$J$2007,IF($B$6="All","*",$B$6),'7) Allocations - DA Costs'!$K$8:$K$2007,IF($B$7="All","*",$B$7),'7) Allocations - DA Costs'!$L$8:$L$2007,IF($B$8="All","*",$B$8))))) -> #N/A | D40: =$B$18*9/36 -> 38550.005
