Workbook
Name band_tbl: Rates!#REF!
Name buffer_major: 'Trip plan'!$B$6
Name buffer_other: 'Trip plan'!$B$7
Name fare_escal: 'Trip plan'!$B$8
Name fx_budget: FX!$G$7:$G$118
Name fx_ccy: FX!$A$7:$A$118
Name loc_list: Rates!$A$5:$A$289
Name loc_list_UK: Additional_Val!$B$4:$B$291
Name month_list: Table2[Month List]
Name rate_date: 'Trip plan'!$B$5
Name rates_tbl: Rates!$A$5:$Q$289
Name season_tbl: Rates!#REF!

Sheet Trip plan
A1: Overseas Trip cost estimator
A2: Multi-strand costing tool, particularly useful for UK-based research institutions. Instant day rate, accommodation and other estimates provided directly from the latest HMRC published overseas scale rates. As flight data and APIs are heavily guarded from public access, there are 2 approaches for costing air fares: 1) Input your own quote from your comparison site of choice (SkySkanner, Expedia etc.); or 2) Use the integrated Google Flights search shortcut to grab a quote that way.
A4: Assumptions | L4: Schedule totals
A5: Rate date | B5: 46260 | C5: The day the exchange rates are taken from. Change it and the whole schedule re-prices. Must be a day the market was open. | L5: Accommodation | M5: Subsistence | N5: Airfare | O5: Other | P5: TOTAL
A6: FX buffer - EUR and USD | B6: 0 | C6: Zero by default: UK research offices use a corporate rate for these. Substitute your own if you have one. | L6: =SUMIFS(O$16:O$40,$U$16:$U$40,">=0") -> 3040.6118 | M6: =SUMIFS(P$16:P$40,$U$16:$U$40,">=0") -> 1185.2129 | N6: =SUMIFS(S$16:S$40,$U$16:$U$40,">=0") -> 3111 | O6: =SUMIFS(T$16:T$40,$U$16:$U$40,">=0") -> 360 | P6: =SUM(L6:O6) -> 7696.8247
A7: FX buffer - all others | B7: 0.1 | C7: Ten per cent (standard UCL research policy for costing). Consider higher for a volatile currency.
A8: Fare escalation | B8: 1 | C8: Multiplier on the band placeholder fares. 1.00 leaves them as published.
A9: Workbook prepared | B9: 1 September 2026 | C9: Rate data captured 26 August 2026. See the Notes sheet for sources.
A11: =IF(N($P$6)<=0,"Pick a destination and a month, then type the number of travellers and nights. Everything else is looked up or calculated.","Of the £"&TEXT($P$6,"#,##0")&" total, "&TEXT(($L$6+$M$6)/$P$6,"0%")&" is backed by a published HMRC rate (accommodation and subsistence) and "&TEXT(($N$6+$O$6)/$P$6,"0%")&" is estimate or user input (airfare and other).") -> Of the £7,697 total, 55% is backed by a published HMRC rate (accommodation and subsistence) and 45% is estimate or user input (airfare and other).
A12: =IF(SUMPRODUCT(($C$16:$C$40<>"")*1)=0,"",IF(SUMPRODUCT(($C$16:$C$40<>"")*($U$16:$U$40=""))=0,"All "&SUMPRODUCT(($C$16:$C$40<>"")*1)&" trip(s) entered are fully costed.",SUMPRODUCT(($C$16:$C$40<>"")*($U$16:$U$40=""))&" of "&SUMPRODUCT(($C$16:$C$40<>"")*1)&" trip(s) entered could not be costed. The total above excludes them. The Check column says what each one needs.")) -> All 3 trip(s) entered are fully costed.
A13: Type in the shaded cells (blue figures). Green cells are looked up from Rates and FX. Black cells are calculated. A blank money cell is never a zero - it means the row is not costable yet.
O14: Backed by a published rate | T14: Estimate
A15: Trip Name | B15: Departure Location (or Closest) [Defaults to London, UK] | C15: Destination Location (or Closest Available) | D15: Date of Departure | E15: Month | F15: Travellers | G15: Nights | H15: Final day, no overnight | I15: Approx Date of Return | J15: Quoted fare £ per traveller | K15: Other £ per traveller | L15: Band | M15: Meals ccy | N15: Room ccy | O15: Accommodation £ | P15: Subsistence £ | Q15: Find Cheapest Airfare | R15: Airfaire Quick Search | S15: Airfare £ | T15: Other £ | U15: Trip total £ | V15: Check Column
A16: Partner workshop | C16: Jakarta, Indonesia | D16: 46305 | E16: =IF(D16<>"",_xlfn.XLOOKUP(MONTH(D16),Table2[Month Number],month_list,"",0,1),"") -> Oct | F16: 2 | G16: 4 | H16: None | I16: =IF(D16<>0,SUM(D16,G16),"") -> 46309 | J16: 664 | K16: 120 | L16: =IF($C16="","",IFERROR(INDEX(rates_tbl,MATCH($C16,loc_list,0),3),"")) -> 5 | M16: =IF($C16="","",IFERROR(INDEX(rates_tbl,MATCH($C16,loc_list,0),4),"")) -> IDR | N16: =IF($C16="","",IFERROR(INDEX(rates_tbl,MATCH($C16,loc_list,0),5),"")) -> USD | O16: =IF(NOT(AND($C16<>"",ISNUMBER(MATCH($C16,loc_list,0)),ISNUMBER($F16),$F16>0,OR(N($G16)>0,$H16<>""))),"",IF(N($G16)<=0,0,IF(NOT(ISNUMBER(IFERROR(INDEX(fx_budget,MATCH($N16,fx_ccy,0)),""))),"",N($G16)*INDEX(rates_tbl,MATCH($C16,loc_list,0),10)*$F16/IFERROR(INDEX(fx_budget,MATCH($N16,fx_ccy,0)),"")))) -> 909.75789 | P16: =IF(NOT(AND($C16<>"",ISNUMBER(MATCH($C16,loc_list,0)),ISNUMBER($F16),$F16>0,OR(N($G16)>0,$H16<>""))),"",IF(NOT(ISNUMBER(IFERROR(INDEX(fx_budget,MATCH($M16,fx_ccy,0)),""))),"",(N($G16)*INDEX(rates_tbl,MATCH($C16,loc_list,0),9)+IF($H16="Over 10 hours",INDEX(rates_tbl,MATCH($C16,loc_list,0),8),IF($H16="Over 5 hours",INDEX(rates_tbl,MATCH($C16,loc_list,0),7),0)))*$F16/IFERROR(INDEX(fx_budget,MATCH($M16,fx_ccy,0)),""))) -> 359.70829 | Q16: =IF(LEN(R16)-LEN(SUBSTITUTE(R16,"+",""))>=4, HYPERLINK(R16, _xlfn.TEXTJOIN(" ",TRUE,"Click for Google Flights Prices for",IF(B16="","London",IFERROR(_xlfn.TEXTBEFORE(B16,", "),B16)),"to",IFERROR(_xlfn.TEXTBEFORE(C16,", "),C16))), "") -> Click for Google Flights Prices for London to Jakarta | R16: =HYPERLINK((IF(OR(C16="",D16="",I16=""),"","https://www.google.com/search?q=flights+from+"&SUBSTITUTE(IF(B16="","London, UK",B16)," ","+")&"+to+"&SUBSTITUTE(C16," ","+")&"+"&TEXT(D16,"d+mmmm+yyyy")&"+to+"&TEXT(I16,"d+mmmm+yyyy")))) -> https://www.google.com/search?q=flights+from+London,+UK+to+Jakarta,+Indonesia+10+October+2026+to+14+October+2026 | S16: =IF(J16<>0,PRODUCT(J16,F16),"") -> 1328 | T16: =IF(NOT(AND($C16<>"",ISNUMBER(MATCH($C16,loc_list,0)),ISNUMBER($F16),$F16>0,OR(N($G16)>0,$H16<>""))),"",N($K16)*$F16) -> 240 | U16: =IF(NOT(AND($C16<>"",ISNUMBER(MATCH($C16,loc_list,0)),ISNUMBER($F16),$F16>0,OR(N($G16)>0,$H16<>""))),"",IF(COUNT($O16:$T16)<4,"",SUM($O16:$T16))) -> 2837.4662 | V16: =IF($C16="","",IF(NOT(ISNUMBER(MATCH($C16,loc_list,0))),"Destination not recognised. Choose one from the dropdown.",IF(NOT(ISNUMBER($F16)),"Enter the number of travellers.",IF($F16<=0,"Travellers must be 1 or more.",IF(AND(N($G16)<=0,$H16=""),"Enter the number of nights. For a day of travel with no overnight, set the final-day column — choose None if no subsistence is claimed.",IF(NOT(ISNUMBER(IFERROR(INDEX(fx_budget,MATCH($M16,fx_ccy,0)),""))),"No exchange rate for "&$M16&IF($M16=$N16,""," (the meals currency)")&". Add one on the FX sheet.",IF(AND(N($N16)>0,NOT(ISNUMBER(IFERROR(INDEX(fx_budget,MATCH($N16,fx_ccy,0)),"")))),"No exchange rate for "&$N16&" (the room-rate currency). Add one on the FX sheet.",IF(NOT(ISNUMBER($G16)),"Enter a quoted fare or search for one using the Google Flights link!",IF($M16<>$N16,"Dual currency: meals in "&$M16&", room rate in "&$N16&". Converted separately.",""))))))))) -> Dual currency: meals in IDR, room rate in USD. Converted separately.
A17: SHOC 2.0 Travel | B17: London, UK | C17: Bogota, Colombia | D17: 46309 | E17: =IF(D17<>"",_xlfn.XLOOKUP(MONTH(D17),Table2[Month Number],month_list,"",0,1),"") -> Oct | F17: 2 | G17: 6 | I17: =IF(D17<>0,SUM(D17,G17),"") -> 46315 | J17: 674 | L17: =IF($C17="","",IFERROR(INDEX(rates_tbl,MATCH($C17,loc_list,0),3),"")) -> 4 | M17: =IF($C17="","",IFERROR(INDEX(rates_tbl,MATCH($C17,loc_list,0),4),"")) -> COP | N17: =IF($C17="","",IFERROR(INDEX(rates_tbl,MATCH($C17,loc_list,0),5),"")) -> COP | O17: =IF(NOT(AND($C17<>"",ISNUMBER(MATCH($C17,loc_list,0)),ISNUMBER($F17),$F17>0,OR(N($G17)>0,$H17<>""))),"",IF(N($G17)<=0,0,IF(NOT(ISNUMBER(IFERROR(INDEX(fx_budget,MATCH($N17,fx_ccy,0)),""))),"",N($G17)*INDEX(rates_tbl,MATCH($C17,loc_list,0),10)*$F17/IFERROR(INDEX(fx_budget,MATCH($N17,fx_ccy,0)),"")))) -> 1280.6827 | P17: =IF(NOT(AND($C17<>"",ISNUMBER(MATCH($C17,loc_list,0)),ISNUMBER($F17),$F17>0,OR(N($G17)>0,$H17<>""))),"",IF(NOT(ISNUMBER(IFERROR(INDEX(fx_budget,MATCH($M17,fx_ccy,0)),""))),"",(N($G17)*INDEX(rates_tbl,MATCH($C17,loc_list,0),9)+IF($H17="Over 10 hours",INDEX(rates_tbl,MATCH($C17,loc_list,0),8),IF($H17="Over 5 hours",INDEX(rates_tbl,MATCH($C17,loc_list,0),7),0)))*$F17/IFERROR(INDEX(fx_budget,MATCH($M17,fx_ccy,0)),""))) -> 435.09362 | Q17: =IF(LEN(R17)-LEN(SUBSTITUTE(R17,"+",""))>=4, HYPERLINK(R17, _xlfn.TEXTJOIN(" ",TRUE,"Click for Google Flights Prices for",IF(B17="","London",IFERROR(_xlfn.TEXTBEFORE(B17,", "),B17)),"to",IFERROR(_xlfn.TEXTBEFORE(C17,", "),C17))), "") -> Click for Google Flights Prices for London to Bogota | R17: =HYPERLINK((IF(OR(C17="",D17="",I17=""),"","https://www.google.com/search?q=flights+from+"&SUBSTITUTE(IF(B17="","London, UK",B17)," ","+")&"+to+"&SUBSTITUTE(C17," ","+")&"+"&TEXT(D17,"d+mmmm+yyyy")&"+to+"&TEXT(I17,"d+mmmm+yyyy")))) -> https://www.google.com/search?q=flights+from+London,+UK+to+Bogota,+Colombia+14+October+2026+to+20+October+2026 | S17: =IF(J17<>0,PRODUCT(J17,F17),"") -> 1348 | T17: =IF(NOT(AND($C17<>"",ISNUMBER(MATCH($C17,loc_list,0)),ISNUMBER($F17),$F17>0,OR(N($G17)>0,$H17<>""))),"",N($K17)*$F17) -> 0 | U17: =IF(NOT(AND($C17<>"",ISNUMBER(MATCH($C17,loc_list,0)),ISNUMBER($F17),$F17>0,OR(N($G17)>0,$H17<>""))),"",IF(COUNT($O17:$T17)<4,"",SUM($O17:$T17))) -> 3063.7763 | V17: =IF($C17="","",IF(NOT(ISNUMBER(MATCH($C17,loc_list,0))),"Destination not recognised. Choose one from the dropdown.",IF(NOT(ISNUMBER($F17)),"Enter the number of travellers.",IF($F17<=0,"Travellers must be 1 or more.",IF(AND(N($G17)<=0,$H17=""),"Enter the number of nights. For a day of travel with no overnight, set the final-day column — choose None if no subsistence is claimed.",IF(NOT(ISNUMBER(IFERROR(INDEX(fx_budget,MATCH($M17,fx_ccy,0)),""))),"No exchange rate for "&$M17&IF($M17=$N17,""," (the meals currency)")&". Add one on the FX sheet.",IF(AND(N($N17)>0,NOT(ISNUMBER(IFERROR(INDEX(fx_budget,MATCH($N17,fx_ccy,0)),"")))),"No exchange rate for "&$N17&" (the room-rate currency). Add one on the FX sheet.",IF(NOT(ISNUMBER($G17)),"Enter a quoted fare or search for one using the Google Flights link!",IF($M17<>$N17,"Dual currency: meals in "&$M17&", room rate in "&$N17&". Converted separately.","")))))))))
A18: Donor conference | C18: Brussels, Belgium | D18: 45843 | E18: =IF(D18<>"",_xlfn.XLOOKUP(MONTH(D18),Table2[Month Number],month_list,"",0,1),"") -> Jul | F18: 3 | G18: 2 | H18: None | I18: =IF(D18<>0,SUM(D18,G18),"") -> 45845 | J18: 145 | K18: 40 | L18: =IF($C18="","",IFERROR(INDEX(rates_tbl,MATCH($C18,loc_list,0),3),"")) -> 1 | M18: =IF($C18="","",IFERROR(INDEX(rates_tbl,MATCH($C18,loc_list,0),4),"")) -> EUR | N18: =IF($C18="","",IFERROR(INDEX(rates_tbl,MATCH($C18,loc_list,0),5),"")) -> EUR | O18: =IF(NOT(AND($C18<>"",ISNUMBER(MATCH($C18,loc_list,0)),ISNUMBER($F18),$F18>0,OR(N($G18)>0,$H18<>""))),"",IF(N($G18)<=0,0,IF(NOT(ISNUMBER(IFERROR(INDEX(fx_budget,MATCH($N18,fx_ccy,0)),""))),"",N($G18)*INDEX(rates_tbl,MATCH($C18,loc_list,0),10)*$F18/IFERROR(INDEX(fx_budget,MATCH($N18,fx_ccy,0)),"")))) -> 850.17123 | P18: =IF(NOT(AND($C18<>"",ISNUMBER(MATCH($C18,loc_list,0)),ISNUMBER($F18),$F18>0,OR(N($G18)>0,$H18<>""))),"",IF(NOT(ISNUMBER(IFERROR(INDEX(fx_budget,MATCH($M18,fx_ccy,0)),""))),"",(N($G18)*INDEX(rates_tbl,MATCH($C18,loc_list,0),9)+IF($H18="Over 10 hours",INDEX(rates_tbl,MATCH($C18,loc_list,0),8),IF($H18="Over 5 hours",INDEX(rates_tbl,MATCH($C18,loc_list,0),7),0)))*$F18/IFERROR(INDEX(fx_budget,MATCH($M18,fx_ccy,0)),""))) -> 390.41096 | Q18: =IF(LEN(R18)-LEN(SUBSTITUTE(R18,"+",""))>=4, HYPERLINK(R18, _xlfn.TEXTJOIN(" ",TRUE,"Click for Google Flights Prices for",IF(B18="","London",IFERROR(_xlfn.TEXTBEFORE(B18,", "),B18)),"to",IFERROR(_xlfn.TEXTBEFORE(C18,", "),C18))), "") -> Click for Google Flights Prices for London to Brussels | R18: =HYPERLINK((IF(OR(C18="",D18="",I18=""),"","https://www.google.com/search?q=flights+from+"&SUBSTITUTE(IF(B18="","London, UK",B18)," ","+")&"+to+"&SUBSTITUTE(C18," ","+")&"+"&TEXT(D18,"d+mmmm+yyyy")&"+to+"&TEXT(I18,"d+mmmm+yyyy")))) -> https://www.google.com/search?q=flights+from+London,+UK+to+Brussels,+Belgium+5+July+2025+to+7+July+2025 | S18: =IF(J18<>0,PRODUCT(J18,F18),"") -> 435 | T18: =IF(NOT(AND($C18<>"",ISNUMBER(MATCH($C18,loc_list,0)),ISNUMBER($F18),$F18>0,OR(N($G18)>0,$H18<>""))),"",N($K18)*$F18) -> 120 | U18: =IF(NOT(AND($C18<>"",ISNUMBER(MATCH($C18,loc_list,0)),ISNUMBER($F18),$F18>0,OR(N($G18)>0,$H18<>""))),"",IF(COUNT($O18:$T18)<4,"",SUM($O18:$T18))) -> 1795.5822 | V18: =IF($C18="","",IF(NOT(ISNUMBER(MATCH($C18,loc_list,0))),"Destination not recognised. Choose one from the dropdown.",IF(NOT(ISNUMBER($F18)),"Enter the number of travellers.",IF($F18<=0,"Travellers must be 1 or more.",IF(AND(N($G18)<=0,$H18=""),"Enter the number of nights. For a day of travel with no overnight, set the final-day column — choose None if no subsistence is claimed.",IF(NOT(ISNUMBER(IFERROR(INDEX(fx_budget,MATCH($M18,fx_ccy,0)),""))),"No exchange rate for "&$M18&IF($M18=$N18,""," (the meals currency)")&". Add one on the FX sheet.",IF(AND(N($N18)>0,NOT(ISNUMBER(IFERROR(INDEX(fx_budget,MATCH($N18,fx_ccy,0)),"")))),"No exchange rate for "&$N18&" (the room-rate currency). Add one on the FX sheet.",IF(NOT(ISNUMBER($G18)),"Enter a quoted fare or search for one using the Google Flights link!",IF($M18<>$N18,"Dual currency: meals in "&$M18&", room rate in "&$N18&". Converted separately.","")))))))))
E19: =IF(D19<>"",_xlfn.XLOOKUP(MONTH(D19),Table2[Month Number],month_list,"",0,1),"") | I19: =IF(D19<>0,SUM(D19,G19),"") | L19: =IF($C19="","",IFERROR(INDEX(rates_tbl,MATCH($C19,loc_list,0),3),"")) | M19: =IF($C19="","",IFERROR(INDEX(rates_tbl,MATCH($C19,loc_list,0),4),"")) | N19: =IF($C19="","",IFERROR(INDEX(rates_tbl,MATCH($C19,loc_list,0),5),"")) | O19: =IF(NOT(AND($C19<>"",ISNUMBER(MATCH($C19,loc_list,0)),ISNUMBER($F19),$F19>0,OR(N($G19)>0,$H19<>""))),"",IF(N($G19)<=0,0,IF(NOT(ISNUMBER(IFERROR(INDEX(fx_budget,MATCH($N19,fx_ccy,0)),""))),"",N($G19)*INDEX(rates_tbl,MATCH($C19,loc_list,0),10)*$F19/IFERROR(INDEX(fx_budget,MATCH($N19,fx_ccy,0)),"")))) | P19: =IF(NOT(AND($C19<>"",ISNUMBER(MATCH($C19,loc_list,0)),ISNUMBER($F19),$F19>0,OR(N($G19)>0,$H19<>""))),"",IF(NOT(ISNUMBER(IFERROR(INDEX(fx_budget,MATCH($M19,fx_ccy,0)),""))),"",(N($G19)*INDEX(rates_tbl,MATCH($C19,loc_list,0),9)+IF($H19="Over 10 hours",INDEX(rates_tbl,MATCH($C19,loc_list,0),8),IF($H19="Over 5 hours",INDEX(rates_tbl,MATCH($C19,loc_list,0),7),0)))*$F19/IFERROR(INDEX(fx_budget,MATCH($M19,fx_ccy,0)),""))) | Q19: =IF(LEN(R19)-LEN(SUBSTITUTE(R19,"+",""))>=4, HYPERLINK(R19, _xlfn.TEXTJOIN(" ",TRUE,"Click for Google Flights Prices for",IF(B19="","London",IFERROR(_xlfn.TEXTBEFORE(B19,", "),B19)),"to",IFERROR(_xlfn.TEXTBEFORE(C19,", "),C19))), "") | R19: =HYPERLINK((IF(OR(C19="",D19="",I19=""),"","https://www.google.com/search?q=flights+from+"&SUBSTITUTE(IF(B19="","London, UK",B19)," ","+")&"+to+"&SUBSTITUTE(C19," ","+")&"+"&TEXT(D19,"d+mmmm+yyyy")&"+to+"&TEXT(I19,"d+mmmm+yyyy")))) | S19: =IF(J19<>0,PRODUCT(J19,F19),"") | T19: =IF(NOT(AND($C19<>"",ISNUMBER(MATCH($C19,loc_list,0)),ISNUMBER($F19),$F19>0,OR(N($G19)>0,$H19<>""))),"",N($K19)*$F19) | U19: =IF(NOT(AND($C19<>"",ISNUMBER(MATCH($C19,loc_list,0)),ISNUMBER($F19),$F19>0,OR(N($G19)>0,$H19<>""))),"",IF(COUNT($O19:$T19)<4,"",SUM($O19:$T19))) | V19: =IF($C19="","",IF(NOT(ISNUMBER(MATCH($C19,loc_list,0))),"Destination not recognised. Choose one from the dropdown.",IF(NOT(ISNUMBER($F19)),"Enter the number of travellers.",IF($F19<=0,"Travellers must be 1 or more.",IF(AND(N($G19)<=0,$H19=""),"Enter the number of nights. For a day of travel with no overnight, set the final-day column — choose None if no subsistence is claimed.",IF(NOT(ISNUMBER(IFERROR(INDEX(fx_budget,MATCH($M19,fx_ccy,0)),""))),"No exchange rate for "&$M19&IF($M19=$N19,""," (the meals currency)")&". Add one on the FX sheet.",IF(AND(N($N19)>0,NOT(ISNUMBER(IFERROR(INDEX(fx_budget,MATCH($N19,fx_ccy,0)),"")))),"No exchange rate for "&$N19&" (the room-rate currency). Add one on the FX sheet.",IF(NOT(ISNUMBER($G19)),"Enter a quoted fare or search for one using the Google Flights link!",IF($M19<>$N19,"Dual currency: meals in "&$M19&", room rate in "&$N19&". Converted separately.","")))))))))
E20: =IF(D20<>"",_xlfn.XLOOKUP(MONTH(D20),Table2[Month Number],month_list,"",0,1),"") | I20: =IF(D20<>0,SUM(D20,G20),"") | L20: =IF($C20="","",IFERROR(INDEX(rates_tbl,MATCH($C20,loc_list,0),3),"")) | M20: =IF($C20="","",IFERROR(INDEX(rates_tbl,MATCH($C20,loc_list,0),4),"")) | N20: =IF($C20="","",IFERROR(INDEX(rates_tbl,MATCH($C20,loc_list,0),5),"")) | O20: =IF(NOT(AND($C20<>"",ISNUMBER(MATCH($C20,loc_list,0)),ISNUMBER($F20),$F20>0,OR(N($G20)>0,$H20<>""))),"",IF(N($G20)<=0,0,IF(NOT(ISNUMBER(IFERROR(INDEX(fx_budget,MATCH($N20,fx_ccy,0)),""))),"",N($G20)*INDEX(rates_tbl,MATCH($C20,loc_list,0),10)*$F20/IFERROR(INDEX(fx_budget,MATCH($N20,fx_ccy,0)),"")))) | P20: =IF(NOT(AND($C20<>"",ISNUMBER(MATCH($C20,loc_list,0)),ISNUMBER($F20),$F20>0,OR(N($G20)>0,$H20<>""))),"",IF(NOT(ISNUMBER(IFERROR(INDEX(fx_budget,MATCH($M20,fx_ccy,0)),""))),"",(N($G20)*INDEX(rates_tbl,MATCH($C20,loc_list,0),9)+IF($H20="Over 10 hours",INDEX(rates_tbl,MATCH($C20,loc_list,0),8),IF($H20="Over 5 hours",INDEX(rates_tbl,MATCH($C20,loc_list,0),7),0)))*$F20/IFERROR(INDEX(fx_budget,MATCH($M20,fx_ccy,0)),""))) | Q20: =IF(LEN(R20)-LEN(SUBSTITUTE(R20,"+",""))>=4, HYPERLINK(R20, _xlfn.TEXTJOIN(" ",TRUE,"Click for Google Flights Prices for",IF(B20="","London",IFERROR(_xlfn.TEXTBEFORE(B20,", "),B20)),"to",IFERROR(_xlfn.TEXTBEFORE(C20,", "),C20))), "") | R20: =HYPERLINK((IF(OR(C20="",D20="",I20=""),"","https://www.google.com/search?q=flights+from+"&SUBSTITUTE(IF(B20="","London, UK",B20)," ","+")&"+to+"&SUBSTITUTE(C20," ","+")&"+"&TEXT(D20,"d+mmmm+yyyy")&"+to+"&TEXT(I20,"d+mmmm+yyyy")))) | S20: =IF(J20<>0,PRODUCT(J20,F20),"") | T20: =IF(NOT(AND($C20<>"",ISNUMBER(MATCH($C20,loc_list,0)),ISNUMBER($F20),$F20>0,OR(N($G20)>0,$H20<>""))),"",N($K20)*$F20) | U20: =IF(NOT(AND($C20<>"",ISNUMBER(MATCH($C20,loc_list,0)),ISNUMBER($F20),$F20>0,OR(N($G20)>0,$H20<>""))),"",IF(COUNT($O20:$T20)<4,"",SUM($O20:$T20))) | V20: =IF($C20="","",IF(NOT(ISNUMBER(MATCH($C20,loc_list,0))),"Destination not recognised. Choose one from the dropdown.",IF(NOT(ISNUMBER($F20)),"Enter the number of travellers.",IF($F20<=0,"Travellers must be 1 or more.",IF(AND(N($G20)<=0,$H20=""),"Enter the number of nights. For a day of travel with no overnight, set the final-day column — choose None if no subsistence is claimed.",IF(NOT(ISNUMBER(IFERROR(INDEX(fx_budget,MATCH($M20,fx_ccy,0)),""))),"No exchange rate for "&$M20&IF($M20=$N20,""," (the meals currency)")&". Add one on the FX sheet.",IF(AND(N($N20)>0,NOT(ISNUMBER(IFERROR(INDEX(fx_budget,MATCH($N20,fx_ccy,0)),"")))),"No exchange rate for "&$N20&" (the room-rate currency). Add one on the FX sheet.",IF(NOT(ISNUMBER($G20)),"Enter a quoted fare or search for one using the Google Flights link!",IF($M20<>$N20,"Dual currency: meals in "&$M20&", room rate in "&$N20&". Converted separately.","")))))))))
E21: =IF(D21<>"",_xlfn.XLOOKUP(MONTH(D21),Table2[Month Number],month_list,"",0,1),"") | I21: =IF(D21<>0,SUM(D21,G21),"") | L21: =IF($C21="","",IFERROR(INDEX(rates_tbl,MATCH($C21,loc_list,0),3),"")) | M21: =IF($C21="","",IFERROR(INDEX(rates_tbl,MATCH($C21,loc_list,0),4),"")) | N21: =IF($C21="","",IFERROR(INDEX(rates_tbl,MATCH($C21,loc_list,0),5),"")) | O21: =IF(NOT(AND($C21<>"",ISNUMBER(MATCH($C21,loc_list,0)),ISNUMBER($F21),$F21>0,OR(N($G21)>0,$H21<>""))),"",IF(N($G21)<=0,0,IF(NOT(ISNUMBER(IFERROR(INDEX(fx_budget,MATCH($N21,fx_ccy,0)),""))),"",N($G21)*INDEX(rates_tbl,MATCH($C21,loc_list,0),10)*$F21/IFERROR(INDEX(fx_budget,MATCH($N21,fx_ccy,0)),"")))) | P21: =IF(NOT(AND($C21<>"",ISNUMBER(MATCH($C21,loc_list,0)),ISNUMBER($F21),$F21>0,OR(N($G21)>0,$H21<>""))),"",IF(NOT(ISNUMBER(IFERROR(INDEX(fx_budget,MATCH($M21,fx_ccy,0)),""))),"",(N($G21)*INDEX(rates_tbl,MATCH($C21,loc_list,0),9)+IF($H21="Over 10 hours",INDEX(rates_tbl,MATCH($C21,loc_list,0),8),IF($H21="Over 5 hours",INDEX(rates_tbl,MATCH($C21,loc_list,0),7),0)))*$F21/IFERROR(INDEX(fx_budget,MATCH($M21,fx_ccy,0)),""))) | Q21: =IF(LEN(R21)-LEN(SUBSTITUTE(R21,"+",""))>=4, HYPERLINK(R21, _xlfn.TEXTJOIN(" ",TRUE,"Click for Google Flights Prices for",IF(B21="","London",IFERROR(_xlfn.TEXTBEFORE(B21,", "),B21)),"to",IFERROR(_xlfn.TEXTBEFORE(C21,", "),C21))), "") | R21: =HYPERLINK((IF(OR(C21="",D21="",I21=""),"","https://www.google.com/search?q=flights+from+"&SUBSTITUTE(IF(B21="","London, UK",B21)," ","+")&"+to+"&SUBSTITUTE(C21," ","+")&"+"&TEXT(D21,"d+mmmm+yyyy")&"+to+"&TEXT(I21,"d+mmmm+yyyy")))) | S21: =IF(J21<>0,PRODUCT(J21,F21),"") | T21: =IF(NOT(AND($C21<>"",ISNUMBER(MATCH($C21,loc_list,0)),ISNUMBER($F21),$F21>0,OR(N($G21)>0,$H21<>""))),"",N($K21)*$F21) | U21: =IF(NOT(AND($C21<>"",ISNUMBER(MATCH($C21,loc_list,0)),ISNUMBER($F21),$F21>0,OR(N($G21)>0,$H21<>""))),"",IF(COUNT($O21:$T21)<4,"",SUM($O21:$T21))) | V21: =IF($C21="","",IF(NOT(ISNUMBER(MATCH($C21,loc_list,0))),"Destination not recognised. Choose one from the dropdown.",IF(NOT(ISNUMBER($F21)),"Enter the number of travellers.",IF($F21<=0,"Travellers must be 1 or more.",IF(AND(N($G21)<=0,$H21=""),"Enter the number of nights. For a day of travel with no overnight, set the final-day column — choose None if no subsistence is claimed.",IF(NOT(ISNUMBER(IFERROR(INDEX(fx_budget,MATCH($M21,fx_ccy,0)),""))),"No exchange rate for "&$M21&IF($M21=$N21,""," (the meals currency)")&". Add one on the FX sheet.",IF(AND(N($N21)>0,NOT(ISNUMBER(IFERROR(INDEX(fx_budget,MATCH($N21,fx_ccy,0)),"")))),"No exchange rate for "&$N21&" (the room-rate currency). Add one on the FX sheet.",IF(NOT(ISNUMBER($G21)),"Enter a quoted fare or search for one using the Google Flights link!",IF($M21<>$N21,"Dual currency: meals in "&$M21&", room rate in "&$N21&". Converted separately.","")))))))))
E22: =IF(D22<>"",_xlfn.XLOOKUP(MONTH(D22),Table2[Month Number],month_list,"",0,1),"") | I22: =IF(D22<>0,SUM(D22,G22),"") | L22: =IF($C22="","",IFERROR(INDEX(rates_tbl,MATCH($C22,loc_list,0),3),"")) | M22: =IF($C22="","",IFERROR(INDEX(rates_tbl,MATCH($C22,loc_list,0),4),"")) | N22: =IF($C22="","",IFERROR(INDEX(rates_tbl,MATCH($C22,loc_list,0),5),"")) | O22: =IF(NOT(AND($C22<>"",ISNUMBER(MATCH($C22,loc_list,0)),ISNUMBER($F22),$F22>0,OR(N($G22)>0,$H22<>""))),"",IF(N($G22)<=0,0,IF(NOT(ISNUMBER(IFERROR(INDEX(fx_budget,MATCH($N22,fx_ccy,0)),""))),"",N($G22)*INDEX(rates_tbl,MATCH($C22,loc_list,0),10)*$F22/IFERROR(INDEX(fx_budget,MATCH($N22,fx_ccy,0)),"")))) | P22: =IF(NOT(AND($C22<>"",ISNUMBER(MATCH($C22,loc_list,0)),ISNUMBER($F22),$F22>0,OR(N($G22)>0,$H22<>""))),"",IF(NOT(ISNUMBER(IFERROR(INDEX(fx_budget,MATCH($M22,fx_ccy,0)),""))),"",(N($G22)*INDEX(rates_tbl,MATCH($C22,loc_list,0),9)+IF($H22="Over 10 hours",INDEX(rates_tbl,MATCH($C22,loc_list,0),8),IF($H22="Over 5 hours",INDEX(rates_tbl,MATCH($C22,loc_list,0),7),0)))*$F22/IFERROR(INDEX(fx_budget,MATCH($M22,fx_ccy,0)),""))) | Q22: =IF(LEN(R22)-LEN(SUBSTITUTE(R22,"+",""))>=4, HYPERLINK(R22, _xlfn.TEXTJOIN(" ",TRUE,"Click for Google Flights Prices for",IF(B22="","London",IFERROR(_xlfn.TEXTBEFORE(B22,", "),B22)),"to",IFERROR(_xlfn.TEXTBEFORE(C22,", "),C22))), "") | R22: =HYPERLINK((IF(OR(C22="",D22="",I22=""),"","https://www.google.com/search?q=flights+from+"&SUBSTITUTE(IF(B22="","London, UK",B22)," ","+")&"+to+"&SUBSTITUTE(C22," ","+")&"+"&TEXT(D22,"d+mmmm+yyyy")&"+to+"&TEXT(I22,"d+mmmm+yyyy")))) | S22: =IF(J22<>0,PRODUCT(J22,F22),"") | T22: =IF(NOT(AND($C22<>"",ISNUMBER(MATCH($C22,loc_list,0)),ISNUMBER($F22),$F22>0,OR(N($G22)>0,$H22<>""))),"",N($K22)*$F22) | U22: =IF(NOT(AND($C22<>"",ISNUMBER(MATCH($C22,loc_list,0)),ISNUMBER($F22),$F22>0,OR(N($G22)>0,$H22<>""))),"",IF(COUNT($O22:$T22)<4,"",SUM($O22:$T22))) | V22: =IF($C22="","",IF(NOT(ISNUMBER(MATCH($C22,loc_list,0))),"Destination not recognised. Choose one from the dropdown.",IF(NOT(ISNUMBER($F22)),"Enter the number of travellers.",IF($F22<=0,"Travellers must be 1 or more.",IF(AND(N($G22)<=0,$H22=""),"Enter the number of nights. For a day of travel with no overnight, set the final-day column — choose None if no subsistence is claimed.",IF(NOT(ISNUMBER(IFERROR(INDEX(fx_budget,MATCH($M22,fx_ccy,0)),""))),"No exchange rate for "&$M22&IF($M22=$N22,""," (the meals currency)")&". Add one on the FX sheet.",IF(AND(N($N22)>0,NOT(ISNUMBER(IFERROR(INDEX(fx_budget,MATCH($N22,fx_ccy,0)),"")))),"No exchange rate for "&$N22&" (the room-rate currency). Add one on the FX sheet.",IF(NOT(ISNUMBER($G22)),"Enter a quoted fare or search for one using the Google Flights link!",IF($M22<>$N22,"Dual currency: meals in "&$M22&", room rate in "&$N22&". Converted separately.","")))))))))
E23: =IF(D23<>"",_xlfn.XLOOKUP(MONTH(D23),Table2[Month Number],month_list,"",0,1),"") | I23: =IF(D23<>0,SUM(D23,G23),"") | L23: =IF($C23="","",IFERROR(INDEX(rates_tbl,MATCH($C23,loc_list,0),3),"")) | M23: =IF($C23="","",IFERROR(INDEX(rates_tbl,MATCH($C23,loc_list,0),4),"")) | N23: =IF($C23="","",IFERROR(INDEX(rates_tbl,MATCH($C23,loc_list,0),5),"")) | O23: =IF(NOT(AND($C23<>"",ISNUMBER(MATCH($C23,loc_list,0)),ISNUMBER($F23),$F23>0,OR(N($G23)>0,$H23<>""))),"",IF(N($G23)<=0,0,IF(NOT(ISNUMBER(IFERROR(INDEX(fx_budget,MATCH($N23,fx_ccy,0)),""))),"",N($G23)*INDEX(rates_tbl,MATCH($C23,loc_list,0),10)*$F23/IFERROR(INDEX(fx_budget,MATCH($N23,fx_ccy,0)),"")))) | P23: =IF(NOT(AND($C23<>"",ISNUMBER(MATCH($C23,loc_list,0)),ISNUMBER($F23),$F23>0,OR(N($G23)>0,$H23<>""))),"",IF(NOT(ISNUMBER(IFERROR(INDEX(fx_budget,MATCH($M23,fx_ccy,0)),""))),"",(N($G23)*INDEX(rates_tbl,MATCH($C23,loc_list,0),9)+IF($H23="Over 10 hours",INDEX(rates_tbl,MATCH($C23,loc_list,0),8),IF($H23="Over 5 hours",INDEX(rates_tbl,MATCH($C23,loc_list,0),7),0)))*$F23/IFERROR(INDEX(fx_budget,MATCH($M23,fx_ccy,0)),""))) | Q23: =IF(LEN(R23)-LEN(SUBSTITUTE(R23,"+",""))>=4, HYPERLINK(R23, _xlfn.TEXTJOIN(" ",TRUE,"Click for Google Flights Prices for",IF(B23="","London",IFERROR(_xlfn.TEXTBEFORE(B23,", "),B23)),"to",IFERROR(_xlfn.TEXTBEFORE(C23,", "),C23))), "") | R23: =HYPERLINK((IF(OR(C23="",D23="",I23=""),"","https://www.google.com/search?q=flights+from+"&SUBSTITUTE(IF(B23="","London, UK",B23)," ","+")&"+to+"&SUBSTITUTE(C23," ","+")&"+"&TEXT(D23,"d+mmmm+yyyy")&"+to+"&TEXT(I23,"d+mmmm+yyyy")))) | S23: =IF(J23<>0,PRODUCT(J23,F23),"") | T23: =IF(NOT(AND($C23<>"",ISNUMBER(MATCH($C23,loc_list,0)),ISNUMBER($F23),$F23>0,OR(N($G23)>0,$H23<>""))),"",N($K23)*$F23) | U23: =IF(NOT(AND($C23<>"",ISNUMBER(MATCH($C23,loc_list,0)),ISNUMBER($F23),$F23>0,OR(N($G23)>0,$H23<>""))),"",IF(COUNT($O23:$T23)<4,"",SUM($O23:$T23))) | V23: =IF($C23="","",IF(NOT(ISNUMBER(MATCH($C23,loc_list,0))),"Destination not recognised. Choose one from the dropdown.",IF(NOT(ISNUMBER($F23)),"Enter the number of travellers.",IF($F23<=0,"Travellers must be 1 or more.",IF(AND(N($G23)<=0,$H23=""),"Enter the number of nights. For a day of travel with no overnight, set the final-day column — choose None if no subsistence is claimed.",IF(NOT(ISNUMBER(IFERROR(INDEX(fx_budget,MATCH($M23,fx_ccy,0)),""))),"No exchange rate for "&$M23&IF($M23=$N23,""," (the meals currency)")&". Add one on the FX sheet.",IF(AND(N($N23)>0,NOT(ISNUMBER(IFERROR(INDEX(fx_budget,MATCH($N23,fx_ccy,0)),"")))),"No exchange rate for "&$N23&" (the room-rate currency). Add one on the FX sheet.",IF(NOT(ISNUMBER($G23)),"Enter a quoted fare or search for one using the Google Flights link!",IF($M23<>$N23,"Dual currency: meals in "&$M23&", room rate in "&$N23&". Converted separately.","")))))))))
E24: =IF(D24<>"",_xlfn.XLOOKUP(MONTH(D24),Table2[Month Number],month_list,"",0,1),"") | I24: =IF(D24<>0,SUM(D24,G24),"") | L24: =IF($C24="","",IFERROR(INDEX(rates_tbl,MATCH($C24,loc_list,0),3),"")) | M24: =IF($C24="","",IFERROR(INDEX(rates_tbl,MATCH($C24,loc_list,0),4),"")) | N24: =IF($C24="","",IFERROR(INDEX(rates_tbl,MATCH($C24,loc_list,0),5),"")) | O24: =IF(NOT(AND($C24<>"",ISNUMBER(MATCH($C24,loc_list,0)),ISNUMBER($F24),$F24>0,OR(N($G24)>0,$H24<>""))),"",IF(N($G24)<=0,0,IF(NOT(ISNUMBER(IFERROR(INDEX(fx_budget,MATCH($N24,fx_ccy,0)),""))),"",N($G24)*INDEX(rates_tbl,MATCH($C24,loc_list,0),10)*$F24/IFERROR(INDEX(fx_budget,MATCH($N24,fx_ccy,0)),"")))) | P24: =IF(NOT(AND($C24<>"",ISNUMBER(MATCH($C24,loc_list,0)),ISNUMBER($F24),$F24>0,OR(N($G24)>0,$H24<>""))),"",IF(NOT(ISNUMBER(IFERROR(INDEX(fx_budget,MATCH($M24,fx_ccy,0)),""))),"",(N($G24)*INDEX(rates_tbl,MATCH($C24,loc_list,0),9)+IF($H24="Over 10 hours",INDEX(rates_tbl,MATCH($C24,loc_list,0),8),IF($H24="Over 5 hours",INDEX(rates_tbl,MATCH($C24,loc_list,0),7),0)))*$F24/IFERROR(INDEX(fx_budget,MATCH($M24,fx_ccy,0)),""))) | Q24: =IF(LEN(R24)-LEN(SUBSTITUTE(R24,"+",""))>=4, HYPERLINK(R24, _xlfn.TEXTJOIN(" ",TRUE,"Click for Google Flights Prices for",IF(B24="","London",IFERROR(_xlfn.TEXTBEFORE(B24,", "),B24)),"to",IFERROR(_xlfn.TEXTBEFORE(C24,", "),C24))), "") | R24: =HYPERLINK((IF(OR(C24="",D24="",I24=""),"","https://www.google.com/search?q=flights+from+"&SUBSTITUTE(IF(B24="","London, UK",B24)," ","+")&"+to+"&SUBSTITUTE(C24," ","+")&"+"&TEXT(D24,"d+mmmm+yyyy")&"+to+"&TEXT(I24,"d+mmmm+yyyy")))) | S24: =IF(J24<>0,PRODUCT(J24,F24),"") | T24: =IF(NOT(AND($C24<>"",ISNUMBER(MATCH($C24,loc_list,0)),ISNUMBER($F24),$F24>0,OR(N($G24)>0,$H24<>""))),"",N($K24)*$F24) | U24: =IF(NOT(AND($C24<>"",ISNUMBER(MATCH($C24,loc_list,0)),ISNUMBER($F24),$F24>0,OR(N($G24)>0,$H24<>""))),"",IF(COUNT($O24:$T24)<4,"",SUM($O24:$T24))) | V24: =IF($C24="","",IF(NOT(ISNUMBER(MATCH($C24,loc_list,0))),"Destination not recognised. Choose one from the dropdown.",IF(NOT(ISNUMBER($F24)),"Enter the number of travellers.",IF($F24<=0,"Travellers must be 1 or more.",IF(AND(N($G24)<=0,$H24=""),"Enter the number of nights. For a day of travel with no overnight, set the final-day column — choose None if no subsistence is claimed.",IF(NOT(ISNUMBER(IFERROR(INDEX(fx_budget,MATCH($M24,fx_ccy,0)),""))),"No exchange rate for "&$M24&IF($M24=$N24,""," (the meals currency)")&". Add one on the FX sheet.",IF(AND(N($N24)>0,NOT(ISNUMBER(IFERROR(INDEX(fx_budget,MATCH($N24,fx_ccy,0)),"")))),"No exchange rate for "&$N24&" (the room-rate currency). Add one on the FX sheet.",IF(NOT(ISNUMBER($G24)),"Enter a quoted fare or search for one using the Google Flights link!",IF($M24<>$N24,"Dual currency: meals in "&$M24&", room rate in "&$N24&". Converted separately.","")))))))))
E25: =IF(D25<>"",_xlfn.XLOOKUP(MONTH(D25),Table2[Month Number],month_list,"",0,1),"") | I25: =IF(D25<>0,SUM(D25,G25),"") | L25: =IF($C25="","",IFERROR(INDEX(rates_tbl,MATCH($C25,loc_list,0),3),"")) | M25: =IF($C25="","",IFERROR(INDEX(rates_tbl,MATCH($C25,loc_list,0),4),"")) | N25: =IF($C25="","",IFERROR(INDEX(rates_tbl,MATCH($C25,loc_list,0),5),"")) | O25: =IF(NOT(AND($C25<>"",ISNUMBER(MATCH($C25,loc_list,0)),ISNUMBER($F25),$F25>0,OR(N($G25)>0,$H25<>""))),"",IF(N($G25)<=0,0,IF(NOT(ISNUMBER(IFERROR(INDEX(fx_budget,MATCH($N25,fx_ccy,0)),""))),"",N($G25)*INDEX(rates_tbl,MATCH($C25,loc_list,0),10)*$F25/IFERROR(INDEX(fx_budget,MATCH($N25,fx_ccy,0)),"")))) | P25: =IF(NOT(AND($C25<>"",ISNUMBER(MATCH($C25,loc_list,0)),ISNUMBER($F25),$F25>0,OR(N($G25)>0,$H25<>""))),"",IF(NOT(ISNUMBER(IFERROR(INDEX(fx_budget,MATCH($M25,fx_ccy,0)),""))),"",(N($G25)*INDEX(rates_tbl,MATCH($C25,loc_list,0),9)+IF($H25="Over 10 hours",INDEX(rates_tbl,MATCH($C25,loc_list,0),8),IF($H25="Over 5 hours",INDEX(rates_tbl,MATCH($C25,loc_list,0),7),0)))*$F25/IFERROR(INDEX(fx_budget,MATCH($M25,fx_ccy,0)),""))) | Q25: =IF(LEN(R25)-LEN(SUBSTITUTE(R25,"+",""))>=4, HYPERLINK(R25, _xlfn.TEXTJOIN(" ",TRUE,"Click for Google Flights Prices for",IF(B25="","London",IFERROR(_xlfn.TEXTBEFORE(B25,", "),B25)),"to",IFERROR(_xlfn.TEXTBEFORE(C25,", "),C25))), "") | R25: =HYPERLINK((IF(OR(C25="",D25="",I25=""),"","https://www.google.com/search?q=flights+from+"&SUBSTITUTE(IF(B25="","London, UK",B25)," ","+")&"+to+"&SUBSTITUTE(C25," ","+")&"+"&TEXT(D25,"d+mmmm+yyyy")&"+to+"&TEXT(I25,"d+mmmm+yyyy")))) | S25: =IF(J25<>0,PRODUCT(J25,F25),"") | T25: =IF(NOT(AND($C25<>"",ISNUMBER(MATCH($C25,loc_list,0)),ISNUMBER($F25),$F25>0,OR(N($G25)>0,$H25<>""))),"",N($K25)*$F25) | U25: =IF(NOT(AND($C25<>"",ISNUMBER(MATCH($C25,loc_list,0)),ISNUMBER($F25),$F25>0,OR(N($G25)>0,$H25<>""))),"",IF(COUNT($O25:$T25)<4,"",SUM($O25:$T25))) | V25: =IF($C25="","",IF(NOT(ISNUMBER(MATCH($C25,loc_list,0))),"Destination not recognised. Choose one from the dropdown.",IF(NOT(ISNUMBER($F25)),"Enter the number of travellers.",IF($F25<=0,"Travellers must be 1 or more.",IF(AND(N($G25)<=0,$H25=""),"Enter the number of nights. For a day of travel with no overnight, set the final-day column — choose None if no subsistence is claimed.",IF(NOT(ISNUMBER(IFERROR(INDEX(fx_budget,MATCH($M25,fx_ccy,0)),""))),"No exchange rate for "&$M25&IF($M25=$N25,""," (the meals currency)")&". Add one on the FX sheet.",IF(AND(N($N25)>0,NOT(ISNUMBER(IFERROR(INDEX(fx_budget,MATCH($N25,fx_ccy,0)),"")))),"No exchange rate for "&$N25&" (the room-rate currency). Add one on the FX sheet.",IF(NOT(ISNUMBER($G25)),"Enter a quoted fare or search for one using the Google Flights link!",IF($M25<>$N25,"Dual currency: meals in "&$M25&", room rate in "&$N25&". Converted separately.","")))))))))
E26: =IF(D26<>"",_xlfn.XLOOKUP(MONTH(D26),Table2[Month Number],month_list,"",0,1),"") | I26: =IF(D26<>0,SUM(D26,G26),"") | L26: =IF($C26="","",IFERROR(INDEX(rates_tbl,MATCH($C26,loc_list,0),3),"")) | M26: =IF($C26="","",IFERROR(INDEX(rates_tbl,MATCH($C26,loc_list,0),4),"")) | N26: =IF($C26="","",IFERROR(INDEX(rates_tbl,MATCH($C26,loc_list,0),5),"")) | O26: =IF(NOT(AND($C26<>"",ISNUMBER(MATCH($C26,loc_list,0)),ISNUMBER($F26),$F26>0,OR(N($G26)>0,$H26<>""))),"",IF(N($G26)<=0,0,IF(NOT(ISNUMBER(IFERROR(INDEX(fx_budget,MATCH($N26,fx_ccy,0)),""))),"",N($G26)*INDEX(rates_tbl,MATCH($C26,loc_list,0),10)*$F26/IFERROR(INDEX(fx_budget,MATCH($N26,fx_ccy,0)),"")))) | P26: =IF(NOT(AND($C26<>"",ISNUMBER(MATCH($C26,loc_list,0)),ISNUMBER($F26),$F26>0,OR(N($G26)>0,$H26<>""))),"",IF(NOT(ISNUMBER(IFERROR(INDEX(fx_budget,MATCH($M26,fx_ccy,0)),""))),"",(N($G26)*INDEX(rates_tbl,MATCH($C26,loc_list,0),9)+IF($H26="Over 10 hours",INDEX(rates_tbl,MATCH($C26,loc_list,0),8),IF($H26="Over 5 hours",INDEX(rates_tbl,MATCH($C26,loc_list,0),7),0)))*$F26/IFERROR(INDEX(fx_budget,MATCH($M26,fx_ccy,0)),""))) | Q26: =IF(LEN(R26)-LEN(SUBSTITUTE(R26,"+",""))>=4, HYPERLINK(R26, _xlfn.TEXTJOIN(" ",TRUE,"Click for Google Flights Prices for",IF(B26="","London",IFERROR(_xlfn.TEXTBEFORE(B26,", "),B26)),"to",IFERROR(_xlfn.TEXTBEFORE(C26,", "),C26))), "") | R26: =HYPERLINK((IF(OR(C26="",D26="",I26=""),"","https://www.google.com/search?q=flights+from+"&SUBSTITUTE(IF(B26="","London, UK",B26)," ","+")&"+to+"&SUBSTITUTE(C26," ","+")&"+"&TEXT(D26,"d+mmmm+yyyy")&"+to+"&TEXT(I26,"d+mmmm+yyyy")))) | S26: =IF(J26<>0,PRODUCT(J26,F26),"") | T26: =IF(NOT(AND($C26<>"",ISNUMBER(MATCH($C26,loc_list,0)),ISNUMBER($F26),$F26>0,OR(N($G26)>0,$H26<>""))),"",N($K26)*$F26) | U26: =IF(NOT(AND($C26<>"",ISNUMBER(MATCH($C26,loc_list,0)),ISNUMBER($F26),$F26>0,OR(N($G26)>0,$H26<>""))),"",IF(COUNT($O26:$T26)<4,"",SUM($O26:$T26))) | V26: =IF($C26="","",IF(NOT(ISNUMBER(MATCH($C26,loc_list,0))),"Destination not recognised. Choose one from the dropdown.",IF(NOT(ISNUMBER($F26)),"Enter the number of travellers.",IF($F26<=0,"Travellers must be 1 or more.",IF(AND(N($G26)<=0,$H26=""),"Enter the number of nights. For a day of travel with no overnight, set the final-day column — choose None if no subsistence is claimed.",IF(NOT(ISNUMBER(IFERROR(INDEX(fx_budget,MATCH($M26,fx_ccy,0)),""))),"No exchange rate for "&$M26&IF($M26=$N26,""," (the meals currency)")&". Add one on the FX sheet.",IF(AND(N($N26)>0,NOT(ISNUMBER(IFERROR(INDEX(fx_budget,MATCH($N26,fx_ccy,0)),"")))),"No exchange rate for "&$N26&" (the room-rate currency). Add one on the FX sheet.",IF(NOT(ISNUMBER($G26)),"Enter a quoted fare or search for one using the Google Flights link!",IF($M26<>$N26,"Dual currency: meals in "&$M26&", room rate in "&$N26&". Converted separately.","")))))))))
E27: =IF(D27<>"",_xlfn.XLOOKUP(MONTH(D27),Table2[Month Number],month_list,"",0,1),"") | I27: =IF(D27<>0,SUM(D27,G27),"") | L27: =IF($C27="","",IFERROR(INDEX(rates_tbl,MATCH($C27,loc_list,0),3),"")) | M27: =IF($C27="","",IFERROR(INDEX(rates_tbl,MATCH($C27,loc_list,0),4),"")) | N27: =IF($C27="","",IFERROR(INDEX(rates_tbl,MATCH($C27,loc_list,0),5),"")) | O27: =IF(NOT(AND($C27<>"",ISNUMBER(MATCH($C27,loc_list,0)),ISNUMBER($F27),$F27>0,OR(N($G27)>0,$H27<>""))),"",IF(N($G27)<=0,0,IF(NOT(ISNUMBER(IFERROR(INDEX(fx_budget,MATCH($N27,fx_ccy,0)),""))),"",N($G27)*INDEX(rates_tbl,MATCH($C27,loc_list,0),10)*$F27/IFERROR(INDEX(fx_budget,MATCH($N27,fx_ccy,0)),"")))) | P27: =IF(NOT(AND($C27<>"",ISNUMBER(MATCH($C27,loc_list,0)),ISNUMBER($F27),$F27>0,OR(N($G27)>0,$H27<>""))),"",IF(NOT(ISNUMBER(IFERROR(INDEX(fx_budget,MATCH($M27,fx_ccy,0)),""))),"",(N($G27)*INDEX(rates_tbl,MATCH($C27,loc_list,0),9)+IF($H27="Over 10 hours",INDEX(rates_tbl,MATCH($C27,loc_list,0),8),IF($H27="Over 5 hours",INDEX(rates_tbl,MATCH($C27,loc_list,0),7),0)))*$F27/IFERROR(INDEX(fx_budget,MATCH($M27,fx_ccy,0)),""))) | Q27: =IF(LEN(R27)-LEN(SUBSTITUTE(R27,"+",""))>=4, HYPERLINK(R27, _xlfn.TEXTJOIN(" ",TRUE,"Click for Google Flights Prices for",IF(B27="","London",IFERROR(_xlfn.TEXTBEFORE(B27,", "),B27)),"to",IFERROR(_xlfn.TEXTBEFORE(C27,", "),C27))), "") | R27: =HYPERLINK((IF(OR(C27="",D27="",I27=""),"","https://www.google.com/search?q=flights+from+"&SUBSTITUTE(IF(B27="","London, UK",B27)," ","+")&"+to+"&SUBSTITUTE(C27," ","+")&"+"&TEXT(D27,"d+mmmm+yyyy")&"+to+"&TEXT(I27,"d+mmmm+yyyy")))) | S27: =IF(J27<>0,PRODUCT(J27,F27),"") | T27: =IF(NOT(AND($C27<>"",ISNUMBER(MATCH($C27,loc_list,0)),ISNUMBER($F27),$F27>0,OR(N($G27)>0,$H27<>""))),"",N($K27)*$F27) | U27: =IF(NOT(AND($C27<>"",ISNUMBER(MATCH($C27,loc_list,0)),ISNUMBER($F27),$F27>0,OR(N($G27)>0,$H27<>""))),"",IF(COUNT($O27:$T27)<4,"",SUM($O27:$T27))) | V27: =IF($C27="","",IF(NOT(ISNUMBER(MATCH($C27,loc_list,0))),"Destination not recognised. Choose one from the dropdown.",IF(NOT(ISNUMBER($F27)),"Enter the number of travellers.",IF($F27<=0,"Travellers must be 1 or more.",IF(AND(N($G27)<=0,$H27=""),"Enter the number of nights. For a day of travel with no overnight, set the final-day column — choose None if no subsistence is claimed.",IF(NOT(ISNUMBER(IFERROR(INDEX(fx_budget,MATCH($M27,fx_ccy,0)),""))),"No exchange rate for "&$M27&IF($M27=$N27,""," (the meals currency)")&". Add one on the FX sheet.",IF(AND(N($N27)>0,NOT(ISNUMBER(IFERROR(INDEX(fx_budget,MATCH($N27,fx_ccy,0)),"")))),"No exchange rate for "&$N27&" (the room-rate currency). Add one on the FX sheet.",IF(NOT(ISNUMBER($G27)),"Enter a quoted fare or search for one using the Google Flights link!",IF($M27<>$N27,"Dual currency: meals in "&$M27&", room rate in "&$N27&". Converted separately.","")))))))))
E28: =IF(D28<>"",_xlfn.XLOOKUP(MONTH(D28),Table2[Month Number],month_list,"",0,1),"") | I28: =IF(D28<>0,SUM(D28,G28),"") | L28: =IF($C28="","",IFERROR(INDEX(rates_tbl,MATCH($C28,loc_list,0),3),"")) | M28: =IF($C28="","",IFERROR(INDEX(rates_tbl,MATCH($C28,loc_list,0),4),"")) | N28: =IF($C28="","",IFERROR(INDEX(rates_tbl,MATCH($C28,loc_list,0),5),"")) | O28: =IF(NOT(AND($C28<>"",ISNUMBER(MATCH($C28,loc_list,0)),ISNUMBER($F28),$F28>0,OR(N($G28)>0,$H28<>""))),"",IF(N($G28)<=0,0,IF(NOT(ISNUMBER(IFERROR(INDEX(fx_budget,MATCH($N28,fx_ccy,0)),""))),"",N($G28)*INDEX(rates_tbl,MATCH($C28,loc_list,0),10)*$F28/IFERROR(INDEX(fx_budget,MATCH($N28,fx_ccy,0)),"")))) | P28: =IF(NOT(AND($C28<>"",ISNUMBER(MATCH($C28,loc_list,0)),ISNUMBER($F28),$F28>0,OR(N($G28)>0,$H28<>""))),"",IF(NOT(ISNUMBER(IFERROR(INDEX(fx_budget,MATCH($M28,fx_ccy,0)),""))),"",(N($G28)*INDEX(rates_tbl,MATCH($C28,loc_list,0),9)+IF($H28="Over 10 hours",INDEX(rates_tbl,MATCH($C28,loc_list,0),8),IF($H28="Over 5 hours",INDEX(rates_tbl,MATCH($C28,loc_list,0),7),0)))*$F28/IFERROR(INDEX(fx_budget,MATCH($M28,fx_ccy,0)),""))) | Q28: =IF(LEN(R28)-LEN(SUBSTITUTE(R28,"+",""))>=4, HYPERLINK(R28, _xlfn.TEXTJOIN(" ",TRUE,"Click for Google Flights Prices for",IF(B28="","London",IFERROR(_xlfn.TEXTBEFORE(B28,", "),B28)),"to",IFERROR(_xlfn.TEXTBEFORE(C28,", "),C28))), "") | R28: =HYPERLINK((IF(OR(C28="",D28="",I28=""),"","https://www.google.com/search?q=flights+from+"&SUBSTITUTE(IF(B28="","London, UK",B28)," ","+")&"+to+"&SUBSTITUTE(C28," ","+")&"+"&TEXT(D28,"d+mmmm+yyyy")&"+to+"&TEXT(I28,"d+mmmm+yyyy")))) | S28: =IF(J28<>0,PRODUCT(J28,F28),"") | T28: =IF(NOT(AND($C28<>"",ISNUMBER(MATCH($C28,loc_list,0)),ISNUMBER($F28),$F28>0,OR(N($G28)>0,$H28<>""))),"",N($K28)*$F28) | U28: =IF(NOT(AND($C28<>"",ISNUMBER(MATCH($C28,loc_list,0)),ISNUMBER($F28),$F28>0,OR(N($G28)>0,$H28<>""))),"",IF(COUNT($O28:$T28)<4,"",SUM($O28:$T28))) | V28: =IF($C28="","",IF(NOT(ISNUMBER(MATCH($C28,loc_list,0))),"Destination not recognised. Choose one from the dropdown.",IF(NOT(ISNUMBER($F28)),"Enter the number of travellers.",IF($F28<=0,"Travellers must be 1 or more.",IF(AND(N($G28)<=0,$H28=""),"Enter the number of nights. For a day of travel with no overnight, set the final-day column — choose None if no subsistence is claimed.",IF(NOT(ISNUMBER(IFERROR(INDEX(fx_budget,MATCH($M28,fx_ccy,0)),""))),"No exchange rate for "&$M28&IF($M28=$N28,""," (the meals currency)")&". Add one on the FX sheet.",IF(AND(N($N28)>0,NOT(ISNUMBER(IFERROR(INDEX(fx_budget,MATCH($N28,fx_ccy,0)),"")))),"No exchange rate for "&$N28&" (the room-rate currency). Add one on the FX sheet.",IF(NOT(ISNUMBER($G28)),"Enter a quoted fare or search for one using the Google Flights link!",IF($M28<>$N28,"Dual currency: meals in "&$M28&", room rate in "&$N28&". Converted separately.","")))))))))
E29: =IF(D29<>"",_xlfn.XLOOKUP(MONTH(D29),Table2[Month Number],month_list,"",0,1),"") | I29: =IF(D29<>0,SUM(D29,G29),"") | L29: =IF($C29="","",IFERROR(INDEX(rates_tbl,MATCH($C29,loc_list,0),3),"")) | M29: =IF($C29="","",IFERROR(INDEX(rates_tbl,MATCH($C29,loc_list,0),4),"")) | N29: =IF($C29="","",IFERROR(INDEX(rates_tbl,MATCH($C29,loc_list,0),5),"")) | O29: =IF(NOT(AND($C29<>"",ISNUMBER(MATCH($C29,loc_list,0)),ISNUMBER($F29),$F29>0,OR(N($G29)>0,$H29<>""))),"",IF(N($G29)<=0,0,IF(NOT(ISNUMBER(IFERROR(INDEX(fx_budget,MATCH($N29,fx_ccy,0)),""))),"",N($G29)*INDEX(rates_tbl,MATCH($C29,loc_list,0),10)*$F29/IFERROR(INDEX(fx_budget,MATCH($N29,fx_ccy,0)),"")))) | P29: =IF(NOT(AND($C29<>"",ISNUMBER(MATCH($C29,loc_list,0)),ISNUMBER($F29),$F29>0,OR(N($G29)>0,$H29<>""))),"",IF(NOT(ISNUMBER(IFERROR(INDEX(fx_budget,MATCH($M29,fx_ccy,0)),""))),"",(N($G29)*INDEX(rates_tbl,MATCH($C29,loc_list,0),9)+IF($H29="Over 10 hours",INDEX(rates_tbl,MATCH($C29,loc_list,0),8),IF($H29="Over 5 hours",INDEX(rates_tbl,MATCH($C29,loc_list,0),7),0)))*$F29/IFERROR(INDEX(fx_budget,MATCH($M29,fx_ccy,0)),""))) | Q29: =IF(LEN(R29)-LEN(SUBSTITUTE(R29,"+",""))>=4, HYPERLINK(R29, _xlfn.TEXTJOIN(" ",TRUE,"Click for Google Flights Prices for",IF(B29="","London",IFERROR(_xlfn.TEXTBEFORE(B29,", "),B29)),"to",IFERROR(_xlfn.TEXTBEFORE(C29,", "),C29))), "") | R29: =HYPERLINK((IF(OR(C29="",D29="",I29=""),"","https://www.google.com/search?q=flights+from+"&SUBSTITUTE(IF(B29="","London, UK",B29)," ","+")&"+to+"&SUBSTITUTE(C29," ","+")&"+"&TEXT(D29,"d+mmmm+yyyy")&"+to+"&TEXT(I29,"d+mmmm+yyyy")))) | S29: =IF(J29<>0,PRODUCT(J29,F29),"") | T29: =IF(NOT(AND($C29<>"",ISNUMBER(MATCH($C29,loc_list,0)),ISNUMBER($F29),$F29>0,OR(N($G29)>0,$H29<>""))),"",N($K29)*$F29) | U29: =IF(NOT(AND($C29<>"",ISNUMBER(MATCH($C29,loc_list,0)),ISNUMBER($F29),$F29>0,OR(N($G29)>0,$H29<>""))),"",IF(COUNT($O29:$T29)<4,"",SUM($O29:$T29))) | V29: =IF($C29="","",IF(NOT(ISNUMBER(MATCH($C29,loc_list,0))),"Destination not recognised. Choose one from the dropdown.",IF(NOT(ISNUMBER($F29)),"Enter the number of travellers.",IF($F29<=0,"Travellers must be 1 or more.",IF(AND(N($G29)<=0,$H29=""),"Enter the number of nights. For a day of travel with no overnight, set the final-day column — choose None if no subsistence is claimed.",IF(NOT(ISNUMBER(IFERROR(INDEX(fx_budget,MATCH($M29,fx_ccy,0)),""))),"No exchange rate for "&$M29&IF($M29=$N29,""," (the meals currency)")&". Add one on the FX sheet.",IF(AND(N($N29)>0,NOT(ISNUMBER(IFERROR(INDEX(fx_budget,MATCH($N29,fx_ccy,0)),"")))),"No exchange rate for "&$N29&" (the room-rate currency). Add one on the FX sheet.",IF(NOT(ISNUMBER($G29)),"Enter a quoted fare or search for one using the Google Flights link!",IF($M29<>$N29,"Dual currency: meals in "&$M29&", room rate in "&$N29&". Converted separately.","")))))))))
E30: =IF(D30<>"",_xlfn.XLOOKUP(MONTH(D30),Table2[Month Number],month_list,"",0,1),"") | I30: =IF(D30<>0,SUM(D30,G30),"") | L30: =IF($C30="","",IFERROR(INDEX(rates_tbl,MATCH($C30,loc_list,0),3),"")) | M30: =IF($C30="","",IFERROR(INDEX(rates_tbl,MATCH($C30,loc_list,0),4),"")) | N30: =IF($C30="","",IFERROR(INDEX(rates_tbl,MATCH($C30,loc_list,0),5),"")) | O30: =IF(NOT(AND($C30<>"",ISNUMBER(MATCH($C30,loc_list,0)),ISNUMBER($F30),$F30>0,OR(N($G30)>0,$H30<>""))),"",IF(N($G30)<=0,0,IF(NOT(ISNUMBER(IFERROR(INDEX(fx_budget,MATCH($N30,fx_ccy,0)),""))),"",N($G30)*INDEX(rates_tbl,MATCH($C30,loc_list,0),10)*$F30/IFERROR(INDEX(fx_budget,MATCH($N30,fx_ccy,0)),"")))) | P30: =IF(NOT(AND($C30<>"",ISNUMBER(MATCH($C30,loc_list,0)),ISNUMBER($F30),$F30>0,OR(N($G30)>0,$H30<>""))),"",IF(NOT(ISNUMBER(IFERROR(INDEX(fx_budget,MATCH($M30,fx_ccy,0)),""))),"",(N($G30)*INDEX(rates_tbl,MATCH($C30,loc_list,0),9)+IF($H30="Over 10 hours",INDEX(rates_tbl,MATCH($C30,loc_list,0),8),IF($H30="Over 5 hours",INDEX(rates_tbl,MATCH($C30,loc_list,0),7),0)))*$F30/IFERROR(INDEX(fx_budget,MATCH($M30,fx_ccy,0)),""))) | Q30: =IF(LEN(R30)-LEN(SUBSTITUTE(R30,"+",""))>=4, HYPERLINK(R30, _xlfn.TEXTJOIN(" ",TRUE,"Click for Google Flights Prices for",IF(B30="","London",IFERROR(_xlfn.TEXTBEFORE(B30,", "),B30)),"to",IFERROR(_xlfn.TEXTBEFORE(C30,", "),C30))), "") | R30: =HYPERLINK((IF(OR(C30="",D30="",I30=""),"","https://www.google.com/search?q=flights+from+"&SUBSTITUTE(IF(B30="","London, UK",B30)," ","+")&"+to+"&SUBSTITUTE(C30," ","+")&"+"&TEXT(D30,"d+mmmm+yyyy")&"+to+"&TEXT(I30,"d+mmmm+yyyy")))) | S30: =IF(J30<>0,PRODUCT(J30,F30),"") | T30: =IF(NOT(AND($C30<>"",ISNUMBER(MATCH($C30,loc_list,0)),ISNUMBER($F30),$F30>0,OR(N($G30)>0,$H30<>""))),"",N($K30)*$F30) | U30: =IF(NOT(AND($C30<>"",ISNUMBER(MATCH($C30,loc_list,0)),ISNUMBER($F30),$F30>0,OR(N($G30)>0,$H30<>""))),"",IF(COUNT($O30:$T30)<4,"",SUM($O30:$T30))) | V30: =IF($C30="","",IF(NOT(ISNUMBER(MATCH($C30,loc_list,0))),"Destination not recognised. Choose one from the dropdown.",IF(NOT(ISNUMBER($F30)),"Enter the number of travellers.",IF($F30<=0,"Travellers must be 1 or more.",IF(AND(N($G30)<=0,$H30=""),"Enter the number of nights. For a day of travel with no overnight, set the final-day column — choose None if no subsistence is claimed.",IF(NOT(ISNUMBER(IFERROR(INDEX(fx_budget,MATCH($M30,fx_ccy,0)),""))),"No exchange rate for "&$M30&IF($M30=$N30,""," (the meals currency)")&". Add one on the FX sheet.",IF(AND(N($N30)>0,NOT(ISNUMBER(IFERROR(INDEX(fx_budget,MATCH($N30,fx_ccy,0)),"")))),"No exchange rate for "&$N30&" (the room-rate currency). Add one on the FX sheet.",IF(NOT(ISNUMBER($G30)),"Enter a quoted fare or search for one using the Google Flights link!",IF($M30<>$N30,"Dual currency: meals in "&$M30&", room rate in "&$N30&". Converted separately.","")))))))))
... E40: =IF(D40<>"",_xlfn.XLOOKUP(MONTH(D40),Table2[Month Number],month_list,"",0,1),"") | I40: =IF(D40<>0,SUM(D40,G40),"") | L40: =IF($C40="","",IFERROR(INDEX(rates_tbl,MATCH($C40,loc_list,0),3),"")) | M40: =IF($C40="","",IFERROR(INDEX(rates_tbl,MATCH($C40,loc_list,0),4),"")) | N40: =IF($C40="","",IFERROR(INDEX(rates_tbl,MATCH($C40,loc_list,0),5),"")) | O40: =IF(NOT(AND($C40<>"",ISNUMBER(MATCH($C40,loc_list,0)),ISNUMBER($F40),$F40>0,OR(N($G40)>0,$H40<>""))),"",IF(N($G40)<=0,0,IF(NOT(ISNUMBER(IFERROR(INDEX(fx_budget,MATCH($N40,fx_ccy,0)),""))),"",N($G40)*INDEX(rates_tbl,MATCH($C40,loc_list,0),10)*$F40/IFERROR(INDEX(fx_budget,MATCH($N40,fx_ccy,0)),"")))) | P40: =IF(NOT(AND($C40<>"",ISNUMBER(MATCH($C40,loc_list,0)),ISNUMBER($F40),$F40>0,OR(N($G40)>0,$H40<>""))),"",IF(NOT(ISNUMBER(IFERROR(INDEX(fx_budget,MATCH($M40,fx_ccy,0)),""))),"",(N($G40)*INDEX(rates_tbl,MATCH($C40,loc_list,0),9)+IF($H40="Over 10 hours",INDEX(rates_tbl,MATCH($C40,loc_list,0),8),IF($H40="Over 5 hours",INDEX(rates_tbl,MATCH($C40,loc_list,0),7),0)))*$F40/IFERROR(INDEX(fx_budget,MATCH($M40,fx_ccy,0)),""))) | Q40: =IF(LEN(R40)-LEN(SUBSTITUTE(R40,"+",""))>=4, HYPERLINK(R40, _xlfn.TEXTJOIN(" ",TRUE,"Click for Google Flights Prices for",IF(B40="","London",IFERROR(_xlfn.TEXTBEFORE(B40,", "),B40)),"to",IFERROR(_xlfn.TEXTBEFORE(C40,", "),C40))), "") | R40: =HYPERLINK((IF(OR(C40="",D40="",I40=""),"","https://www.google.com/search?q=flights+from+"&SUBSTITUTE(IF(B40="","London, UK",B40)," ","+")&"+to+"&SUBSTITUTE(C40," ","+")&"+"&TEXT(D40,"d+mmmm+yyyy")&"+to+"&TEXT(I40,"d+mmmm+yyyy")))) | S40: =IF(J40<>0,PRODUCT(J40,F40),"") | T40: =IF(NOT(AND($C40<>"",ISNUMBER(MATCH($C40,loc_list,0)),ISNUMBER($F40),$F40>0,OR(N($G40)>0,$H40<>""))),"",N($K40)*$F40) | U40: =IF(NOT(AND($C40<>"",ISNUMBER(MATCH($C40,loc_list,0)),ISNUMBER($F40),$F40>0,OR(N($G40)>0,$H40<>""))),"",IF(COUNT($O40:$T40)<4,"",SUM($O40:$T40))) | V40: =IF($C40="","",IF(NOT(ISNUMBER(MATCH($C40,loc_list,0))),"Destination not recognised. Choose one from the dropdown.",IF(NOT(ISNUMBER($F40)),"Enter the number of travellers.",IF($F40<=0,"Travellers must be 1 or more.",IF(AND(N($G40)<=0,$H40=""),"Enter the number of nights. For a day of travel with no overnight, set the final-day column — choose None if no subsistence is claimed.",IF(NOT(ISNUMBER(IFERROR(INDEX(fx_budget,MATCH($M40,fx_ccy,0)),""))),"No exchange rate for "&$M40&IF($M40=$N40,""," (the meals currency)")&". Add one on the FX sheet.",IF(AND(N($N40)>0,NOT(ISNUMBER(IFERROR(INDEX(fx_budget,MATCH($N40,fx_ccy,0)),"")))),"No exchange rate for "&$N40&" (the room-rate currency). Add one on the FX sheet.",IF(NOT(ISNUMBER($G40)),"Enter a quoted fare or search for one using the Google Flights link!",IF($M40<>$N40,"Dual currency: meals in "&$M40&", room rate in "&$N40&". Converted separately.","")))))))))
A42: HMRC calculates the reimbursement amount for an overnight stay as: the costs of a room (hotel etc.) PLUS the 24 hour rate. Breakfast, lunch and dinner are taken as covered by the 24 hour rate. Use the final-day column only for a day of travel with no overnight stay (these rates don't include a room)
A43: Final Note: Although widely used as a reference point. HMRC scale rates do not represent a minimum standard for all employers or funders to abide by (they represent the maximum reimbursable amount that one can claim without receipts for tax purposes). Airfare, visas, insurance and ground transport are estimates or your own inputs. HMRC does not publish rates for any of these elements.

Sheet Rates
A1: Reference data - do not edit. Static tables, each with the date it was captured.
A2: Source: https://www.gov.uk/guidance/expenses-rates-for-employees-travelling-outside-the-uk
A3: HMRC overseas scale rates - 285 locations, 171 countries. Captured 26 August 2026. Maximum reimbursable without receipts for tax purposes; an employer or funder policy may be lower.
A4: Location | B4: Country | C4: Haul band | D4: Meals currency | E4: Room currency | F4: Dual currency | G4: Over 5 hours | H4: Over 10 hours | I4: 24 hour rate | J4: Room rate | K4: Breakfast | L4: Lunch | M4: Dinner | N4: Other | O4: Drinks | P4: Hotel to office | Q4: Total residual
A5: Abu Dhabi, United Arab Emirates | B5: United Arab Emirates | C5: 3 | D5: AED | E5: AED | G5: 98 | H5: 242.5 | I5: 373.5 | J5: 637 | K5: 85.5 | L5: 82 | M5: 128.5 | N5: 15 | O5: 32 | P5: 30.5 | Q5: 373.5
A6: Abuja, Nigeria | B6: Nigeria | C6: 3 | D6: NGN | E6: NGN | G6: 7644.5 | H6: 17836.5 | I6: 27529 | J6: 79560 | K6: 7233 | L6: 6986.5 | M6: 9534.5 | N6: 1068.5 | O6: 1315.5 | P6: 1391 | Q6: 27529
A7: Accra, Ghana | B7: Ghana | C7: 3 | D7: GHS | E7: USD | F7: Y | G7: 42.5 | H7: 127.5 | I7: 149.5 | J7: 200 | K7: 0 | L7: 38 | M7: 80.5 | N7: 5.5 | O7: 9 | P7: 16.5 | Q7: 149.5
A8: Addis Ababa, Ethiopia | B8: Ethiopia | C8: 3 | D8: ETB | E8: USD | F8: Y | G8: 677 | H8: 1548.5 | I8: 1719.5 | J8: 274.5 | K8: 0 | L8: 610 | M8: 805 | N8: 0 | O8: 133.5 | P8: 171 | Q8: 1719.5
A9: Adelaide, Australia | B9: Australia | C9: 6 | D9: AUD | E9: AUD | G9: 57 | H9: 133 | I9: 176 | J9: 262.5 | K9: 33.5 | L9: 51 | M9: 70.5 | N9: 0 | O9: 11.5 | P9: 9.5 | Q9: 176
A10: Agadir, Morocco | B10: Morocco | C10: 2 | D10: MAD | E10: MAD | G10: 209.5 | H10: 559.5 | I10: 648.5 | J10: 1304 | K10: 0 | L10: 183 | M10: 324 | N10: 37 | O10: 52.5 | P10: 52 | Q10: 648.5
A11: Ahmedabad, India | B11: India | C11: 3 | D11: INR | E11: INR | G11: 1016 | H11: 2212.5 | I11: 2753 | J11: 9420.5 | K11: 0 | L11: 893 | M11: 1073.5 | N11: 0 | O11: 246 | P11: 540.5 | Q11: 2753
A12: Al Khobar, Saudi Arabia | B12: Saudi Arabia | C12: 3 | D12: SAR | E12: SAR | G12: 114 | H12: 257 | I12: 374.5 | J12: 532.5 | K12: 78.5 | L12: 99.5 | M12: 129 | N12: 11.5 | O12: 28.5 | P12: 27.5 | Q12: 374.5
A13: Alexandria, Egypt | B13: Egypt | C13: 2 | D13: EGP | E13: EGP | G13: 154 | H13: 370.5 | I13: 445 | J13: 1118 | K13: 0 | L13: 138 | M13: 201 | N13: 0 | O13: 31.5 | P13: 74.5 | Q13: 445
A14: Algiers, Algeria | B14: Algeria | C14: 2 | D14: DZD | E14: DZD | G14: 2641.5 | H14: 7537.5 | I14: 9973 | J14: 23383.5 | K14: 1804 | L14: 2383.5 | M14: 4638.5 | N14: 0 | O14: 515.5 | P14: 631.5 | Q14: 9973
A15: Almaty, Kazakhstan | B15: Kazakhstan | C15: 3 | D15: KZT | E15: KZT | G15: 9460 | H15: 23650 | I15: 25036 | J15: 43626.5 | K15: 0 | L15: 8437 | M15: 13077 | N15: 0 | O15: 2226 | P15: 1386 | Q15: 25036
A16: Amman, Jordan | B16: Jordan | C16: 2 | D16: JOD | E16: JOD | G16: 30.5 | H16: 73.5 | I16: 84.5 | J16: 131.5 | K16: 0 | L16: 25.5 | M16: 38 | N16: 3.5 | O16: 10 | P16: 7.5 | Q16: 84.5
A17: Amsterdam, Netherlands | B17: Netherlands | C17: 1 | D17: EUR | E17: EUR | G17: 25 | H17: 65 | I17: 72 | J17: 150 | K17: 0 | L17: 22 | M17: 37.5 | N17: 0 | O17: 5.5 | P17: 7 | Q17: 72
A18: Anguilla, Anguilla | B18: Anguilla | C18: 4 | D18: USD | E18: USD | G18: 39 | H18: 122 | I18: 150.5 | J18: 235.5 | K18: 15.5 | L18: 31 | M18: 75.5 | N18: 4 | O18: 15.5 | P18: 9 | Q18: 150.5
A19: Ankara, Turkey | B19: Turkey | C19: 2 | D19: TRY | E19: EUR | F19: Y | G19: 93 | H19: 223.5 | I19: 239.5 | J19: 160 | K19: 0 | L19: 79.5 | M19: 117.5 | N19: 0 | O19: 26.5 | P19: 16 | Q19: 239.5
A20: Antananarivo, Madagascar | B20: Madagascar | C20: 4 | D20: MGA | E20: MGA | G20: 56012 | H20: 146819.5 | I20: 219663.5 | J20: 471687.5 | K20: 45828 | L20: 50920 | M20: 85715.5 | N20: 6789.5 | O20: 10184 | P20: 20226.5 | Q20: 219663.5
A21: Apia, Samoa | B21: Samoa | C21: 6 | D21: WST | E21: USD | F21: Y | G21: 63 | H21: 147 | I21: 205.5 | J21: 133 | K21: 28 | L21: 57 | M21: 78.5 | N21: 11.5 | O21: 11.5 | P21: 19 | Q21: 205.5
A22: Aqaba, Jordan | B22: Jordan | C22: 2 | D22: JOD | E22: JOD | G22: 26 | H22: 58 | I22: 65.5 | J22: 107 | K22: 0 | L22: 22.5 | M22: 29 | N22: 0 | O22: 6.5 | P22: 7.5 | Q22: 65.5
A23: Ashgabat, Turkmenistan | B23: Turkmenistan | C23: 3 | D23: TMT | E23: USD | F23: Y | G23: 45 | H23: 117.5 | I23: 143 | J23: 72.5 | K23: 0 | L23: 40 | M23: 67.5 | N23: 4 | O23: 10 | P23: 21.5 | Q23: 143
A24: Asmara, Eritrea | B24: Eritrea | C24: 3 | D24: ERN | E24: USD | F24: Y | G24: 363 | H24: 1084 | I24: 1295 | J24: 133.5 | K24: 0 | L24: 350 | M24: 708.5 | N24: 0 | O24: 25.5 | P24: 211 | Q24: 1295
A25: Astana, Kazakhstan | B25: Kazakhstan | C25: 3 | D25: USD | E25: USD | G25: 43 | H25: 120 | I25: 131 | J25: 263 | K25: 0 | L25: 35.5 | M25: 70 | N25: 4 | O25: 14.5 | P25: 7 | Q25: 131
A26: Athens, Greece | B26: Greece | C26: 1 | D26: EUR | E26: EUR | G26: 28.5 | H26: 62.5 | I26: 67.5 | J26: 153.5 | K26: 0 | L26: 25 | M26: 30.5 | N26: 0 | O26: 7 | P26: 5 | Q26: 67.5
A27: Atlanta, United States of America | B27: United States of America | C27: 4 | D27: USD | E27: USD | G27: 30.5 | H27: 75 | I27: 98.5 | J27: 127 | K27: 15 | L27: 27.5 | M27: 42 | N27: 0 | O27: 5.5 | P27: 8.5 | Q27: 98.5
A28: Atyrau, Kazakhstan | B28: Kazakhstan | C28: 3 | D28: KZT | E28: KZT | G28: 5234 | H28: 14591 | I28: 16227.5 | J28: 27595 | K28: 0 | L28: 4599.5 | M28: 8722.5 | N28: 634.5 | O28: 1269 | P28: 1002 | Q28: 16227.5
A29: Auckland, New Zealand | B29: New Zealand | C29: 6 | D29: NZD | E29: NZD | G29: 54 | H29: 133 | I29: 180.5 | J29: 205.5 | K29: 36 | L29: 48 | M29: 73.5 | N29: 0 | O29: 11.5 | P29: 11.5 | Q29: 180.5 | S29: Final day options
A30: Azores, Portugal | B30: Portugal | C30: 1 | D30: EUR | E30: EUR | G30: 16.5 | H30: 44.5 | I30: 49.5 | J30: 107 | K30: 0 | L30: 14 | M30: 26 | N30: 0 | O30: 4.5 | P30: 5 | Q30: 49.5 | S30: None
A31: Bahrain, Bahrain | B31: Bahrain | C31: 3 | D31: BHD | E31: BHD | G31: 17 | H31: 40.5 | I31: 56.5 | J31: 115.5 | K31: 13 | L31: 14.5 | M31: 21.5 | N31: 0 | O31: 4.5 | P31: 3 | Q31: 56.5 | S31: Over 5 hours
A32: Baku, Azerbaijan | B32: Azerbaijan | C32: 2 | D32: AZN | E32: AZN | G32: 31 | H32: 71 | I32: 85.5 | J32: 195 | K32: 0 | L32: 24.5 | M32: 34 | N32: 6 | O32: 12.5 | P32: 8.5 | Q32: 85.5 | S32: Over 10 hours
A33: Bamako, Mali | B33: Mali | C33: 3 | D33: XOF | E33: XOF | G33: 12241 | H33: 33940 | I33: 48629.5 | J33: 61759.5 | K33: 9459 | L33: 10571.5 | M33: 20030 | N33: 2003 | O33: 3338.5 | P33: 3227.5 | Q33: 48629.5
A34: Bandar Seri Begawan, Brunei | B34: Brunei | C34: 5 | D34: BND | E34: BND | G34: 37 | H34: 121.5 | I34: 134.5 | J34: 203 | K34: 0 | L34: 31 | M34: 79 | N34: 0 | O34: 11.5 | P34: 13 | Q34: 134.5
A35: Bangalore, India | B35: India | C35: 3 | D35: INR | E35: INR | G35: 1685.5 | H35: 3746 | I35: 4629.5 | J35: 16809.5 | K35: 0 | L35: 1406 | M35: 1781 | N35: 369 | O35: 559 | P35: 514.5 | Q35: 4629.5
A36: Bangkok, Thailand | B36: Thailand | C36: 4 | D36: THB | E36: THB | G36: 1048 | H36: 2565.5 | I36: 2965 | J36: 5442.5 | K36: 0 | L36: 884.5 | M36: 1354 | N36: 163.5 | O36: 327 | P36: 236 | Q36: 2965
A37: Banjul, Gambia | B37: Gambia | C37: 3 | D37: GMD | E37: EUR | F37: Y | G37: 531.5 | H37: 1485.5 | I37: 1860.5 | J37: 90 | K37: 0 | L37: 480.5 | M37: 903 | N37: 102 | O37: 102 | P37: 273 | Q37: 1860.5
A38: Barcelona, Spain | B38: Spain | C38: 1 | D38: EUR | E38: EUR | G38: 28 | H38: 76 | I38: 101.5 | J38: 176 | K38: 20 | L38: 24.5 | M38: 44.5 | N38: 0 | O38: 7 | P38: 5.5 | Q38: 101.5
A39: Basseterre, St Kitts and Nevis | B39: St Kitts and Nevis | C39: 4 | D39: XCD | E39: USD | F39: Y | G39: 94 | H39: 187 | I39: 250 | J39: 179 | K39: 41 | L39: 89.5 | M39: 88.5 | N39: 0 | O39: 9 | P39: 22 | Q39: 250
A40: Beijing, China | B40: China | C40: 4 | D40: CNY | E40: CNY | G40: 232 | H40: 563 | I40: 605.5 | J40: 1344.5 | K40: 0 | L40: 205 | M40: 304 | N40: 0 | O40: 54 | P40: 42.5 | Q40: 605.5
A41: Belgrade, Serbia | B41: Serbia | C41: 1 | D41: RSD | E41: EUR | F41: Y | G41: 2883.5 | H41: 7530.5 | I41: 8090.5 | J41: 190.5 | K41: 0 | L41: 2575.5 | M41: 4399 | N41: 0 | O41: 616 | P41: 560 | Q41: 8090.5
A42: Belize City, Belize | B42: Belize | C42: 4 | D42: BZD | E42: USD | F42: Y | G42: 41.5 | H42: 125 | I42: 167 | J42: 141 | K42: 24.5 | L42: 37.5 | M42: 80 | N42: 0 | O42: 7.5 | P42: 17.5 | Q42: 167
A43: Belmopan, Belize | B43: Belize | C43: 4 | D43: BZD | E43: BZD | G43: 20.5 | H43: 54.5 | I43: 85 | J43: 150.5 | K43: 13 | L43: 19 | M43: 33 | N43: 0 | O43: 2.5 | P43: 17.5 | Q43: 85
A44: Bergen, Norway | B44: Norway | C44: 1 | D44: NOK | E44: NOK | G44: 422 | H44: 1134.5 | I44: 1176 | J44: 1388.5 | K44: 0 | L44: 381.5 | M44: 672 | N44: 0 | O44: 81 | P44: 41.5 | Q44: 1176
A45: Berlin, Germany | B45: Germany | C45: 1 | D45: EUR | E45: EUR | G45: 22 | H45: 65.5 | I45: 72 | J45: 167.5 | K45: 0 | L45: 18.5 | M45: 40.5 | N45: 0 | O45: 6.5 | P45: 6.5 | Q45: 72
A46: Berne, Switzerland | B46: Switzerland | C46: 1 | D46: CHF | E46: CHF | G46: 47 | H46: 109.5 | I46: 118 | J46: 184.5 | K46: 0 | L46: 43 | M46: 59 | N46: 0 | O46: 7.5 | P46: 8.5 | Q46: 118
A47: Bishkek, Kyrgyzstan | B47: Kyrgyzstan | C47: 3 | D47: USD | E47: USD | G47: 28 | H47: 75.5 | I47: 82.5 | J47: 161.5 | K47: 0 | L47: 24.5 | M47: 44 | N47: 0 | O47: 7 | P47: 7 | Q47: 82.5
A48: Bogota, Colombia | B48: Colombia | C48: 4 | D48: COP | E48: COP | G48: 49827 | H48: 118240.5 | I48: 140054 | J48: 412244 | K48: 0 | L48: 45537.5 | M48: 64124.5 | N48: 5505 | O48: 8578.5 | P48: 16308.5 | Q48: 140054
A49: Bologna, Florence, Genoa, Milan, Turin and Venice, Italy | B49: Italy | C49: 1 | D49: EUR | E49: EUR | G49: 34 | H49: 84.5 | I49: 96.5 | J49: 230 | K49: 0 | L49: 31.5 | M49: 48 | N49: 6.5 | O49: 5 | P49: 5.5 | Q49: 96.5
A50: Bordeaux, France | B50: France | C50: 1 | D50: EUR | E50: EUR | G50: 44 | H50: 114 | I50: 135 | J50: 120 | K50: 15.5 | L50: 40.5 | M50: 66.5 | N50: 0 | O50: 7 | P50: 5.5 | Q50: 135
A51: Boston, United States of America | B51: United States of America | C51: 4 | D51: USD | E51: USD | G51: 32 | H51: 76.5 | I51: 97.5 | J51: 239 | K51: 13 | L51: 29 | M51: 41.5 | N51: 0 | O51: 6 | P51: 8 | Q51: 97.5
A52: Brasilia, Brazil | B52: Brazil | C52: 5 | D52: BRL | E52: BRL | G52: 61 | H52: 155 | I52: 177.5 | J52: 442.5 | K52: 0 | L52: 55 | M52: 88 | N52: 4.5 | O52: 12 | P52: 18 | Q52: 177.5
A53: Bratislava, Slovakia | B53: Slovakia | C53: 1 | D53: EUR | E53: EUR | G53: 19 | H53: 48 | I53: 53.5 | J53: 110.5 | K53: 0 | L53: 16 | M53: 26.5 | N53: 0 | O53: 5.5 | P53: 5.5 | Q53: 53.5
A54: Bridgetown, Barbados | B54: Barbados | C54: 4 | D54: BBD | E54: USD | F54: Y | G54: 58 | H54: 179 | I54: 199.5 | J54: 170.5 | K54: 0 | L54: 51.5 | M54: 114.5 | N54: 0 | O54: 13 | P54: 20.5 | Q54: 199.5
A55: Brisbane, Australia | B55: Australia | C55: 6 | D55: AUD | E55: AUD | G55: 49.5 | H55: 128.5 | I55: 156.5 | J55: 291 | K55: 18.5 | L55: 44 | M55: 73.5 | N55: 0 | O55: 11 | P55: 9.5 | Q55: 156.5
A56: Brussels, Belgium | B56: Belgium | C56: 1 | D56: EUR | E56: EUR | G56: 27 | H56: 71 | I56: 76 | J56: 165.5 | K56: 0 | L56: 23 | M56: 40 | N56: 0 | O56: 8 | P56: 5 | Q56: 76
A57: Bucharest, Romania | B57: Romania | C57: 1 | D57: RON | E57: EUR | F57: Y | G57: 96 | H57: 218.5 | I57: 243 | J57: 147 | K57: 0 | L57: 86.5 | M57: 113.5 | N57: 0 | O57: 18.5 | P57: 24.5 | Q57: 243
A58: Budapest, Hungary | B58: Hungary | C58: 1 | D58: HUF | E58: EUR | F58: Y | G58: 6092 | H58: 14512.5 | I58: 16001 | J58: 137 | K58: 0 | L58: 5136 | M58: 7465 | N58: 0 | O58: 1911.5 | P58: 1488.5 | Q58: 16001
A59: Buenos Aires, Argentina | B59: Argentina | C59: 5 | D59: ARS | E59: USD | F59: Y | G59: 147 | H59: 346.5 | I59: 391 | J59: 215.5 | K59: 0 | L59: 131.5 | M59: 184.5 | N59: 0 | O59: 30.5 | P59: 44.5 | Q59: 391
A60: Bujumbura, Burundi | B60: Burundi | C60: 3 | D60: BIF | E60: USD | F60: Y | G60: 23893 | H60: 64741.5 | I60: 80502 | J60: 111.5 | K60: 0 | L60: 21580.5 | M60: 38536.5 | N60: 3854 | O60: 4624.5 | P60: 11906.5 | Q60: 80502
A61: Cairo, Egypt | B61: Egypt | C61: 2 | D61: EGP | E61: USD | F61: Y | G61: 279 | H61: 702 | I61: 761 | J61: 181.5 | K61: 0 | L61: 247 | M61: 391.5 | N61: 0 | O61: 63.5 | P61: 59 | Q61: 761
A62: Calgary, Alberta, Canada | B62: Canada | C62: 4 | D62: CAD | E62: CAD | G62: 61.5 | H62: 142 | I62: 179.5 | J62: 156 | K62: 27.5 | L62: 56.5 | M62: 75.5 | N62: 0 | O62: 10 | P62: 10 | Q62: 179.5
A63: Cali, Colombia | B63: Colombia | C63: 4 | D63: COP | E63: COP | G63: 55045.5 | H63: 140116 | I63: 161005.5 | J63: 288446 | K63: 0 | L63: 51471 | M63: 81496 | N63: 5004.5 | O63: 7149 | P63: 15885 | Q63: 161005.5
A64: Canberra, Australia | B64: Australia | C64: 6 | D64: AUD | E64: AUD | G64: 55 | H64: 132.5 | I64: 164.5 | J64: 238.5 | K64: 22 | L64: 50 | M64: 73 | N64: 0 | O64: 9.5 | P64: 10 | Q64: 164.5
A65: Cape Town, South Africa | B65: South Africa | C65: 4 | D65: ZAR | E65: ZAR | G65: 147 | H65: 388.5 | I65: 456 | J65: 2051.5 | K65: 0 | L65: 130 | M65: 224.5 | N65: 0 | O65: 34 | P65: 67.5 | Q65: 456
A66: Caracas, Venezuela | B66: Venezuela | C66: 4 | D66: VES | E66: VES | G66: 482.5 | H66: 1106.5 | I66: 1247 | J66: 3567 | K66: 0 | L66: 443.5 | M66: 585 | N66: 88 | O66: 78 | P66: 52.5 | Q66: 1247
A67: Cartagena, Colombia | B67: Colombia | C67: 4 | D67: COP | E67: COP | G67: 69899 | H67: 182236.5 | I67: 206034.5 | J67: 597997.5 | K67: 0 | L67: 63658 | M67: 106096.5 | N67: 7489.5 | O67: 12482 | P67: 16308.5 | Q67: 206034.5
A68: Casablanca, Morocco | B68: Morocco | C68: 2 | D68: MAD | E68: MAD | G68: 365.5 | H68: 888 | I68: 1305.5 | J68: 2036 | K68: 272 | L68: 318.5 | M68: 475.5 | N68: 94 | O68: 94 | P68: 51.5 | Q68: 1305.5
A69: Castries, St Lucia | B69: St Lucia | C69: 4 | D69: XCD | E69: XCD | G69: 52 | H69: 154 | I69: 216.5 | J69: 357 | K69: 37 | L69: 46.5 | M69: 96.5 | N69: 0 | O69: 11 | P69: 25.5 | Q69: 216.5
A70: Cebu, Philippines | B70: Philippines | C70: 5 | D70: PHP | E70: USD | F70: Y | G70: 1036.5 | H70: 2472.5 | I70: 3033 | J70: 129.5 | K70: 0 | L70: 880.5 | M70: 1280 | N70: 149.5 | O70: 312 | P70: 411 | Q70: 3033
A71: Chandigarh, India | B71: India | C71: 3 | D71: INR | E71: INR | G71: 1751 | H71: 3917 | I71: 5364.5 | J71: 10485.5 | K71: 922 | L71: 1520.5 | M71: 1935.5 | N71: 0 | O71: 461 | P71: 525.5 | Q71: 5364.5
A72: Chennai (Madras), India | B72: India | C72: 3 | D72: INR | E72: INR | G72: 2203.5 | H72: 5097.5 | I72: 5917 | J72: 14540.5 | K72: 0 | L72: 1843.5 | M72: 2534.5 | N72: 305 | O72: 719.5 | P72: 514.5 | Q72: 5917
A73: Chicago, United States of America | B73: United States of America | C73: 4 | D73: USD | E73: USD | G73: 34.5 | H73: 84 | I73: 112.5 | J73: 198 | K73: 21 | L73: 30 | M73: 45 | N73: 0 | O73: 9 | P73: 7.5 | Q73: 112.5
A74: Chisinau, Moldova | B74: Moldova | C74: 1 | D74: MDL | E74: EUR | F74: Y | G74: 432 | H74: 989.5 | I74: 1165 | J74: 130.5 | K74: 0 | L74: 352 | M74: 478 | N74: 80 | O74: 159.5 | P74: 95.5 | Q74: 1165
A75: Chongqing, China | B75: China | C75: 4 | D75: CNY | E75: CNY | G75: 232 | H75: 563 | I75: 605.5 | J75: 582.5 | K75: 0 | L75: 205 | M75: 304 | N75: 0 | O75: 54 | P75: 42.5 | Q75: 605.5
A76: Christchurch, New Zealand | B76: New Zealand | C76: 6 | D76: NZD | E76: NZD | G76: 43 | H76: 109 | I76: 147.5 | J76: 110 | K76: 27 | L76: 39 | M76: 62 | N76: 0 | O76: 8 | P76: 11.5 | Q76: 147.5
A77: Cochabamba, Bolivia | B77: Bolivia | C77: 5 | D77: BOB | E77: USD | F77: Y | G77: 77 | H77: 190 | I77: 272.5 | J77: 56 | K77: 0 | L77: 70.5 | M77: 106.5 | N77: 9.5 | O77: 13 | P77: 73 | Q77: 272.5
A78: Colombo, Sri Lanka | B78: Sri Lanka | C78: 4 | D78: LKR | E78: USD | F78: Y | G78: 1474 | H78: 3444 | I78: 4295 | J78: 123.5 | K78: 0 | L78: 1271.5 | M78: 1768 | N78: 253 | O78: 404.5 | P78: 598 | Q78: 4295
A79: Conakry, Guinea | B79: Guinea | C79: 3 | D79: GNF | E79: USD | F79: Y | G79: 144877 | H79: 338725.5 | I79: 443812.5 | J79: 100.5 | K79: 0 | L79: 128552.5 | M79: 177524.5 | N79: 20405.5 | O79: 32648.5 | P79: 84681.5 | Q79: 443812.5
A80: Copenhagen, Denmark | B80: Denmark | C80: 1 | D80: DKK | E80: DKK | G80: 235 | H80: 683 | I80: 895.5 | J80: 1200 | K80: 164 | L80: 213 | M80: 426 | N80: 0 | O80: 44 | P80: 48.5 | Q80: 895.5
A81: Corfu, Greece | B81: Greece | C81: 1 | D81: EUR | E81: EUR | G81: 30.5 | H81: 76 | I81: 82.5 | J81: 92.5 | K81: 0 | L81: 28 | M81: 43 | N81: 0 | O81: 5 | P81: 6.5 | Q81: 82.5
A82: Crete, Greece | B82: Greece | C82: 1 | D82: EUR | E82: EUR | G82: 23 | H82: 54 | I82: 60 | J82: 83 | K82: 0 | L82: 19.5 | M82: 27.5 | N82: 0 | O82: 7 | P82: 6 | Q82: 60
A83: Dakar, Senegal | B83: Senegal | C83: 3 | D83: XOF | E83: XOF | G83: 12200.5 | H83: 32888.5 | I83: 48650.5 | J83: 70019.5 | K83: 11670 | L83: 10609 | M83: 19096.5 | N83: 0 | O83: 3183 | P83: 4092 | Q83: 48650.5
A84: Dar Es Salaam, Tanzania | B84: Tanzania | C84: 3 | D84: TZS | E84: USD | F84: Y | G84: 43888.5 | H84: 114696.5 | I84: 130163.5 | J84: 179 | K84: 0 | L84: 40951.5 | M84: 67871.5 | N84: 0 | O84: 5873.5 | P84: 15467 | Q84: 130163.5
A85: Darwin, Australia | B85: Australia | C85: 6 | D85: AUD | E85: AUD | G85: 45.5 | H85: 118 | I85: 157.5 | J85: 230 | K85: 30 | L85: 40.5 | M85: 68 | N85: 0 | O85: 9.5 | P85: 9.5 | Q85: 157.5
A86: Dhaka, Bangladesh | B86: Bangladesh | C86: 3 | D86: BDT | E86: USD | F86: Y | G86: 1132 | H86: 2962.5 | I86: 3753.5 | J86: 139 | K86: 0 | L86: 968.5 | M86: 1667.5 | N86: 0 | O86: 326.5 | P86: 791 | Q86: 3753.5
A87: Djibouti, Djibouti | B87: Djibouti | C87: 3 | D87: DJF | E87: DJF | G87: 4277.5 | H87: 10218 | I87: 11753 | J87: 35640.5 | K87: 0 | L87: 3861.5 | M87: 5524.5 | N87: 0 | O87: 832 | P87: 1535 | Q87: 11753
A88: Doha, Qatar | B88: Qatar | C88: 3 | D88: QAR | E88: QAR | G88: 227 | H88: 524.5 | I88: 617.5 | J88: 711 | K88: 45.5 | L88: 197 | M88: 268 | N88: 15.5 | O88: 59.5 | P88: 32 | Q88: 617.5
A89: Douala, Cameroon | B89: Cameroon | C89: 3 | D89: XAF | E89: XAF | G89: 19210 | H89: 51269.5 | I89: 69805.5 | J89: 88871 | K89: 12055.5 | L89: 16692.5 | M89: 29542 | N89: 2777.5 | O89: 5035 | P89: 3703 | Q89: 69805.5
A90: Dubai, United Arab Emirates | B90: United Arab Emirates | C90: 3 | D90: AED | E90: AED | G90: 161 | H90: 432 | I90: 614.5 | J90: 949.5 | K90: 127 | L90: 139.5 | M90: 250 | N90: 23.5 | O90: 42.5 | P90: 32 | Q90: 614.5
A91: Dublin, Ireland | B91: Ireland | C91: 1 | D91: EUR | E91: EUR | G91: 38.5 | H91: 94 | I91: 99 | J91: 149 | K91: 0 | L91: 34 | M91: 51.5 | N91: 0 | O91: 8.5 | P91: 5 | Q91: 99
A92: Dubrovnik, Croatia | B92: Croatia | C92: 1 | D92: HRK | E92: EUR | F92: Y | G92: 241 | H92: 515 | I92: 552.5 | J92: 285.5 | K92: 0 | L92: 225.5 | M92: 258.5 | N92: 0 | O92: 31 | P92: 37.5 | Q92: 552.5
A93: Dushanbe, Tajikistan | B93: Tajikistan | C93: 3 | D93: TJS | E93: USD | F93: Y | G93: 247 | H93: 571 | I93: 601.5 | J93: 320.5 | K93: 0 | L93: 211.5 | M93: 289 | N93: 0 | O93: 70.5 | P93: 30.5 | Q93: 601.5
A94: Dusseldorf, Germany | B94: Germany | C94: 1 | D94: EUR | E94: EUR | G94: 23 | H94: 59 | I94: 66 | J94: 110.5 | K94: 0 | L94: 19.5 | M94: 33 | N94: 0 | O94: 6.5 | P94: 7 | Q94: 66
A95: Edmonton, Alberta, Canada | B95: Canada | C95: 4 | D95: CAD | E95: CAD | G95: 28.5 | H95: 72.5 | I95: 99.5 | J95: 132.5 | K95: 16.5 | L95: 25 | M95: 41 | N95: 0 | O95: 6.5 | P95: 10.5 | Q95: 99.5
A96: Ekaterinburg, Russia | B96: Russia | C96: 2 | D96: RUB | E96: RUB | G96: 963.5 | H96: 2301.5 | I96: 2559.5 | J96: 6639 | K96: 0 | L96: 852.5 | M96: 1227 | N96: 0 | O96: 222 | P96: 258 | Q96: 2559.5
A97: Fes, Morocco | B97: Morocco | C97: 2 | D97: MAD | E97: MAD | G97: 178 | H97: 502 | I97: 553.5 | J97: 1086.5 | K97: 0 | L97: 157 | M97: 303 | N97: 0 | O97: 42 | P97: 51.5 | Q97: 553.5
A98: Freetown, Sierra Leone | B98: Sierra Leone | C98: 3 | D98: SLE | E98: USD | F98: Y | G98: 140147.5 | H98: 333381 | I98: 375694 | J98: 145 | K98: 0 | L98: 129530 | M98: 182616.5 | N98: 8494 | O98: 21234.5 | P98: 33819 | Q98: 375694
A99: Funchal (Madeira), Portugal | B99: Portugal | C99: 1 | D99: EUR | E99: EUR | G99: 23.5 | H99: 60 | I99: 65 | J99: 103 | K99: 0 | L99: 20.5 | M99: 34 | N99: 0 | O99: 5.5 | P99: 5 | Q99: 65
A100: Gaborone, Botswana | B100: Botswana | C100: 4 | D100: BWP | E100: BWP | G100: 213.5 | H100: 503.5 | I100: 517.5 | J100: 853 | K100: 0 | L100: 196.5 | M100: 273 | N100: 0 | O100: 34 | P100: 68 | Q100: 571.5
...

Sheet FX
A1: Exchange rates
A2: One row per currency in the HMRC rate data. Sterling costs are calculated as foreign amount ÷ budget rate.
A4: The market rate is fetched by STOCKHISTORY for the rate date set on the Trip plan. It needs a Microsoft 365 subscription and doesn't extend to all currencies. Where it is blank, type a market rate by hand and record where you got it (this will have the appropriate buffer applied).
A6: Currency | B6: Pair | C6: Trips in plan | D6: Market rate - fetched | E6: Buffer | F6: Market rate - typed | G6: Budget rate - used | H6: Source of the typed rate | I6: Basis
A7: AED | B7: GBP:AED | C7: =SUMPRODUCT(--(('Trip plan'!$M$16:$M$40=$A7)+('Trip plan'!$N$16:$N$40=$A7)>0)) -> 0 | D7: =IF($C7=0,"",IFERROR(_xlfn.STOCKHISTORY("GBP:"&$A7,rate_date,rate_date,0,0,1),"")) | E7: =IF(OR($A7="EUR",$A7="USD"),buffer_major,buffer_other) -> 0.1 | G7: =IF(OR(ISNUMBER($F7),ISNUMBER($D7)),IF(ISNUMBER($F7),$F7,$D7)/(1+N($E7)),"") | I7: =IF($C7=0,"",IF(ISNUMBER($F7),"Market rate typed by hand"&IF($H7=""," - record your source in the previous column",": "&$H7)&IF(N($E7)=0,", with no buffer: these are treated as corporate-rate currencies.",", less a "&TEXT(N($E7),"0%")&" prudence buffer."),IF(ISNUMBER($D7),"LSEG via STOCKHISTORY"&IF(ISNUMBER(rate_date)," at "&TEXT(rate_date,"d mmm yyyy"),"")&IF(N($E7)=0,", with no buffer: these are treated as corporate-rate currencies.",", less a "&TEXT(N($E7),"0%")&" prudence buffer."),"NO RATE. STOCKHISTORY returned nothing - the pair may not be covered, the rate date may not have been a trading day, or there may be no Microsoft 365 subscription. Type a market rate in the previous column.")))
A8: ALL | B8: GBP:ALL | C8: =SUMPRODUCT(--(('Trip plan'!$M$16:$M$40=$A8)+('Trip plan'!$N$16:$N$40=$A8)>0)) -> 0 | D8: =IF($C8=0,"",IFERROR(_xlfn.STOCKHISTORY("GBP:"&$A8,rate_date,rate_date,0,0,1),"")) | E8: =IF(OR($A8="EUR",$A8="USD"),buffer_major,buffer_other) -> 0.1 | G8: =IF(OR(ISNUMBER($F8),ISNUMBER($D8)),IF(ISNUMBER($F8),$F8,$D8)/(1+N($E8)),"") | I8: =IF($C8=0,"",IF(ISNUMBER($F8),"Market rate typed by hand"&IF($H8=""," - record your source in the previous column",": "&$H8)&IF(N($E8)=0,", with no buffer: these are treated as corporate-rate currencies.",", less a "&TEXT(N($E8),"0%")&" prudence buffer."),IF(ISNUMBER($D8),"LSEG via STOCKHISTORY"&IF(ISNUMBER(rate_date)," at "&TEXT(rate_date,"d mmm yyyy"),"")&IF(N($E8)=0,", with no buffer: these are treated as corporate-rate currencies.",", less a "&TEXT(N($E8),"0%")&" prudence buffer."),"NO RATE. STOCKHISTORY returned nothing - the pair may not be covered, the rate date may not have been a trading day, or there may be no Microsoft 365 subscription. Type a market rate in the previous column.")))
A9: AMD | B9: GBP:AMD | C9: =SUMPRODUCT(--(('Trip plan'!$M$16:$M$40=$A9)+('Trip plan'!$N$16:$N$40=$A9)>0)) -> 0 | D9: =IF($C9=0,"",IFERROR(_xlfn.STOCKHISTORY("GBP:"&$A9,rate_date,rate_date,0,0,1),"")) | E9: =IF(OR($A9="EUR",$A9="USD"),buffer_major,buffer_other) -> 0.1 | G9: =IF(OR(ISNUMBER($F9),ISNUMBER($D9)),IF(ISNUMBER($F9),$F9,$D9)/(1+N($E9)),"") | I9: =IF($C9=0,"",IF(ISNUMBER($F9),"Market rate typed by hand"&IF($H9=""," - record your source in the previous column",": "&$H9)&IF(N($E9)=0,", with no buffer: these are treated as corporate-rate currencies.",", less a "&TEXT(N($E9),"0%")&" prudence buffer."),IF(ISNUMBER($D9),"LSEG via STOCKHISTORY"&IF(ISNUMBER(rate_date)," at "&TEXT(rate_date,"d mmm yyyy"),"")&IF(N($E9)=0,", with no buffer: these are treated as corporate-rate currencies.",", less a "&TEXT(N($E9),"0%")&" prudence buffer."),"NO RATE. STOCKHISTORY returned nothing - the pair may not be covered, the rate date may not have been a trading day, or there may be no Microsoft 365 subscription. Type a market rate in the previous column.")))
A10: AOA | B10: GBP:AOA | C10: =SUMPRODUCT(--(('Trip plan'!$M$16:$M$40=$A10)+('Trip plan'!$N$16:$N$40=$A10)>0)) -> 0 | D10: =IF($C10=0,"",IFERROR(_xlfn.STOCKHISTORY("GBP:"&$A10,rate_date,rate_date,0,0,1),"")) | E10: =IF(OR($A10="EUR",$A10="USD"),buffer_major,buffer_other) -> 0.1 | G10: =IF(OR(ISNUMBER($F10),ISNUMBER($D10)),IF(ISNUMBER($F10),$F10,$D10)/(1+N($E10)),"") | I10: =IF($C10=0,"",IF(ISNUMBER($F10),"Market rate typed by hand"&IF($H10=""," - record your source in the previous column",": "&$H10)&IF(N($E10)=0,", with no buffer: these are treated as corporate-rate currencies.",", less a "&TEXT(N($E10),"0%")&" prudence buffer."),IF(ISNUMBER($D10),"LSEG via STOCKHISTORY"&IF(ISNUMBER(rate_date)," at "&TEXT(rate_date,"d mmm yyyy"),"")&IF(N($E10)=0,", with no buffer: these are treated as corporate-rate currencies.",", less a "&TEXT(N($E10),"0%")&" prudence buffer."),"NO RATE. STOCKHISTORY returned nothing - the pair may not be covered, the rate date may not have been a trading day, or there may be no Microsoft 365 subscription. Type a market rate in the previous column.")))
A11: ARS | B11: GBP:ARS | C11: =SUMPRODUCT(--(('Trip plan'!$M$16:$M$40=$A11)+('Trip plan'!$N$16:$N$40=$A11)>0)) -> 0 | D11: =IF($C11=0,"",IFERROR(_xlfn.STOCKHISTORY("GBP:"&$A11,rate_date,rate_date,0,0,1),"")) | E11: =IF(OR($A11="EUR",$A11="USD"),buffer_major,buffer_other) -> 0.1 | G11: =IF(OR(ISNUMBER($F11),ISNUMBER($D11)),IF(ISNUMBER($F11),$F11,$D11)/(1+N($E11)),"") | I11: =IF($C11=0,"",IF(ISNUMBER($F11),"Market rate typed by hand"&IF($H11=""," - record your source in the previous column",": "&$H11)&IF(N($E11)=0,", with no buffer: these are treated as corporate-rate currencies.",", less a "&TEXT(N($E11),"0%")&" prudence buffer."),IF(ISNUMBER($D11),"LSEG via STOCKHISTORY"&IF(ISNUMBER(rate_date)," at "&TEXT(rate_date,"d mmm yyyy"),"")&IF(N($E11)=0,", with no buffer: these are treated as corporate-rate currencies.",", less a "&TEXT(N($E11),"0%")&" prudence buffer."),"NO RATE. STOCKHISTORY returned nothing - the pair may not be covered, the rate date may not have been a trading day, or there may be no Microsoft 365 subscription. Type a market rate in the previous column.")))
A12: AUD | B12: GBP:AUD | C12: =SUMPRODUCT(--(('Trip plan'!$M$16:$M$40=$A12)+('Trip plan'!$N$16:$N$40=$A12)>0)) -> 0 | D12: =IF($C12=0,"",IFERROR(_xlfn.STOCKHISTORY("GBP:"&$A12,rate_date,rate_date,0,0,1),"")) | E12: =IF(OR($A12="EUR",$A12="USD"),buffer_major,buffer_other) -> 0.1 | G12: =IF(OR(ISNUMBER($F12),ISNUMBER($D12)),IF(ISNUMBER($F12),$F12,$D12)/(1+N($E12)),"") | I12: =IF($C12=0,"",IF(ISNUMBER($F12),"Market rate typed by hand"&IF($H12=""," - record your source in the previous column",": "&$H12)&IF(N($E12)=0,", with no buffer: these are treated as corporate-rate currencies.",", less a "&TEXT(N($E12),"0%")&" prudence buffer."),IF(ISNUMBER($D12),"LSEG via STOCKHISTORY"&IF(ISNUMBER(rate_date)," at "&TEXT(rate_date,"d mmm yyyy"),"")&IF(N($E12)=0,", with no buffer: these are treated as corporate-rate currencies.",", less a "&TEXT(N($E12),"0%")&" prudence buffer."),"NO RATE. STOCKHISTORY returned nothing - the pair may not be covered, the rate date may not have been a trading day, or there may be no Microsoft 365 subscription. Type a market rate in the previous column.")))
A13: AZN | B13: GBP:AZN | C13: =SUMPRODUCT(--(('Trip plan'!$M$16:$M$40=$A13)+('Trip plan'!$N$16:$N$40=$A13)>0)) -> 0 | D13: =IF($C13=0,"",IFERROR(_xlfn.STOCKHISTORY("GBP:"&$A13,rate_date,rate_date,0,0,1),"")) | E13: =IF(OR($A13="EUR",$A13="USD"),buffer_major,buffer_other) -> 0.1 | G13: =IF(OR(ISNUMBER($F13),ISNUMBER($D13)),IF(ISNUMBER($F13),$F13,$D13)/(1+N($E13)),"") | I13: =IF($C13=0,"",IF(ISNUMBER($F13),"Market rate typed by hand"&IF($H13=""," - record your source in the previous column",": "&$H13)&IF(N($E13)=0,", with no buffer: these are treated as corporate-rate currencies.",", less a "&TEXT(N($E13),"0%")&" prudence buffer."),IF(ISNUMBER($D13),"LSEG via STOCKHISTORY"&IF(ISNUMBER(rate_date)," at "&TEXT(rate_date,"d mmm yyyy"),"")&IF(N($E13)=0,", with no buffer: these are treated as corporate-rate currencies.",", less a "&TEXT(N($E13),"0%")&" prudence buffer."),"NO RATE. STOCKHISTORY returned nothing - the pair may not be covered, the rate date may not have been a trading day, or there may be no Microsoft 365 subscription. Type a market rate in the previous column.")))
A14: BAM | B14: GBP:BAM | C14: =SUMPRODUCT(--(('Trip plan'!$M$16:$M$40=$A14)+('Trip plan'!$N$16:$N$40=$A14)>0)) -> 0 | D14: =IF($C14=0,"",IFERROR(_xlfn.STOCKHISTORY("GBP:"&$A14,rate_date,rate_date,0,0,1),"")) | E14: =IF(OR($A14="EUR",$A14="USD"),buffer_major,buffer_other) -> 0.1 | G14: =IF(OR(ISNUMBER($F14),ISNUMBER($D14)),IF(ISNUMBER($F14),$F14,$D14)/(1+N($E14)),"") | I14: =IF($C14=0,"",IF(ISNUMBER($F14),"Market rate typed by hand"&IF($H14=""," - record your source in the previous column",": "&$H14)&IF(N($E14)=0,", with no buffer: these are treated as corporate-rate currencies.",", less a "&TEXT(N($E14),"0%")&" prudence buffer."),IF(ISNUMBER($D14),"LSEG via STOCKHISTORY"&IF(ISNUMBER(rate_date)," at "&TEXT(rate_date,"d mmm yyyy"),"")&IF(N($E14)=0,", with no buffer: these are treated as corporate-rate currencies.",", less a "&TEXT(N($E14),"0%")&" prudence buffer."),"NO RATE. STOCKHISTORY returned nothing - the pair may not be covered, the rate date may not have been a trading day, or there may be no Microsoft 365 subscription. Type a market rate in the previous column.")))
A15: BBD | B15: GBP:BBD | C15: =SUMPRODUCT(--(('Trip plan'!$M$16:$M$40=$A15)+('Trip plan'!$N$16:$N$40=$A15)>0)) -> 0 | D15: =IF($C15=0,"",IFERROR(_xlfn.STOCKHISTORY("GBP:"&$A15,rate_date,rate_date,0,0,1),"")) | E15: =IF(OR($A15="EUR",$A15="USD"),buffer_major,buffer_other) -> 0.1 | G15: =IF(OR(ISNUMBER($F15),ISNUMBER($D15)),IF(ISNUMBER($F15),$F15,$D15)/(1+N($E15)),"") | I15: =IF($C15=0,"",IF(ISNUMBER($F15),"Market rate typed by hand"&IF($H15=""," - record your source in the previous column",": "&$H15)&IF(N($E15)=0,", with no buffer: these are treated as corporate-rate currencies.",", less a "&TEXT(N($E15),"0%")&" prudence buffer."),IF(ISNUMBER($D15),"LSEG via STOCKHISTORY"&IF(ISNUMBER(rate_date)," at "&TEXT(rate_date,"d mmm yyyy"),"")&IF(N($E15)=0,", with no buffer: these are treated as corporate-rate currencies.",", less a "&TEXT(N($E15),"0%")&" prudence buffer."),"NO RATE. STOCKHISTORY returned nothing - the pair may not be covered, the rate date may not have been a trading day, or there may be no Microsoft 365 subscription. Type a market rate in the previous column.")))
A16: BDT | B16: GBP:BDT | C16: =SUMPRODUCT(--(('Trip plan'!$M$16:$M$40=$A16)+('Trip plan'!$N$16:$N$40=$A16)>0)) -> 0 | D16: =IF($C16=0,"",IFERROR(_xlfn.STOCKHISTORY("GBP:"&$A16,rate_date,rate_date,0,0,1),"")) | E16: =IF(OR($A16="EUR",$A16="USD"),buffer_major,buffer_other) -> 0.1 | G16: =IF(OR(ISNUMBER($F16),ISNUMBER($D16)),IF(ISNUMBER($F16),$F16,$D16)/(1+N($E16)),"") | I16: =IF($C16=0,"",IF(ISNUMBER($F16),"Market rate typed by hand"&IF($H16=""," - record your source in the previous column",": "&$H16)&IF(N($E16)=0,", with no buffer: these are treated as corporate-rate currencies.",", less a "&TEXT(N($E16),"0%")&" prudence buffer."),IF(ISNUMBER($D16),"LSEG via STOCKHISTORY"&IF(ISNUMBER(rate_date)," at "&TEXT(rate_date,"d mmm yyyy"),"")&IF(N($E16)=0,", with no buffer: these are treated as corporate-rate currencies.",", less a "&TEXT(N($E16),"0%")&" prudence buffer."),"NO RATE. STOCKHISTORY returned nothing - the pair may not be covered, the rate date may not have been a trading day, or there may be no Microsoft 365 subscription. Type a market rate in the previous column.")))
A17: BGN | B17: GBP:BGN | C17: =SUMPRODUCT(--(('Trip plan'!$M$16:$M$40=$A17)+('Trip plan'!$N$16:$N$40=$A17)>0)) -> 0 | D17: =IF($C17=0,"",IFERROR(_xlfn.STOCKHISTORY("GBP:"&$A17,rate_date,rate_date,0,0,1),"")) | E17: =IF(OR($A17="EUR",$A17="USD"),buffer_major,buffer_other) -> 0.1 | G17: =IF(OR(ISNUMBER($F17),ISNUMBER($D17)),IF(ISNUMBER($F17),$F17,$D17)/(1+N($E17)),"") | I17: =IF($C17=0,"",IF(ISNUMBER($F17),"Market rate typed by hand"&IF($H17=""," - record your source in the previous column",": "&$H17)&IF(N($E17)=0,", with no buffer: these are treated as corporate-rate currencies.",", less a "&TEXT(N($E17),"0%")&" prudence buffer."),IF(ISNUMBER($D17),"LSEG via STOCKHISTORY"&IF(ISNUMBER(rate_date)," at "&TEXT(rate_date,"d mmm yyyy"),"")&IF(N($E17)=0,", with no buffer: these are treated as corporate-rate currencies.",", less a "&TEXT(N($E17),"0%")&" prudence buffer."),"NO RATE. STOCKHISTORY returned nothing - the pair may not be covered, the rate date may not have been a trading day, or there may be no Microsoft 365 subscription. Type a market rate in the previous column.")))
A18: BHD | B18: GBP:BHD | C18: =SUMPRODUCT(--(('Trip plan'!$M$16:$M$40=$A18)+('Trip plan'!$N$16:$N$40=$A18)>0)) -> 0 | D18: =IF($C18=0,"",IFERROR(_xlfn.STOCKHISTORY("GBP:"&$A18,rate_date,rate_date,0,0,1),"")) | E18: =IF(OR($A18="EUR",$A18="USD"),buffer_major,buffer_other) -> 0.1 | G18: =IF(OR(ISNUMBER($F18),ISNUMBER($D18)),IF(ISNUMBER($F18),$F18,$D18)/(1+N($E18)),"") | I18: =IF($C18=0,"",IF(ISNUMBER($F18),"Market rate typed by hand"&IF($H18=""," - record your source in the previous column",": "&$H18)&IF(N($E18)=0,", with no buffer: these are treated as corporate-rate currencies.",", less a "&TEXT(N($E18),"0%")&" prudence buffer."),IF(ISNUMBER($D18),"LSEG via STOCKHISTORY"&IF(ISNUMBER(rate_date)," at "&TEXT(rate_date,"d mmm yyyy"),"")&IF(N($E18)=0,", with no buffer: these are treated as corporate-rate currencies.",", less a "&TEXT(N($E18),"0%")&" prudence buffer."),"NO RATE. STOCKHISTORY returned nothing - the pair may not be covered, the rate date may not have been a trading day, or there may be no Microsoft 365 subscription. Type a market rate in the previous column.")))
... A39: ETB | B39: GBP:ETB | C39: =SUMPRODUCT(--(('Trip plan'!$M$16:$M$40=$A39)+('Trip plan'!$N$16:$N$40=$A39)>0)) -> 0 | D39: =IF($C39=0,"",IFERROR(_xlfn.STOCKHISTORY("GBP:"&$A39,rate_date,rate_date,0,0,1),"")) | E39: =IF(OR($A39="EUR",$A39="USD"),buffer_major,buffer_other) -> 0.1 | G39: =IF(OR(ISNUMBER($F39),ISNUMBER($D39)),IF(ISNUMBER($F39),$F39,$D39)/(1+N($E39)),"") | I39: =IF($C39=0,"",IF(ISNUMBER($F39),"Market rate typed by hand"&IF($H39=""," - record your source in the previous column",": "&$H39)&IF(N($E39)=0,", with no buffer: these are treated as corporate-rate currencies.",", less a "&TEXT(N($E39),"0%")&" prudence buffer."),IF(ISNUMBER($D39),"LSEG via STOCKHISTORY"&IF(ISNUMBER(rate_date)," at "&TEXT(rate_date,"d mmm yyyy"),"")&IF(N($E39)=0,", with no buffer: these are treated as corporate-rate currencies.",", less a "&TEXT(N($E39),"0%")&" prudence buffer."),"NO RATE. STOCKHISTORY returned nothing - the pair may not be covered, the rate date may not have been a trading day, or there may be no Microsoft 365 subscription. Type a market rate in the previous column.")))
A40: EUR | B40: GBP:EUR | C40: =SUMPRODUCT(--(('Trip plan'!$M$16:$M$40=$A40)+('Trip plan'!$N$16:$N$40=$A40)>0)) -> 1 | D40: =IF($C40=0,"",IFERROR(_xlfn.STOCKHISTORY("GBP:"&$A40,rate_date,rate_date,0,0,1),"")) -> 1.1666 | E40: =IF(OR($A40="EUR",$A40="USD"),buffer_major,buffer_other) -> 0 | F40: 1.168 | G40: =IF(OR(ISNUMBER($F40),ISNUMBER($D40)),IF(ISNUMBER($F40),$F40,$D40)/(1+N($E40)),"") -> 1.168 | H40: Derived from European Central Bank euro reference rates for 26 August 2026, via the Frankfurter API | I40: =IF($C40=0,"",IF(ISNUMBER($F40),"Market rate typed by hand"&IF($H40=""," - record your source in the previous column",": "&$H40)&IF(N($E40)=0,", with no buffer: these are treated as corporate-rate currencies.",", less a "&TEXT(N($E40),"0%")&" prudence buffer."),IF(ISNUMBER($D40),"LSEG via STOCKHISTORY"&IF(ISNUMBER(rate_date)," at "&TEXT(rate_date,"d mmm yyyy"),"")&IF(N($E40)=0,", with no buffer: these are treated as corporate-rate currencies.",", less a "&TEXT(N($E40),"0%")&" prudence buffer."),"NO RATE. STOCKHISTORY returned nothing - the pair may not be covered, the rate date may not have been a trading day, or there may be no Microsoft 365 subscription. Type a market rate in the previous column."))) -> Market rate typed by hand: Derived from European Central Bank euro reference rates for 26 August 2026, via the Frankfurter API, with no buffer: these are treated as corporate-rate currencies.
A41: FJD | B41: GBP:FJD | C41: =SUMPRODUCT(--(('Trip plan'!$M$16:$M$40=$A41)+('Trip plan'!$N$16:$N$40=$A41)>0)) -> 0 | D41: =IF($C41=0,"",IFERROR(_xlfn.STOCKHISTORY("GBP:"&$A41,rate_date,rate_date,0,0,1),"")) | E41: =IF(OR($A41="EUR",$A41="USD"),buffer_major,buffer_other) -> 0.1 | G41: =IF(OR(ISNUMBER($F41),ISNUMBER($D41)),IF(ISNUMBER($F41),$F41,$D41)/(1+N($E41)),"") | I41: =IF($C41=0,"",IF(ISNUMBER($F41),"Market rate typed by hand"&IF($H41=""," - record your source in the previous column",": "&$H41)&IF(N($E41)=0,", with no buffer: these are treated as corporate-rate currencies.",", less a "&TEXT(N($E41),"0%")&" prudence buffer."),IF(ISNUMBER($D41),"LSEG via STOCKHISTORY"&IF(ISNUMBER(rate_date)," at "&TEXT(rate_date,"d mmm yyyy"),"")&IF(N($E41)=0,", with no buffer: these are treated as corporate-rate currencies.",", less a "&TEXT(N($E41),"0%")&" prudence buffer."),"NO RATE. STOCKHISTORY returned nothing - the pair may not be covered, the rate date may not have been a trading day, or there may be no Microsoft 365 subscription. Type a market rate in the previous column.")))
A42: FKP | B42: GBP:FKP | C42: =SUMPRODUCT(--(('Trip plan'!$M$16:$M$40=$A42)+('Trip plan'!$N$16:$N$40=$A42)>0)) -> 0 | D42: =IF($C42=0,"",IFERROR(_xlfn.STOCKHISTORY("GBP:"&$A42,rate_date,rate_date,0,0,1),"")) | E42: =IF(OR($A42="EUR",$A42="USD"),buffer_major,buffer_other) -> 0.1 | G42: =IF(OR(ISNUMBER($F42),ISNUMBER($D42)),IF(ISNUMBER($F42),$F42,$D42)/(1+N($E42)),"") | I42: =IF($C42=0,"",IF(ISNUMBER($F42),"Market rate typed by hand"&IF($H42=""," - record your source in the previous column",": "&$H42)&IF(N($E42)=0,", with no buffer: these are treated as corporate-rate currencies.",", less a "&TEXT(N($E42),"0%")&" prudence buffer."),IF(ISNUMBER($D42),"LSEG via STOCKHISTORY"&IF(ISNUMBER(rate_date)," at "&TEXT(rate_date,"d mmm yyyy"),"")&IF(N($E42)=0,", with no buffer: these are treated as corporate-rate currencies.",", less a "&TEXT(N($E42),"0%")&" prudence buffer."),"NO RATE. STOCKHISTORY returned nothing - the pair may not be covered, the rate date may not have been a trading day, or there may be no Microsoft 365 subscription. Type a market rate in the previous column.")))
A43: GEL | B43: GBP:GEL | C43: =SUMPRODUCT(--(('Trip plan'!$M$16:$M$40=$A43)+('Trip plan'!$N$16:$N$40=$A43)>0)) -> 0 | D43: =IF($C43=0,"",IFERROR(_xlfn.STOCKHISTORY("GBP:"&$A43,rate_date,rate_date,0,0,1),"")) | E43: =IF(OR($A43="EUR",$A43="USD"),buffer_major,buffer_other) -> 0.1 | G43: =IF(OR(ISNUMBER($F43),ISNUMBER($D43)),IF(ISNUMBER($F43),$F43,$D43)/(1+N($E43)),"") | I43: =IF($C43=0,"",IF(ISNUMBER($F43),"Market rate typed by hand"&IF($H43=""," - record your source in the previous column",": "&$H43)&IF(N($E43)=0,", with no buffer: these are treated as corporate-rate currencies.",", less a "&TEXT(N($E43),"0%")&" prudence buffer."),IF(ISNUMBER($D43),"LSEG via STOCKHISTORY"&IF(ISNUMBER(rate_date)," at "&TEXT(rate_date,"d mmm yyyy"),"")&IF(N($E43)=0,", with no buffer: these are treated as corporate-rate currencies.",", less a "&TEXT(N($E43),"0%")&" prudence buffer."),"NO RATE. STOCKHISTORY returned nothing - the pair may not be covered, the rate date may not have been a trading day, or there may be no Microsoft 365 subscription. Type a market rate in the previous column.")))
A44: GHS | B44: GBP:GHS | C44: =SUMPRODUCT(--(('Trip plan'!$M$16:$M$40=$A44)+('Trip plan'!$N$16:$N$40=$A44)>0)) -> 0 | D44: =IF($C44=0,"",IFERROR(_xlfn.STOCKHISTORY("GBP:"&$A44,rate_date,rate_date,0,0,1),"")) | E44: =IF(OR($A44="EUR",$A44="USD"),buffer_major,buffer_other) -> 0.1 | G44: =IF(OR(ISNUMBER($F44),ISNUMBER($D44)),IF(ISNUMBER($F44),$F44,$D44)/(1+N($E44)),"") | I44: =IF($C44=0,"",IF(ISNUMBER($F44),"Market rate typed by hand"&IF($H44=""," - record your source in the previous column",": "&$H44)&IF(N($E44)=0,", with no buffer: these are treated as corporate-rate currencies.",", less a "&TEXT(N($E44),"0%")&" prudence buffer."),IF(ISNUMBER($D44),"LSEG via STOCKHISTORY"&IF(ISNUMBER(rate_date)," at "&TEXT(rate_date,"d mmm yyyy"),"")&IF(N($E44)=0,", with no buffer: these are treated as corporate-rate currencies.",", less a "&TEXT(N($E44),"0%")&" prudence buffer."),"NO RATE. STOCKHISTORY returned nothing - the pair may not be covered, the rate date may not have been a trading day, or there may be no Microsoft 365 subscription. Type a market rate in the previous column.")))
A45: GIP | B45: GBP:GIP | C45: =SUMPRODUCT(--(('Trip plan'!$M$16:$M$40=$A45)+('Trip plan'!$N$16:$N$40=$A45)>0)) -> 0 | D45: =IF($C45=0,"",IFERROR(_xlfn.STOCKHISTORY("GBP:"&$A45,rate_date,rate_date,0,0,1),"")) | E45: =IF(OR($A45="EUR",$A45="USD"),buffer_major,buffer_other) -> 0.1 | G45: =IF(OR(ISNUMBER($F45),ISNUMBER($D45)),IF(ISNUMBER($F45),$F45,$D45)/(1+N($E45)),"") | I45: =IF($C45=0,"",IF(ISNUMBER($F45),"Market rate typed by hand"&IF($H45=""," - record your source in the previous column",": "&$H45)&IF(N($E45)=0,", with no buffer: these are treated as corporate-rate currencies.",", less a "&TEXT(N($E45),"0%")&" prudence buffer."),IF(ISNUMBER($D45),"LSEG via STOCKHISTORY"&IF(ISNUMBER(rate_date)," at "&TEXT(rate_date,"d mmm yyyy"),"")&IF(N($E45)=0,", with no buffer: these are treated as corporate-rate currencies.",", less a "&TEXT(N($E45),"0%")&" prudence buffer."),"NO RATE. STOCKHISTORY returned nothing - the pair may not be covered, the rate date may not have been a trading day, or there may be no Microsoft 365 subscription. Type a market rate in the previous column.")))
A46: GMD | B46: GBP:GMD | C46: =SUMPRODUCT(--(('Trip plan'!$M$16:$M$40=$A46)+('Trip plan'!$N$16:$N$40=$A46)>0)) -> 0 | D46: =IF($C46=0,"",IFERROR(_xlfn.STOCKHISTORY("GBP:"&$A46,rate_date,rate_date,0,0,1),"")) | E46: =IF(OR($A46="EUR",$A46="USD"),buffer_major,buffer_other) -> 0.1 | G46: =IF(OR(ISNUMBER($F46),ISNUMBER($D46)),IF(ISNUMBER($F46),$F46,$D46)/(1+N($E46)),"") | I46: =IF($C46=0,"",IF(ISNUMBER($F46),"Market rate typed by hand"&IF($H46=""," - record your source in the previous column",": "&$H46)&IF(N($E46)=0,", with no buffer: these are treated as corporate-rate currencies.",", less a "&TEXT(N($E46),"0%")&" prudence buffer."),IF(ISNUMBER($D46),"LSEG via STOCKHISTORY"&IF(ISNUMBER(rate_date)," at "&TEXT(rate_date,"d mmm yyyy"),"")&IF(N($E46)=0,", with no buffer: these are treated as corporate-rate currencies.",", less a "&TEXT(N($E46),"0%")&" prudence buffer."),"NO RATE. STOCKHISTORY returned nothing - the pair may not be covered, the rate date may not have been a trading day, or there may be no Microsoft 365 subscription. Type a market rate in the previous column.")))
A47: GNF | B47: GBP:GNF | C47: =SUMPRODUCT(--(('Trip plan'!$M$16:$M$40=$A47)+('Trip plan'!$N$16:$N$40=$A47)>0)) -> 0 | D47: =IF($C47=0,"",IFERROR(_xlfn.STOCKHISTORY("GBP:"&$A47,rate_date,rate_date,0,0,1),"")) | E47: =IF(OR($A47="EUR",$A47="USD"),buffer_major,buffer_other) -> 0.1 | G47: =IF(OR(ISNUMBER($F47),ISNUMBER($D47)),IF(ISNUMBER($F47),$F47,$D47)/(1+N($E47)),"") | I47: =IF($C47=0,"",IF(ISNUMBER($F47),"Market rate typed by hand"&IF($H47=""," - record your source in the previous column",": "&$H47)&IF(N($E47)=0,", with no buffer: these are treated as corporate-rate currencies.",", less a "&TEXT(N($E47),"0%")&" prudence buffer."),IF(ISNUMBER($D47),"LSEG via STOCKHISTORY"&IF(ISNUMBER(rate_date)," at "&TEXT(rate_date,"d mmm yyyy"),"")&IF(N($E47)=0,", with no buffer: these are treated as corporate-rate currencies.",", less a "&TEXT(N($E47),"0%")&" prudence buffer."),"NO RATE. STOCKHISTORY returned nothing - the pair may not be covered, the rate date may not have been a trading day, or there may be no Microsoft 365 subscription. Type a market rate in the previous column.")))
A48: GYD | B48: GBP:GYD | C48: =SUMPRODUCT(--(('Trip plan'!$M$16:$M$40=$A48)+('Trip plan'!$N$16:$N$40=$A48)>0)) -> 0 | D48: =IF($C48=0,"",IFERROR(_xlfn.STOCKHISTORY("GBP:"&$A48,rate_date,rate_date,0,0,1),"")) | E48: =IF(OR($A48="EUR",$A48="USD"),buffer_major,buffer_other) -> 0.1 | G48: =IF(OR(ISNUMBER($F48),ISNUMBER($D48)),IF(ISNUMBER($F48),$F48,$D48)/(1+N($E48)),"") | I48: =IF($C48=0,"",IF(ISNUMBER($F48),"Market rate typed by hand"&IF($H48=""," - record your source in the previous column",": "&$H48)&IF(N($E48)=0,", with no buffer: these are treated as corporate-rate currencies.",", less a "&TEXT(N($E48),"0%")&" prudence buffer."),IF(ISNUMBER($D48),"LSEG via STOCKHISTORY"&IF(ISNUMBER(rate_date)," at "&TEXT(rate_date,"d mmm yyyy"),"")&IF(N($E48)=0,", with no buffer: these are treated as corporate-rate currencies.",", less a "&TEXT(N($E48),"0%")&" prudence buffer."),"NO RATE. STOCKHISTORY returned nothing - the pair may not be covered, the rate date may not have been a trading day, or there may be no Microsoft 365 subscription. Type a market rate in the previous column.")))
A49: HKD | B49: GBP:HKD | C49: =SUMPRODUCT(--(('Trip plan'!$M$16:$M$40=$A49)+('Trip plan'!$N$16:$N$40=$A49)>0)) -> 0 | D49: =IF($C49=0,"",IFERROR(_xlfn.STOCKHISTORY("GBP:"&$A49,rate_date,rate_date,0,0,1),"")) | E49: =IF(OR($A49="EUR",$A49="USD"),buffer_major,buffer_other) -> 0.1 | G49: =IF(OR(ISNUMBER($F49),ISNUMBER($D49)),IF(ISNUMBER($F49),$F49,$D49)/(1+N($E49)),"") | I49: =IF($C49=0,"",IF(ISNUMBER($F49),"Market rate typed by hand"&IF($H49=""," - record your source in the previous column",": "&$H49)&IF(N($E49)=0,", with no buffer: these are treated as corporate-rate currencies.",", less a "&TEXT(N($E49),"0%")&" prudence buffer."),IF(ISNUMBER($D49),"LSEG via STOCKHISTORY"&IF(ISNUMBER(rate_date)," at "&TEXT(rate_date,"d mmm yyyy"),"")&IF(N($E49)=0,", with no buffer: these are treated as corporate-rate currencies.",", less a "&TEXT(N($E49),"0%")&" prudence buffer."),"NO RATE. STOCKHISTORY returned nothing - the pair may not be covered, the rate date may not have been a trading day, or there may be no Microsoft 365 subscription. Type a market rate in the previous column.")))
A50: HRK | B50: GBP:HRK | C50: =SUMPRODUCT(--(('Trip plan'!$M$16:$M$40=$A50)+('Trip plan'!$N$16:$N$40=$A50)>0)) -> 0 | D50: =IF($C50=0,"",IFERROR(_xlfn.STOCKHISTORY("GBP:"&$A50,rate_date,rate_date,0,0,1),"")) | E50: =IF(OR($A50="EUR",$A50="USD"),buffer_major,buffer_other) -> 0.1 | G50: =IF(OR(ISNUMBER($F50),ISNUMBER($D50)),IF(ISNUMBER($F50),$F50,$D50)/(1+N($E50)),"") | I50: =IF($C50=0,"",IF(ISNUMBER($F50),"Market rate typed by hand"&IF($H50=""," - record your source in the previous column",": "&$H50)&IF(N($E50)=0,", with no buffer: these are treated as corporate-rate currencies.",", less a "&TEXT(N($E50),"0%")&" prudence buffer."),IF(ISNUMBER($D50),"LSEG via STOCKHISTORY"&IF(ISNUMBER(rate_date)," at "&TEXT(rate_date,"d mmm yyyy"),"")&IF(N($E50)=0,", with no buffer: these are treated as corporate-rate currencies.",", less a "&TEXT(N($E50),"0%")&" prudence buffer."),"NO RATE. STOCKHISTORY returned nothing - the pair may not be covered, the rate date may not have been a trading day, or there may be no Microsoft 365 subscription. Type a market rate in the previous column.")))
A51: HUF | B51: GBP:HUF | C51: =SUMPRODUCT(--(('Trip plan'!$M$16:$M$40=$A51)+('Trip plan'!$N$16:$N$40=$A51)>0)) -> 0 | D51: =IF($C51=0,"",IFERROR(_xlfn.STOCKHISTORY("GBP:"&$A51,rate_date,rate_date,0,0,1),"")) | E51: =IF(OR($A51="EUR",$A51="USD"),buffer_major,buffer_other) -> 0.1 | G51: =IF(OR(ISNUMBER($F51),ISNUMBER($D51)),IF(ISNUMBER($F51),$F51,$D51)/(1+N($E51)),"") | I51: =IF($C51=0,"",IF(ISNUMBER($F51),"Market rate typed by hand"&IF($H51=""," - record your source in the previous column",": "&$H51)&IF(N($E51)=0,", with no buffer: these are treated as corporate-rate currencies.",", less a "&TEXT(N($E51),"0%")&" prudence buffer."),IF(ISNUMBER($D51),"LSEG via STOCKHISTORY"&IF(ISNUMBER(rate_date)," at "&TEXT(rate_date,"d mmm yyyy"),"")&IF(N($E51)=0,", with no buffer: these are treated as corporate-rate currencies.",", less a "&TEXT(N($E51),"0%")&" prudence buffer."),"NO RATE. STOCKHISTORY returned nothing - the pair may not be covered, the rate date may not have been a trading day, or there may be no Microsoft 365 subscription. Type a market rate in the previous column.")))
A52: IDR | B52: GBP:IDR | C52: =SUMPRODUCT(--(('Trip plan'!$M$16:$M$40=$A52)+('Trip plan'!$N$16:$N$40=$A52)>0)) -> 1 | D52: =IF($C52=0,"",IFERROR(_xlfn.STOCKHISTORY("GBP:"&$A52,rate_date,rate_date,0,0,1),"")) -> 24052.81 | E52: =IF(OR($A52="EUR",$A52="USD"),buffer_major,buffer_other) -> 0.1 | F52: 24142 | G52: =IF(OR(ISNUMBER($F52),ISNUMBER($D52)),IF(ISNUMBER($F52),$F52,$D52)/(1+N($E52)),"") -> 21947.273 | H52: Derived from European Central Bank euro reference rates for 26 August 2026, via the Frankfurter API | I52: =IF($C52=0,"",IF(ISNUMBER($F52),"Market rate typed by hand"&IF($H52=""," - record your source in the previous column",": "&$H52)&IF(N($E52)=0,", with no buffer: these are treated as corporate-rate currencies.",", less a "&TEXT(N($E52),"0%")&" prudence buffer."),IF(ISNUMBER($D52),"LSEG via STOCKHISTORY"&IF(ISNUMBER(rate_date)," at "&TEXT(rate_date,"d mmm yyyy"),"")&IF(N($E52)=0,", with no buffer: these are treated as corporate-rate currencies.",", less a "&TEXT(N($E52),"0%")&" prudence buffer."),"NO RATE. STOCKHISTORY returned nothing - the pair may not be covered, the rate date may not have been a trading day, or there may be no Microsoft 365 subscription. Type a market rate in the previous column."))) -> Market rate typed by hand: Derived from European Central Bank euro reference rates for 26 August 2026, via the Frankfurter API, less a 10% prudence buffer.
A53: INR | B53: GBP:INR | C53: =SUMPRODUCT(--(('Trip plan'!$M$16:$M$40=$A53)+('Trip plan'!$N$16:$N$40=$A53)>0)) -> 0 | D53: =IF($C53=0,"",IFERROR(_xlfn.STOCKHISTORY("GBP:"&$A53,rate_date,rate_date,0,0,1),"")) | E53: =IF(OR($A53="EUR",$A53="USD"),buffer_major,buffer_other) -> 0.1 | G53: =IF(OR(ISNUMBER($F53),ISNUMBER($D53)),IF(ISNUMBER($F53),$F53,$D53)/(1+N($E53)),"") | I53: =IF($C53=0,"",IF(ISNUMBER($F53),"Market rate typed by hand"&IF($H53=""," - record your source in the previous column",": "&$H53)&IF(N($E53)=0,", with no buffer: these are treated as corporate-rate currencies.",", less a "&TEXT(N($E53),"0%")&" prudence buffer."),IF(ISNUMBER($D53),"LSEG via STOCKHISTORY"&IF(ISNUMBER(rate_date)," at "&TEXT(rate_date,"d mmm yyyy"),"")&IF(N($E53)=0,", with no buffer: these are treated as corporate-rate currencies.",", less a "&TEXT(N($E53),"0%")&" prudence buffer."),"NO RATE. STOCKHISTORY returned nothing - the pair may not be covered, the rate date may not have been a trading day, or there may be no Microsoft 365 subscription. Type a market rate in the previous column.")))
A54: IRR | B54: GBP:IRR | C54: =SUMPRODUCT(--(('Trip plan'!$M$16:$M$40=$A54)+('Trip plan'!$N$16:$N$40=$A54)>0)) -> 0 | D54: =IF($C54=0,"",IFERROR(_xlfn.STOCKHISTORY("GBP:"&$A54,rate_date,rate_date,0,0,1),"")) | E54: =IF(OR($A54="EUR",$A54="USD"),buffer_major,buffer_other) -> 0.1 | G54: =IF(OR(ISNUMBER($F54),ISNUMBER($D54)),IF(ISNUMBER($F54),$F54,$D54)/(1+N($E54)),"") | I54: =IF($C54=0,"",IF(ISNUMBER($F54),"Market rate typed by hand"&IF($H54=""," - record your source in the previous column",": "&$H54)&IF(N($E54)=0,", with no buffer: these are treated as corporate-rate currencies.",", less a "&TEXT(N($E54),"0%")&" prudence buffer."),IF(ISNUMBER($D54),"LSEG via STOCKHISTORY"&IF(ISNUMBER(rate_date)," at "&TEXT(rate_date,"d mmm yyyy"),"")&IF(N($E54)=0,", with no buffer: these are treated as corporate-rate currencies.",", less a "&TEXT(N($E54),"0%")&" prudence buffer."),"NO RATE. STOCKHISTORY returned nothing - the pair may not be covered, the rate date may not have been a trading day, or there may be no Microsoft 365 subscription. Type a market rate in the previous column.")))
A55: ISK | B55: GBP:ISK | C55: =SUMPRODUCT(--(('Trip plan'!$M$16:$M$40=$A55)+('Trip plan'!$N$16:$N$40=$A55)>0)) -> 0 | D55: =IF($C55=0,"",IFERROR(_xlfn.STOCKHISTORY("GBP:"&$A55,rate_date,rate_date,0,0,1),"")) | E55: =IF(OR($A55="EUR",$A55="USD"),buffer_major,buffer_other) -> 0.1 | G55: =IF(OR(ISNUMBER($F55),ISNUMBER($D55)),IF(ISNUMBER($F55),$F55,$D55)/(1+N($E55)),"") | I55: =IF($C55=0,"",IF(ISNUMBER($F55),"Market rate typed by hand"&IF($H55=""," - record your source in the previous column",": "&$H55)&IF(N($E55)=0,", with no buffer: these are treated as corporate-rate currencies.",", less a "&TEXT(N($E55),"0%")&" prudence buffer."),IF(ISNUMBER($D55),"LSEG via STOCKHISTORY"&IF(ISNUMBER(rate_date)," at "&TEXT(rate_date,"d mmm yyyy"),"")&IF(N($E55)=0,", with no buffer: these are treated as corporate-rate currencies.",", less a "&TEXT(N($E55),"0%")&" prudence buffer."),"NO RATE. STOCKHISTORY returned nothing - the pair may not be covered, the rate date may not have been a trading day, or there may be no Microsoft 365 subscription. Type a market rate in the previous column.")))
A56: JOD | B56: GBP:JOD | C56: =SUMPRODUCT(--(('Trip plan'!$M$16:$M$40=$A56)+('Trip plan'!$N$16:$N$40=$A56)>0)) -> 0 | D56: =IF($C56=0,"",IFERROR(_xlfn.STOCKHISTORY("GBP:"&$A56,rate_date,rate_date,0,0,1),"")) | E56: =IF(OR($A56="EUR",$A56="USD"),buffer_major,buffer_other) -> 0.1 | G56: =IF(OR(ISNUMBER($F56),ISNUMBER($D56)),IF(ISNUMBER($F56),$F56,$D56)/(1+N($E56)),"") | I56: =IF($C56=0,"",IF(ISNUMBER($F56),"Market rate typed by hand"&IF($H56=""," - record your source in the previous column",": "&$H56)&IF(N($E56)=0,", with no buffer: these are treated as corporate-rate currencies.",", less a "&TEXT(N($E56),"0%")&" prudence buffer."),IF(ISNUMBER($D56),"LSEG via STOCKHISTORY"&IF(ISNUMBER(rate_date)," at "&TEXT(rate_date,"d mmm yyyy"),"")&IF(N($E56)=0,", with no buffer: these are treated as corporate-rate currencies.",", less a "&TEXT(N($E56),"0%")&" prudence buffer."),"NO RATE. STOCKHISTORY returned nothing - the pair may not be covered, the rate date may not have been a trading day, or there may be no Microsoft 365 subscription. Type a market rate in the previous column.")))
A57: JPY | B57: GBP:JPY | C57: =SUMPRODUCT(--(('Trip plan'!$M$16:$M$40=$A57)+('Trip plan'!$N$16:$N$40=$A57)>0)) -> 0 | D57: =IF($C57=0,"",IFERROR(_xlfn.STOCKHISTORY("GBP:"&$A57,rate_date,rate_date,0,0,1),"")) | E57: =IF(OR($A57="EUR",$A57="USD"),buffer_major,buffer_other) -> 0.1 | G57: =IF(OR(ISNUMBER($F57),ISNUMBER($D57)),IF(ISNUMBER($F57),$F57,$D57)/(1+N($E57)),"") | I57: =IF($C57=0,"",IF(ISNUMBER($F57),"Market rate typed by hand"&IF($H57=""," - record your source in the previous column",": "&$H57)&IF(N($E57)=0,", with no buffer: these are treated as corporate-rate currencies.",", less a "&TEXT(N($E57),"0%")&" prudence buffer."),IF(ISNUMBER($D57),"LSEG via STOCKHISTORY"&IF(ISNUMBER(rate_date)," at "&TEXT(rate_date,"d mmm yyyy"),"")&IF(N($E57)=0,", with no buffer: these are treated as corporate-rate currencies.",", less a "&TEXT(N($E57),"0%")&" prudence buffer."),"NO RATE. STOCKHISTORY returned nothing - the pair may not be covered, the rate date may not have been a trading day, or there may be no Microsoft 365 subscription. Type a market rate in the previous column.")))
A58: KES | B58: GBP:KES | C58: =SUMPRODUCT(--(('Trip plan'!$M$16:$M$40=$A58)+('Trip plan'!$N$16:$N$40=$A58)>0)) -> 0 | D58: =IF($C58=0,"",IFERROR(_xlfn.STOCKHISTORY("GBP:"&$A58,rate_date,rate_date,0,0,1),"")) | E58: =IF(OR($A58="EUR",$A58="USD"),buffer_major,buffer_other) -> 0.1 | G58: =IF(OR(ISNUMBER($F58),ISNUMBER($D58)),IF(ISNUMBER($F58),$F58,$D58)/(1+N($E58)),"") | I58: =IF($C58=0,"",IF(ISNUMBER($F58),"Market rate typed by hand"&IF($H58=""," - record your source in the previous column",": "&$H58)&IF(N($E58)=0,", with no buffer: these are treated as corporate-rate currencies.",", less a "&TEXT(N($E58),"0%")&" prudence buffer."),IF(ISNUMBER($D58),"LSEG via STOCKHISTORY"&IF(ISNUMBER(rate_date)," at "&TEXT(rate_date,"d mmm yyyy"),"")&IF(N($E58)=0,", with no buffer: these are treated as corporate-rate currencies.",", less a "&TEXT(N($E58),"0%")&" prudence buffer."),"NO RATE. STOCKHISTORY returned nothing - the pair may not be covered, the rate date may not have been a trading day, or there may be no Microsoft 365 subscription. Type a market rate in the previous column.")))
A59: KRW | B59: GBP:KRW | C59: =SUMPRODUCT(--(('Trip plan'!$M$16:$M$40=$A59)+('Trip plan'!$N$16:$N$40=$A59)>0)) -> 0 | D59: =IF($C59=0,"",IFERROR(_xlfn.STOCKHISTORY("GBP:"&$A59,rate_date,rate_date,0,0,1),"")) | E59: =IF(OR($A59="EUR",$A59="USD"),buffer_major,buffer_other) -> 0.1 | G59: =IF(OR(ISNUMBER($F59),ISNUMBER($D59)),IF(ISNUMBER($F59),$F59,$D59)/(1+N($E59)),"") | I59: =IF($C59=0,"",IF(ISNUMBER($F59),"Market rate typed by hand"&IF($H59=""," - record your source in the previous column",": "&$H59)&IF(N($E59)=0,", with no buffer: these are treated as corporate-rate currencies.",", less a "&TEXT(N($E59),"0%")&" prudence buffer."),IF(ISNUMBER($D59),"LSEG via STOCKHISTORY"&IF(ISNUMBER(rate_date)," at "&TEXT(rate_date,"d mmm yyyy"),"")&IF(N($E59)=0,", with no buffer: these are treated as corporate-rate currencies.",", less a "&TEXT(N($E59),"0%")&" prudence buffer."),"NO RATE. STOCKHISTORY returned nothing - the pair may not be covered, the rate date may not have been a trading day, or there may be no Microsoft 365 subscription. Type a market rate in the previous column.")))
A60: KWD | B60: GBP:KWD | C60: =SUMPRODUCT(--(('Trip plan'!$M$16:$M$40=$A60)+('Trip plan'!$N$16:$N$40=$A60)>0)) -> 0 | D60: =IF($C60=0,"",IFERROR(_xlfn.STOCKHISTORY("GBP:"&$A60,rate_date,rate_date,0,0,1),"")) | E60: =IF(OR($A60="EUR",$A60="USD"),buffer_major,buffer_other) -> 0.1 | G60: =IF(OR(ISNUMBER($F60),ISNUMBER($D60)),IF(ISNUMBER($F60),$F60,$D60)/(1+N($E60)),"") | I60: =IF($C60=0,"",IF(ISNUMBER($F60),"Market rate typed by hand"&IF($H60=""," - record your source in the previous column",": "&$H60)&IF(N($E60)=0,", with no buffer: these are treated as corporate-rate currencies.",", less a "&TEXT(N($E60),"0%")&" prudence buffer."),IF(ISNUMBER($D60),"LSEG via STOCKHISTORY"&IF(ISNUMBER(rate_date)," at "&TEXT(rate_date,"d mmm yyyy"),"")&IF(N($E60)=0,", with no buffer: these are treated as corporate-rate currencies.",", less a "&TEXT(N($E60),"0%")&" prudence buffer."),"NO RATE. STOCKHISTORY returned nothing - the pair may not be covered, the rate date may not have been a trading day, or there may be no Microsoft 365 subscription. Type a market rate in the previous column.")))
A61: KYD | B61: GBP:KYD | C61: =SUMPRODUCT(--(('Trip plan'!$M$16:$M$40=$A61)+('Trip plan'!$N$16:$N$40=$A61)>0)) -> 0 | D61: =IF($C61=0,"",IFERROR(_xlfn.STOCKHISTORY("GBP:"&$A61,rate_date,rate_date,0,0,1),"")) | E61: =IF(OR($A61="EUR",$A61="USD"),buffer_major,buffer_other) -> 0.1 | G61: =IF(OR(ISNUMBER($F61),ISNUMBER($D61)),IF(ISNUMBER($F61),$F61,$D61)/(1+N($E61)),"") | I61: =IF($C61=0,"",IF(ISNUMBER($F61),"Market rate typed by hand"&IF($H61=""," - record your source in the previous column",": "&$H61)&IF(N($E61)=0,", with no buffer: these are treated as corporate-rate currencies.",", less a "&TEXT(N($E61),"0%")&" prudence buffer."),IF(ISNUMBER($D61),"LSEG via STOCKHISTORY"&IF(ISNUMBER(rate_date)," at "&TEXT(rate_date,"d mmm yyyy"),"")&IF(N($E61)=0,", with no buffer: these are treated as corporate-rate currencies.",", less a "&TEXT(N($E61),"0%")&" prudence buffer."),"NO RATE. STOCKHISTORY returned nothing - the pair may not be covered, the rate date may not have been a trading day, or there may be no Microsoft 365 subscription. Type a market rate in the previous column.")))
A62: KZT | B62: GBP:KZT | C62: =SUMPRODUCT(--(('Trip plan'!$M$16:$M$40=$A62)+('Trip plan'!$N$16:$N$40=$A62)>0)) -> 0 | D62: =IF($C62=0,"",IFERROR(_xlfn.STOCKHISTORY("GBP:"&$A62,rate_date,rate_date,0,0,1),"")) | E62: =IF(OR($A62="EUR",$A62="USD"),buffer_major,buffer_other) -> 0.1 | G62: =IF(OR(ISNUMBER($F62),ISNUMBER($D62)),IF(ISNUMBER($F62),$F62,$D62)/(1+N($E62)),"") | I62: =IF($C62=0,"",IF(ISNUMBER($F62),"Market rate typed by hand"&IF($H62=""," - record your source in the previous column",": "&$H62)&IF(N($E62)=0,", with no buffer: these are treated as corporate-rate currencies.",", less a "&TEXT(N($E62),"0%")&" prudence buffer."),IF(ISNUMBER($D62),"LSEG via STOCKHISTORY"&IF(ISNUMBER(rate_date)," at "&TEXT(rate_date,"d mmm yyyy"),"")&IF(N($E62)=0,", with no buffer: these are treated as corporate-rate currencies.",", less a "&TEXT(N($E62),"0%")&" prudence buffer."),"NO RATE. STOCKHISTORY returned nothing - the pair may not be covered, the rate date may not have been a trading day, or there may be no Microsoft 365 subscription. Type a market rate in the previous column.")))
A63: LAK | B63: GBP:LAK | C63: =SUMPRODUCT(--(('Trip plan'!$M$16:$M$40=$A63)+('Trip plan'!$N$16:$N$40=$A63)>0)) -> 0 | D63: =IF($C63=0,"",IFERROR(_xlfn.STOCKHISTORY("GBP:"&$A63,rate_date,rate_date,0,0,1),"")) | E63: =IF(OR($A63="EUR",$A63="USD"),buffer_major,buffer_other) -> 0.1 | G63: =IF(OR(ISNUMBER($F63),ISNUMBER($D63)),IF(ISNUMBER($F63),$F63,$D63)/(1+N($E63)),"") | I63: =IF($C63=0,"",IF(ISNUMBER($F63),"Market rate typed by hand"&IF($H63=""," - record your source in the previous column",": "&$H63)&IF(N($E63)=0,", with no buffer: these are treated as corporate-rate currencies.",", less a "&TEXT(N($E63),"0%")&" prudence buffer."),IF(ISNUMBER($D63),"LSEG via STOCKHISTORY"&IF(ISNUMBER(rate_date)," at "&TEXT(rate_date,"d mmm yyyy"),"")&IF(N($E63)=0,", with no buffer: these are treated as corporate-rate currencies.",", less a "&TEXT(N($E63),"0%")&" prudence buffer."),"NO RATE. STOCKHISTORY returned nothing - the pair may not be covered, the rate date may not have been a trading day, or there may be no Microsoft 365 subscription. Type a market rate in the previous column.")))
A64: LKR | B64: GBP:LKR | C64: =SUMPRODUCT(--(('Trip plan'!$M$16:$M$40=$A64)+('Trip plan'!$N$16:$N$40=$A64)>0)) -> 0 | D64: =IF($C64=0,"",IFERROR(_xlfn.STOCKHISTORY("GBP:"&$A64,rate_date,rate_date,0,0,1),"")) | E64: =IF(OR($A64="EUR",$A64="USD"),buffer_major,buffer_other) -> 0.1 | G64: =IF(OR(ISNUMBER($F64),ISNUMBER($D64)),IF(ISNUMBER($F64),$F64,$D64)/(1+N($E64)),"") | I64: =IF($C64=0,"",IF(ISNUMBER($F64),"Market rate typed by hand"&IF($H64=""," - record your source in the previous column",": "&$H64)&IF(N($E64)=0,", with no buffer: these are treated as corporate-rate currencies.",", less a "&TEXT(N($E64),"0%")&" prudence buffer."),IF(ISNUMBER($D64),"LSEG via STOCKHISTORY"&IF(ISNUMBER(rate_date)," at "&TEXT(rate_date,"d mmm yyyy"),"")&IF(N($E64)=0,", with no buffer: these are treated as corporate-rate currencies.",", less a "&TEXT(N($E64),"0%")&" prudence buffer."),"NO RATE. STOCKHISTORY returned nothing - the pair may not be covered, the rate date may not have been a trading day, or there may be no Microsoft 365 subscription. Type a market rate in the previous column.")))
... A108: UAH | B108: GBP:UAH | C108: =SUMPRODUCT(--(('Trip plan'!$M$16:$M$40=$A108)+('Trip plan'!$N$16:$N$40=$A108)>0)) -> 0 | D108: =IF($C108=0,"",IFERROR(_xlfn.STOCKHISTORY("GBP:"&$A108,rate_date,rate_date,0,0,1),"")) | E108: =IF(OR($A108="EUR",$A108="USD"),buffer_major,buffer_other) -> 0.1 | G108: =IF(OR(ISNUMBER($F108),ISNUMBER($D108)),IF(ISNUMBER($F108),$F108,$D108)/(1+N($E108)),"") | I108: =IF($C108=0,"",IF(ISNUMBER($F108),"Market rate typed by hand"&IF($H108=""," - record your source in the previous column",": "&$H108)&IF(N($E108)=0,", with no buffer: these are treated as corporate-rate currencies.",", less a "&TEXT(N($E108),"0%")&" prudence buffer."),IF(ISNUMBER($D108),"LSEG via STOCKHISTORY"&IF(ISNUMBER(rate_date)," at "&TEXT(rate_date,"d mmm yyyy"),"")&IF(N($E108)=0,", with no buffer: these are treated as corporate-rate currencies.",", less a "&TEXT(N($E108),"0%")&" prudence buffer."),"NO RATE. STOCKHISTORY returned nothing - the pair may not be covered, the rate date may not have been a trading day, or there may be no Microsoft 365 subscription. Type a market rate in the previous column.")))
A109: USD | B109: GBP:USD | C109: =SUMPRODUCT(--(('Trip plan'!$M$16:$M$40=$A109)+('Trip plan'!$N$16:$N$40=$A109)>0)) -> 1 | D109: =IF($C109=0,"",IFERROR(_xlfn.STOCKHISTORY("GBP:"&$A109,rate_date,rate_date,0,0,1),"")) -> 1.3593 | E109: =IF(OR($A109="EUR",$A109="USD"),buffer_major,buffer_other) -> 0 | F109: 1.363 | G109: =IF(OR(ISNUMBER($F109),ISNUMBER($D109)),IF(ISNUMBER($F109),$F109,$D109)/(1+N($E109)),"") -> 1.363 | H109: Derived from European Central Bank euro reference rates for 26 August 2026, via the Frankfurter API | I109: =IF($C109=0,"",IF(ISNUMBER($F109),"Market rate typed by hand"&IF($H109=""," - record your source in the previous column",": "&$H109)&IF(N($E109)=0,", with no buffer: these are treated as corporate-rate currencies.",", less a "&TEXT(N($E109),"0%")&" prudence buffer."),IF(ISNUMBER($D109),"LSEG via STOCKHISTORY"&IF(ISNUMBER(rate_date)," at "&TEXT(rate_date,"d mmm yyyy"),"")&IF(N($E109)=0,", with no buffer: these are treated as corporate-rate currencies.",", less a "&TEXT(N($E109),"0%")&" prudence buffer."),"NO RATE. STOCKHISTORY returned nothing - the pair may not be covered, the rate date may not have been a trading day, or there may be no Microsoft 365 subscription. Type a market rate in the previous column."))) -> Market rate typed by hand: Derived from European Central Bank euro reference rates for 26 August 2026, via the Frankfurter API, with no buffer: these are treated as corporate-rate currencies.
A110: VES | B110: GBP:VES | C110: =SUMPRODUCT(--(('Trip plan'!$M$16:$M$40=$A110)+('Trip plan'!$N$16:$N$40=$A110)>0)) -> 0 | D110: =IF($C110=0,"",IFERROR(_xlfn.STOCKHISTORY("GBP:"&$A110,rate_date,rate_date,0,0,1),"")) | E110: =IF(OR($A110="EUR",$A110="USD"),buffer_major,buffer_other) -> 0.1 | G110: =IF(OR(ISNUMBER($F110),ISNUMBER($D110)),IF(ISNUMBER($F110),$F110,$D110)/(1+N($E110)),"") | I110: =IF($C110=0,"",IF(ISNUMBER($F110),"Market rate typed by hand"&IF($H110=""," - record your source in the previous column",": "&$H110)&IF(N($E110)=0,", with no buffer: these are treated as corporate-rate currencies.",", less a "&TEXT(N($E110),"0%")&" prudence buffer."),IF(ISNUMBER($D110),"LSEG via STOCKHISTORY"&IF(ISNUMBER(rate_date)," at "&TEXT(rate_date,"d mmm yyyy"),"")&IF(N($E110)=0,", with no buffer: these are treated as corporate-rate currencies.",", less a "&TEXT(N($E110),"0%")&" prudence buffer."),"NO RATE. STOCKHISTORY returned nothing - the pair may not be covered, the rate date may not have been a trading day, or there may be no Microsoft 365 subscription. Type a market rate in the previous column.")))
A111: VUV | B111: GBP:VUV | C111: =SUMPRODUCT(--(('Trip plan'!$M$16:$M$40=$A111)+('Trip plan'!$N$16:$N$40=$A111)>0)) -> 0 | D111: =IF($C111=0,"",IFERROR(_xlfn.STOCKHISTORY("GBP:"&$A111,rate_date,rate_date,0,0,1),"")) | E111: =IF(OR($A111="EUR",$A111="USD"),buffer_major,buffer_other) -> 0.1 | G111: =IF(OR(ISNUMBER($F111),ISNUMBER($D111)),IF(ISNUMBER($F111),$F111,$D111)/(1+N($E111)),"") | I111: =IF($C111=0,"",IF(ISNUMBER($F111),"Market rate typed by hand"&IF($H111=""," - record your source in the previous column",": "&$H111)&IF(N($E111)=0,", with no buffer: these are treated as corporate-rate currencies.",", less a "&TEXT(N($E111),"0%")&" prudence buffer."),IF(ISNUMBER($D111),"LSEG via STOCKHISTORY"&IF(ISNUMBER(rate_date)," at "&TEXT(rate_date,"d mmm yyyy"),"")&IF(N($E111)=0,", with no buffer: these are treated as corporate-rate currencies.",", less a "&TEXT(N($E111),"0%")&" prudence buffer."),"NO RATE. STOCKHISTORY returned nothing - the pair may not be covered, the rate date may not have been a trading day, or there may be no Microsoft 365 subscription. Type a market rate in the previous column.")))
A112: WST | B112: GBP:WST | C112: =SUMPRODUCT(--(('Trip plan'!$M$16:$M$40=$A112)+('Trip plan'!$N$16:$N$40=$A112)>0)) -> 0 | D112: =IF($C112=0,"",IFERROR(_xlfn.STOCKHISTORY("GBP:"&$A112,rate_date,rate_date,0,0,1),"")) | E112: =IF(OR($A112="EUR",$A112="USD"),buffer_major,buffer_other) -> 0.1 | G112: =IF(OR(ISNUMBER($F112),ISNUMBER($D112)),IF(ISNUMBER($F112),$F112,$D112)/(1+N($E112)),"") | I112: =IF($C112=0,"",IF(ISNUMBER($F112),"Market rate typed by hand"&IF($H112=""," - record your source in the previous column",": "&$H112)&IF(N($E112)=0,", with no buffer: these are treated as corporate-rate currencies.",", less a "&TEXT(N($E112),"0%")&" prudence buffer."),IF(ISNUMBER($D112),"LSEG via STOCKHISTORY"&IF(ISNUMBER(rate_date)," at "&TEXT(rate_date,"d mmm yyyy"),"")&IF(N($E112)=0,", with no buffer: these are treated as corporate-rate currencies.",", less a "&TEXT(N($E112),"0%")&" prudence buffer."),"NO RATE. STOCKHISTORY returned nothing - the pair may not be covered, the rate date may not have been a trading day, or there may be no Microsoft 365 subscription. Type a market rate in the previous column.")))
A113: XAF | B113: GBP:XAF | C113: =SUMPRODUCT(--(('Trip plan'!$M$16:$M$40=$A113)+('Trip plan'!$N$16:$N$40=$A113)>0)) -> 0 | D113: =IF($C113=0,"",IFERROR(_xlfn.STOCKHISTORY("GBP:"&$A113,rate_date,rate_date,0,0,1),"")) | E113: =IF(OR($A113="EUR",$A113="USD"),buffer_major,buffer_other) -> 0.1 | G113: =IF(OR(ISNUMBER($F113),ISNUMBER($D113)),IF(ISNUMBER($F113),$F113,$D113)/(1+N($E113)),"") | I113: =IF($C113=0,"",IF(ISNUMBER($F113),"Market rate typed by hand"&IF($H113=""," - record your source in the previous column",": "&$H113)&IF(N($E113)=0,", with no buffer: these are treated as corporate-rate currencies.",", less a "&TEXT(N($E113),"0%")&" prudence buffer."),IF(ISNUMBER($D113),"LSEG via STOCKHISTORY"&IF(ISNUMBER(rate_date)," at "&TEXT(rate_date,"d mmm yyyy"),"")&IF(N($E113)=0,", with no buffer: these are treated as corporate-rate currencies.",", less a "&TEXT(N($E113),"0%")&" prudence buffer."),"NO RATE. STOCKHISTORY returned nothing - the pair may not be covered, the rate date may not have been a trading day, or there may be no Microsoft 365 subscription. Type a market rate in the previous column.")))
A114: XCD | B114: GBP:XCD | C114: =SUMPRODUCT(--(('Trip plan'!$M$16:$M$40=$A114)+('Trip plan'!$N$16:$N$40=$A114)>0)) -> 0 | D114: =IF($C114=0,"",IFERROR(_xlfn.STOCKHISTORY("GBP:"&$A114,rate_date,rate_date,0,0,1),"")) | E114: =IF(OR($A114="EUR",$A114="USD"),buffer_major,buffer_other) -> 0.1 | G114: =IF(OR(ISNUMBER($F114),ISNUMBER($D114)),IF(ISNUMBER($F114),$F114,$D114)/(1+N($E114)),"") | I114: =IF($C114=0,"",IF(ISNUMBER($F114),"Market rate typed by hand"&IF($H114=""," - record your source in the previous column",": "&$H114)&IF(N($E114)=0,", with no buffer: these are treated as corporate-rate currencies.",", less a "&TEXT(N($E114),"0%")&" prudence buffer."),IF(ISNUMBER($D114),"LSEG via STOCKHISTORY"&IF(ISNUMBER(rate_date)," at "&TEXT(rate_date,"d mmm yyyy"),"")&IF(N($E114)=0,", with no buffer: these are treated as corporate-rate currencies.",", less a "&TEXT(N($E114),"0%")&" prudence buffer."),"NO RATE. STOCKHISTORY returned nothing - the pair may not be covered, the rate date may not have been a trading day, or there may be no Microsoft 365 subscription. Type a market rate in the previous column.")))
A115: XOF | B115: GBP:XOF | C115: =SUMPRODUCT(--(('Trip plan'!$M$16:$M$40=$A115)+('Trip plan'!$N$16:$N$40=$A115)>0)) -> 0 | D115: =IF($C115=0,"",IFERROR(_xlfn.STOCKHISTORY("GBP:"&$A115,rate_date,rate_date,0,0,1),"")) | E115: =IF(OR($A115="EUR",$A115="USD"),buffer_major,buffer_other) -> 0.1 | G115: =IF(OR(ISNUMBER($F115),ISNUMBER($D115)),IF(ISNUMBER($F115),$F115,$D115)/(1+N($E115)),"") | I115: =IF($C115=0,"",IF(ISNUMBER($F115),"Market rate typed by hand"&IF($H115=""," - record your source in the previous column",": "&$H115)&IF(N($E115)=0,", with no buffer: these are treated as corporate-rate currencies.",", less a "&TEXT(N($E115),"0%")&" prudence buffer."),IF(ISNUMBER($D115),"LSEG via STOCKHISTORY"&IF(ISNUMBER(rate_date)," at "&TEXT(rate_date,"d mmm yyyy"),"")&IF(N($E115)=0,", with no buffer: these are treated as corporate-rate currencies.",", less a "&TEXT(N($E115),"0%")&" prudence buffer."),"NO RATE. STOCKHISTORY returned nothing - the pair may not be covered, the rate date may not have been a trading day, or there may be no Microsoft 365 subscription. Type a market rate in the previous column.")))
A116: XPF | B116: GBP:XPF | C116: =SUMPRODUCT(--(('Trip plan'!$M$16:$M$40=$A116)+('Trip plan'!$N$16:$N$40=$A116)>0)) -> 0 | D116: =IF($C116=0,"",IFERROR(_xlfn.STOCKHISTORY("GBP:"&$A116,rate_date,rate_date,0,0,1),"")) | E116: =IF(OR($A116="EUR",$A116="USD"),buffer_major,buffer_other) -> 0.1 | G116: =IF(OR(ISNUMBER($F116),ISNUMBER($D116)),IF(ISNUMBER($F116),$F116,$D116)/(1+N($E116)),"") | I116: =IF($C116=0,"",IF(ISNUMBER($F116),"Market rate typed by hand"&IF($H116=""," - record your source in the previous column",": "&$H116)&IF(N($E116)=0,", with no buffer: these are treated as corporate-rate currencies.",", less a "&TEXT(N($E116),"0%")&" prudence buffer."),IF(ISNUMBER($D116),"LSEG via STOCKHISTORY"&IF(ISNUMBER(rate_date)," at "&TEXT(rate_date,"d mmm yyyy"),"")&IF(N($E116)=0,", with no buffer: these are treated as corporate-rate currencies.",", less a "&TEXT(N($E116),"0%")&" prudence buffer."),"NO RATE. STOCKHISTORY returned nothing - the pair may not be covered, the rate date may not have been a trading day, or there may be no Microsoft 365 subscription. Type a market rate in the previous column.")))
A117: ZAR | B117: GBP:ZAR | C117: =SUMPRODUCT(--(('Trip plan'!$M$16:$M$40=$A117)+('Trip plan'!$N$16:$N$40=$A117)>0)) -> 0 | D117: =IF($C117=0,"",IFERROR(_xlfn.STOCKHISTORY("GBP:"&$A117,rate_date,rate_date,0,0,1),"")) | E117: =IF(OR($A117="EUR",$A117="USD"),buffer_major,buffer_other) -> 0.1 | G117: =IF(OR(ISNUMBER($F117),ISNUMBER($D117)),IF(ISNUMBER($F117),$F117,$D117)/(1+N($E117)),"") | I117: =IF($C117=0,"",IF(ISNUMBER($F117),"Market rate typed by hand"&IF($H117=""," - record your source in the previous column",": "&$H117)&IF(N($E117)=0,", with no buffer: these are treated as corporate-rate currencies.",", less a "&TEXT(N($E117),"0%")&" prudence buffer."),IF(ISNUMBER($D117),"LSEG via STOCKHISTORY"&IF(ISNUMBER(rate_date)," at "&TEXT(rate_date,"d mmm yyyy"),"")&IF(N($E117)=0,", with no buffer: these are treated as corporate-rate currencies.",", less a "&TEXT(N($E117),"0%")&" prudence buffer."),"NO RATE. STOCKHISTORY returned nothing - the pair may not be covered, the rate date may not have been a trading day, or there may be no Microsoft 365 subscription. Type a market rate in the previous column.")))
A118: ZMW | B118: GBP:ZMW | C118: =SUMPRODUCT(--(('Trip plan'!$M$16:$M$40=$A118)+('Trip plan'!$N$16:$N$40=$A118)>0)) -> 0 | D118: =IF($C118=0,"",IFERROR(_xlfn.STOCKHISTORY("GBP:"&$A118,rate_date,rate_date,0,0,1),"")) | E118: =IF(OR($A118="EUR",$A118="USD"),buffer_major,buffer_other) -> 0.1 | G118: =IF(OR(ISNUMBER($F118),ISNUMBER($D118)),IF(ISNUMBER($F118),$F118,$D118)/(1+N($E118)),"") | I118: =IF($C118=0,"",IF(ISNUMBER($F118),"Market rate typed by hand"&IF($H118=""," - record your source in the previous column",": "&$H118)&IF(N($E118)=0,", with no buffer: these are treated as corporate-rate currencies.",", less a "&TEXT(N($E118),"0%")&" prudence buffer."),IF(ISNUMBER($D118),"LSEG via STOCKHISTORY"&IF(ISNUMBER(rate_date)," at "&TEXT(rate_date,"d mmm yyyy"),"")&IF(N($E118)=0,", with no buffer: these are treated as corporate-rate currencies.",", less a "&TEXT(N($E118),"0%")&" prudence buffer."),"NO RATE. STOCKHISTORY returned nothing - the pair may not be covered, the rate date may not have been a trading day, or there may be no Microsoft 365 subscription. Type a market rate in the previous column.")))

Sheet Additional_Val
B3: Locations w/ UK | D3: Google Search Syntax | G3: Month Number | H3: Month List
B4: {=_xlfn.VSTACK("London, UK", "Manchester, UK", "East Midlands, UK", loc_list)} -> London, UK | D4: https://www.google.com/search?q=flights+from+ | G4: 1 | H4: Jan
B5: Manchester, UK | D5: [DEPARTURE LOCATION/LONDON] | G5: 2 | H5: Feb
B6: East Midlands, UK | D6: "+to+" | G6: 3 | H6: Mar
B7: Abu Dhabi, United Arab Emirates | D7: [TABLE VALUE FOR DESTINATION] | G7: 4 | H7: Apr
B8: Abuja, Nigeria | D8: [OUTBOUND DAY] | G8: 5 | H8: May
B9: Accra, Ghana | D9: "+", | G9: 6 | H9: Jun
B10: Addis Ababa, Ethiopia | D10: [OUTBOUND MONTH] | G10: 7 | H10: Jul
B11: Adelaide, Australia | D11: "+" | G11: 8 | H11: Aug
B12: Agadir, Morocco | D12: "to" | G12: 9 | H12: Sep
B13: Ahmedabad, India | D13: [RETURN DAY] | G13: 10 | H13: Oct
B14: Al Khobar, Saudi Arabia | D14: "+" | G14: 11 | H14: Nov
B15: Alexandria, Egypt | D15: [RETURN MONTH] | G15: 12 | H15: Dec
B16: Algiers, Algeria
B17: Almaty, Kazakhstan
B18: Amman, Jordan
B19: Amsterdam, Netherlands
B20: Anguilla, Anguilla
B21: Ankara, Turkey
B22: Antananarivo, Madagascar
B23: Apia, Samoa
B24: Aqaba, Jordan
B25: Ashgabat, Turkmenistan
B26: Asmara, Eritrea
B27: Astana, Kazakhstan
... B291: Zanzibar, Tanzania
